Workbook

Sheet Legende
A1: Budget prévisionnel migration IKS vers ROKS, V3
A2: Sources en tables Excel dynamiques, capacity planning mensuel par cluster, vrai calcul du double run, présentation simplifiée
A4: Onglet | B4: Rôle | C4: À savoir
A5: Inventaire | B5: Table tblApplications. Une ligne par application : classification, P95 observé, cible avec marge, dates ROKS/IKS, cluster auto | C5: Ajoutez une ligne en bas du tableau, tout le classeur suit automatiquement
A6: Dynatrace_Extract | B6: Table tblDynatrace. Consommation réelle P95 par application | C6: À remplacer par l'export réel
A7: Tarifs_ABS | B7: Table tblTarifsABS. Tarif CPU/RAM par environnement, et coefficient de dimensionnement P95 vers cible | C7: Ajustez le coefficient selon la marge de sécurité souhaitée
A8: Flavors_Catalogue | B8: Table tblFlavors. Référentiel réel des flavors AsCode et DMZR | C8: Fourni, pas besoin d'y toucher
A9: Clusters_ROKS | B9: Table tblClusters. Registre réel des clusters, avec la charge déjà existante hors migration | C9: Renseignez la charge existante par cluster pour un calcul de saturation fiable
A10: Regles_Selection_Cluster | B10: Table tblRegles. Région/secret/environnement vers cluster principal et cluster de repli | C10: Complétez les lignes marquées à confirmer
A11: Projection_Clusters | B11: Mois x Cluster : charge existante, migrations cumulées, taux d'occupation, workers à ajouter | C11: C'est la vue qui répond à la question, combien de CPU faut-il en plus sur tel cluster en tel mois
A12: Consolidation_Mensuelle | B12: Coût IKS, coût ROKS et vrai surcoût du double run, mois par mois | C12: 100% formule, rien à saisir
A13: Dashboard | B13: 5 indicateurs clés et les deux courbes IKS/ROKS | C13: 100% formule, rien à saisir
A16: Ce qui a changé par rapport à la V2
A17: - L'Inventaire ne montre plus que 22 colonnes utiles au lieu de 41 : 14 à remplir, 8 calculées et lisibles au quotidien (cluster choisi, type, P95, cible, date d'arrêt IKS, statut).
A18: - Le détail du calcul (région effective, clé de sélection, cluster principal et de repli, vérification de capacité) existe toujours, au même endroit, mais replié sous un petit "+" au-dessus des colonnes. Rien n'est supprimé, juste rangé : cliquez sur le "+" pour l'auditer, ignorez-le sinon.
A19: - Trois colonnes de diagnostic (type de cluster attendu, cohérence, alerte de capacité) ont été fusionnées en une seule colonne Statut affectation cluster, qui raconte toute l'histoire en une phrase.
A20: - Même logique appliquée à Clusters_ROKS : les 4 colonnes sur la famille de flavor sont repliées par défaut.
A22: Rappel des apports de la V2 (toujours valables)
A23: - Toutes les sources sont des Tables Excel (tblApplications, tblDynatrace, tblClusters, tblTarifsABS, tblFlavors, tblRegles). Les formules utilisent des références de table, donc ajouter une ligne suffit, aucune formule à étendre à la main.
A24: - CPU/RAM réel P95 (Dynatrace) et CPU/RAM cible ROKS (P95 majoré d'un coefficient de dimensionnement, réglable dans Tarifs_ABS, et multiplié par le nombre de réplicas du service) sont deux choses distinctes. Tout le budget se base sur la cible, pas sur le P95 brut.
A25: - Onglet Projection_Clusters : capacité, charge existante et migrations cumulées mois par mois et cluster par cluster, avec le nombre de workers à commander en plus.
A26: - La bascule vers un cluster de repli se décide par date de migration prévue, et non par position de ligne dans le tableau.
A27: - Chaque application a une date de mise en service ROKS et une durée de double run, d'où une date d'arrêt IKS. Le double run mesure le vrai surcoût, la période où les deux environnements sont payés pour la même charge, et non le coût total pendant la coexistence.
A28: - Un indicateur Inclus dans la projection (O/N) permet d'exclure une application du budget sans la supprimer de l'inventaire.
... A30: Code couleur utilise dans le classeur
A31: Texte bleu | B31: Donnee saisie manuellement (hypothese, export, tarif, flavor)
A32: Texte noir | B32: Formule calculee sur la meme feuille
A33: Texte vert | B33: Formule allant chercher une donnee sur un autre onglet ou une autre table
A34: Fond jaune | B34: Hypothese cle de demonstration, a valider et ajuster avant usage reel
A35: Fond orange | B35: Donnee transcrite d'une capture d'ecran encore incertaine, a confirmer
A36: Fond rouge | B36: Cluster dont le taux d'allocation depasse le seuil d'alerte, ou incoherence detectee
A37: Fond jaune pale | B37: Application basculee automatiquement sur son cluster de repli
A38: En-tete gris fonce | B38: Colonne technique de calcul (Inventaire, colonnes Z a AN), pas destinee a la saisie

Sheet Dynatrace_Extract
A1: Export Dynatrace, consommations réelles (p95)
A2: Démo fictive, à remplacer par l'export réel Dynatrace
A4: Application | B4: CPU reel p95 (cores) | C4: RAM reelle p95 (Go)
A5: App01 | B5: 4 | C5: 16
A6: App02 | B6: 2 | C6: 8
A7: App03 | B7: 8 | C7: 32
A8: App04 | B8: 1 | C8: 4
A9: App05 | B9: 6 | C9: 24
A10: App06 | B10: 3 | C10: 12
A11: App07 | B11: 10 | C11: 40
A12: App08 | B12: 2 | C12: 8
A13: App09 | B13: 5 | C13: 20
A14: App10 | B14: 4 | C14: 16
A17: Source, export Dynatrace à coller ici, données ci-dessus fictives pour la démo

Sheet Tarifs_ABS
A1: Grille tarifaire ABS et hypothèse de dimensionnement
A2: Un tarif CPU/RAM par environnement, sans distinction Mutualisé/Dédié
A4: Environnement | B4: Cout CPU (EUR/core/mois) | C4: Cout RAM (EUR/Go/mois)
A5: IKS | B5: 45 | C5: 6
A6: ROKS | B6: 38 | C6: 5
A9: Coefficient de dimensionnement (P95 vers cible) | C9: 1.2
A10: Exemple : Dynatrace mesure 8 CPU, budgété et provisionné = 8 x coefficient, arrondi à l'entier supérieur
A13: Valeurs ci-dessus fictives pour la démo, fond jaune = hypothèse à valider avant usage réel

Sheet Flavors_Catalogue
A1: Catalogue des flavors disponibles
A2: Référentiel fourni (AsCode et DMZR), sert de liste déroulante pour choisir la flavor d'un cluster
A4: Infra | B4: Flavor | C4: vCPU | D4: RAM (Go) | E4: Famille | F4: Cle Famille vCPU
A5: AsCode | B5: cx3d.8x20 | C5: 8 | D5: 20 | E5: =LEFT(B5,MIN(IFERROR(FIND(".",B5),999),IFERROR(FIND("-",B5),999))-1) -> cx3d | F5: =E5&"|"&C5 -> cx3d|8
A6: AsCode | B6: bx3d.8x40 | C6: 8 | D6: 40 | E6: =LEFT(B6,MIN(IFERROR(FIND(".",B6),999),IFERROR(FIND("-",B6),999))-1) -> bx3d | F6: =E6&"|"&C6 -> bx3d|8
A7: AsCode | B7: cx3d.16x40 | C7: 16 | D7: 40 | E7: =LEFT(B7,MIN(IFERROR(FIND(".",B7),999),IFERROR(FIND("-",B7),999))-1) -> cx3d | F7: =E7&"|"&C7 -> cx3d|16
A8: AsCode | B8: bx3d.16x80 | C8: 16 | D8: 80 | E8: =LEFT(B8,MIN(IFERROR(FIND(".",B8),999),IFERROR(FIND("-",B8),999))-1) -> bx3d | F8: =E8&"|"&C8 -> bx3d|16
A9: AsCode | B9: mx3d.24x240 | C9: 24 | D9: 240 | E9: =LEFT(B9,MIN(IFERROR(FIND(".",B9),999),IFERROR(FIND("-",B9),999))-1) -> mx3d | F9: =E9&"|"&C9 -> mx3d|24
A10: AsCode | B10: cx3d.32x80 | C10: 32 | D10: 80 | E10: =LEFT(B10,MIN(IFERROR(FIND(".",B10),999),IFERROR(FIND("-",B10),999))-1) -> cx3d | F10: =E10&"|"&C10 -> cx3d|32
A11: AsCode | B11: bx3d.32x160 | C11: 32 | D11: 160 | E11: =LEFT(B11,MIN(IFERROR(FIND(".",B11),999),IFERROR(FIND("-",B11),999))-1) -> bx3d | F11: =E11&"|"&C11 -> bx3d|32
A12: AsCode | B12: mx3d.32x320 | C12: 32 | D12: 320 | E12: =LEFT(B12,MIN(IFERROR(FIND(".",B12),999),IFERROR(FIND("-",B12),999))-1) -> mx3d | F12: =E12&"|"&C12 -> mx3d|32
A13: AsCode | B13: bx3d.48x240 | C13: 48 | D13: 240 | E13: =LEFT(B13,MIN(IFERROR(FIND(".",B13),999),IFERROR(FIND("-",B13),999))-1) -> bx3d | F13: =E13&"|"&C13 -> bx3d|48
A14: AsCode | B14: cx3d.96x240 | C14: 96 | D14: 240 | E14: =LEFT(B14,MIN(IFERROR(FIND(".",B14),999),IFERROR(FIND("-",B14),999))-1) -> cx3d | F14: =E14&"|"&C14 -> cx3d|96
A15: DMZR | B15: bx2-4x16 | C15: 4 | D15: 16 | E15: =LEFT(B15,MIN(IFERROR(FIND(".",B15),999),IFERROR(FIND("-",B15),999))-1) -> bx2 | F15: =E15&"|"&C15 -> bx2|4
A16: DMZR | B16: mx2-4x32 | C16: 4 | D16: 32 | E16: =LEFT(B16,MIN(IFERROR(FIND(".",B16),999),IFERROR(FIND("-",B16),999))-1) -> mx2 | F16: =E16&"|"&C16 -> mx2|4
... A30: DMZR | B30: mx2-128x1024 | C30: 128 | D30: 1024 | E30: =LEFT(B30,MIN(IFERROR(FIND(".",B30),999),IFERROR(FIND("-",B30),999))-1) -> mx2 | F30: =E30&"|"&C30 -> mx2|128
A32: Référentiel fourni par l'utilisateur. Chaque flavor est unique dans le catalogue. La famille (colonne E) regroupe les flavors du même type (bx3d, cx3d, mx3d, bx2, cx2, mx2) : c'est elle qui sert à savoir si un cluster peut encore monter en gamme de flavor avant de devoir passer sur un autre cluster.

Sheet Clusters_ROKS
A1: Clusters ABS-DMZR, capacité et charge existante
A2: Registre transcrit du fichier ABS-DMZR-2026-05.xlsx, complété par la charge déjà en place hors migration
A4: Compte | B4: Cluster | C4: Infra | D4: Utilisation | E4: Type (deduit) | F4: Environnement | G4: Flavor | H4: Worker Count | I4: Charge existante CPU hors migration | J4: Charge existante RAM hors migration (Go) | K4: vCPU / noeud (deduit) | L4: RAM / noeud - Go (deduit) | M4: CPU max (cores) | N4: RAM max (Go) | O4: CPU alloue migration (cores) | P4: RAM allouee migration (Go) | Q4: CPU total projete (cores) | R4: RAM totale projetee (Go) | S4: Taux CPU | T4: Taux RAM | U4: Statut | V4: Extension necessaire un jour O/N | W4: Famille de la flavor | X4: vCPU max de la famille | Y4: Flavor max de la famille atteinte O/N | Z4: Flavor suivante suggeree | AB4: Seuils d'alerte de saturation
A5: ac002i000296 | B5: oc002i000577 | C5: AsCode | D5: Mutualise GIE France | E5: =IF(ISNUMBER(SEARCH("Mutualise",D5)),"Mutualise","Dedie") -> Mutualise | F5: PROD | G5: bx3d.8x40 | H5: 6 | I5: 0 | J5: 0 | K5: =IF(G5="","",IFERROR(INDEX(tblFlavors[vCPU],MATCH(G5,tblFlavors[Flavor],0)),"")) -> 8 | L5: =IF(G5="","",IFERROR(INDEX(tblFlavors[RAM (Go)],MATCH(G5,tblFlavors[Flavor],0)),"")) -> 40 | M5: =IF(OR(G5="",H5=0),0,K5*H5) -> 48 | N5: =IF(OR(G5="",H5=0),0,L5*H5) -> 240 | O5: =SUMIFS(tblApplications[CPU cible ROKS],tblApplications[Cluster ROKS cible (auto)],B5,tblApplications[Inclus projection O/N],"O") -> 16 | P5: =SUMIFS(tblApplications[RAM cible ROKS],tblApplications[Cluster ROKS cible (auto)],B5,tblApplications[Inclus projection O/N],"O") -> 60 | Q5: =I5+O5 -> 16 | R5: =J5+P5 -> 60 | S5: =IF(M5=0,"",Q5/M5) -> 0.33333333 | T5: =IF(N5=0,"",R5/N5) -> 0.25 | U5: =IF(M5=0,IF(Q5>0,"Cluster sans capacite provisionnee","n/a"),IF(OR(S5>=Clusters_ROKS!$AC$5,T5>=Clusters_ROKS!$AC$5,H5>=Clusters_ROKS!$AC$6),"Seuil depasse","OK")) -> OK | V5: =IF(COUNTIFS(tblProjection[Cluster],B5,tblProjection[Statut],"Seuil depasse")>0,"O","N") -> N | W5: =IF(G5="","",IFERROR(INDEX(tblFlavors[Famille],MATCH(G5,tblFlavors[Flavor],0)),"")) -> bx3d | X5: =IF(W5="","",_xlfn.MAXIFS(tblFlavors[vCPU],tblFlavors[Famille],W5)) -> 48 | Y5: =IF(W5="","",IF(K5>=X5,"O","N")) -> N | Z5: =IF(OR(W5="",Y5="O"),"",IFERROR(INDEX(tblFlavors[Flavor],MATCH(W5&"|"&_xlfn.MINIFS(tblFlavors[vCPU],tblFlavors[Famille],W5,tblFlavors[vCPU],">"&K5),tblFlavors[Cle Famille vCPU],0)),"")) -> bx3d.16x80 | AB5: Seuil (% de la capacite max, CPU ou RAM) | AC5: 0.66
A6: ac002i000293 | B6: oc002i000578 | C6: AsCode | D6: Mutualise GIE France | E6: =IF(ISNUMBER(SEARCH("Mutualise",D6)),"Mutualise","Dedie") -> Mutualise | F6: HORSPROD | G6: cx3d.32x80 | H6: 6 | I6: 0 | J6: 0 | K6: =IF(G6="","",IFERROR(INDEX(tblFlavors[vCPU],MATCH(G6,tblFlavors[Flavor],0)),"")) -> 32 | L6: =IF(G6="","",IFERROR(INDEX(tblFlavors[RAM (Go)],MATCH(G6,tblFlavors[Flavor],0)),"")) -> 80 | M6: =IF(OR(G6="",H6=0),0,K6*H6) -> 192 | N6: =IF(OR(G6="",H6=0),0,L6*H6) -> 480 | O6: =SUMIFS(tblApplications[CPU cible ROKS],tblApplications[Cluster ROKS cible (auto)],B6,tblApplications[Inclus projection O/N],"O") -> 19 | P6: =SUMIFS(tblApplications[RAM cible ROKS],tblApplications[Cluster ROKS cible (auto)],B6,tblApplications[Inclus projection O/N],"O") -> 70 | Q6: =I6+O6 -> 19 | R6: =J6+P6 -> 70 | S6: =IF(M6=0,"",Q6/M6) -> 0.098958333 | T6: =IF(N6=0,"",R6/N6) -> 0.14583333 | U6: =IF(M6=0,IF(Q6>0,"Cluster sans capacite provisionnee","n/a"),IF(OR(S6>=Clusters_ROKS!$AC$5,T6>=Clusters_ROKS!$AC$5,H6>=Clusters_ROKS!$AC$6),"Seuil depasse","OK")) -> OK | V6: =IF(COUNTIFS(tblProjection[Cluster],B6,tblProjection[Statut],"Seuil depasse")>0,"O","N") -> N | W6: =IF(G6="","",IFERROR(INDEX(tblFlavors[Famille],MATCH(G6,tblFlavors[Flavor],0)),"")) -> cx3d | X6: =IF(W6="","",_xlfn.MAXIFS(tblFlavors[vCPU],tblFlavors[Famille],W6)) -> 96 | Y6: =IF(W6="","",IF(K6>=X6,"O","N")) -> N | Z6: =IF(OR(W6="",Y6="O"),"",IFERROR(INDEX(tblFlavors[Flavor],MATCH(W6&"|"&_xlfn.MINIFS(tblFlavors[vCPU],tblFlavors[Famille],W6,tblFlavors[vCPU],">"&K6),tblFlavors[Cle Famille vCPU],0)),"")) -> cx3d.96x240 | AB6: Seuil (nombre de workers max) | AC6: 12
A7: ac002i000293 | B7: oc002i000807 | C7: AsCode | D7: Mutualise Secret GIE France | E7: =IF(ISNUMBER(SEARCH("Mutualise",D7)),"Mutualise","Dedie") -> Mutualise | F7: HORSPROD | G7: bx3d.16x80 | H7: 6 | I7: 0 | J7: 0 | K7: =IF(G7="","",IFERROR(INDEX(tblFlavors[vCPU],MATCH(G7,tblFlavors[Flavor],0)),"")) -> 16 | L7: =IF(G7="","",IFERROR(INDEX(tblFlavors[RAM (Go)],MATCH(G7,tblFlavors[Flavor],0)),"")) -> 80 | M7: =IF(OR(G7="",H7=0),0,K7*H7) -> 96 | N7: =IF(OR(G7="",H7=0),0,L7*H7) -> 480 | O7: =SUMIFS(tblApplications[CPU cible ROKS],tblApplications[Cluster ROKS cible (auto)],B7,tblApplications[Inclus projection O/N],"O") -> 0 | P7: =SUMIFS(tblApplications[RAM cible ROKS],tblApplications[Cluster ROKS cible (auto)],B7,tblApplications[Inclus projection O/N],"O") -> 0 | Q7: =I7+O7 -> 0 | R7: =J7+P7 -> 0 | S7: =IF(M7=0,"",Q7/M7) -> 0 | T7: =IF(N7=0,"",R7/N7) -> 0 | U7: =IF(M7=0,IF(Q7>0,"Cluster sans capacite provisionnee","n/a"),IF(OR(S7>=Clusters_ROKS!$AC$5,T7>=Clusters_ROKS!$AC$5,H7>=Clusters_ROKS!$AC$6),"Seuil depasse","OK")) -> OK | V7: =IF(COUNTIFS(tblProjection[Cluster],B7,tblProjection[Statut],"Seuil depasse")>0,"O","N") -> N | W7: =IF(G7="","",IFERROR(INDEX(tblFlavors[Famille],MATCH(G7,tblFlavors[Flavor],0)),"")) -> bx3d | X7: =IF(W7="","",_xlfn.MAXIFS(tblFlavors[vCPU],tblFlavors[Famille],W7)) -> 48 | Y7: =IF(W7="","",IF(K7>=X7,"O","N")) -> N | Z7: =IF(OR(W7="",Y7="O"),"",IFERROR(INDEX(tblFlavors[Flavor],MATCH(W7&"|"&_xlfn.MINIFS(tblFlavors[vCPU],tblFlavors[Famille],W7,tblFlavors[vCPU],">"&K7),tblFlavors[Cle Famille vCPU],0)),"")) -> bx3d.32x160
A8: ac002i000296 | B8: oc002i000809 | C8: AsCode | D8: Mutualise Secret GIE France | E8: =IF(ISNUMBER(SEARCH("Mutualise",D8)),"Mutualise","Dedie") -> Mutualise | F8: PROD | G8: bx3d.8x40 | H8: 6 | I8: 0 | J8: 0 | K8: =IF(G8="","",IFERROR(INDEX(tblFlavors[vCPU],MATCH(G8,tblFlavors[Flavor],0)),"")) -> 8 | L8: =IF(G8="","",IFERROR(INDEX(tblFlavors[RAM (Go)],MATCH(G8,tblFlavors[Flavor],0)),"")) -> 40 | M8: =IF(OR(G8="",H8=0),0,K8*H8) -> 48 | N8: =IF(OR(G8="",H8=0),0,L8*H8) -> 240 | O8: =SUMIFS(tblApplications[CPU cible ROKS],tblApplications[Cluster ROKS cible (auto)],B8,tblApplications[Inclus projection O/N],"O") -> 0 | P8: =SUMIFS(tblApplications[RAM cible ROKS],tblApplications[Cluster ROKS cible (auto)],B8,tblApplications[Inclus projection O/N],"O") -> 0 | Q8: =I8+O8 -> 0 | R8: =J8+P8 -> 0 | S8: =IF(M8=0,"",Q8/M8) -> 0 | T8: =IF(N8=0,"",R8/N8) -> 0 | U8: =IF(M8=0,IF(Q8>0,"Cluster sans capacite provisionnee","n/a"),IF(OR(S8>=Clusters_ROKS!$AC$5,T8>=Clusters_ROKS!$AC$5,H8>=Clusters_ROKS!$AC$6),"Seuil depasse","OK")) -> OK | V8: =IF(COUNTIFS(tblProjection[Cluster],B8,tblProjection[Statut],"Seuil depasse")>0,"O","N") -> N | W8: =IF(G8="","",IFERROR(INDEX(tblFlavors[Famille],MATCH(G8,tblFlavors[Flavor],0)),"")) -> bx3d | X8: =IF(W8="","",_xlfn.MAXIFS(tblFlavors[vCPU],tblFlavors[Famille],W8)) -> 48 | Y8: =IF(W8="","",IF(K8>=X8,"O","N")) -> N | Z8: =IF(OR(W8="",Y8="O"),"",IFERROR(INDEX(tblFlavors[Flavor],MATCH(W8&"|"&_xlfn.MINIFS(tblFlavors[vCPU],tblFlavors[Famille],W8,tblFlavors[vCPU],">"&K8),tblFlavors[Cle Famille vCPU],0)),"")) -> bx3d.16x80
A9: ac002i000411 | B9: oc002i000849 | C9: AsCode | D9: Italy No Secret Hors-Prod | E9: =IF(ISNUMBER(SEARCH("Mutualise",D9)),"Mutualise","Dedie") -> Dedie | F9: PROD | G9: bx3d.8x40 | H9: 6 | I9: 0 | J9: 0 | K9: =IF(G9="","",IFERROR(INDEX(tblFlavors[vCPU],MATCH(G9,tblFlavors[Flavor],0)),"")) -> 8 | L9: =IF(G9="","",IFERROR(INDEX(tblFlavors[RAM (Go)],MATCH(G9,tblFlavors[Flavor],0)),"")) -> 40 | M9: =IF(OR(G9="",H9=0),0,K9*H9) -> 48 | N9: =IF(OR(G9="",H9=0),0,L9*H9) -> 240 | O9: =SUMIFS(tblApplications[CPU cible ROKS],tblApplications[Cluster ROKS cible (auto)],B9,tblApplications[Inclus projection O/N],"O") -> 0 | P9: =SUMIFS(tblApplications[RAM cible ROKS],tblApplications[Cluster ROKS cible (auto)],B9,tblApplications[Inclus projection O/N],"O") -> 0 | Q9: =I9+O9 -> 0 | R9: =J9+P9 -> 0 | S9: =IF(M9=0,"",Q9/M9) -> 0 | T9: =IF(N9=0,"",R9/N9) -> 0 | U9: =IF(M9=0,IF(Q9>0,"Cluster sans capacite provisionnee","n/a"),IF(OR(S9>=Clusters_ROKS!$AC$5,T9>=Clusters_ROKS!$AC$5,H9>=Clusters_ROKS!$AC$6),"Seuil depasse","OK")) -> OK | V9: =IF(COUNTIFS(tblProjection[Cluster],B9,tblProjection[Statut],"Seuil depasse")>0,"O","N") -> N | W9: =IF(G9="","",IFERROR(INDEX(tblFlavors[Famille],MATCH(G9,tblFlavors[Flavor],0)),"")) -> bx3d | X9: =IF(W9="","",_xlfn.MAXIFS(tblFlavors[vCPU],tblFlavors[Famille],W9)) -> 48 | Y9: =IF(W9="","",IF(K9>=X9,"O","N")) -> N | Z9: =IF(OR(W9="",Y9="O"),"",IFERROR(INDEX(tblFlavors[Flavor],MATCH(W9&"|"&_xlfn.MINIFS(tblFlavors[vCPU],tblFlavors[Famille],W9,tblFlavors[vCPU],">"&K9),tblFlavors[Cle Famille vCPU],0)),"")) -> bx3d.16x80
A10: ac002i000365 | B10: oc002i000850 | C10: AsCode | D10: Italy No Secret Prod | E10: =IF(ISNUMBER(SEARCH("Mutualise",D10)),"Mutualise","Dedie") -> Dedie | F10: HORSPROD | G10: bx3d.8x40 | H10: 6 | I10: 0 | J10: 0 | K10: =IF(G10="","",IFERROR(INDEX(tblFlavors[vCPU],MATCH(G10,tblFlavors[Flavor],0)),"")) -> 8 | L10: =IF(G10="","",IFERROR(INDEX(tblFlavors[RAM (Go)],MATCH(G10,tblFlavors[Flavor],0)),"")) -> 40 | M10: =IF(OR(G10="",H10=0),0,K10*H10) -> 48 | N10: =IF(OR(G10="",H10=0),0,L10*H10) -> 240 | O10: =SUMIFS(tblApplications[CPU cible ROKS],tblApplications[Cluster ROKS cible (auto)],B10,tblApplications[Inclus projection O/N],"O") -> 0 | P10: =SUMIFS(tblApplications[RAM cible ROKS],tblApplications[Cluster ROKS cible (auto)],B10,tblApplications[Inclus projection O/N],"O") -> 0 | Q10: =I10+O10 -> 0 | R10: =J10+P10 -> 0 | S10: =IF(M10=0,"",Q10/M10) -> 0 | T10: =IF(N10=0,"",R10/N10) -> 0 | U10: =IF(M10=0,IF(Q10>0,"Cluster sans capacite provisionnee","n/a"),IF(OR(S10>=Clusters_ROKS!$AC$5,T10>=Clusters_ROKS!$AC$5,H10>=Clusters_ROKS!$AC$6),"Seuil depasse","OK")) -> OK | V10: =IF(COUNTIFS(tblProjection[Cluster],B10,tblProjection[Statut],"Seuil depasse")>0,"O","N") -> N | W10: =IF(G10="","",IFERROR(INDEX(tblFlavors[Famille],MATCH(G10,tblFlavors[Flavor],0)),"")) -> bx3d | X10: =IF(W10="","",_xlfn.MAXIFS(tblFlavors[vCPU],tblFlavors[Famille],W10)) -> 48 | Y10: =IF(W10="","",IF(K10>=X10,"O","N")) -> N | Z10: =IF(OR(W10="",Y10="O"),"",IFERROR(INDEX(tblFlavors[Flavor],MATCH(W10&"|"&_xlfn.MINIFS(tblFlavors[vCPU],tblFlavors[Famille],W10,tblFlavors[vCPU],">"&K10),tblFlavors[Cle Famille vCPU],0)),"")) -> bx3d.16x80
B11: oc002i001009 | C11: AsCode | D11: LATAM Hors-Prod | E11: =IF(ISNUMBER(SEARCH("Mutualise",D11)),"Mutualise","Dedie") -> Dedie | F11: PROD | G11: bx3d.8x40 | H11: 6 | I11: 0 | J11: 0 | K11: =IF(G11="","",IFERROR(INDEX(tblFlavors[vCPU],MATCH(G11,tblFlavors[Flavor],0)),"")) -> 8 | L11: =IF(G11="","",IFERROR(INDEX(tblFlavors[RAM (Go)],MATCH(G11,tblFlavors[Flavor],0)),"")) -> 40 | M11: =IF(OR(G11="",H11=0),0,K11*H11) -> 48 | N11: =IF(OR(G11="",H11=0),0,L11*H11) -> 240 | O11: =SUMIFS(tblApplications[CPU cible ROKS],tblApplications[Cluster ROKS cible (auto)],B11,tblApplications[Inclus projection O/N],"O") -> 0 | P11: =SUMIFS(tblApplications[RAM cible ROKS],tblApplications[Cluster ROKS cible (auto)],B11,tblApplications[Inclus projection O/N],"O") -> 0 | Q11: =I11+O11 -> 0 | R11: =J11+P11 -> 0 | S11: =IF(M11=0,"",Q11/M11) -> 0 | T11: =IF(N11=0,"",R11/N11) -> 0 | U11: =IF(M11=0,IF(Q11>0,"Cluster sans capacite provisionnee","n/a"),IF(OR(S11>=Clusters_ROKS!$AC$5,T11>=Clusters_ROKS!$AC$5,H11>=Clusters_ROKS!$AC$6),"Seuil depasse","OK")) -> OK | V11: =IF(COUNTIFS(tblProjection[Cluster],B11,tblProjection[Statut],"Seuil depasse")>0,"O","N") -> N | W11: =IF(G11="","",IFERROR(INDEX(tblFlavors[Famille],MATCH(G11,tblFlavors[Flavor],0)),"")) -> bx3d | X11: =IF(W11="","",_xlfn.MAXIFS(tblFlavors[vCPU],tblFlavors[Famille],W11)) -> 48 | Y11: =IF(W11="","",IF(K11>=X11,"O","N")) -> N | Z11: =IF(OR(W11="",Y11="O"),"",IFERROR(INDEX(tblFlavors[Flavor],MATCH(W11&"|"&_xlfn.MINIFS(tblFlavors[vCPU],tblFlavors[Famille],W11,tblFlavors[vCPU],">"&K11),tblFlavors[Cle Famille vCPU],0)),"")) -> bx3d.16x80
A12: ac002i000293 | B12: oc002i001010 | C12: AsCode | D12: LATAM Hors-Prod | E12: =IF(ISNUMBER(SEARCH("Mutualise",D12)),"Mutualise","Dedie") -> Dedie | F12: HORSPROD | H12: 0 | I12: 0 | J12: 0 | K12: =IF(G12="","",IFERROR(INDEX(tblFlavors[vCPU],MATCH(G12,tblFlavors[Flavor],0)),"")) | L12: =IF(G12="","",IFERROR(INDEX(tblFlavors[RAM (Go)],MATCH(G12,tblFlavors[Flavor],0)),"")) | M12: =IF(OR(G12="",H12=0),0,K12*H12) -> 0 | N12: =IF(OR(G12="",H12=0),0,L12*H12) -> 0 | O12: =SUMIFS(tblApplications[CPU cible ROKS],tblApplications[Cluster ROKS cible (auto)],B12,tblApplications[Inclus projection O/N],"O") -> 0 | P12: =SUMIFS(tblApplications[RAM cible ROKS],tblApplications[Cluster ROKS cible (auto)],B12,tblApplications[Inclus projection O/N],"O") -> 0 | Q12: =I12+O12 -> 0 | R12: =J12+P12 -> 0 | S12: =IF(M12=0,"",Q12/M12) | T12: =IF(N12=0,"",R12/N12) | U12: =IF(M12=0,IF(Q12>0,"Cluster sans capacite provisionnee","n/a"),IF(OR(S12>=Clusters_ROKS!$AC$5,T12>=Clusters_ROKS!$AC$5,H12>=Clusters_ROKS!$AC$6),"Seuil depasse","OK")) -> n/a | V12: =IF(COUNTIFS(tblProjection[Cluster],B12,tblProjection[Statut],"Seuil depasse")>0,"O","N") -> N | W12: =IF(G12="","",IFERROR(INDEX(tblFlavors[Famille],MATCH(G12,tblFlavors[Flavor],0)),"")) | X12: =IF(W12="","",_xlfn.MAXIFS(tblFlavors[vCPU],tblFlavors[Famille],W12)) | Y12: =IF(W12="","",IF(K12>=X12,"O","N")) | Z12: =IF(OR(W12="",Y12="O"),"",IFERROR(INDEX(tblFlavors[Flavor],MATCH(W12&"|"&_xlfn.MINIFS(tblFlavors[vCPU],tblFlavors[Famille],W12,tblFlavors[vCPU],">"&K12),tblFlavors[Cle Famille vCPU],0)),""))
B13: oc002i001011 | C13: AsCode | D13: LATAM SECRET PROD | E13: =IF(ISNUMBER(SEARCH("Mutualise",D13)),"Mutualise","Dedie") -> Dedie | F13: HORSPROD | H13: 0 | I13: 0 | J13: 0 | K13: =IF(G13="","",IFERROR(INDEX(tblFlavors[vCPU],MATCH(G13,tblFlavors[Flavor],0)),"")) | L13: =IF(G13="","",IFERROR(INDEX(tblFlavors[RAM (Go)],MATCH(G13,tblFlavors[Flavor],0)),"")) | M13: =IF(OR(G13="",H13=0),0,K13*H13) -> 0 | N13: =IF(OR(G13="",H13=0),0,L13*H13) -> 0 | O13: =SUMIFS(tblApplications[CPU cible ROKS],tblApplications[Cluster ROKS cible (auto)],B13,tblApplications[Inclus projection O/N],"O") -> 0 | P13: =SUMIFS(tblApplications[RAM cible ROKS],tblApplications[Cluster ROKS cible (auto)],B13,tblApplications[Inclus projection O/N],"O") -> 0 | Q13: =I13+O13 -> 0 | R13: =J13+P13 -> 0 | S13: =IF(M13=0,"",Q13/M13) | T13: =IF(N13=0,"",R13/N13) | U13: =IF(M13=0,IF(Q13>0,"Cluster sans capacite provisionnee","n/a"),IF(OR(S13>=Clusters_ROKS!$AC$5,T13>=Clusters_ROKS!$AC$5,H13>=Clusters_ROKS!$AC$6),"Seuil depasse","OK")) -> n/a | V13: =IF(COUNTIFS(tblProjection[Cluster],B13,tblProjection[Statut],"Seuil depasse")>0,"O","N") -> N | W13: =IF(G13="","",IFERROR(INDEX(tblFlavors[Famille],MATCH(G13,tblFlavors[Flavor],0)),"")) | X13: =IF(W13="","",_xlfn.MAXIFS(tblFlavors[vCPU],tblFlavors[Famille],W13)) | Y13: =IF(W13="","",IF(K13>=X13,"O","N")) | Z13: =IF(OR(W13="",Y13="O"),"",IFERROR(INDEX(tblFlavors[Flavor],MATCH(W13&"|"&_xlfn.MINIFS(tblFlavors[vCPU],tblFlavors[Famille],W13,tblFlavors[vCPU],">"&K13),tblFlavors[Cle Famille vCPU],0)),""))
A14: ac002i000296 | B14: oc002i001019 | C14: AsCode | D14: LATAM SECRET PROD | E14: =IF(ISNUMBER(SEARCH("Mutualise",D14)),"Mutualise","Dedie") -> Dedie | F14: HORSPROD | G14: bx3d.8x40 | H14: 6 | I14: 0 | J14: 0 | K14: =IF(G14="","",IFERROR(INDEX(tblFlavors[vCPU],MATCH(G14,tblFlavors[Flavor],0)),"")) -> 8 | L14: =IF(G14="","",IFERROR(INDEX(tblFlavors[RAM (Go)],MATCH(G14,tblFlavors[Flavor],0)),"")) -> 40 | M14: =IF(OR(G14="",H14=0),0,K14*H14) -> 48 | N14: =IF(OR(G14="",H14=0),0,L14*H14) -> 240 | O14: =SUMIFS(tblApplications[CPU cible ROKS],tblApplications[Cluster ROKS cible (auto)],B14,tblApplications[Inclus projection O/N],"O") -> 0 | P14: =SUMIFS(tblApplications[RAM cible ROKS],tblApplications[Cluster ROKS cible (auto)],B14,tblApplications[Inclus projection O/N],"O") -> 0 | Q14: =I14+O14 -> 0 | R14: =J14+P14 -> 0 | S14: =IF(M14=0,"",Q14/M14) -> 0 | T14: =IF(N14=0,"",R14/N14) -> 0 | U14: =IF(M14=0,IF(Q14>0,"Cluster sans capacite provisionnee","n/a"),IF(OR(S14>=Clusters_ROKS!$AC$5,T14>=Clusters_ROKS!$AC$5,H14>=Clusters_ROKS!$AC$6),"Seuil depasse","OK")) -> OK | V14: =IF(COUNTIFS(tblProjection[Cluster],B14,tblProjection[Statut],"Seuil depasse")>0,"O","N") -> N | W14: =IF(G14="","",IFERROR(INDEX(tblFlavors[Famille],MATCH(G14,tblFlavors[Flavor],0)),"")) -> bx3d | X14: =IF(W14="","",_xlfn.MAXIFS(tblFlavors[vCPU],tblFlavors[Famille],W14)) -> 48 | Y14: =IF(W14="","",IF(K14>=X14,"O","N")) -> N | Z14: =IF(OR(W14="",Y14="O"),"",IFERROR(INDEX(tblFlavors[Flavor],MATCH(W14&"|"&_xlfn.MINIFS(tblFlavors[vCPU],tblFlavors[Famille],W14,tblFlavors[vCPU],">"&K14),tblFlavors[Cle Famille vCPU],0)),"")) -> bx3d.16x80
A15: ac002i000293 | B15: oc-EMEA-NPR | C15: AsCode | D15: EMEA Non Secret Hors-Prod | E15: =IF(ISNUMBER(SEARCH("Mutualise",D15)),"Mutualise","Dedie") -> Dedie | F15: PROD | G15: bx3d.8x40 | H15: 6 | I15: 0 | J15: 0 | K15: =IF(G15="","",IFERROR(INDEX(tblFlavors[vCPU],MATCH(G15,tblFlavors[Flavor],0)),"")) -> 8 | L15: =IF(G15="","",IFERROR(INDEX(tblFlavors[RAM (Go)],MATCH(G15,tblFlavors[Flavor],0)),"")) -> 40 | M15: =IF(OR(G15="",H15=0),0,K15*H15) -> 48 | N15: =IF(OR(G15="",H15=0),0,L15*H15) -> 240 | O15: =SUMIFS(tblApplications[CPU cible ROKS],tblApplications[Cluster ROKS cible (auto)],B15,tblApplications[Inclus projection O/N],"O") -> 0 | P15: =SUMIFS(tblApplications[RAM cible ROKS],tblApplications[Cluster ROKS cible (auto)],B15,tblApplications[Inclus projection O/N],"O") -> 0 | Q15: =I15+O15 -> 0 | R15: =J15+P15 -> 0 | S15: =IF(M15=0,"",Q15/M15) -> 0 | T15: =IF(N15=0,"",R15/N15) -> 0 | U15: =IF(M15=0,IF(Q15>0,"Cluster sans capacite provisionnee","n/a"),IF(OR(S15>=Clusters_ROKS!$AC$5,T15>=Clusters_ROKS!$AC$5,H15>=Clusters_ROKS!$AC$6),"Seuil depasse","OK")) -> OK | V15: =IF(COUNTIFS(tblProjection[Cluster],B15,tblProjection[Statut],"Seuil depasse")>0,"O","N") -> N | W15: =IF(G15="","",IFERROR(INDEX(tblFlavors[Famille],MATCH(G15,tblFlavors[Flavor],0)),"")) -> bx3d | X15: =IF(W15="","",_xlfn.MAXIFS(tblFlavors[vCPU],tblFlavors[Famille],W15)) -> 48 | Y15: =IF(W15="","",IF(K15>=X15,"O","N")) -> N | Z15: =IF(OR(W15="",Y15="O"),"",IFERROR(INDEX(tblFlavors[Flavor],MATCH(W15&"|"&_xlfn.MINIFS(tblFlavors[vCPU],tblFlavors[Famille],W15,tblFlavors[vCPU],">"&K15),tblFlavors[Cle Famille vCPU],0)),"")) -> bx3d.16x80
A16: ac002i000296 | B16: oc-EMEA-NOS-PRD | C16: AsCode | D16: EMEA Non Secret Prod | E16: =IF(ISNUMBER(SEARCH("Mutualise",D16)),"Mutualise","Dedie") -> Dedie | F16: HORSPROD | G16: bx3d.8x40 | H16: 6 | I16: 0 | J16: 0 | K16: =IF(G16="","",IFERROR(INDEX(tblFlavors[vCPU],MATCH(G16,tblFlavors[Flavor],0)),"")) -> 8 | L16: =IF(G16="","",IFERROR(INDEX(tblFlavors[RAM (Go)],MATCH(G16,tblFlavors[Flavor],0)),"")) -> 40 | M16: =IF(OR(G16="",H16=0),0,K16*H16) -> 48 | N16: =IF(OR(G16="",H16=0),0,L16*H16) -> 240 | O16: =SUMIFS(tblApplications[CPU cible ROKS],tblApplications[Cluster ROKS cible (auto)],B16,tblApplications[Inclus projection O/N],"O") -> 0 | P16: =SUMIFS(tblApplications[RAM cible ROKS],tblApplications[Cluster ROKS cible (auto)],B16,tblApplications[Inclus projection O/N],"O") -> 0 | Q16: =I16+O16 -> 0 | R16: =J16+P16 -> 0 | S16: =IF(M16=0,"",Q16/M16) -> 0 | T16: =IF(N16=0,"",R16/N16) -> 0 | U16: =IF(M16=0,IF(Q16>0,"Cluster sans capacite provisionnee","n/a"),IF(OR(S16>=Clusters_ROKS!$AC$5,T16>=Clusters_ROKS!$AC$5,H16>=Clusters_ROKS!$AC$6),"Seuil depasse","OK")) -> OK | V16: =IF(COUNTIFS(tblProjection[Cluster],B16,tblProjection[Statut],"Seuil depasse")>0,"O","N") -> N | W16: =IF(G16="","",IFERROR(INDEX(tblFlavors[Famille],MATCH(G16,tblFlavors[Flavor],0)),"")) -> bx3d | X16: =IF(W16="","",_xlfn.MAXIFS(tblFlavors[vCPU],tblFlavors[Famille],W16)) -> 48 | Y16: =IF(W16="","",IF(K16>=X16,"O","N")) -> N | Z16: =IF(OR(W16="",Y16="O"),"",IFERROR(INDEX(tblFlavors[Flavor],MATCH(W16&"|"&_xlfn.MINIFS(tblFlavors[vCPU],tblFlavors[Famille],W16,tblFlavors[vCPU],">"&K16),tblFlavors[Cle Famille vCPU],0)),"")) -> bx3d.16x80
A17: ac002i000296 | B17: oc-EMEA-SEC-PRD | C17: AsCode | D17: EMEA Secret Prod | E17: =IF(ISNUMBER(SEARCH("Mutualise",D17)),"Mutualise","Dedie") -> Dedie | F17: PROD | G17: bx3d.8x40 | H17: 6 | I17: 0 | J17: 0 | K17: =IF(G17="","",IFERROR(INDEX(tblFlavors[vCPU],MATCH(G17,tblFlavors[Flavor],0)),"")) -> 8 | L17: =IF(G17="","",IFERROR(INDEX(tblFlavors[RAM (Go)],MATCH(G17,tblFlavors[Flavor],0)),"")) -> 40 | M17: =IF(OR(G17="",H17=0),0,K17*H17) -> 48 | N17: =IF(OR(G17="",H17=0),0,L17*H17) -> 240 | O17: =SUMIFS(tblApplications[CPU cible ROKS],tblApplications[Cluster ROKS cible (auto)],B17,tblApplications[Inclus projection O/N],"O") -> 24 | P17: =SUMIFS(tblApplications[RAM cible ROKS],tblApplications[Cluster ROKS cible (auto)],B17,tblApplications[Inclus projection O/N],"O") -> 87 | Q17: =I17+O17 -> 24 | R17: =J17+P17 -> 87 | S17: =IF(M17=0,"",Q17/M17) -> 0.5 | T17: =IF(N17=0,"",R17/N17) -> 0.3625 | U17: =IF(M17=0,IF(Q17>0,"Cluster sans capacite provisionnee","n/a"),IF(OR(S17>=Clusters_ROKS!$AC$5,T17>=Clusters_ROKS!$AC$5,H17>=Clusters_ROKS!$AC$6),"Seuil depasse","OK")) -> OK | V17: =IF(COUNTIFS(tblProjection[Cluster],B17,tblProjection[Statut],"Seuil depasse")>0,"O","N") -> N | W17: =IF(G17="","",IFERROR(INDEX(tblFlavors[Famille],MATCH(G17,tblFlavors[Flavor],0)),"")) -> bx3d | X17: =IF(W17="","",_xlfn.MAXIFS(tblFlavors[vCPU],tblFlavors[Famille],W17)) -> 48 | Y17: =IF(W17="","",IF(K17>=X17,"O","N")) -> N | Z17: =IF(OR(W17="",Y17="O"),"",IFERROR(INDEX(tblFlavors[Flavor],MATCH(W17&"|"&_xlfn.MINIFS(tblFlavors[vCPU],tblFlavors[Famille],W17,tblFlavors[vCPU],">"&K17),tblFlavors[Cle Famille vCPU],0)),"")) -> bx3d.16x80
A18: ac002i000296 | B18: oc-JUMP-AEP-PRD | C18: AsCode | D18: JUMP AEP PROD | E18: =IF(ISNUMBER(SEARCH("Mutualise",D18)),"Mutualise","Dedie") -> Dedie | F18: PROD | H18: 0 | I18: 0 | J18: 0 | K18: =IF(G18="","",IFERROR(INDEX(tblFlavors[vCPU],MATCH(G18,tblFlavors[Flavor],0)),"")) | L18: =IF(G18="","",IFERROR(INDEX(tblFlavors[RAM (Go)],MATCH(G18,tblFlavors[Flavor],0)),"")) | M18: =IF(OR(G18="",H18=0),0,K18*H18) -> 0 | N18: =IF(OR(G18="",H18=0),0,L18*H18) -> 0 | O18: =SUMIFS(tblApplications[CPU cible ROKS],tblApplications[Cluster ROKS cible (auto)],B18,tblApplications[Inclus projection O/N],"O") -> 12 | P18: =SUMIFS(tblApplications[RAM cible ROKS],tblApplications[Cluster ROKS cible (auto)],B18,tblApplications[Inclus projection O/N],"O") -> 48 | Q18: =I18+O18 -> 12 | R18: =J18+P18 -> 48 | S18: =IF(M18=0,"",Q18/M18) | T18: =IF(N18=0,"",R18/N18) | U18: =IF(M18=0,IF(Q18>0,"Cluster sans capacite provisionnee","n/a"),IF(OR(S18>=Clusters_ROKS!$AC$5,T18>=Clusters_ROKS!$AC$5,H18>=Clusters_ROKS!$AC$6),"Seuil depasse","OK")) -> Cluster sans capacite provisionnee | V18: =IF(COUNTIFS(tblProjection[Cluster],B18,tblProjection[Statut],"Seuil depasse")>0,"O","N") -> N | W18: =IF(G18="","",IFERROR(INDEX(tblFlavors[Famille],MATCH(G18,tblFlavors[Flavor],0)),"")) | X18: =IF(W18="","",_xlfn.MAXIFS(tblFlavors[vCPU],tblFlavors[Famille],W18)) | Y18: =IF(W18="","",IF(K18>=X18,"O","N")) | Z18: =IF(OR(W18="",Y18="O"),"",IFERROR(INDEX(tblFlavors[Flavor],MATCH(W18&"|"&_xlfn.MINIFS(tblFlavors[vCPU],tblFlavors[Famille],W18,tblFlavors[vCPU],">"&K18),tblFlavors[Cle Famille vCPU],0)),""))
A19: ac002i000296 | B19: oc-JUMP-CLV-PRD | C19: AsCode | D19: JUMP CLV PROD | E19: =IF(ISNUMBER(SEARCH("Mutualise",D19)),"Mutualise","Dedie") -> Dedie | F19: PROD | H19: 0 | I19: 0 | J19: 0 | K19: =IF(G19="","",IFERROR(INDEX(tblFlavors[vCPU],MATCH(G19,tblFlavors[Flavor],0)),"")) | L19: =IF(G19="","",IFERROR(INDEX(tblFlavors[RAM (Go)],MATCH(G19,tblFlavors[Flavor],0)),"")) | M19: =IF(OR(G19="",H19=0),0,K19*H19) -> 0 | N19: =IF(OR(G19="",H19=0),0,L19*H19) -> 0 | O19: =SUMIFS(tblApplications[CPU cible ROKS],tblApplications[Cluster ROKS cible (auto)],B19,tblApplications[Inclus projection O/N],"O") -> 36 | P19: =SUMIFS(tblApplications[RAM cible ROKS],tblApplications[Cluster ROKS cible (auto)],B19,tblApplications[Inclus projection O/N],"O") -> 144 | Q19: =I19+O19 -> 36 | R19: =J19+P19 -> 144 | S19: =IF(M19=0,"",Q19/M19) | T19: =IF(N19=0,"",R19/N19) | U19: =IF(M19=0,IF(Q19>0,"Cluster sans capacite provisionnee","n/a"),IF(OR(S19>=Clusters_ROKS!$AC$5,T19>=Clusters_ROKS!$AC$5,H19>=Clusters_ROKS!$AC$6),"Seuil depasse","OK")) -> Cluster sans capacite provisionnee | V19: =IF(COUNTIFS(tblProjection[Cluster],B19,tblProjection[Statut],"Seuil depasse")>0,"O","N") -> N | W19: =IF(G19="","",IFERROR(INDEX(tblFlavors[Famille],MATCH(G19,tblFlavors[Flavor],0)),"")) | X19: =IF(W19="","",_xlfn.MAXIFS(tblFlavors[vCPU],tblFlavors[Famille],W19)) | Y19: =IF(W19="","",IF(K19>=X19,"O","N")) | Z19: =IF(OR(W19="",Y19="O"),"",IFERROR(INDEX(tblFlavors[Flavor],MATCH(W19&"|"&_xlfn.MINIFS(tblFlavors[vCPU],tblFlavors[Famille],W19,tblFlavors[vCPU],">"&K19),tblFlavors[Cle Famille vCPU],0)),""))
A20: ac002i000296 | B20: oc-JUMP-AEP-NPR | C20: AsCode | D20: JUMP AEP NON PROD | E20: =IF(ISNUMBER(SEARCH("Mutualise",D20)),"Mutualise","Dedie") -> Dedie | F20: HORSPROD | H20: 0 | I20: 0 | J20: 0 | K20: =IF(G20="","",IFERROR(INDEX(tblFlavors[vCPU],MATCH(G20,tblFlavors[Flavor],0)),"")) | L20: =IF(G20="","",IFERROR(INDEX(tblFlavors[RAM (Go)],MATCH(G20,tblFlavors[Flavor],0)),"")) | M20: =IF(OR(G20="",H20=0),0,K20*H20) -> 0 | N20: =IF(OR(G20="",H20=0),0,L20*H20) -> 0 | O20: =SUMIFS(tblApplications[CPU cible ROKS],tblApplications[Cluster ROKS cible (auto)],B20,tblApplications[Inclus projection O/N],"O") -> 0 | P20: =SUMIFS(tblApplications[RAM cible ROKS],tblApplications[Cluster ROKS cible (auto)],B20,tblApplications[Inclus projection O/N],"O") -> 0 | Q20: =I20+O20 -> 0 | R20: =J20+P20 -> 0 | S20: =IF(M20=0,"",Q20/M20) | T20: =IF(N20=0,"",R20/N20) | U20: =IF(M20=0,IF(Q20>0,"Cluster sans capacite provisionnee","n/a"),IF(OR(S20>=Clusters_ROKS!$AC$5,T20>=Clusters_ROKS!$AC$5,H20>=Clusters_ROKS!$AC$6),"Seuil depasse","OK")) -> n/a | V20: =IF(COUNTIFS(tblProjection[Cluster],B20,tblProjection[Statut],"Seuil depasse")>0,"O","N") -> N | W20: =IF(G20="","",IFERROR(INDEX(tblFlavors[Famille],MATCH(G20,tblFlavors[Flavor],0)),"")) | X20: =IF(W20="","",_xlfn.MAXIFS(tblFlavors[vCPU],tblFlavors[Famille],W20)) | Y20: =IF(W20="","",IF(K20>=X20,"O","N")) | Z20: =IF(OR(W20="",Y20="O"),"",IFERROR(INDEX(tblFlavors[Flavor],MATCH(W20&"|"&_xlfn.MINIFS(tblFlavors[vCPU],tblFlavors[Famille],W20,tblFlavors[vCPU],">"&K20),tblFlavors[Cle Famille vCPU],0)),""))
A21: ac002i000296 | B21: oc-JUMP-CLV-NPR | C21: AsCode | D21: JUMP CLV NON PROD | E21: =IF(ISNUMBER(SEARCH("Mutualise",D21)),"Mutualise","Dedie") -> Dedie | F21: HORSPROD | H21: 0 | I21: 0 | J21: 0 | K21: =IF(G21="","",IFERROR(INDEX(tblFlavors[vCPU],MATCH(G21,tblFlavors[Flavor],0)),"")) | L21: =IF(G21="","",IFERROR(INDEX(tblFlavors[RAM (Go)],MATCH(G21,tblFlavors[Flavor],0)),"")) | M21: =IF(OR(G21="",H21=0),0,K21*H21) -> 0 | N21: =IF(OR(G21="",H21=0),0,L21*H21) -> 0 | O21: =SUMIFS(tblApplications[CPU cible ROKS],tblApplications[Cluster ROKS cible (auto)],B21,tblApplications[Inclus projection O/N],"O") -> 0 | P21: =SUMIFS(tblApplications[RAM cible ROKS],tblApplications[Cluster ROKS cible (auto)],B21,tblApplications[Inclus projection O/N],"O") -> 0 | Q21: =I21+O21 -> 0 | R21: =J21+P21 -> 0 | S21: =IF(M21=0,"",Q21/M21) | T21: =IF(N21=0,"",R21/N21) | U21: =IF(M21=0,IF(Q21>0,"Cluster sans capacite provisionnee","n/a"),IF(OR(S21>=Clusters_ROKS!$AC$5,T21>=Clusters_ROKS!$AC$5,H21>=Clusters_ROKS!$AC$6),"Seuil depasse","OK")) -> n/a | V21: =IF(COUNTIFS(tblProjection[Cluster],B21,tblProjection[Statut],"Seuil depasse")>0,"O","N") -> N | W21: =IF(G21="","",IFERROR(INDEX(tblFlavors[Famille],MATCH(G21,tblFlavors[Flavor],0)),"")) | X21: =IF(W21="","",_xlfn.MAXIFS(tblFlavors[vCPU],tblFlavors[Famille],W21)) | Y21: =IF(W21="","",IF(K21>=X21,"O","N")) | Z21: =IF(OR(W21="",Y21="O"),"",IFERROR(INDEX(tblFlavors[Flavor],MATCH(W21&"|"&_xlfn.MINIFS(tblFlavors[vCPU],tblFlavors[Famille],W21,tblFlavors[vCPU],">"&K21),tblFlavors[Cle Famille vCPU],0)),""))
A22: ac002i000461 | B22: oc002i001021 | C22: AsCode | D22: PREZ-I GIE PROD | E22: =IF(ISNUMBER(SEARCH("Mutualise",D22)),"Mutualise","Dedie") -> Dedie | F22: PROD | G22: bx3d.8x40 | H22: 6 | I22: 0 | J22: 0 | K22: =IF(G22="","",IFERROR(INDEX(tblFlavors[vCPU],MATCH(G22,tblFlavors[Flavor],0)),"")) -> 8 | L22: =IF(G22="","",IFERROR(INDEX(tblFlavors[RAM (Go)],MATCH(G22,tblFlavors[Flavor],0)),"")) -> 40 | M22: =IF(OR(G22="",H22=0),0,K22*H22) -> 48 | N22: =IF(OR(G22="",H22=0),0,L22*H22) -> 240 | O22: =SUMIFS(tblApplications[CPU cible ROKS],tblApplications[Cluster ROKS cible (auto)],B22,tblApplications[Inclus projection O/N],"O") -> 0 | P22: =SUMIFS(tblApplications[RAM cible ROKS],tblApplications[Cluster ROKS cible (auto)],B22,tblApplications[Inclus projection O/N],"O") -> 0 | Q22: =I22+O22 -> 0 | R22: =J22+P22 -> 0 | S22: =IF(M22=0,"",Q22/M22) -> 0 | T22: =IF(N22=0,"",R22/N22) -> 0 | U22: =IF(M22=0,IF(Q22>0,"Cluster sans capacite provisionnee","n/a"),IF(OR(S22>=Clusters_ROKS!$AC$5,T22>=Clusters_ROKS!$AC$5,H22>=Clusters_ROKS!$AC$6),"Seuil depasse","OK")) -> OK | V22: =IF(COUNTIFS(tblProjection[Cluster],B22,tblProjection[Statut],"Seuil depasse")>0,"O","N") -> N | W22: =IF(G22="","",IFERROR(INDEX(tblFlavors[Famille],MATCH(G22,tblFlavors[Flavor],0)),"")) -> bx3d | X22: =IF(W22="","",_xlfn.MAXIFS(tblFlavors[vCPU],tblFlavors[Famille],W22)) -> 48 | Y22: =IF(W22="","",IF(K22>=X22,"O","N")) -> N | Z22: =IF(OR(W22="",Y22="O"),"",IFERROR(INDEX(tblFlavors[Flavor],MATCH(W22&"|"&_xlfn.MINIFS(tblFlavors[vCPU],tblFlavors[Famille],W22,tblFlavors[vCPU],">"&K22),tblFlavors[Cle Famille vCPU],0)),"")) -> bx3d.16x80
A23: ac002i000442 | B23: oc002i001016 | C23: AsCode | D23: PREZ-I GIE HORS-PROD | E23: =IF(ISNUMBER(SEARCH("Mutualise",D23)),"Mutualise","Dedie") -> Dedie | F23: HORSPROD | H23: 0 | I23: 0 | J23: 0 | K23: =IF(G23="","",IFERROR(INDEX(tblFlavors[vCPU],MATCH(G23,tblFlavors[Flavor],0)),"")) | L23: =IF(G23="","",IFERROR(INDEX(tblFlavors[RAM (Go)],MATCH(G23,tblFlavors[Flavor],0)),"")) | M23: =IF(OR(G23="",H23=0),0,K23*H23) -> 0 | N23: =IF(OR(G23="",H23=0),0,L23*H23) -> 0 | O23: =SUMIFS(tblApplications[CPU cible ROKS],tblApplications[Cluster ROKS cible (auto)],B23,tblApplications[Inclus projection O/N],"O") -> 0 | P23: =SUMIFS(tblApplications[RAM cible ROKS],tblApplications[Cluster ROKS cible (auto)],B23,tblApplications[Inclus projection O/N],"O") -> 0 | Q23: =I23+O23 -> 0 | R23: =J23+P23 -> 0 | S23: =IF(M23=0,"",Q23/M23) | T23: =IF(N23=0,"",R23/N23) | U23: =IF(M23=0,IF(Q23>0,"Cluster sans capacite provisionnee","n/a"),IF(OR(S23>=Clusters_ROKS!$AC$5,T23>=Clusters_ROKS!$AC$5,H23>=Clusters_ROKS!$AC$6),"Seuil depasse","OK")) -> n/a | V23: =IF(COUNTIFS(tblProjection[Cluster],B23,tblProjection[Statut],"Seuil depasse")>0,"O","N") -> N | W23: =IF(G23="","",IFERROR(INDEX(tblFlavors[Famille],MATCH(G23,tblFlavors[Flavor],0)),"")) | X23: =IF(W23="","",_xlfn.MAXIFS(tblFlavors[vCPU],tblFlavors[Famille],W23)) | Y23: =IF(W23="","",IF(K23>=X23,"O","N")) | Z23: =IF(OR(W23="",Y23="O"),"",IFERROR(INDEX(tblFlavors[Flavor],MATCH(W23&"|"&_xlfn.MINIFS(tblFlavors[vCPU],tblFlavors[Famille],W23,tblFlavors[vCPU],">"&K23),tblFlavors[Cle Famille vCPU],0)),""))
B24: ku002i000249 | C24: DMZR | D24: Mutualise | E24: =IF(ISNUMBER(SEARCH("Mutualise",D24)),"Mutualise","Dedie") -> Mutualise | F24: PROD | H24: 0 | I24: 0 | J24: 0 | K24: =IF(G24="","",IFERROR(INDEX(tblFlavors[vCPU],MATCH(G24,tblFlavors[Flavor],0)),"")) | L24: =IF(G24="","",IFERROR(INDEX(tblFlavors[RAM (Go)],MATCH(G24,tblFlavors[Flavor],0)),"")) | M24: =IF(OR(G24="",H24=0),0,K24*H24) -> 0 | N24: =IF(OR(G24="",H24=0),0,L24*H24) -> 0 | O24: =SUMIFS(tblApplications[CPU cible ROKS],tblApplications[Cluster ROKS cible (auto)],B24,tblApplications[Inclus projection O/N],"O") -> 0 | P24: =SUMIFS(tblApplications[RAM cible ROKS],tblApplications[Cluster ROKS cible (auto)],B24,tblApplications[Inclus projection O/N],"O") -> 0 | Q24: =I24+O24 -> 0 | R24: =J24+P24 -> 0 | S24: =IF(M24=0,"",Q24/M24) | T24: =IF(N24=0,"",R24/N24) | U24: =IF(M24=0,IF(Q24>0,"Cluster sans capacite provisionnee","n/a"),IF(OR(S24>=Clusters_ROKS!$AC$5,T24>=Clusters_ROKS!$AC$5,H24>=Clusters_ROKS!$AC$6),"Seuil depasse","OK")) -> n/a | V24: =IF(COUNTIFS(tblProjection[Cluster],B24,tblProjection[Statut],"Seuil depasse")>0,"O","N") -> N | W24: =IF(G24="","",IFERROR(INDEX(tblFlavors[Famille],MATCH(G24,tblFlavors[Flavor],0)),"")) | X24: =IF(W24="","",_xlfn.MAXIFS(tblFlavors[vCPU],tblFlavors[Famille],W24)) | Y24: =IF(W24="","",IF(K24>=X24,"O","N")) | Z24: =IF(OR(W24="",Y24="O"),"",IFERROR(INDEX(tblFlavors[Flavor],MATCH(W24&"|"&_xlfn.MINIFS(tblFlavors[vCPU],tblFlavors[Famille],W24,tblFlavors[vCPU],">"&K24),tblFlavors[Cle Famille vCPU],0)),""))
B25: ku002i000246 | C25: DMZR | D25: Mutualise | E25: =IF(ISNUMBER(SEARCH("Mutualise",D25)),"Mutualise","Dedie") -> Mutualise | F25: HORSPROD | G25: bx2-32x128 | H25: 15 | I25: 0 | J25: 0 | K25: =IF(G25="","",IFERROR(INDEX(tblFlavors[vCPU],MATCH(G25,tblFlavors[Flavor],0)),"")) -> 32 | L25: =IF(G25="","",IFERROR(INDEX(tblFlavors[RAM (Go)],MATCH(G25,tblFlavors[Flavor],0)),"")) -> 128 | M25: =IF(OR(G25="",H25=0),0,K25*H25) -> 480 | N25: =IF(OR(G25="",H25=0),0,L25*H25) -> 1920 | O25: =SUMIFS(tblApplications[CPU cible ROKS],tblApplications[Cluster ROKS cible (auto)],B25,tblApplications[Inclus projection O/N],"O") -> 0 | P25: =SUMIFS(tblApplications[RAM cible ROKS],tblApplications[Cluster ROKS cible (auto)],B25,tblApplications[Inclus projection O/N],"O") -> 0 | Q25: =I25+O25 -> 0 | R25: =J25+P25 -> 0 | S25: =IF(M25=0,"",Q25/M25) -> 0 | T25: =IF(N25=0,"",R25/N25) -> 0 | U25: =IF(M25=0,IF(Q25>0,"Cluster sans capacite provisionnee","n/a"),IF(OR(S25>=Clusters_ROKS!$AC$5,T25>=Clusters_ROKS!$AC$5,H25>=Clusters_ROKS!$AC$6),"Seuil depasse","OK")) -> Seuil depasse | V25: =IF(COUNTIFS(tblProjection[Cluster],B25,tblProjection[Statut],"Seuil depasse")>0,"O","N") -> N | W25: =IF(G25="","",IFERROR(INDEX(tblFlavors[Famille],MATCH(G25,tblFlavors[Flavor],0)),"")) -> bx2 | X25: =IF(W25="","",_xlfn.MAXIFS(tblFlavors[vCPU],tblFlavors[Famille],W25)) -> 48 | Y25: =IF(W25="","",IF(K25>=X25,"O","N")) -> N | Z25: =IF(OR(W25="",Y25="O"),"",IFERROR(INDEX(tblFlavors[Flavor],MATCH(W25&"|"&_xlfn.MINIFS(tblFlavors[vCPU],tblFlavors[Famille],W25,tblFlavors[vCPU],">"&K25),tblFlavors[Cle Famille vCPU],0)),"")) -> bx2-48x192
B26: ku002i000510 | C26: DMZR | D26: PREZ-i | E26: =IF(ISNUMBER(SEARCH("Mutualise",D26)),"Mutualise","Dedie") -> Dedie | F26: HORSPROD | G26: bx2-32x128 | H26: 15 | I26: 0 | J26: 0 | K26: =IF(G26="","",IFERROR(INDEX(tblFlavors[vCPU],MATCH(G26,tblFlavors[Flavor],0)),"")) -> 32 | L26: =IF(G26="","",IFERROR(INDEX(tblFlavors[RAM (Go)],MATCH(G26,tblFlavors[Flavor],0)),"")) -> 128 | M26: =IF(OR(G26="",H26=0),0,K26*H26) -> 480 | N26: =IF(OR(G26="",H26=0),0,L26*H26) -> 1920 | O26: =SUMIFS(tblApplications[CPU cible ROKS],tblApplications[Cluster ROKS cible (auto)],B26,tblApplications[Inclus projection O/N],"O") -> 0 | P26: =SUMIFS(tblApplications[RAM cible ROKS],tblApplications[Cluster ROKS cible (auto)],B26,tblApplications[Inclus projection O/N],"O") -> 0 | Q26: =I26+O26 -> 0 | R26: =J26+P26 -> 0 | S26: =IF(M26=0,"",Q26/M26) -> 0 | T26: =IF(N26=0,"",R26/N26) -> 0 | U26: =IF(M26=0,IF(Q26>0,"Cluster sans capacite provisionnee","n/a"),IF(OR(S26>=Clusters_ROKS!$AC$5,T26>=Clusters_ROKS!$AC$5,H26>=Clusters_ROKS!$AC$6),"Seuil depasse","OK")) -> Seuil depasse | V26: =IF(COUNTIFS(tblProjection[Cluster],B26,tblProjection[Statut],"Seuil depasse")>0,"O","N") -> N | W26: =IF(G26="","",IFERROR(INDEX(tblFlavors[Famille],MATCH(G26,tblFlavors[Flavor],0)),"")) -> bx2 | X26: =IF(W26="","",_xlfn.MAXIFS(tblFlavors[vCPU],tblFlavors[Famille],W26)) -> 48 | Y26: =IF(W26="","",IF(K26>=X26,"O","N")) -> N | Z26: =IF(OR(W26="",Y26="O"),"",IFERROR(INDEX(tblFlavors[Flavor],MATCH(W26&"|"&_xlfn.MINIFS(tblFlavors[vCPU],tblFlavors[Famille],W26,tblFlavors[vCPU],">"&K26),tblFlavors[Cle Famille vCPU],0)),"")) -> bx2-48x192
B27: ku002i000565 | C27: DMZR | D27: PREZ-i | E27: =IF(ISNUMBER(SEARCH("Mutualise",D27)),"Mutualise","Dedie") -> Dedie | F27: PROD | G27: bx2-8x32 | H27: 6 | I27: 0 | J27: 0 | K27: =IF(G27="","",IFERROR(INDEX(tblFlavors[vCPU],MATCH(G27,tblFlavors[Flavor],0)),"")) -> 8 | L27: =IF(G27="","",IFERROR(INDEX(tblFlavors[RAM (Go)],MATCH(G27,tblFlavors[Flavor],0)),"")) -> 32 | M27: =IF(OR(G27="",H27=0),0,K27*H27) -> 48 | N27: =IF(OR(G27="",H27=0),0,L27*H27) -> 192 | O27: =SUMIFS(tblApplications[CPU cible ROKS],tblApplications[Cluster ROKS cible (auto)],B27,tblApplications[Inclus projection O/N],"O") -> 0 | P27: =SUMIFS(tblApplications[RAM cible ROKS],tblApplications[Cluster ROKS cible (auto)],B27,tblApplications[Inclus projection O/N],"O") -> 0 | Q27: =I27+O27 -> 0 | R27: =J27+P27 -> 0 | S27: =IF(M27=0,"",Q27/M27) -> 0 | T27: =IF(N27=0,"",R27/N27) -> 0 | U27: =IF(M27=0,IF(Q27>0,"Cluster sans capacite provisionnee","n/a"),IF(OR(S27>=Clusters_ROKS!$AC$5,T27>=Clusters_ROKS!$AC$5,H27>=Clusters_ROKS!$AC$6),"Seuil depasse","OK")) -> OK | V27: =IF(COUNTIFS(tblProjection[Cluster],B27,tblProjection[Statut],"Seuil depasse")>0,"O","N") -> N | W27: =IF(G27="","",IFERROR(INDEX(tblFlavors[Famille],MATCH(G27,tblFlavors[Flavor],0)),"")) -> bx2 | X27: =IF(W27="","",_xlfn.MAXIFS(tblFlavors[vCPU],tblFlavors[Famille],W27)) -> 48 | Y27: =IF(W27="","",IF(K27>=X27,"O","N")) -> N | Z27: =IF(OR(W27="",Y27="O"),"",IFERROR(INDEX(tblFlavors[Flavor],MATCH(W27&"|"&_xlfn.MINIFS(tblFlavors[vCPU],tblFlavors[Famille],W27,tblFlavors[vCPU],">"&K27),tblFlavors[Cle Famille vCPU],0)),"")) -> bx2-16x64
B28: ku002i000829 | C28: DMZR | D28: JUMP AEP | E28: =IF(ISNUMBER(SEARCH("Mutualise",D28)),"Mutualise","Dedie") -> Dedie | F28: HORSPROD | G28: mx2-64x512 | H28: 6 | I28: 0 | J28: 0 | K28: =IF(G28="","",IFERROR(INDEX(tblFlavors[vCPU],MATCH(G28,tblFlavors[Flavor],0)),"")) -> 64 | L28: =IF(G28="","",IFERROR(INDEX(tblFlavors[RAM (Go)],MATCH(G28,tblFlavors[Flavor],0)),"")) -> 512 | M28: =IF(OR(G28="",H28=0),0,K28*H28) -> 384 | N28: =IF(OR(G28="",H28=0),0,L28*H28) -> 3072 | O28: =SUMIFS(tblApplications[CPU cible ROKS],tblApplications[Cluster ROKS cible (auto)],B28,tblApplications[Inclus projection O/N],"O") -> 0 | P28: =SUMIFS(tblApplications[RAM cible ROKS],tblApplications[Cluster ROKS cible (auto)],B28,tblApplications[Inclus projection O/N],"O") -> 0 | Q28: =I28+O28 -> 0 | R28: =J28+P28 -> 0 | S28: =IF(M28=0,"",Q28/M28) -> 0 | T28: =IF(N28=0,"",R28/N28) -> 0 | U28: =IF(M28=0,IF(Q28>0,"Cluster sans capacite provisionnee","n/a"),IF(OR(S28>=Clusters_ROKS!$AC$5,T28>=Clusters_ROKS!$AC$5,H28>=Clusters_ROKS!$AC$6),"Seuil depasse","OK")) -> OK | V28: =IF(COUNTIFS(tblProjection[Cluster],B28,tblProjection[Statut],"Seuil depasse")>0,"O","N") -> N | W28: =IF(G28="","",IFERROR(INDEX(tblFlavors[Famille],MATCH(G28,tblFlavors[Flavor],0)),"")) -> mx2 | X28: =IF(W28="","",_xlfn.MAXIFS(tblFlavors[vCPU],tblFlavors[Famille],W28)) -> 128 | Y28: =IF(W28="","",IF(K28>=X28,"O","N")) -> N | Z28: =IF(OR(W28="",Y28="O"),"",IFERROR(INDEX(tblFlavors[Flavor],MATCH(W28&"|"&_xlfn.MINIFS(tblFlavors[vCPU],tblFlavors[Famille],W28,tblFlavors[vCPU],">"&K28),tblFlavors[Cle Famille vCPU],0)),"")) -> mx2-128x1024
B29: ku002i000908 | C29: DMZR | D29: JUMP CLV | E29: =IF(ISNUMBER(SEARCH("Mutualise",D29)),"Mutualise","Dedie") -> Dedie | F29: PROD | G29: mx2-32x256 | H29: 6 | I29: 0 | J29: 0 | K29: =IF(G29="","",IFERROR(INDEX(tblFlavors[vCPU],MATCH(G29,tblFlavors[Flavor],0)),"")) -> 32 | L29: =IF(G29="","",IFERROR(INDEX(tblFlavors[RAM (Go)],MATCH(G29,tblFlavors[Flavor],0)),"")) -> 256 | M29: =IF(OR(G29="",H29=0),0,K29*H29) -> 192 | N29: =IF(OR(G29="",H29=0),0,L29*H29) -> 1536 | O29: =SUMIFS(tblApplications[CPU cible ROKS],tblApplications[Cluster ROKS cible (auto)],B29,tblApplications[Inclus projection O/N],"O") -> 0 | P29: =SUMIFS(tblApplications[RAM cible ROKS],tblApplications[Cluster ROKS cible (auto)],B29,tblApplications[Inclus projection O/N],"O") -> 0 | Q29: =I29+O29 -> 0 | R29: =J29+P29 -> 0 | S29: =IF(M29=0,"",Q29/M29) -> 0 | T29: =IF(N29=0,"",R29/N29) -> 0 | U29: =IF(M29=0,IF(Q29>0,"Cluster sans capacite provisionnee","n/a"),IF(OR(S29>=Clusters_ROKS!$AC$5,T29>=Clusters_ROKS!$AC$5,H29>=Clusters_ROKS!$AC$6),"Seuil depasse","OK")) -> OK | V29: =IF(COUNTIFS(tblProjection[Cluster],B29,tblProjection[Statut],"Seuil depasse")>0,"O","N") -> N | W29: =IF(G29="","",IFERROR(INDEX(tblFlavors[Famille],MATCH(G29,tblFlavors[Flavor],0)),"")) -> mx2 | X29: =IF(W29="","",_xlfn.MAXIFS(tblFlavors[vCPU],tblFlavors[Famille],W29)) -> 128 | Y29: =IF(W29="","",IF(K29>=X29,"O","N")) -> N | Z29: =IF(OR(W29="",Y29="O"),"",IFERROR(INDEX(tblFlavors[Flavor],MATCH(W29&"|"&_xlfn.MINIFS(tblFlavors[vCPU],tblFlavors[Famille],W29,tblFlavors[vCPU],">"&K29),tblFlavors[Cle Famille vCPU],0)),"")) -> mx2-48x384
B30: ku002i001021 | C30: DMZR | D30: JUMP CLV | E30: =IF(ISNUMBER(SEARCH("Mutualise",D30)),"Mutualise","Dedie") -> Dedie | F30: HORSPROD | G30: mx2-32x256 | H30: 9 | I30: 0 | J30: 0 | K30: =IF(G30="","",IFERROR(INDEX(tblFlavors[vCPU],MATCH(G30,tblFlavors[Flavor],0)),"")) -> 32 | L30: =IF(G30="","",IFERROR(INDEX(tblFlavors[RAM (Go)],MATCH(G30,tblFlavors[Flavor],0)),"")) -> 256 | M30: =IF(OR(G30="",H30=0),0,K30*H30) -> 288 | N30: =IF(OR(G30="",H30=0),0,L30*H30) -> 2304 | O30: =SUMIFS(tblApplications[CPU cible ROKS],tblApplications[Cluster ROKS cible (auto)],B30,tblApplications[Inclus projection O/N],"O") -> 0 | P30: =SUMIFS(tblApplications[RAM cible ROKS],tblApplications[Cluster ROKS cible (auto)],B30,tblApplications[Inclus projection O/N],"O") -> 0 | Q30: =I30+O30 -> 0 | R30: =J30+P30 -> 0 | S30: =IF(M30=0,"",Q30/M30) -> 0 | T30: =IF(N30=0,"",R30/N30) -> 0 | U30: =IF(M30=0,IF(Q30>0,"Cluster sans capacite provisionnee","n/a"),IF(OR(S30>=Clusters_ROKS!$AC$5,T30>=Clusters_ROKS!$AC$5,H30>=Clusters_ROKS!$AC$6),"Seuil depasse","OK")) -> OK | V30: =IF(COUNTIFS(tblProjection[Cluster],B30,tblProjection[Statut],"Seuil depasse")>0,"O","N") -> N | W30: =IF(G30="","",IFERROR(INDEX(tblFlavors[Famille],MATCH(G30,tblFlavors[Flavor],0)),"")) -> mx2 | X30: =IF(W30="","",_xlfn.MAXIFS(tblFlavors[vCPU],tblFlavors[Famille],W30)) -> 128 | Y30: =IF(W30="","",IF(K30>=X30,"O","N")) -> N | Z30: =IF(OR(W30="",Y30="O"),"",IFERROR(INDEX(tblFlavors[Flavor],MATCH(W30&"|"&_xlfn.MINIFS(tblFlavors[vCPU],tblFlavors[Famille],W30,tblFlavors[vCPU],">"&K30),tblFlavors[Cle Famille vCPU],0)),"")) -> mx2-48x384
B31: ku002i001071 | C31: DMZR | D31: JUMP AEP | E31: =IF(ISNUMBER(SEARCH("Mutualise",D31)),"Mutualise","Dedie") -> Dedie | F31: PROD | G31: mx2-64x512 | H31: 6 | I31: 0 | J31: 0 | K31: =IF(G31="","",IFERROR(INDEX(tblFlavors[vCPU],MATCH(G31,tblFlavors[Flavor],0)),"")) -> 64 | L31: =IF(G31="","",IFERROR(INDEX(tblFlavors[RAM (Go)],MATCH(G31,tblFlavors[Flavor],0)),"")) -> 512 | M31: =IF(OR(G31="",H31=0),0,K31*H31) -> 384 | N31: =IF(OR(G31="",H31=0),0,L31*H31) -> 3072 | O31: =SUMIFS(tblApplications[CPU cible ROKS],tblApplications[Cluster ROKS cible (auto)],B31,tblApplications[Inclus projection O/N],"O") -> 0 | P31: =SUMIFS(tblApplications[RAM cible ROKS],tblApplications[Cluster ROKS cible (auto)],B31,tblApplications[Inclus projection O/N],"O") -> 0 | Q31: =I31+O31 -> 0 | R31: =J31+P31 -> 0 | S31: =IF(M31=0,"",Q31/M31) -> 0 | T31: =IF(N31=0,"",R31/N31) -> 0 | U31: =IF(M31=0,IF(Q31>0,"Cluster sans capacite provisionnee","n/a"),IF(OR(S31>=Clusters_ROKS!$AC$5,T31>=Clusters_ROKS!$AC$5,H31>=Clusters_ROKS!$AC$6),"Seuil depasse","OK")) -> OK | V31: =IF(COUNTIFS(tblProjection[Cluster],B31,tblProjection[Statut],"Seuil depasse")>0,"O","N") -> N | W31: =IF(G31="","",IFERROR(INDEX(tblFlavors[Famille],MATCH(G31,tblFlavors[Flavor],0)),"")) -> mx2 | X31: =IF(W31="","",_xlfn.MAXIFS(tblFlavors[vCPU],tblFlavors[Famille],W31)) -> 128 | Y31: =IF(W31="","",IF(K31>=X31,"O","N")) -> N | Z31: =IF(OR(W31="",Y31="O"),"",IFERROR(INDEX(tblFlavors[Flavor],MATCH(W31&"|"&_xlfn.MINIFS(tblFlavors[vCPU],tblFlavors[Famille],W31,tblFlavors[vCPU],">"&K31),tblFlavors[Cle Famille vCPU],0)),"")) -> mx2-128x1024
B32: oc-LATAM-NOS-PRD | C32: AsCode | D32: LATAM NO-SEC PROD | E32: =IF(ISNUMBER(SEARCH("Mutualise",D32)),"Mutualise","Dedie") -> Dedie | F32: PROD | H32: 0 | I32: 0 | J32: 0 | K32: =IF(G32="","",IFERROR(INDEX(tblFlavors[vCPU],MATCH(G32,tblFlavors[Flavor],0)),"")) | L32: =IF(G32="","",IFERROR(INDEX(tblFlavors[RAM (Go)],MATCH(G32,tblFlavors[Flavor],0)),"")) | M32: =IF(OR(G32="",H32=0),0,K32*H32) -> 0 | N32: =IF(OR(G32="",H32=0),0,L32*H32) -> 0 | O32: =SUMIFS(tblApplications[CPU cible ROKS],tblApplications[Cluster ROKS cible (auto)],B32,tblApplications[Inclus projection O/N],"O") -> 20 | P32: =SUMIFS(tblApplications[RAM cible ROKS],tblApplications[Cluster ROKS cible (auto)],B32,tblApplications[Inclus projection O/N],"O") -> 78 | Q32: =I32+O32 -> 20 | R32: =J32+P32 -> 78 | S32: =IF(M32=0,"",Q32/M32) | T32: =IF(N32=0,"",R32/N32) | U32: =IF(M32=0,IF(Q32>0,"Cluster sans capacite provisionnee","n/a"),IF(OR(S32>=Clusters_ROKS!$AC$5,T32>=Clusters_ROKS!$AC$5,H32>=Clusters_ROKS!$AC$6),"Seuil depasse","OK")) -> Cluster sans capacite provisionnee | V32: =IF(COUNTIFS(tblProjection[Cluster],B32,tblProjection[Statut],"Seuil depasse")>0,"O","N") -> N | W32: =IF(G32="","",IFERROR(INDEX(tblFlavors[Famille],MATCH(G32,tblFlavors[Flavor],0)),"")) | X32: =IF(W32="","",_xlfn.MAXIFS(tblFlavors[vCPU],tblFlavors[Famille],W32)) | Y32: =IF(W32="","",IF(K32>=X32,"O","N")) | Z32: =IF(OR(W32="",Y32="O"),"",IFERROR(INDEX(tblFlavors[Flavor],MATCH(W32&"|"&_xlfn.MINIFS(tblFlavors[vCPU],tblFlavors[Famille],W32,tblFlavors[vCPU],">"&K32),tblFlavors[Cle Famille vCPU],0)),""))
B33: oc-ITALY-SEC-PRD | C33: AsCode | D33: Italy Secret Prod | E33: =IF(ISNUMBER(SEARCH("Mutualise",D33)),"Mutualise","Dedie") -> Dedie | F33: PROD | H33: 0 | I33: 0 | J33: 0 | K33: =IF(G33="","",IFERROR(INDEX(tblFlavors[vCPU],MATCH(G33,tblFlavors[Flavor],0)),"")) | L33: =IF(G33="","",IFERROR(INDEX(tblFlavors[RAM (Go)],MATCH(G33,tblFlavors[Flavor],0)),"")) | M33: =IF(OR(G33="",H33=0),0,K33*H33) -> 0 | N33: =IF(OR(G33="",H33=0),0,L33*H33) -> 0 | O33: =SUMIFS(tblApplications[CPU cible ROKS],tblApplications[Cluster ROKS cible (auto)],B33,tblApplications[Inclus projection O/N],"O") -> 0 | P33: =SUMIFS(tblApplications[RAM cible ROKS],tblApplications[Cluster ROKS cible (auto)],B33,tblApplications[Inclus projection O/N],"O") -> 0 | Q33: =I33+O33 -> 0 | R33: =J33+P33 -> 0 | S33: =IF(M33=0,"",Q33/M33) | T33: =IF(N33=0,"",R33/N33) | U33: =IF(M33=0,IF(Q33>0,"Cluster sans capacite provisionnee","n/a"),IF(OR(S33>=Clusters_ROKS!$AC$5,T33>=Clusters_ROKS!$AC$5,H33>=Clusters_ROKS!$AC$6),"Seuil depasse","OK")) -> n/a | V33: =IF(COUNTIFS(tblProjection[Cluster],B33,tblProjection[Statut],"Seuil depasse")>0,"O","N") -> N | W33: =IF(G33="","",IFERROR(INDEX(tblFlavors[Famille],MATCH(G33,tblFlavors[Flavor],0)),"")) | X33: =IF(W33="","",_xlfn.MAXIFS(tblFlavors[vCPU],tblFlavors[Famille],W33)) | Y33: =IF(W33="","",IF(K33>=X33,"O","N")) | Z33: =IF(OR(W33="",Y33="O"),"",IFERROR(INDEX(tblFlavors[Flavor],MATCH(W33&"|"&_xlfn.MINIFS(tblFlavors[vCPU],tblFlavors[Famille],W33,tblFlavors[vCPU],">"&K33),tblFlavors[Cle Famille vCPU],0)),""))
B34: ku002i001098 | C34: DMZR | D34: Italy HORS-PROD | E34: =IF(ISNUMBER(SEARCH("Mutualise",D34)),"Mutualise","Dedie") -> Dedie | F34: HORSPROD | H34: 0 | I34: 0 | J34: 0 | K34: =IF(G34="","",IFERROR(INDEX(tblFlavors[vCPU],MATCH(G34,tblFlavors[Flavor],0)),"")) | L34: =IF(G34="","",IFERROR(INDEX(tblFlavors[RAM (Go)],MATCH(G34,tblFlavors[Flavor],0)),"")) | M34: =IF(OR(G34="",H34=0),0,K34*H34) -> 0 | N34: =IF(OR(G34="",H34=0),0,L34*H34) -> 0 | O34: =SUMIFS(tblApplications[CPU cible ROKS],tblApplications[Cluster ROKS cible (auto)],B34,tblApplications[Inclus projection O/N],"O") -> 0 | P34: =SUMIFS(tblApplications[RAM cible ROKS],tblApplications[Cluster ROKS cible (auto)],B34,tblApplications[Inclus projection O/N],"O") -> 0 | Q34: =I34+O34 -> 0 | R34: =J34+P34 -> 0 | S34: =IF(M34=0,"",Q34/M34) | T34: =IF(N34=0,"",R34/N34) | U34: =IF(M34=0,IF(Q34>0,"Cluster sans capacite provisionnee","n/a"),IF(OR(S34>=Clusters_ROKS!$AC$5,T34>=Clusters_ROKS!$AC$5,H34>=Clusters_ROKS!$AC$6),"Seuil depasse","OK")) -> n/a | V34: =IF(COUNTIFS(tblProjection[Cluster],B34,tblProjection[Statut],"Seuil depasse")>0,"O","N") -> N | W34: =IF(G34="","",IFERROR(INDEX(tblFlavors[Famille],MATCH(G34,tblFlavors[Flavor],0)),"")) | X34: =IF(W34="","",_xlfn.MAXIFS(tblFlavors[vCPU],tblFlavors[Famille],W34)) | Y34: =IF(W34="","",IF(K34>=X34,"O","N")) | Z34: =IF(OR(W34="",Y34="O"),"",IFERROR(INDEX(tblFlavors[Flavor],MATCH(W34&"|"&_xlfn.MINIFS(tblFlavors[vCPU],tblFlavors[Famille],W34,tblFlavors[vCPU],">"&K34),tblFlavors[Cle Famille vCPU],0)),""))
A36: Le CPU/RAM alloué migration reprend désormais la cible ROKS avec marge (et non plus le P95 brut), et le total projeté additionne la charge existante hors migration. Le statut Cluster sans capacité provisionnée signale un cluster qui reçoit une allocation sans worker ni flavor défini, à provisionner avant la migration. Les colonnes W à Z (famille de flavor) sont repliées par défaut sous le petit "+" : à consulter uniquement quand vous cherchez à savoir si un cluster peut encore monter en gamme de flavor.

Sheet Regles_Selection_Cluster
A1: Règles de sélection automatique du cluster ROKS
A2: Reprend l'arbre de décision, secret, RGPD-région, isolement, volume. Chaque combinaison pointe vers un cluster de Clusters_ROKS
A3: Certaines combinaisons n'ont pas de cluster identifié avec certitude dans le registre transcrit (cellules à confirmer, fond orange), à trancher avec le référent DMZR. La colonne Cluster de repli est optionnelle : tant que le cluster principal a de la place (moins de 66% CPU/RAM et moins de 12 workers), Inventaire continue de l'utiliser, au delà il bascule automatiquement sur le repli s'il est renseigné.
A4: Region / Perimetre | B4: Donnees secretes O/N | C4: Environnement | D4: Cluster ROKS cible principal | E4: Cluster de repli optionnel | F4: Cle de selection | G4: Principal trouve | H4: Repli trouve
A5: GIE France | B5: N | C5: PROD | D5: oc002i000577 | F5: =A5&"|"&B5&"|"&C5 -> GIE France|N|PROD | G5: =IF(COUNTIF(tblClusters[Cluster],D5)>0,"OK","Introuvable") -> OK | H5: =IF(E5="","",IF(COUNTIF(tblClusters[Cluster],E5)>0,"OK","Introuvable"))
A6: GIE France | B6: N | C6: HORSPROD | D6: oc002i000578 | F6: =A6&"|"&B6&"|"&C6 -> GIE France|N|HORSPROD | G6: =IF(COUNTIF(tblClusters[Cluster],D6)>0,"OK","Introuvable") -> OK | H6: =IF(E6="","",IF(COUNTIF(tblClusters[Cluster],E6)>0,"OK","Introuvable"))
A7: GIE France | B7: O | C7: PROD | D7: oc002i000807 | F7: =A7&"|"&B7&"|"&C7 -> GIE France|O|PROD | G7: =IF(COUNTIF(tblClusters[Cluster],D7)>0,"OK","Introuvable") -> OK | H7: =IF(E7="","",IF(COUNTIF(tblClusters[Cluster],E7)>0,"OK","Introuvable"))
A8: GIE France | B8: O | C8: HORSPROD | D8: oc002i000809 | F8: =A8&"|"&B8&"|"&C8 -> GIE France|O|HORSPROD | G8: =IF(COUNTIF(tblClusters[Cluster],D8)>0,"OK","Introuvable") -> OK | H8: =IF(E8="","",IF(COUNTIF(tblClusters[Cluster],E8)>0,"OK","Introuvable"))
A9: Italy | B9: N | C9: PROD | D9: oc002i000849 | F9: =A9&"|"&B9&"|"&C9 -> Italy|N|PROD | G9: =IF(COUNTIF(tblClusters[Cluster],D9)>0,"OK","Introuvable") -> OK | H9: =IF(E9="","",IF(COUNTIF(tblClusters[Cluster],E9)>0,"OK","Introuvable"))
A10: Italy | B10: N | C10: HORSPROD | D10: oc002i000850 | F10: =A10&"|"&B10&"|"&C10 -> Italy|N|HORSPROD | G10: =IF(COUNTIF(tblClusters[Cluster],D10)>0,"OK","Introuvable") -> OK | H10: =IF(E10="","",IF(COUNTIF(tblClusters[Cluster],E10)>0,"OK","Introuvable"))
A11: Italy | B11: O | C11: PROD | D11: oc-ITALY-SEC-PRD | F11: =A11&"|"&B11&"|"&C11 -> Italy|O|PROD | G11: =IF(COUNTIF(tblClusters[Cluster],D11)>0,"OK","Introuvable") -> OK | H11: =IF(E11="","",IF(COUNTIF(tblClusters[Cluster],E11)>0,"OK","Introuvable"))
A12: Italy | B12: O | C12: HORSPROD | D12: A confirmer | F12: =A12&"|"&B12&"|"&C12 -> Italy|O|HORSPROD | G12: =IF(COUNTIF(tblClusters[Cluster],D12)>0,"OK","Introuvable") -> Introuvable | H12: =IF(E12="","",IF(COUNTIF(tblClusters[Cluster],E12)>0,"OK","Introuvable"))
A13: LATAM | B13: N | C13: PROD | D13: oc-LATAM-NOS-PRD | F13: =A13&"|"&B13&"|"&C13 -> LATAM|N|PROD | G13: =IF(COUNTIF(tblClusters[Cluster],D13)>0,"OK","Introuvable") -> OK | H13: =IF(E13="","",IF(COUNTIF(tblClusters[Cluster],E13)>0,"OK","Introuvable"))
A14: LATAM | B14: N | C14: HORSPROD | D14: oc002i001009 | F14: =A14&"|"&B14&"|"&C14 -> LATAM|N|HORSPROD | G14: =IF(COUNTIF(tblClusters[Cluster],D14)>0,"OK","Introuvable") -> OK | H14: =IF(E14="","",IF(COUNTIF(tblClusters[Cluster],E14)>0,"OK","Introuvable"))
A15: LATAM | B15: O | C15: PROD | D15: A confirmer | F15: =A15&"|"&B15&"|"&C15 -> LATAM|O|PROD | G15: =IF(COUNTIF(tblClusters[Cluster],D15)>0,"OK","Introuvable") -> Introuvable | H15: =IF(E15="","",IF(COUNTIF(tblClusters[Cluster],E15)>0,"OK","Introuvable"))
A16: LATAM | B16: O | C16: HORSPROD | D16: oc002i001019 | F16: =A16&"|"&B16&"|"&C16 -> LATAM|O|HORSPROD | G16: =IF(COUNTIF(tblClusters[Cluster],D16)>0,"OK","Introuvable") -> OK | H16: =IF(E16="","",IF(COUNTIF(tblClusters[Cluster],E16)>0,"OK","Introuvable"))
... A36: Mutualise Standard DMZR | B36: O | C36: HORSPROD | D36: ku002i000246 | F36: =A36&"|"&B36&"|"&C36 -> Mutualise Standard DMZR|O|HORSPROD | G36: =IF(COUNTIF(tblClusters[Cluster],D36)>0,"OK","Introuvable") -> OK | H36: =IF(E36="","",IF(COUNTIF(tblClusters[Cluster],E36)>0,"OK","Introuvable"))
A38: La colonne Clé concatène Région, Secret et Environnement, c'est cette clé que l'Inventaire recherche pour déterminer automatiquement le cluster cible de chaque application. Ajoutez une ligne pour toute nouvelle combinaison, et un cluster de repli dès qu'une alternative existe.

Sheet Inventaire
A1: Inventaire du périmètre de migration
A2: Colonnes bleues (A à N) à remplir ; le reste (jusqu'à V) se calcule seul
A3: Pour ajouter une application, remplissez les colonnes bleues A à N (cliquez sous la dernière ligne du tableau). Les colonnes O à V se calculent seules. Le détail du calcul (comment le cluster est choisi) est replié à droite sous le petit "+" au-dessus de la colonne W : cliquez dessus si vous voulez l'auditer, sinon ignorez-le complètement.
A4: Application | B4: Namespace | C4: Cluster IKS source | D4: Statut | E4: Compte NPR/PRD | F4: Donnees secretes O/N | G4: Contrainte RGPD/compliance forte O/N | H4: Isolement fort requis O/N | I4: Volume important de ressources O/N | J4: Nombre de replicas du service | K4: Mois de bascule prevu | L4: Duree double run (mois) | M4: Inclus projection O/N | N4: Region / Perimetre | O4: Cluster ROKS cible (auto) | P4: Type de cluster (Mutualise/Dedie) | Q4: CPU reel p95 par replica (cores) | R4: RAM reelle p95 par replica (Go) | S4: CPU cible ROKS | T4: RAM cible ROKS | U4: Date arret IKS calculee | V4: Statut affectation cluster | W4: Environnement deduit | X4: Region effective deduite | Y4: Cle de selection deduite | Z4: Type du cluster cible (controle) | AA4: Coherence type / cluster | AB4: Cluster principal candidat | AC4: Cluster de repli candidat | AD4: CPU deja engage principal (avant cette date) | AE4: RAM deja engagee principal (avant cette date) | AF4: CPU max du principal | AG4: RAM max du principal | AH4: Workers du principal | AI4: Principal disponible pour cette appli | AJ4: CPU deja engage repli (avant cette date) | AK4: RAM deja engagee repli (avant cette date) | AL4: CPU max du repli | AM4: RAM max du repli | AN4: Workers du repli | AO4: Repli disponible pour cette appli
A5: App01 | B5: ns-app01 | C5: iks-prod-01 | D5: a migrer | E5: PRD | F5: N | G5: N | H5: N | I5: N | J5: 2 | K5: 46402 | L5: 1 | M5: O | N5: GIE France | O5: =IF(AB5="","Cluster a definir",IF(AI5="OUI",AB5,IF(AO5="OUI",AC5,AB5))) -> oc002i000577 | P5: =IF(OR(F5="O",G5="O",H5="O",I5="O"),"Dedie","Mutualise") -> Mutualise | Q5: =IFERROR(INDEX(tblDynatrace[CPU reel p95 (cores)],MATCH(A5,tblDynatrace[Application],0)),"") -> 4 | R5: =IFERROR(INDEX(tblDynatrace[RAM reelle p95 (Go)],MATCH(A5,tblDynatrace[Application],0)),"") -> 16 | S5: =IF(Q5="","",ROUNDUP(Q5*Tarifs_ABS!$C$9,0)*J5) -> 10 | T5: =IF(R5="","",ROUNDUP(R5*Tarifs_ABS!$C$9,0)*J5) -> 40 | U5: =EDATE(K5,L5) -> 46433 | V5: =IF(AB5="","Cluster a definir : aucune regle ne correspond",IF(AA5="Incoherent","Attention, type de cluster incoherent",IF(AI5="OUI","OK",IF(AO5="OUI","Bascule sur le cluster de repli ("&AC5&")",IF(AC5<>"","Principal et repli tous deux pleins, cluster supplementaire a prevoir","Cluster principal plein, aucun repli defini, cluster supplementaire a prevoir"))))) -> OK | W5: =IF(E5="PRD","PROD","HORSPROD") -> PROD | X5: =IF(H5="O","JUMP CLV",IF(I5="O","JUMP AEP",N5)) -> GIE France | Y5: =X5&"|"&F5&"|"&W5 -> GIE France|N|PROD | Z5: =IFERROR(INDEX(tblClusters[Type (deduit)],MATCH(O5,tblClusters[Cluster],0)),"") -> Mutualise | AA5: =IF(Z5="","",IF(P5=Z5,"OK","Incoherent")) -> OK | AB5: =IFERROR(INDEX(tblRegles[Cluster ROKS cible principal],MATCH(Y5,tblRegles[Cle de selection],0)),"") -> oc002i000577 | AC5: =IFERROR(IF(INDEX(tblRegles[Cluster de repli optionnel],MATCH(Y5,tblRegles[Cle de selection],0))=0,"",INDEX(tblRegles[Cluster de repli optionnel],MATCH(Y5,tblRegles[Cle de selection],0))),"") | AD5: =SUMIFS(tblApplications[CPU cible ROKS],tblApplications[Cluster ROKS cible (auto)],AB5,tblApplications[Mois de bascule prevu],"<"&K5) -> 0 | AE5: =SUMIFS(tblApplications[RAM cible ROKS],tblApplications[Cluster ROKS cible (auto)],AB5,tblApplications[Mois de bascule prevu],"<"&K5) -> 0 | AF5: =IFERROR(INDEX(tblClusters[CPU max (cores)],MATCH(AB5,tblClusters[Cluster],0)),0) -> 48 | AG5: =IFERROR(INDEX(tblClusters[RAM max (Go)],MATCH(AB5,tblClusters[Cluster],0)),0) -> 240 | AH5: =IFERROR(INDEX(tblClusters[Worker Count],MATCH(AB5,tblClusters[Cluster],0)),0) -> 6 | AI5: =IF(AB5="","NON",IF(AF5=0,"NON",IF(OR((AD5+S5)/AF5>=Clusters_ROKS!$AC$5,(AE5+T5)/AG5>=Clusters_ROKS!$AC$5,AH5>=Clusters_ROKS!$AC$6),"NON","OUI"))) -> OUI | AJ5: =IF(AC5="",0,SUMIFS(tblApplications[CPU cible ROKS],tblApplications[Cluster ROKS cible (auto)],AC5,tblApplications[Mois de bascule prevu],"<"&K5)) -> 0 | AK5: =IF(AC5="",0,SUMIFS(tblApplications[RAM cible ROKS],tblApplications[Cluster ROKS cible (auto)],AC5,tblApplications[Mois de bascule prevu],"<"&K5)) -> 0 | AL5: =IF(AC5="",0,IFERROR(INDEX(tblClusters[CPU max (cores)],MATCH(AC5,tblClusters[Cluster],0)),0)) -> 0 | AM5: =IF(AC5="",0,IFERROR(INDEX(tblClusters[RAM max (Go)],MATCH(AC5,tblClusters[Cluster],0)),0)) -> 0 | AN5: =IF(AC5="",0,IFERROR(INDEX(tblClusters[Worker Count],MATCH(AC5,tblClusters[Cluster],0)),0)) -> 0 | AO5: =IF(AC5="","NON",IF(AL5=0,"NON",IF(OR((AJ5+S5)/AL5>=Clusters_ROKS!$AC$5,(AK5+T5)/AM5>=Clusters_ROKS!$AC$5,AN5>=Clusters_ROKS!$AC$6),"NON","OUI"))) -> NON
A6: App02 | B6: ns-app02 | C6: iks-prod-01 | D6: a migrer | E6: PRD | F6: N | G6: N | H6: N | I6: N | J6: 2 | K6: 46433 | L6: 1 | M6: O | N6: GIE France | O6: =IF(AB6="","Cluster a definir",IF(AI6="OUI",AB6,IF(AO6="OUI",AC6,AB6))) -> oc002i000577 | P6: =IF(OR(F6="O",G6="O",H6="O",I6="O"),"Dedie","Mutualise") -> Mutualise | Q6: =IFERROR(INDEX(tblDynatrace[CPU reel p95 (cores)],MATCH(A6,tblDynatrace[Application],0)),"") -> 2 | R6: =IFERROR(INDEX(tblDynatrace[RAM reelle p95 (Go)],MATCH(A6,tblDynatrace[Application],0)),"") -> 8 | S6: =IF(Q6="","",ROUNDUP(Q6*Tarifs_ABS!$C$9,0)*J6) -> 6 | T6: =IF(R6="","",ROUNDUP(R6*Tarifs_ABS!$C$9,0)*J6) -> 20 | U6: =EDATE(K6,L6) -> 46461 | V6: =IF(AB6="","Cluster a definir : aucune regle ne correspond",IF(AA6="Incoherent","Attention, type de cluster incoherent",IF(AI6="OUI","OK",IF(AO6="OUI","Bascule sur le cluster de repli ("&AC6&")",IF(AC6<>"","Principal et repli tous deux pleins, cluster supplementaire a prevoir","Cluster principal plein, aucun repli defini, cluster supplementaire a prevoir"))))) -> OK | W6: =IF(E6="PRD","PROD","HORSPROD") -> PROD | X6: =IF(H6="O","JUMP CLV",IF(I6="O","JUMP AEP",N6)) -> GIE France | Y6: =X6&"|"&F6&"|"&W6 -> GIE France|N|PROD | Z6: =IFERROR(INDEX(tblClusters[Type (deduit)],MATCH(O6,tblClusters[Cluster],0)),"") -> Mutualise | AA6: =IF(Z6="","",IF(P6=Z6,"OK","Incoherent")) -> OK | AB6: =IFERROR(INDEX(tblRegles[Cluster ROKS cible principal],MATCH(Y6,tblRegles[Cle de selection],0)),"") -> oc002i000577 | AC6: =IFERROR(IF(INDEX(tblRegles[Cluster de repli optionnel],MATCH(Y6,tblRegles[Cle de selection],0))=0,"",INDEX(tblRegles[Cluster de repli optionnel],MATCH(Y6,tblRegles[Cle de selection],0))),"") | AD6: =SUMIFS(tblApplications[CPU cible ROKS],tblApplications[Cluster ROKS cible (auto)],AB6,tblApplications[Mois de bascule prevu],"<"&K6) -> 10 | AE6: =SUMIFS(tblApplications[RAM cible ROKS],tblApplications[Cluster ROKS cible (auto)],AB6,tblApplications[Mois de bascule prevu],"<"&K6) -> 40 | AF6: =IFERROR(INDEX(tblClusters[CPU max (cores)],MATCH(AB6,tblClusters[Cluster],0)),0) -> 48 | AG6: =IFERROR(INDEX(tblClusters[RAM max (Go)],MATCH(AB6,tblClusters[Cluster],0)),0) -> 240 | AH6: =IFERROR(INDEX(tblClusters[Worker Count],MATCH(AB6,tblClusters[Cluster],0)),0) -> 6 | AI6: =IF(AB6="","NON",IF(AF6=0,"NON",IF(OR((AD6+S6)/AF6>=Clusters_ROKS!$AC$5,(AE6+T6)/AG6>=Clusters_ROKS!$AC$5,AH6>=Clusters_ROKS!$AC$6),"NON","OUI"))) -> OUI | AJ6: =IF(AC6="",0,SUMIFS(tblApplications[CPU cible ROKS],tblApplications[Cluster ROKS cible (auto)],AC6,tblApplications[Mois de bascule prevu],"<"&K6)) -> 0 | AK6: =IF(AC6="",0,SUMIFS(tblApplications[RAM cible ROKS],tblApplications[Cluster ROKS cible (auto)],AC6,tblApplications[Mois de bascule prevu],"<"&K6)) -> 0 | AL6: =IF(AC6="",0,IFERROR(INDEX(tblClusters[CPU max (cores)],MATCH(AC6,tblClusters[Cluster],0)),0)) -> 0 | AM6: =IF(AC6="",0,IFERROR(INDEX(tblClusters[RAM max (Go)],MATCH(AC6,tblClusters[Cluster],0)),0)) -> 0 | AN6: =IF(AC6="",0,IFERROR(INDEX(tblClusters[Worker Count],MATCH(AC6,tblClusters[Cluster],0)),0)) -> 0 | AO6: =IF(AC6="","NON",IF(AL6=0,"NON",IF(OR((AJ6+S6)/AL6>=Clusters_ROKS!$AC$5,(AK6+T6)/AM6>=Clusters_ROKS!$AC$5,AN6>=Clusters_ROKS!$AC$6),"NON","OUI"))) -> NON
A7: App03 | B7: ns-app03 | C7: iks-prod-02 | D7: a migrer | E7: PRD | F7: N | G7: O | H7: N | I7: N | J7: 2 | K7: 46461 | L7: 1 | M7: O | N7: LATAM | O7: =IF(AB7="","Cluster a definir",IF(AI7="OUI",AB7,IF(AO7="OUI",AC7,AB7))) -> oc-LATAM-NOS-PRD | P7: =IF(OR(F7="O",G7="O",H7="O",I7="O"),"Dedie","Mutualise") -> Dedie | Q7: =IFERROR(INDEX(tblDynatrace[CPU reel p95 (cores)],MATCH(A7,tblDynatrace[Application],0)),"") -> 8 | R7: =IFERROR(INDEX(tblDynatrace[RAM reelle p95 (Go)],MATCH(A7,tblDynatrace[Application],0)),"") -> 32 | S7: =IF(Q7="","",ROUNDUP(Q7*Tarifs_ABS!$C$9,0)*J7) -> 20 | T7: =IF(R7="","",ROUNDUP(R7*Tarifs_ABS!$C$9,0)*J7) -> 78 | U7: =EDATE(K7,L7) -> 46492 | V7: =IF(AB7="","Cluster a definir : aucune regle ne correspond",IF(AA7="Incoherent","Attention, type de cluster incoherent",IF(AI7="OUI","OK",IF(AO7="OUI","Bascule sur le cluster de repli ("&AC7&")",IF(AC7<>"","Principal et repli tous deux pleins, cluster supplementaire a prevoir","Cluster principal plein, aucun repli defini, cluster supplementaire a prevoir"))))) -> Cluster principal plein, aucun repli defini, cluster supplementaire a prevoir | W7: =IF(E7="PRD","PROD","HORSPROD") -> PROD | X7: =IF(H7="O","JUMP CLV",IF(I7="O","JUMP AEP",N7)) -> LATAM | Y7: =X7&"|"&F7&"|"&W7 -> LATAM|N|PROD | Z7: =IFERROR(INDEX(tblClusters[Type (deduit)],MATCH(O7,tblClusters[Cluster],0)),"") -> Dedie | AA7: =IF(Z7="","",IF(P7=Z7,"OK","Incoherent")) -> OK | AB7: =IFERROR(INDEX(tblRegles[Cluster ROKS cible principal],MATCH(Y7,tblRegles[Cle de selection],0)),"") -> oc-LATAM-NOS-PRD | AC7: =IFERROR(IF(INDEX(tblRegles[Cluster de repli optionnel],MATCH(Y7,tblRegles[Cle de selection],0))=0,"",INDEX(tblRegles[Cluster de repli optionnel],MATCH(Y7,tblRegles[Cle de selection],0))),"") | AD7: =SUMIFS(tblApplications[CPU cible ROKS],tblApplications[Cluster ROKS cible (auto)],AB7,tblApplications[Mois de bascule prevu],"<"&K7) -> 0 | AE7: =SUMIFS(tblApplications[RAM cible ROKS],tblApplications[Cluster ROKS cible (auto)],AB7,tblApplications[Mois de bascule prevu],"<"&K7) -> 0 | AF7: =IFERROR(INDEX(tblClusters[CPU max (cores)],MATCH(AB7,tblClusters[Cluster],0)),0) -> 0 | AG7: =IFERROR(INDEX(tblClusters[RAM max (Go)],MATCH(AB7,tblClusters[Cluster],0)),0) -> 0 | AH7: =IFERROR(INDEX(tblClusters[Worker Count],MATCH(AB7,tblClusters[Cluster],0)),0) -> 0 | AI7: =IF(AB7="","NON",IF(AF7=0,"NON",IF(OR((AD7+S7)/AF7>=Clusters_ROKS!$AC$5,(AE7+T7)/AG7>=Clusters_ROKS!$AC$5,AH7>=Clusters_ROKS!$AC$6),"NON","OUI"))) -> NON | AJ7: =IF(AC7="",0,SUMIFS(tblApplications[CPU cible ROKS],tblApplications[Cluster ROKS cible (auto)],AC7,tblApplications[Mois de bascule prevu],"<"&K7)) -> 0 | AK7: =IF(AC7="",0,SUMIFS(tblApplications[RAM cible ROKS],tblApplications[Cluster ROKS cible (auto)],AC7,tblApplications[Mois de bascule prevu],"<"&K7)) -> 0 | AL7: =IF(AC7="",0,IFERROR(INDEX(tblClusters[CPU max (cores)],MATCH(AC7,tblClusters[Cluster],0)),0)) -> 0 | AM7: =IF(AC7="",0,IFERROR(INDEX(tblClusters[RAM max (Go)],MATCH(AC7,tblClusters[Cluster],0)),0)) -> 0 | AN7: =IF(AC7="",0,IFERROR(INDEX(tblClusters[Worker Count],MATCH(AC7,tblClusters[Cluster],0)),0)) -> 0 | AO7: =IF(AC7="","NON",IF(AL7=0,"NON",IF(OR((AJ7+S7)/AL7>=Clusters_ROKS!$AC$5,(AK7+T7)/AM7>=Clusters_ROKS!$AC$5,AN7>=Clusters_ROKS!$AC$6),"NON","OUI"))) -> NON
A8: App04 | B8: ns-app04 | C8: iks-npr-01 | D8: a migrer | E8: NPR | F8: N | G8: N | H8: N | I8: N | J8: 1 | K8: 46402 | L8: 1 | M8: O | N8: GIE France | O8: =IF(AB8="","Cluster a definir",IF(AI8="OUI",AB8,IF(AO8="OUI",AC8,AB8))) -> oc002i000578 | P8: =IF(OR(F8="O",G8="O",H8="O",I8="O"),"Dedie","Mutualise") -> Mutualise | Q8: =IFERROR(INDEX(tblDynatrace[CPU reel p95 (cores)],MATCH(A8,tblDynatrace[Application],0)),"") -> 1 | R8: =IFERROR(INDEX(tblDynatrace[RAM reelle p95 (Go)],MATCH(A8,tblDynatrace[Application],0)),"") -> 4 | S8: =IF(Q8="","",ROUNDUP(Q8*Tarifs_ABS!$C$9,0)*J8) -> 2 | T8: =IF(R8="","",ROUNDUP(R8*Tarifs_ABS!$C$9,0)*J8) -> 5 | U8: =EDATE(K8,L8) -> 46433 | V8: =IF(AB8="","Cluster a definir : aucune regle ne correspond",IF(AA8="Incoherent","Attention, type de cluster incoherent",IF(AI8="OUI","OK",IF(AO8="OUI","Bascule sur le cluster de repli ("&AC8&")",IF(AC8<>"","Principal et repli tous deux pleins, cluster supplementaire a prevoir","Cluster principal plein, aucun repli defini, cluster supplementaire a prevoir"))))) -> OK | W8: =IF(E8="PRD","PROD","HORSPROD") -> HORSPROD | X8: =IF(H8="O","JUMP CLV",IF(I8="O","JUMP AEP",N8)) -> GIE France | Y8: =X8&"|"&F8&"|"&W8 -> GIE France|N|HORSPROD | Z8: =IFERROR(INDEX(tblClusters[Type (deduit)],MATCH(O8,tblClusters[Cluster],0)),"") -> Mutualise | AA8: =IF(Z8="","",IF(P8=Z8,"OK","Incoherent")) -> OK | AB8: =IFERROR(INDEX(tblRegles[Cluster ROKS cible principal],MATCH(Y8,tblRegles[Cle de selection],0)),"") -> oc002i000578 | AC8: =IFERROR(IF(INDEX(tblRegles[Cluster de repli optionnel],MATCH(Y8,tblRegles[Cle de selection],0))=0,"",INDEX(tblRegles[Cluster de repli optionnel],MATCH(Y8,tblRegles[Cle de selection],0))),"") | AD8: =SUMIFS(tblApplications[CPU cible ROKS],tblApplications[Cluster ROKS cible (auto)],AB8,tblApplications[Mois de bascule prevu],"<"&K8) -> 0 | AE8: =SUMIFS(tblApplications[RAM cible ROKS],tblApplications[Cluster ROKS cible (auto)],AB8,tblApplications[Mois de bascule prevu],"<"&K8) -> 0 | AF8: =IFERROR(INDEX(tblClusters[CPU max (cores)],MATCH(AB8,tblClusters[Cluster],0)),0) -> 192 | AG8: =IFERROR(INDEX(tblClusters[RAM max (Go)],MATCH(AB8,tblClusters[Cluster],0)),0) -> 480 | AH8: =IFERROR(INDEX(tblClusters[Worker Count],MATCH(AB8,tblClusters[Cluster],0)),0) -> 6 | AI8: =IF(AB8="","NON",IF(AF8=0,"NON",IF(OR((AD8+S8)/AF8>=Clusters_ROKS!$AC$5,(AE8+T8)/AG8>=Clusters_ROKS!$AC$5,AH8>=Clusters_ROKS!$AC$6),"NON","OUI"))) -> OUI | AJ8: =IF(AC8="",0,SUMIFS(tblApplications[CPU cible ROKS],tblApplications[Cluster ROKS cible (auto)],AC8,tblApplications[Mois de bascule prevu],"<"&K8)) -> 0 | AK8: =IF(AC8="",0,SUMIFS(tblApplications[RAM cible ROKS],tblApplications[Cluster ROKS cible (auto)],AC8,tblApplications[Mois de bascule prevu],"<"&K8)) -> 0 | AL8: =IF(AC8="",0,IFERROR(INDEX(tblClusters[CPU max (cores)],MATCH(AC8,tblClusters[Cluster],0)),0)) -> 0 | AM8: =IF(AC8="",0,IFERROR(INDEX(tblClusters[RAM max (Go)],MATCH(AC8,tblClusters[Cluster],0)),0)) -> 0 | AN8: =IF(AC8="",0,IFERROR(INDEX(tblClusters[Worker Count],MATCH(AC8,tblClusters[Cluster],0)),0)) -> 0 | AO8: =IF(AC8="","NON",IF(AL8=0,"NON",IF(OR((AJ8+S8)/AL8>=Clusters_ROKS!$AC$5,(AK8+T8)/AM8>=Clusters_ROKS!$AC$5,AN8>=Clusters_ROKS!$AC$6),"NON","OUI"))) -> NON
A9: App05 | B9: ns-app05 | C9: iks-prod-02 | D9: a migrer | E9: PRD | F9: O | G9: N | H9: N | I9: N | J9: 3 | K9: 46492 | L9: 1 | M9: O | N9: EMEA | O9: =IF(AB9="","Cluster a definir",IF(AI9="OUI",AB9,IF(AO9="OUI",AC9,AB9))) -> oc-EMEA-SEC-PRD | P9: =IF(OR(F9="O",G9="O",H9="O",I9="O"),"Dedie","Mutualise") -> Dedie | Q9: =IFERROR(INDEX(tblDynatrace[CPU reel p95 (cores)],MATCH(A9,tblDynatrace[Application],0)),"") -> 6 | R9: =IFERROR(INDEX(tblDynatrace[RAM reelle p95 (Go)],MATCH(A9,tblDynatrace[Application],0)),"") -> 24 | S9: =IF(Q9="","",ROUNDUP(Q9*Tarifs_ABS!$C$9,0)*J9) -> 24 | T9: =IF(R9="","",ROUNDUP(R9*Tarifs_ABS!$C$9,0)*J9) -> 87 | U9: =EDATE(K9,L9) -> 46522 | V9: =IF(AB9="","Cluster a definir : aucune regle ne correspond",IF(AA9="Incoherent","Attention, type de cluster incoherent",IF(AI9="OUI","OK",IF(AO9="OUI","Bascule sur le cluster de repli ("&AC9&")",IF(AC9<>"","Principal et repli tous deux pleins, cluster supplementaire a prevoir","Cluster principal plein, aucun repli defini, cluster supplementaire a prevoir"))))) -> OK | W9: =IF(E9="PRD","PROD","HORSPROD") -> PROD | X9: =IF(H9="O","JUMP CLV",IF(I9="O","JUMP AEP",N9)) -> EMEA | Y9: =X9&"|"&F9&"|"&W9 -> EMEA|O|PROD | Z9: =IFERROR(INDEX(tblClusters[Type (deduit)],MATCH(O9,tblClusters[Cluster],0)),"") -> Dedie | AA9: =IF(Z9="","",IF(P9=Z9,"OK","Incoherent")) -> OK | AB9: =IFERROR(INDEX(tblRegles[Cluster ROKS cible principal],MATCH(Y9,tblRegles[Cle de selection],0)),"") -> oc-EMEA-SEC-PRD | AC9: =IFERROR(IF(INDEX(tblRegles[Cluster de repli optionnel],MATCH(Y9,tblRegles[Cle de selection],0))=0,"",INDEX(tblRegles[Cluster de repli optionnel],MATCH(Y9,tblRegles[Cle de selection],0))),"") | AD9: =SUMIFS(tblApplications[CPU cible ROKS],tblApplications[Cluster ROKS cible (auto)],AB9,tblApplications[Mois de bascule prevu],"<"&K9) -> 0 | AE9: =SUMIFS(tblApplications[RAM cible ROKS],tblApplications[Cluster ROKS cible (auto)],AB9,tblApplications[Mois de bascule prevu],"<"&K9) -> 0 | AF9: =IFERROR(INDEX(tblClusters[CPU max (cores)],MATCH(AB9,tblClusters[Cluster],0)),0) -> 48 | AG9: =IFERROR(INDEX(tblClusters[RAM max (Go)],MATCH(AB9,tblClusters[Cluster],0)),0) -> 240 | AH9: =IFERROR(INDEX(tblClusters[Worker Count],MATCH(AB9,tblClusters[Cluster],0)),0) -> 6 | AI9: =IF(AB9="","NON",IF(AF9=0,"NON",IF(OR((AD9+S9)/AF9>=Clusters_ROKS!$AC$5,(AE9+T9)/AG9>=Clusters_ROKS!$AC$5,AH9>=Clusters_ROKS!$AC$6),"NON","OUI"))) -> OUI | AJ9: =IF(AC9="",0,SUMIFS(tblApplications[CPU cible ROKS],tblApplications[Cluster ROKS cible (auto)],AC9,tblApplications[Mois de bascule prevu],"<"&K9)) -> 0 | AK9: =IF(AC9="",0,SUMIFS(tblApplications[RAM cible ROKS],tblApplications[Cluster ROKS cible (auto)],AC9,tblApplications[Mois de bascule prevu],"<"&K9)) -> 0 | AL9: =IF(AC9="",0,IFERROR(INDEX(tblClusters[CPU max (cores)],MATCH(AC9,tblClusters[Cluster],0)),0)) -> 0 | AM9: =IF(AC9="",0,IFERROR(INDEX(tblClusters[RAM max (Go)],MATCH(AC9,tblClusters[Cluster],0)),0)) -> 0 | AN9: =IF(AC9="",0,IFERROR(INDEX(tblClusters[Worker Count],MATCH(AC9,tblClusters[Cluster],0)),0)) -> 0 | AO9: =IF(AC9="","NON",IF(AL9=0,"NON",IF(OR((AJ9+S9)/AL9>=Clusters_ROKS!$AC$5,(AK9+T9)/AM9>=Clusters_ROKS!$AC$5,AN9>=Clusters_ROKS!$AC$6),"NON","OUI"))) -> NON
A10: App06 | B10: ns-app06 | C10: iks-npr-01 | D10: a migrer | E10: NPR | F10: N | G10: N | H10: N | I10: N | J10: 1 | K10: 46433 | L10: 1 | M10: O | N10: GIE France | O10: =IF(AB10="","Cluster a definir",IF(AI10="OUI",AB10,IF(AO10="OUI",AC10,AB10))) -> oc002i000578 | P10: =IF(OR(F10="O",G10="O",H10="O",I10="O"),"Dedie","Mutualise") -> Mutualise | Q10: =IFERROR(INDEX(tblDynatrace[CPU reel p95 (cores)],MATCH(A10,tblDynatrace[Application],0)),"") -> 3 | R10: =IFERROR(INDEX(tblDynatrace[RAM reelle p95 (Go)],MATCH(A10,tblDynatrace[Application],0)),"") -> 12 | S10: =IF(Q10="","",ROUNDUP(Q10*Tarifs_ABS!$C$9,0)*J10) -> 4 | T10: =IF(R10="","",ROUNDUP(R10*Tarifs_ABS!$C$9,0)*J10) -> 15 | U10: =EDATE(K10,L10) -> 46461 | V10: =IF(AB10="","Cluster a definir : aucune regle ne correspond",IF(AA10="Incoherent","Attention, type de cluster incoherent",IF(AI10="OUI","OK",IF(AO10="OUI","Bascule sur le cluster de repli ("&AC10&")",IF(AC10<>"","Principal et repli tous deux pleins, cluster supplementaire a prevoir","Cluster principal plein, aucun repli defini, cluster supplementaire a prevoir"))))) -> OK | W10: =IF(E10="PRD","PROD","HORSPROD") -> HORSPROD | X10: =IF(H10="O","JUMP CLV",IF(I10="O","JUMP AEP",N10)) -> GIE France | Y10: =X10&"|"&F10&"|"&W10 -> GIE France|N|HORSPROD | Z10: =IFERROR(INDEX(tblClusters[Type (deduit)],MATCH(O10,tblClusters[Cluster],0)),"") -> Mutualise | AA10: =IF(Z10="","",IF(P10=Z10,"OK","Incoherent")) -> OK | AB10: =IFERROR(INDEX(tblRegles[Cluster ROKS cible principal],MATCH(Y10,tblRegles[Cle de selection],0)),"") -> oc002i000578 | AC10: =IFERROR(IF(INDEX(tblRegles[Cluster de repli optionnel],MATCH(Y10,tblRegles[Cle de selection],0))=0,"",INDEX(tblRegles[Cluster de repli optionnel],MATCH(Y10,tblRegles[Cle de selection],0))),"") | AD10: =SUMIFS(tblApplications[CPU cible ROKS],tblApplications[Cluster ROKS cible (auto)],AB10,tblApplications[Mois de bascule prevu],"<"&K10) -> 2 | AE10: =SUMIFS(tblApplications[RAM cible ROKS],tblApplications[Cluster ROKS cible (auto)],AB10,tblApplications[Mois de bascule prevu],"<"&K10) -> 5 | AF10: =IFERROR(INDEX(tblClusters[CPU max (cores)],MATCH(AB10,tblClusters[Cluster],0)),0) -> 192 | AG10: =IFERROR(INDEX(tblClusters[RAM max (Go)],MATCH(AB10,tblClusters[Cluster],0)),0) -> 480 | AH10: =IFERROR(INDEX(tblClusters[Worker Count],MATCH(AB10,tblClusters[Cluster],0)),0) -> 6 | AI10: =IF(AB10="","NON",IF(AF10=0,"NON",IF(OR((AD10+S10)/AF10>=Clusters_ROKS!$AC$5,(AE10+T10)/AG10>=Clusters_ROKS!$AC$5,AH10>=Clusters_ROKS!$AC$6),"NON","OUI"))) -> OUI | AJ10: =IF(AC10="",0,SUMIFS(tblApplications[CPU cible ROKS],tblApplications[Cluster ROKS cible (auto)],AC10,tblApplications[Mois de bascule prevu],"<"&K10)) -> 0 | AK10: =IF(AC10="",0,SUMIFS(tblApplications[RAM cible ROKS],tblApplications[Cluster ROKS cible (auto)],AC10,tblApplications[Mois de bascule prevu],"<"&K10)) -> 0 | AL10: =IF(AC10="",0,IFERROR(INDEX(tblClusters[CPU max (cores)],MATCH(AC10,tblClusters[Cluster],0)),0)) -> 0 | AM10: =IF(AC10="",0,IFERROR(INDEX(tblClusters[RAM max (Go)],MATCH(AC10,tblClusters[Cluster],0)),0)) -> 0 | AN10: =IF(AC10="",0,IFERROR(INDEX(tblClusters[Worker Count],MATCH(AC10,tblClusters[Cluster],0)),0)) -> 0 | AO10: =IF(AC10="","NON",IF(AL10=0,"NON",IF(OR((AJ10+S10)/AL10>=Clusters_ROKS!$AC$5,(AK10+T10)/AM10>=Clusters_ROKS!$AC$5,AN10>=Clusters_ROKS!$AC$6),"NON","OUI"))) -> NON
A11: App07 | B11: ns-app07 | C11: iks-prod-03 | D11: a migrer | E11: PRD | F11: N | G11: N | H11: O | I11: N | J11: 3 | K11: 46522 | L11: 2 | M11: O | N11: GIE France | O11: =IF(AB11="","Cluster a definir",IF(AI11="OUI",AB11,IF(AO11="OUI",AC11,AB11))) -> oc-JUMP-CLV-PRD | P11: =IF(OR(F11="O",G11="O",H11="O",I11="O"),"Dedie","Mutualise") -> Dedie | Q11: =IFERROR(INDEX(tblDynatrace[CPU reel p95 (cores)],MATCH(A11,tblDynatrace[Application],0)),"") -> 10 | R11: =IFERROR(INDEX(tblDynatrace[RAM reelle p95 (Go)],MATCH(A11,tblDynatrace[Application],0)),"") -> 40 | S11: =IF(Q11="","",ROUNDUP(Q11*Tarifs_ABS!$C$9,0)*J11) -> 36 | T11: =IF(R11="","",ROUNDUP(R11*Tarifs_ABS!$C$9,0)*J11) -> 144 | U11: =EDATE(K11,L11) -> 46583 | V11: =IF(AB11="","Cluster a definir : aucune regle ne correspond",IF(AA11="Incoherent","Attention, type de cluster incoherent",IF(AI11="OUI","OK",IF(AO11="OUI","Bascule sur le cluster de repli ("&AC11&")",IF(AC11<>"","Principal et repli tous deux pleins, cluster supplementaire a prevoir","Cluster principal plein, aucun repli defini, cluster supplementaire a prevoir"))))) -> Cluster principal plein, aucun repli defini, cluster supplementaire a prevoir | W11: =IF(E11="PRD","PROD","HORSPROD") -> PROD | X11: =IF(H11="O","JUMP CLV",IF(I11="O","JUMP AEP",N11)) -> JUMP CLV | Y11: =X11&"|"&F11&"|"&W11 -> JUMP CLV|N|PROD | Z11: =IFERROR(INDEX(tblClusters[Type (deduit)],MATCH(O11,tblClusters[Cluster],0)),"") -> Dedie | AA11: =IF(Z11="","",IF(P11=Z11,"OK","Incoherent")) -> OK | AB11: =IFERROR(INDEX(tblRegles[Cluster ROKS cible principal],MATCH(Y11,tblRegles[Cle de selection],0)),"") -> oc-JUMP-CLV-PRD | AC11: =IFERROR(IF(INDEX(tblRegles[Cluster de repli optionnel],MATCH(Y11,tblRegles[Cle de selection],0))=0,"",INDEX(tblRegles[Cluster de repli optionnel],MATCH(Y11,tblRegles[Cle de selection],0))),"") | AD11: =SUMIFS(tblApplications[CPU cible ROKS],tblApplications[Cluster ROKS cible (auto)],AB11,tblApplications[Mois de bascule prevu],"<"&K11) -> 0 | AE11: =SUMIFS(tblApplications[RAM cible ROKS],tblApplications[Cluster ROKS cible (auto)],AB11,tblApplications[Mois de bascule prevu],"<"&K11) -> 0 | AF11: =IFERROR(INDEX(tblClusters[CPU max (cores)],MATCH(AB11,tblClusters[Cluster],0)),0) -> 0 | AG11: =IFERROR(INDEX(tblClusters[RAM max (Go)],MATCH(AB11,tblClusters[Cluster],0)),0) -> 0 | AH11: =IFERROR(INDEX(tblClusters[Worker Count],MATCH(AB11,tblClusters[Cluster],0)),0) -> 0 | AI11: =IF(AB11="","NON",IF(AF11=0,"NON",IF(OR((AD11+S11)/AF11>=Clusters_ROKS!$AC$5,(AE11+T11)/AG11>=Clusters_ROKS!$AC$5,AH11>=Clusters_ROKS!$AC$6),"NON","OUI"))) -> NON | AJ11: =IF(AC11="",0,SUMIFS(tblApplications[CPU cible ROKS],tblApplications[Cluster ROKS cible (auto)],AC11,tblApplications[Mois de bascule prevu],"<"&K11)) -> 0 | AK11: =IF(AC11="",0,SUMIFS(tblApplications[RAM cible ROKS],tblApplications[Cluster ROKS cible (auto)],AC11,tblApplications[Mois de bascule prevu],"<"&K11)) -> 0 | AL11: =IF(AC11="",0,IFERROR(INDEX(tblClusters[CPU max (cores)],MATCH(AC11,tblClusters[Cluster],0)),0)) -> 0 | AM11: =IF(AC11="",0,IFERROR(INDEX(tblClusters[RAM max (Go)],MATCH(AC11,tblClusters[Cluster],0)),0)) -> 0 | AN11: =IF(AC11="",0,IFERROR(INDEX(tblClusters[Worker Count],MATCH(AC11,tblClusters[Cluster],0)),0)) -> 0 | AO11: =IF(AC11="","NON",IF(AL11=0,"NON",IF(OR((AJ11+S11)/AL11>=Clusters_ROKS!$AC$5,(AK11+T11)/AM11>=Clusters_ROKS!$AC$5,AN11>=Clusters_ROKS!$AC$6),"NON","OUI"))) -> NON
A12: App08 | B12: ns-app08 | C12: iks-npr-02 | D12: a migrer | E12: NPR | F12: N | G12: N | H12: N | I12: N | J12: 1 | K12: 46461 | L12: 1 | M12: O | N12: GIE France | O12: =IF(AB12="","Cluster a definir",IF(AI12="OUI",AB12,IF(AO12="OUI",AC12,AB12))) -> oc002i000578 | P12: =IF(OR(F12="O",G12="O",H12="O",I12="O"),"Dedie","Mutualise") -> Mutualise | Q12: =IFERROR(INDEX(tblDynatrace[CPU reel p95 (cores)],MATCH(A12,tblDynatrace[Application],0)),"") -> 2 | R12: =IFERROR(INDEX(tblDynatrace[RAM reelle p95 (Go)],MATCH(A12,tblDynatrace[Application],0)),"") -> 8 | S12: =IF(Q12="","",ROUNDUP(Q12*Tarifs_ABS!$C$9,0)*J12) -> 3 | T12: =IF(R12="","",ROUNDUP(R12*Tarifs_ABS!$C$9,0)*J12) -> 10 | U12: =EDATE(K12,L12) -> 46492 | V12: =IF(AB12="","Cluster a definir : aucune regle ne correspond",IF(AA12="Incoherent","Attention, type de cluster incoherent",IF(AI12="OUI","OK",IF(AO12="OUI","Bascule sur le cluster de repli ("&AC12&")",IF(AC12<>"","Principal et repli tous deux pleins, cluster supplementaire a prevoir","Cluster principal plein, aucun repli defini, cluster supplementaire a prevoir"))))) -> OK | W12: =IF(E12="PRD","PROD","HORSPROD") -> HORSPROD | X12: =IF(H12="O","JUMP CLV",IF(I12="O","JUMP AEP",N12)) -> GIE France | Y12: =X12&"|"&F12&"|"&W12 -> GIE France|N|HORSPROD | Z12: =IFERROR(INDEX(tblClusters[Type (deduit)],MATCH(O12,tblClusters[Cluster],0)),"") -> Mutualise | AA12: =IF(Z12="","",IF(P12=Z12,"OK","Incoherent")) -> OK | AB12: =IFERROR(INDEX(tblRegles[Cluster ROKS cible principal],MATCH(Y12,tblRegles[Cle de selection],0)),"") -> oc002i000578 | AC12: =IFERROR(IF(INDEX(tblRegles[Cluster de repli optionnel],MATCH(Y12,tblRegles[Cle de selection],0))=0,"",INDEX(tblRegles[Cluster de repli optionnel],MATCH(Y12,tblRegles[Cle de selection],0))),"") | AD12: =SUMIFS(tblApplications[CPU cible ROKS],tblApplications[Cluster ROKS cible (auto)],AB12,tblApplications[Mois de bascule prevu],"<"&K12) -> 6 | AE12: =SUMIFS(tblApplications[RAM cible ROKS],tblApplications[Cluster ROKS cible (auto)],AB12,tblApplications[Mois de bascule prevu],"<"&K12) -> 20 | AF12: =IFERROR(INDEX(tblClusters[CPU max (cores)],MATCH(AB12,tblClusters[Cluster],0)),0) -> 192 | AG12: =IFERROR(INDEX(tblClusters[RAM max (Go)],MATCH(AB12,tblClusters[Cluster],0)),0) -> 480 | AH12: =IFERROR(INDEX(tblClusters[Worker Count],MATCH(AB12,tblClusters[Cluster],0)),0) -> 6 | AI12: =IF(AB12="","NON",IF(AF12=0,"NON",IF(OR((AD12+S12)/AF12>=Clusters_ROKS!$AC$5,(AE12+T12)/AG12>=Clusters_ROKS!$AC$5,AH12>=Clusters_ROKS!$AC$6),"NON","OUI"))) -> OUI | AJ12: =IF(AC12="",0,SUMIFS(tblApplications[CPU cible ROKS],tblApplications[Cluster ROKS cible (auto)],AC12,tblApplications[Mois de bascule prevu],"<"&K12)) -> 0 | AK12: =IF(AC12="",0,SUMIFS(tblApplications[RAM cible ROKS],tblApplications[Cluster ROKS cible (auto)],AC12,tblApplications[Mois de bascule prevu],"<"&K12)) -> 0 | AL12: =IF(AC12="",0,IFERROR(INDEX(tblClusters[CPU max (cores)],MATCH(AC12,tblClusters[Cluster],0)),0)) -> 0 | AM12: =IF(AC12="",0,IFERROR(INDEX(tblClusters[RAM max (Go)],MATCH(AC12,tblClusters[Cluster],0)),0)) -> 0 | AN12: =IF(AC12="",0,IFERROR(INDEX(tblClusters[Worker Count],MATCH(AC12,tblClusters[Cluster],0)),0)) -> 0 | AO12: =IF(AC12="","NON",IF(AL12=0,"NON",IF(OR((AJ12+S12)/AL12>=Clusters_ROKS!$AC$5,(AK12+T12)/AM12>=Clusters_ROKS!$AC$5,AN12>=Clusters_ROKS!$AC$6),"NON","OUI"))) -> NON
A13: App09 | B13: ns-app09 | C13: iks-prod-03 | D13: migre | E13: PRD | F13: N | G13: N | H13: N | I13: O | J13: 2 | K13: 46371 | L13: 0 | M13: O | N13: GIE France | O13: =IF(AB13="","Cluster a definir",IF(AI13="OUI",AB13,IF(AO13="OUI",AC13,AB13))) -> oc-JUMP-AEP-PRD | P13: =IF(OR(F13="O",G13="O",H13="O",I13="O"),"Dedie","Mutualise") -> Dedie | Q13: =IFERROR(INDEX(tblDynatrace[CPU reel p95 (cores)],MATCH(A13,tblDynatrace[Application],0)),"") -> 5 | R13: =IFERROR(INDEX(tblDynatrace[RAM reelle p95 (Go)],MATCH(A13,tblDynatrace[Application],0)),"") -> 20 | S13: =IF(Q13="","",ROUNDUP(Q13*Tarifs_ABS!$C$9,0)*J13) -> 12 | T13: =IF(R13="","",ROUNDUP(R13*Tarifs_ABS!$C$9,0)*J13) -> 48 | U13: =EDATE(K13,L13) -> 46371 | V13: =IF(AB13="","Cluster a definir : aucune regle ne correspond",IF(AA13="Incoherent","Attention, type de cluster incoherent",IF(AI13="OUI","OK",IF(AO13="OUI","Bascule sur le cluster de repli ("&AC13&")",IF(AC13<>"","Principal et repli tous deux pleins, cluster supplementaire a prevoir","Cluster principal plein, aucun repli defini, cluster supplementaire a prevoir"))))) -> Cluster principal plein, aucun repli defini, cluster supplementaire a prevoir | W13: =IF(E13="PRD","PROD","HORSPROD") -> PROD | X13: =IF(H13="O","JUMP CLV",IF(I13="O","JUMP AEP",N13)) -> JUMP AEP | Y13: =X13&"|"&F13&"|"&W13 -> JUMP AEP|N|PROD | Z13: =IFERROR(INDEX(tblClusters[Type (deduit)],MATCH(O13,tblClusters[Cluster],0)),"") -> Dedie | AA13: =IF(Z13="","",IF(P13=Z13,"OK","Incoherent")) -> OK | AB13: =IFERROR(INDEX(tblRegles[Cluster ROKS cible principal],MATCH(Y13,tblRegles[Cle de selection],0)),"") -> oc-JUMP-AEP-PRD | AC13: =IFERROR(IF(INDEX(tblRegles[Cluster de repli optionnel],MATCH(Y13,tblRegles[Cle de selection],0))=0,"",INDEX(tblRegles[Cluster de repli optionnel],MATCH(Y13,tblRegles[Cle de selection],0))),"") | AD13: =SUMIFS(tblApplications[CPU cible ROKS],tblApplications[Cluster ROKS cible (auto)],AB13,tblApplications[Mois de bascule prevu],"<"&K13) -> 0 | AE13: =SUMIFS(tblApplications[RAM cible ROKS],tblApplications[Cluster ROKS cible (auto)],AB13,tblApplications[Mois de bascule prevu],"<"&K13) -> 0 | AF13: =IFERROR(INDEX(tblClusters[CPU max (cores)],MATCH(AB13,tblClusters[Cluster],0)),0) -> 0 | AG13: =IFERROR(INDEX(tblClusters[RAM max (Go)],MATCH(AB13,tblClusters[Cluster],0)),0) -> 0 | AH13: =IFERROR(INDEX(tblClusters[Worker Count],MATCH(AB13,tblClusters[Cluster],0)),0) -> 0 | AI13: =IF(AB13="","NON",IF(AF13=0,"NON",IF(OR((AD13+S13)/AF13>=Clusters_ROKS!$AC$5,(AE13+T13)/AG13>=Clusters_ROKS!$AC$5,AH13>=Clusters_ROKS!$AC$6),"NON","OUI"))) -> NON | AJ13: =IF(AC13="",0,SUMIFS(tblApplications[CPU cible ROKS],tblApplications[Cluster ROKS cible (auto)],AC13,tblApplications[Mois de bascule prevu],"<"&K13)) -> 0 | AK13: =IF(AC13="",0,SUMIFS(tblApplications[RAM cible ROKS],tblApplications[Cluster ROKS cible (auto)],AC13,tblApplications[Mois de bascule prevu],"<"&K13)) -> 0 | AL13: =IF(AC13="",0,IFERROR(INDEX(tblClusters[CPU max (cores)],MATCH(AC13,tblClusters[Cluster],0)),0)) -> 0 | AM13: =IF(AC13="",0,IFERROR(INDEX(tblClusters[RAM max (Go)],MATCH(AC13,tblClusters[Cluster],0)),0)) -> 0 | AN13: =IF(AC13="",0,IFERROR(INDEX(tblClusters[Worker Count],MATCH(AC13,tblClusters[Cluster],0)),0)) -> 0 | AO13: =IF(AC13="","NON",IF(AL13=0,"NON",IF(OR((AJ13+S13)/AL13>=Clusters_ROKS!$AC$5,(AK13+T13)/AM13>=Clusters_ROKS!$AC$5,AN13>=Clusters_ROKS!$AC$6),"NON","OUI"))) -> NON
A14: App10 | B14: ns-app10 | C14: iks-npr-02 | D14: a migrer | E14: NPR | F14: N | G14: N | H14: N | I14: N | J14: 2 | K14: 46553 | L14: 1 | M14: O | N14: GIE France | O14: =IF(AB14="","Cluster a definir",IF(AI14="OUI",AB14,IF(AO14="OUI",AC14,AB14))) -> oc002i000578 | P14: =IF(OR(F14="O",G14="O",H14="O",I14="O"),"Dedie","Mutualise") -> Mutualise | Q14: =IFERROR(INDEX(tblDynatrace[CPU reel p95 (cores)],MATCH(A14,tblDynatrace[Application],0)),"") -> 4 | R14: =IFERROR(INDEX(tblDynatrace[RAM reelle p95 (Go)],MATCH(A14,tblDynatrace[Application],0)),"") -> 16 | S14: =IF(Q14="","",ROUNDUP(Q14*Tarifs_ABS!$C$9,0)*J14) -> 10 | T14: =IF(R14="","",ROUNDUP(R14*Tarifs_ABS!$C$9,0)*J14) -> 40 | U14: =EDATE(K14,L14) -> 46583 | V14: =IF(AB14="","Cluster a definir : aucune regle ne correspond",IF(AA14="Incoherent","Attention, type de cluster incoherent",IF(AI14="OUI","OK",IF(AO14="OUI","Bascule sur le cluster de repli ("&AC14&")",IF(AC14<>"","Principal et repli tous deux pleins, cluster supplementaire a prevoir","Cluster principal plein, aucun repli defini, cluster supplementaire a prevoir"))))) -> OK | W14: =IF(E14="PRD","PROD","HORSPROD") -> HORSPROD | X14: =IF(H14="O","JUMP CLV",IF(I14="O","JUMP AEP",N14)) -> GIE France | Y14: =X14&"|"&F14&"|"&W14 -> GIE France|N|HORSPROD | Z14: =IFERROR(INDEX(tblClusters[Type (deduit)],MATCH(O14,tblClusters[Cluster],0)),"") -> Mutualise | AA14: =IF(Z14="","",IF(P14=Z14,"OK","Incoherent")) -> OK | AB14: =IFERROR(INDEX(tblRegles[Cluster ROKS cible principal],MATCH(Y14,tblRegles[Cle de selection],0)),"") -> oc002i000578 | AC14: =IFERROR(IF(INDEX(tblRegles[Cluster de repli optionnel],MATCH(Y14,tblRegles[Cle de selection],0))=0,"",INDEX(tblRegles[Cluster de repli optionnel],MATCH(Y14,tblRegles[Cle de selection],0))),"") | AD14: =SUMIFS(tblApplications[CPU cible ROKS],tblApplications[Cluster ROKS cible (auto)],AB14,tblApplications[Mois de bascule prevu],"<"&K14) -> 9 | AE14: =SUMIFS(tblApplications[RAM cible ROKS],tblApplications[Cluster ROKS cible (auto)],AB14,tblApplications[Mois de bascule prevu],"<"&K14) -> 30 | AF14: =IFERROR(INDEX(tblClusters[CPU max (cores)],MATCH(AB14,tblClusters[Cluster],0)),0) -> 192 | AG14: =IFERROR(INDEX(tblClusters[RAM max (Go)],MATCH(AB14,tblClusters[Cluster],0)),0) -> 480 | AH14: =IFERROR(INDEX(tblClusters[Worker Count],MATCH(AB14,tblClusters[Cluster],0)),0) -> 6 | AI14: =IF(AB14="","NON",IF(AF14=0,"NON",IF(OR((AD14+S14)/AF14>=Clusters_ROKS!$AC$5,(AE14+T14)/AG14>=Clusters_ROKS!$AC$5,AH14>=Clusters_ROKS!$AC$6),"NON","OUI"))) -> OUI | AJ14: =IF(AC14="",0,SUMIFS(tblApplications[CPU cible ROKS],tblApplications[Cluster ROKS cible (auto)],AC14,tblApplications[Mois de bascule prevu],"<"&K14)) -> 0 | AK14: =IF(AC14="",0,SUMIFS(tblApplications[RAM cible ROKS],tblApplications[Cluster ROKS cible (auto)],AC14,tblApplications[Mois de bascule prevu],"<"&K14)) -> 0 | AL14: =IF(AC14="",0,IFERROR(INDEX(tblClusters[CPU max (cores)],MATCH(AC14,tblClusters[Cluster],0)),0)) -> 0 | AM14: =IF(AC14="",0,IFERROR(INDEX(tblClusters[RAM max (Go)],MATCH(AC14,tblClusters[Cluster],0)),0)) -> 0 | AN14: =IF(AC14="",0,IFERROR(INDEX(tblClusters[Worker Count],MATCH(AC14,tblClusters[Cluster],0)),0)) -> 0 | AO14: =IF(AC14="","NON",IF(AL14=0,"NON",IF(OR((AJ14+S14)/AL14>=Clusters_ROKS!$AC$5,(AK14+T14)/AM14>=Clusters_ROKS!$AC$5,AN14>=Clusters_ROKS!$AC$6),"NON","OUI"))) -> NON
A16: Le CPU/RAM cible additionne tous les replicas du service : (P95 par replica x coefficient, arrondi) x nombre de replicas. Le cluster ROKS cible se déduit automatiquement de la région, des données secrètes et de l'environnement (l'isolement fort et le volume important priment et orientent vers Jump CLV / Jump AEP). Tant que le cluster principal a de la place, il continue d'être choisi ; au delà, la sélection bascule sur le cluster de repli si disponible. La colonne Statut résume tout en une phrase. Le détail du calcul est dans le bloc replié à droite.

Sheet Projection_Clusters
A1: Capacity planning, mois par mois et cluster par cluster
A2: Charge existante + migrations cumulées, taux d'occupation et workers à commander en plus, par cluster et par mois
A4: Mois | B4: Cluster | C4: Utilisation | D4: Type | E4: CPU max (cores) | F4: RAM max (Go) | G4: Charge existante CPU | H4: Charge existante RAM | I4: Nouvelles migrations CPU cumulees | J4: Nouvelles migrations RAM cumulees | K4: Charge projetee CPU | L4: Charge projetee RAM | M4: Taux CPU | N4: Taux RAM | O4: Statut | P4: Capacite CPU a ajouter | Q4: Capacite RAM a ajouter | R4: Workers supplementaires necessaires
A5: 46388 | B5: oc002i000577 | C5: =IFERROR(INDEX(tblClusters[Utilisation],MATCH($B5,tblClusters[Cluster],0)),"") -> Mutualise GIE France | D5: =IFERROR(INDEX(tblClusters[Type (deduit)],MATCH($B5,tblClusters[Cluster],0)),"") -> Mutualise | E5: =IFERROR(INDEX(tblClusters[CPU max (cores)],MATCH($B5,tblClusters[Cluster],0)),0) -> 48 | F5: =IFERROR(INDEX(tblClusters[RAM max (Go)],MATCH($B5,tblClusters[Cluster],0)),0) -> 240 | G5: =IFERROR(INDEX(tblClusters[Charge existante CPU hors migration],MATCH($B5,tblClusters[Cluster],0)),0) -> 0 | H5: =IFERROR(INDEX(tblClusters[Charge existante RAM hors migration (Go)],MATCH($B5,tblClusters[Cluster],0)),0) -> 0 | I5: =SUMIFS(tblApplications[CPU cible ROKS],tblApplications[Cluster ROKS cible (auto)],$B5,tblApplications[Mois de bascule prevu],"<="&EOMONTH($A5,0),tblApplications[Inclus projection O/N],"O") -> 10 | J5: =SUMIFS(tblApplications[RAM cible ROKS],tblApplications[Cluster ROKS cible (auto)],$B5,tblApplications[Mois de bascule prevu],"<="&EOMONTH($A5,0),tblApplications[Inclus projection O/N],"O") -> 40 | K5: =G5+I5 -> 10 | L5: =H5+J5 -> 40 | M5: =IF(E5=0,"",K5/E5) -> 0.20833333 | N5: =IF(F5=0,"",L5/F5) -> 0.16666667 | O5: =IF(E5=0,IF(K5>0,"Cluster sans capacite provisionnee","n/a"),IF(OR(M5>=Clusters_ROKS!$AC$5,N5>=Clusters_ROKS!$AC$5),"Seuil depasse","OK")) -> OK | P5: =MAX(0,K5-E5) -> 0 | Q5: =MAX(0,L5-F5) -> 0 | R5: =IF(AND(P5=0,Q5=0),0,IFERROR(MAX(ROUNDUP(P5/INDEX(tblClusters[vCPU / noeud (deduit)],MATCH($B5,tblClusters[Cluster],0)),0),ROUNDUP(Q5/INDEX(tblClusters[RAM / noeud - Go (deduit)],MATCH($B5,tblClusters[Cluster],0)),0)),"Flavor a definir")) -> 0
A6: 46419 | B6: oc002i000577 | C6: =IFERROR(INDEX(tblClusters[Utilisation],MATCH($B6,tblClusters[Cluster],0)),"") -> Mutualise GIE France | D6: =IFERROR(INDEX(tblClusters[Type (deduit)],MATCH($B6,tblClusters[Cluster],0)),"") -> Mutualise | E6: =IFERROR(INDEX(tblClusters[CPU max (cores)],MATCH($B6,tblClusters[Cluster],0)),0) -> 48 | F6: =IFERROR(INDEX(tblClusters[RAM max (Go)],MATCH($B6,tblClusters[Cluster],0)),0) -> 240 | G6: =IFERROR(INDEX(tblClusters[Charge existante CPU hors migration],MATCH($B6,tblClusters[Cluster],0)),0) -> 0 | H6: =IFERROR(INDEX(tblClusters[Charge existante RAM hors migration (Go)],MATCH($B6,tblClusters[Cluster],0)),0) -> 0 | I6: =SUMIFS(tblApplications[CPU cible ROKS],tblApplications[Cluster ROKS cible (auto)],$B6,tblApplications[Mois de bascule prevu],"<="&EOMONTH($A6,0),tblApplications[Inclus projection O/N],"O") -> 16 | J6: =SUMIFS(tblApplications[RAM cible ROKS],tblApplications[Cluster ROKS cible (auto)],$B6,tblApplications[Mois de bascule prevu],"<="&EOMONTH($A6,0),tblApplications[Inclus projection O/N],"O") -> 60 | K6: =G6+I6 -> 16 | L6: =H6+J6 -> 60 | M6: =IF(E6=0,"",K6/E6) -> 0.33333333 | N6: =IF(F6=0,"",L6/F6) -> 0.25 | O6: =IF(E6=0,IF(K6>0,"Cluster sans capacite provisionnee","n/a"),IF(OR(M6>=Clusters_ROKS!$AC$5,N6>=Clusters_ROKS!$AC$5),"Seuil depasse","OK")) -> OK | P6: =MAX(0,K6-E6) -> 0 | Q6: =MAX(0,L6-F6) -> 0 | R6: =IF(AND(P6=0,Q6=0),0,IFERROR(MAX(ROUNDUP(P6/INDEX(tblClusters[vCPU / noeud (deduit)],MATCH($B6,tblClusters[Cluster],0)),0),ROUNDUP(Q6/INDEX(tblClusters[RAM / noeud - Go (deduit)],MATCH($B6,tblClusters[Cluster],0)),0)),"Flavor a definir")) -> 0
A7: 46447 | B7: oc002i000577 | C7: =IFERROR(INDEX(tblClusters[Utilisation],MATCH($B7,tblClusters[Cluster],0)),"") -> Mutualise GIE France | D7: =IFERROR(INDEX(tblClusters[Type (deduit)],MATCH($B7,tblClusters[Cluster],0)),"") -> Mutualise | E7: =IFERROR(INDEX(tblClusters[CPU max (cores)],MATCH($B7,tblClusters[Cluster],0)),0) -> 48 | F7: =IFERROR(INDEX(tblClusters[RAM max (Go)],MATCH($B7,tblClusters[Cluster],0)),0) -> 240 | G7: =IFERROR(INDEX(tblClusters[Charge existante CPU hors migration],MATCH($B7,tblClusters[Cluster],0)),0) -> 0 | H7: =IFERROR(INDEX(tblClusters[Charge existante RAM hors migration (Go)],MATCH($B7,tblClusters[Cluster],0)),0) -> 0 | I7: =SUMIFS(tblApplications[CPU cible ROKS],tblApplications[Cluster ROKS cible (auto)],$B7,tblApplications[Mois de bascule prevu],"<="&EOMONTH($A7,0),tblApplications[Inclus projection O/N],"O") -> 16 | J7: =SUMIFS(tblApplications[RAM cible ROKS],tblApplications[Cluster ROKS cible (auto)],$B7,tblApplications[Mois de bascule prevu],"<="&EOMONTH($A7,0),tblApplications[Inclus projection O/N],"O") -> 60 | K7: =G7+I7 -> 16 | L7: =H7+J7 -> 60 | M7: =IF(E7=0,"",K7/E7) -> 0.33333333 | N7: =IF(F7=0,"",L7/F7) -> 0.25 | O7: =IF(E7=0,IF(K7>0,"Cluster sans capacite provisionnee","n/a"),IF(OR(M7>=Clusters_ROKS!$AC$5,N7>=Clusters_ROKS!$AC$5),"Seuil depasse","OK")) -> OK | P7: =MAX(0,K7-E7) -> 0 | Q7: =MAX(0,L7-F7) -> 0 | R7: =IF(AND(P7=0,Q7=0),0,IFERROR(MAX(ROUNDUP(P7/INDEX(tblClusters[vCPU / noeud (deduit)],MATCH($B7,tblClusters[Cluster],0)),0),ROUNDUP(Q7/INDEX(tblClusters[RAM / noeud - Go (deduit)],MATCH($B7,tblClusters[Cluster],0)),0)),"Flavor a definir")) -> 0
A8: 46478 | B8: oc002i000577 | C8: =IFERROR(INDEX(tblClusters[Utilisation],MATCH($B8,tblClusters[Cluster],0)),"") -> Mutualise GIE France | D8: =IFERROR(INDEX(tblClusters[Type (deduit)],MATCH($B8,tblClusters[Cluster],0)),"") -> Mutualise | E8: =IFERROR(INDEX(tblClusters[CPU max (cores)],MATCH($B8,tblClusters[Cluster],0)),0) -> 48 | F8: =IFERROR(INDEX(tblClusters[RAM max (Go)],MATCH($B8,tblClusters[Cluster],0)),0) -> 240 | G8: =IFERROR(INDEX(tblClusters[Charge existante CPU hors migration],MATCH($B8,tblClusters[Cluster],0)),0) -> 0 | H8: =IFERROR(INDEX(tblClusters[Charge existante RAM hors migration (Go)],MATCH($B8,tblClusters[Cluster],0)),0) -> 0 | I8: =SUMIFS(tblApplications[CPU cible ROKS],tblApplications[Cluster ROKS cible (auto)],$B8,tblApplications[Mois de bascule prevu],"<="&EOMONTH($A8,0),tblApplications[Inclus projection O/N],"O") -> 16 | J8: =SUMIFS(tblApplications[RAM cible ROKS],tblApplications[Cluster ROKS cible (auto)],$B8,tblApplications[Mois de bascule prevu],"<="&EOMONTH($A8,0),tblApplications[Inclus projection O/N],"O") -> 60 | K8: =G8+I8 -> 16 | L8: =H8+J8 -> 60 | M8: =IF(E8=0,"",K8/E8) -> 0.33333333 | N8: =IF(F8=0,"",L8/F8) -> 0.25 | O8: =IF(E8=0,IF(K8>0,"Cluster sans capacite provisionnee","n/a"),IF(OR(M8>=Clusters_ROKS!$AC$5,N8>=Clusters_ROKS!$AC$5),"Seuil depasse","OK")) -> OK | P8: =MAX(0,K8-E8) -> 0 | Q8: =MAX(0,L8-F8) -> 0 | R8: =IF(AND(P8=0,Q8=0),0,IFERROR(MAX(ROUNDUP(P8/INDEX(tblClusters[vCPU / noeud (deduit)],MATCH($B8,tblClusters[Cluster],0)),0),ROUNDUP(Q8/INDEX(tblClusters[RAM / noeud - Go (deduit)],MATCH($B8,tblClusters[Cluster],0)),0)),"Flavor a definir")) -> 0
A9: 46508 | B9: oc002i000577 | C9: =IFERROR(INDEX(tblClusters[Utilisation],MATCH($B9,tblClusters[Cluster],0)),"") -> Mutualise GIE France | D9: =IFERROR(INDEX(tblClusters[Type (deduit)],MATCH($B9,tblClusters[Cluster],0)),"") -> Mutualise | E9: =IFERROR(INDEX(tblClusters[CPU max (cores)],MATCH($B9,tblClusters[Cluster],0)),0) -> 48 | F9: =IFERROR(INDEX(tblClusters[RAM max (Go)],MATCH($B9,tblClusters[Cluster],0)),0) -> 240 | G9: =IFERROR(INDEX(tblClusters[Charge existante CPU hors migration],MATCH($B9,tblClusters[Cluster],0)),0) -> 0 | H9: =IFERROR(INDEX(tblClusters[Charge existante RAM hors migration (Go)],MATCH($B9,tblClusters[Cluster],0)),0) -> 0 | I9: =SUMIFS(tblApplications[CPU cible ROKS],tblApplications[Cluster ROKS cible (auto)],$B9,tblApplications[Mois de bascule prevu],"<="&EOMONTH($A9,0),tblApplications[Inclus projection O/N],"O") -> 16 | J9: =SUMIFS(tblApplications[RAM cible ROKS],tblApplications[Cluster ROKS cible (auto)],$B9,tblApplications[Mois de bascule prevu],"<="&EOMONTH($A9,0),tblApplications[Inclus projection O/N],"O") -> 60 | K9: =G9+I9 -> 16 | L9: =H9+J9 -> 60 | M9: =IF(E9=0,"",K9/E9) -> 0.33333333 | N9: =IF(F9=0,"",L9/F9) -> 0.25 | O9: =IF(E9=0,IF(K9>0,"Cluster sans capacite provisionnee","n/a"),IF(OR(M9>=Clusters_ROKS!$AC$5,N9>=Clusters_ROKS!$AC$5),"Seuil depasse","OK")) -> OK | P9: =MAX(0,K9-E9) -> 0 | Q9: =MAX(0,L9-F9) -> 0 | R9: =IF(AND(P9=0,Q9=0),0,IFERROR(MAX(ROUNDUP(P9/INDEX(tblClusters[vCPU / noeud (deduit)],MATCH($B9,tblClusters[Cluster],0)),0),ROUNDUP(Q9/INDEX(tblClusters[RAM / noeud - Go (deduit)],MATCH($B9,tblClusters[Cluster],0)),0)),"Flavor a definir")) -> 0
A10: 46539 | B10: oc002i000577 | C10: =IFERROR(INDEX(tblClusters[Utilisation],MATCH($B10,tblClusters[Cluster],0)),"") -> Mutualise GIE France | D10: =IFERROR(INDEX(tblClusters[Type (deduit)],MATCH($B10,tblClusters[Cluster],0)),"") -> Mutualise | E10: =IFERROR(INDEX(tblClusters[CPU max (cores)],MATCH($B10,tblClusters[Cluster],0)),0) -> 48 | F10: =IFERROR(INDEX(tblClusters[RAM max (Go)],MATCH($B10,tblClusters[Cluster],0)),0) -> 240 | G10: =IFERROR(INDEX(tblClusters[Charge existante CPU hors migration],MATCH($B10,tblClusters[Cluster],0)),0) -> 0 | H10: =IFERROR(INDEX(tblClusters[Charge existante RAM hors migration (Go)],MATCH($B10,tblClusters[Cluster],0)),0) -> 0 | I10: =SUMIFS(tblApplications[CPU cible ROKS],tblApplications[Cluster ROKS cible (auto)],$B10,tblApplications[Mois de bascule prevu],"<="&EOMONTH($A10,0),tblApplications[Inclus projection O/N],"O") -> 16 | J10: =SUMIFS(tblApplications[RAM cible ROKS],tblApplications[Cluster ROKS cible (auto)],$B10,tblApplications[Mois de bascule prevu],"<="&EOMONTH($A10,0),tblApplications[Inclus projection O/N],"O") -> 60 | K10: =G10+I10 -> 16 | L10: =H10+J10 -> 60 | M10: =IF(E10=0,"",K10/E10) -> 0.33333333 | N10: =IF(F10=0,"",L10/F10) -> 0.25 | O10: =IF(E10=0,IF(K10>0,"Cluster sans capacite provisionnee","n/a"),IF(OR(M10>=Clusters_ROKS!$AC$5,N10>=Clusters_ROKS!$AC$5),"Seuil depasse","OK")) -> OK | P10: =MAX(0,K10-E10) -> 0 | Q10: =MAX(0,L10-F10) -> 0 | R10: =IF(AND(P10=0,Q10=0),0,IFERROR(MAX(ROUNDUP(P10/INDEX(tblClusters[vCPU / noeud (deduit)],MATCH($B10,tblClusters[Cluster],0)),0),ROUNDUP(Q10/INDEX(tblClusters[RAM / noeud - Go (deduit)],MATCH($B10,tblClusters[Cluster],0)),0)),"Flavor a definir")) -> 0
A11: 46569 | B11: oc002i000577 | C11: =IFERROR(INDEX(tblClusters[Utilisation],MATCH($B11,tblClusters[Cluster],0)),"") -> Mutualise GIE France | D11: =IFERROR(INDEX(tblClusters[Type (deduit)],MATCH($B11,tblClusters[Cluster],0)),"") -> Mutualise | E11: =IFERROR(INDEX(tblClusters[CPU max (cores)],MATCH($B11,tblClusters[Cluster],0)),0) -> 48 | F11: =IFERROR(INDEX(tblClusters[RAM max (Go)],MATCH($B11,tblClusters[Cluster],0)),0) -> 240 | G11: =IFERROR(INDEX(tblClusters[Charge existante CPU hors migration],MATCH($B11,tblClusters[Cluster],0)),0) -> 0 | H11: =IFERROR(INDEX(tblClusters[Charge existante RAM hors migration (Go)],MATCH($B11,tblClusters[Cluster],0)),0) -> 0 | I11: =SUMIFS(tblApplications[CPU cible ROKS],tblApplications[Cluster ROKS cible (auto)],$B11,tblApplications[Mois de bascule prevu],"<="&EOMONTH($A11,0),tblApplications[Inclus projection O/N],"O") -> 16 | J11: =SUMIFS(tblApplications[RAM cible ROKS],tblApplications[Cluster ROKS cible (auto)],$B11,tblApplications[Mois de bascule prevu],"<="&EOMONTH($A11,0),tblApplications[Inclus projection O/N],"O") -> 60 | K11: =G11+I11 -> 16 | L11: =H11+J11 -> 60 | M11: =IF(E11=0,"",K11/E11) -> 0.33333333 | N11: =IF(F11=0,"",L11/F11) -> 0.25 | O11: =IF(E11=0,IF(K11>0,"Cluster sans capacite provisionnee","n/a"),IF(OR(M11>=Clusters_ROKS!$AC$5,N11>=Clusters_ROKS!$AC$5),"Seuil depasse","OK")) -> OK | P11: =MAX(0,K11-E11) -> 0 | Q11: =MAX(0,L11-F11) -> 0 | R11: =IF(AND(P11=0,Q11=0),0,IFERROR(MAX(ROUNDUP(P11/INDEX(tblClusters[vCPU / noeud (deduit)],MATCH($B11,tblClusters[Cluster],0)),0),ROUNDUP(Q11/INDEX(tblClusters[RAM / noeud - Go (deduit)],MATCH($B11,tblClusters[Cluster],0)),0)),"Flavor a definir")) -> 0
A12: 46600 | B12: oc002i000577 | C12: =IFERROR(INDEX(tblClusters[Utilisation],MATCH($B12,tblClusters[Cluster],0)),"") -> Mutualise GIE France | D12: =IFERROR(INDEX(tblClusters[Type (deduit)],MATCH($B12,tblClusters[Cluster],0)),"") -> Mutualise | E12: =IFERROR(INDEX(tblClusters[CPU max (cores)],MATCH($B12,tblClusters[Cluster],0)),0) -> 48 | F12: =IFERROR(INDEX(tblClusters[RAM max (Go)],MATCH($B12,tblClusters[Cluster],0)),0) -> 240 | G12: =IFERROR(INDEX(tblClusters[Charge existante CPU hors migration],MATCH($B12,tblClusters[Cluster],0)),0) -> 0 | H12: =IFERROR(INDEX(tblClusters[Charge existante RAM hors migration (Go)],MATCH($B12,tblClusters[Cluster],0)),0) -> 0 | I12: =SUMIFS(tblApplications[CPU cible ROKS],tblApplications[Cluster ROKS cible (auto)],$B12,tblApplications[Mois de bascule prevu],"<="&EOMONTH($A12,0),tblApplications[Inclus projection O/N],"O") -> 16 | J12: =SUMIFS(tblApplications[RAM cible ROKS],tblApplications[Cluster ROKS cible (auto)],$B12,tblApplications[Mois de bascule prevu],"<="&EOMONTH($A12,0),tblApplications[Inclus projection O/N],"O") -> 60 | K12: =G12+I12 -> 16 | L12: =H12+J12 -> 60 | M12: =IF(E12=0,"",K12/E12) -> 0.33333333 | N12: =IF(F12=0,"",L12/F12) -> 0.25 | O12: =IF(E12=0,IF(K12>0,"Cluster sans capacite provisionnee","n/a"),IF(OR(M12>=Clusters_ROKS!$AC$5,N12>=Clusters_ROKS!$AC$5),"Seuil depasse","OK")) -> OK | P12: =MAX(0,K12-E12) -> 0 | Q12: =MAX(0,L12-F12) -> 0 | R12: =IF(AND(P12=0,Q12=0),0,IFERROR(MAX(ROUNDUP(P12/INDEX(tblClusters[vCPU / noeud (deduit)],MATCH($B12,tblClusters[Cluster],0)),0),ROUNDUP(Q12/INDEX(tblClusters[RAM / noeud - Go (deduit)],MATCH($B12,tblClusters[Cluster],0)),0)),"Flavor a definir")) -> 0
A13: 46631 | B13: oc002i000577 | C13: =IFERROR(INDEX(tblClusters[Utilisation],MATCH($B13,tblClusters[Cluster],0)),"") -> Mutualise GIE France | D13: =IFERROR(INDEX(tblClusters[Type (deduit)],MATCH($B13,tblClusters[Cluster],0)),"") -> Mutualise | E13: =IFERROR(INDEX(tblClusters[CPU max (cores)],MATCH($B13,tblClusters[Cluster],0)),0) -> 48 | F13: =IFERROR(INDEX(tblClusters[RAM max (Go)],MATCH($B13,tblClusters[Cluster],0)),0) -> 240 | G13: =IFERROR(INDEX(tblClusters[Charge existante CPU hors migration],MATCH($B13,tblClusters[Cluster],0)),0) -> 0 | H13: =IFERROR(INDEX(tblClusters[Charge existante RAM hors migration (Go)],MATCH($B13,tblClusters[Cluster],0)),0) -> 0 | I13: =SUMIFS(tblApplications[CPU cible ROKS],tblApplications[Cluster ROKS cible (auto)],$B13,tblApplications[Mois de bascule prevu],"<="&EOMONTH($A13,0),tblApplications[Inclus projection O/N],"O") -> 16 | J13: =SUMIFS(tblApplications[RAM cible ROKS],tblApplications[Cluster ROKS cible (auto)],$B13,tblApplications[Mois de bascule prevu],"<="&EOMONTH($A13,0),tblApplications[Inclus projection O/N],"O") -> 60 | K13: =G13+I13 -> 16 | L13: =H13+J13 -> 60 | M13: =IF(E13=0,"",K13/E13) -> 0.33333333 | N13: =IF(F13=0,"",L13/F13) -> 0.25 | O13: =IF(E13=0,IF(K13>0,"Cluster sans capacite provisionnee","n/a"),IF(OR(M13>=Clusters_ROKS!$AC$5,N13>=Clusters_ROKS!$AC$5),"Seuil depasse","OK")) -> OK | P13: =MAX(0,K13-E13) -> 0 | Q13: =MAX(0,L13-F13) -> 0 | R13: =IF(AND(P13=0,Q13=0),0,IFERROR(MAX(ROUNDUP(P13/INDEX(tblClusters[vCPU / noeud (deduit)],MATCH($B13,tblClusters[Cluster],0)),0),ROUNDUP(Q13/INDEX(tblClusters[RAM / noeud - Go (deduit)],MATCH($B13,tblClusters[Cluster],0)),0)),"Flavor a definir")) -> 0
A14: 46661 | B14: oc002i000577 | C14: =IFERROR(INDEX(tblClusters[Utilisation],MATCH($B14,tblClusters[Cluster],0)),"") -> Mutualise GIE France | D14: =IFERROR(INDEX(tblClusters[Type (deduit)],MATCH($B14,tblClusters[Cluster],0)),"") -> Mutualise | E14: =IFERROR(INDEX(tblClusters[CPU max (cores)],MATCH($B14,tblClusters[Cluster],0)),0) -> 48 | F14: =IFERROR(INDEX(tblClusters[RAM max (Go)],MATCH($B14,tblClusters[Cluster],0)),0) -> 240 | G14: =IFERROR(INDEX(tblClusters[Charge existante CPU hors migration],MATCH($B14,tblClusters[Cluster],0)),0) -> 0 | H14: =IFERROR(INDEX(tblClusters[Charge existante RAM hors migration (Go)],MATCH($B14,tblClusters[Cluster],0)),0) -> 0 | I14: =SUMIFS(tblApplications[CPU cible ROKS],tblApplications[Cluster ROKS cible (auto)],$B14,tblApplications[Mois de bascule prevu],"<="&EOMONTH($A14,0),tblApplications[Inclus projection O/N],"O") -> 16 | J14: =SUMIFS(tblApplications[RAM cible ROKS],tblApplications[Cluster ROKS cible (auto)],$B14,tblApplications[Mois de bascule prevu],"<="&EOMONTH($A14,0),tblApplications[Inclus projection O/N],"O") -> 60 | K14: =G14+I14 -> 16 | L14: =H14+J14 -> 60 | M14: =IF(E14=0,"",K14/E14) -> 0.33333333 | N14: =IF(F14=0,"",L14/F14) -> 0.25 | O14: =IF(E14=0,IF(K14>0,"Cluster sans capacite provisionnee","n/a"),IF(OR(M14>=Clusters_ROKS!$AC$5,N14>=Clusters_ROKS!$AC$5),"Seuil depasse","OK")) -> OK | P14: =MAX(0,K14-E14) -> 0 | Q14: =MAX(0,L14-F14) -> 0 | R14: =IF(AND(P14=0,Q14=0),0,IFERROR(MAX(ROUNDUP(P14/INDEX(tblClusters[vCPU / noeud (deduit)],MATCH($B14,tblClusters[Cluster],0)),0),ROUNDUP(Q14/INDEX(tblClusters[RAM / noeud - Go (deduit)],MATCH($B14,tblClusters[Cluster],0)),0)),"Flavor a definir")) -> 0
A15: 46692 | B15: oc002i000577 | C15: =IFERROR(INDEX(tblClusters[Utilisation],MATCH($B15,tblClusters[Cluster],0)),"") -> Mutualise GIE France | D15: =IFERROR(INDEX(tblClusters[Type (deduit)],MATCH($B15,tblClusters[Cluster],0)),"") -> Mutualise | E15: =IFERROR(INDEX(tblClusters[CPU max (cores)],MATCH($B15,tblClusters[Cluster],0)),0) -> 48 | F15: =IFERROR(INDEX(tblClusters[RAM max (Go)],MATCH($B15,tblClusters[Cluster],0)),0) -> 240 | G15: =IFERROR(INDEX(tblClusters[Charge existante CPU hors migration],MATCH($B15,tblClusters[Cluster],0)),0) -> 0 | H15: =IFERROR(INDEX(tblClusters[Charge existante RAM hors migration (Go)],MATCH($B15,tblClusters[Cluster],0)),0) -> 0 | I15: =SUMIFS(tblApplications[CPU cible ROKS],tblApplications[Cluster ROKS cible (auto)],$B15,tblApplications[Mois de bascule prevu],"<="&EOMONTH($A15,0),tblApplications[Inclus projection O/N],"O") -> 16 | J15: =SUMIFS(tblApplications[RAM cible ROKS],tblApplications[Cluster ROKS cible (auto)],$B15,tblApplications[Mois de bascule prevu],"<="&EOMONTH($A15,0),tblApplications[Inclus projection O/N],"O") -> 60 | K15: =G15+I15 -> 16 | L15: =H15+J15 -> 60 | M15: =IF(E15=0,"",K15/E15) -> 0.33333333 | N15: =IF(F15=0,"",L15/F15) -> 0.25 | O15: =IF(E15=0,IF(K15>0,"Cluster sans capacite provisionnee","n/a"),IF(OR(M15>=Clusters_ROKS!$AC$5,N15>=Clusters_ROKS!$AC$5),"Seuil depasse","OK")) -> OK | P15: =MAX(0,K15-E15) -> 0 | Q15: =MAX(0,L15-F15) -> 0 | R15: =IF(AND(P15=0,Q15=0),0,IFERROR(MAX(ROUNDUP(P15/INDEX(tblClusters[vCPU / noeud (deduit)],MATCH($B15,tblClusters[Cluster],0)),0),ROUNDUP(Q15/INDEX(tblClusters[RAM / noeud - Go (deduit)],MATCH($B15,tblClusters[Cluster],0)),0)),"Flavor a definir")) -> 0
A16: 46722 | B16: oc002i000577 | C16: =IFERROR(INDEX(tblClusters[Utilisation],MATCH($B16,tblClusters[Cluster],0)),"") -> Mutualise GIE France | D16: =IFERROR(INDEX(tblClusters[Type (deduit)],MATCH($B16,tblClusters[Cluster],0)),"") -> Mutualise | E16: =IFERROR(INDEX(tblClusters[CPU max (cores)],MATCH($B16,tblClusters[Cluster],0)),0) -> 48 | F16: =IFERROR(INDEX(tblClusters[RAM max (Go)],MATCH($B16,tblClusters[Cluster],0)),0) -> 240 | G16: =IFERROR(INDEX(tblClusters[Charge existante CPU hors migration],MATCH($B16,tblClusters[Cluster],0)),0) -> 0 | H16: =IFERROR(INDEX(tblClusters[Charge existante RAM hors migration (Go)],MATCH($B16,tblClusters[Cluster],0)),0) -> 0 | I16: =SUMIFS(tblApplications[CPU cible ROKS],tblApplications[Cluster ROKS cible (auto)],$B16,tblApplications[Mois de bascule prevu],"<="&EOMONTH($A16,0),tblApplications[Inclus projection O/N],"O") -> 16 | J16: =SUMIFS(tblApplications[RAM cible ROKS],tblApplications[Cluster ROKS cible (auto)],$B16,tblApplications[Mois de bascule prevu],"<="&EOMONTH($A16,0),tblApplications[Inclus projection O/N],"O") -> 60 | K16: =G16+I16 -> 16 | L16: =H16+J16 -> 60 | M16: =IF(E16=0,"",K16/E16) -> 0.33333333 | N16: =IF(F16=0,"",L16/F16) -> 0.25 | O16: =IF(E16=0,IF(K16>0,"Cluster sans capacite provisionnee","n/a"),IF(OR(M16>=Clusters_ROKS!$AC$5,N16>=Clusters_ROKS!$AC$5),"Seuil depasse","OK")) -> OK | P16: =MAX(0,K16-E16) -> 0 | Q16: =MAX(0,L16-F16) -> 0 | R16: =IF(AND(P16=0,Q16=0),0,IFERROR(MAX(ROUNDUP(P16/INDEX(tblClusters[vCPU / noeud (deduit)],MATCH($B16,tblClusters[Cluster],0)),0),ROUNDUP(Q16/INDEX(tblClusters[RAM / noeud - Go (deduit)],MATCH($B16,tblClusters[Cluster],0)),0)),"Flavor a definir")) -> 0
... A364: 46722 | B364: ku002i001098 | C364: =IFERROR(INDEX(tblClusters[Utilisation],MATCH($B364,tblClusters[Cluster],0)),"") -> Italy HORS-PROD | D364: =IFERROR(INDEX(tblClusters[Type (deduit)],MATCH($B364,tblClusters[Cluster],0)),"") -> Dedie | E364: =IFERROR(INDEX(tblClusters[CPU max (cores)],MATCH($B364,tblClusters[Cluster],0)),0) -> 0 | F364: =IFERROR(INDEX(tblClusters[RAM max (Go)],MATCH($B364,tblClusters[Cluster],0)),0) -> 0 | G364: =IFERROR(INDEX(tblClusters[Charge existante CPU hors migration],MATCH($B364,tblClusters[Cluster],0)),0) -> 0 | H364: =IFERROR(INDEX(tblClusters[Charge existante RAM hors migration (Go)],MATCH($B364,tblClusters[Cluster],0)),0) -> 0 | I364: =SUMIFS(tblApplications[CPU cible ROKS],tblApplications[Cluster ROKS cible (auto)],$B364,tblApplications[Mois de bascule prevu],"<="&EOMONTH($A364,0),tblApplications[Inclus projection O/N],"O") -> 0 | J364: =SUMIFS(tblApplications[RAM cible ROKS],tblApplications[Cluster ROKS cible (auto)],$B364,tblApplications[Mois de bascule prevu],"<="&EOMONTH($A364,0),tblApplications[Inclus projection O/N],"O") -> 0 | K364: =G364+I364 -> 0 | L364: =H364+J364 -> 0 | M364: =IF(E364=0,"",K364/E364) | N364: =IF(F364=0,"",L364/F364) | O364: =IF(E364=0,IF(K364>0,"Cluster sans capacite provisionnee","n/a"),IF(OR(M364>=Clusters_ROKS!$AC$5,N364>=Clusters_ROKS!$AC$5),"Seuil depasse","OK")) -> n/a | P364: =MAX(0,K364-E364) -> 0 | Q364: =MAX(0,L364-F364) -> 0 | R364: =IF(AND(P364=0,Q364=0),0,IFERROR(MAX(ROUNDUP(P364/INDEX(tblClusters[vCPU / noeud (deduit)],MATCH($B364,tblClusters[Cluster],0)),0),ROUNDUP(Q364/INDEX(tblClusters[RAM / noeud - Go (deduit)],MATCH($B364,tblClusters[Cluster],0)),0)),"Flavor a definir")) -> 0
A366: Une ligne par cluster et par mois. La charge projetée additionne ce qui existe déjà hors migration et le cumul des applications migrées jusqu'à ce mois-là. Les workers supplémentaires nécessaires supposent qu'on agrandit le cluster avec sa flavor actuelle, à ajuster si vous changez de flavor.

Sheet Consolidation_Mensuelle
A1: Consolidation mensuelle, coût IKS, coût ROKS et vrai surcoût du double run
A2: Le double run ne compte que la charge qui existe réellement des deux côtés au même moment
A4: Mois | B4: Fin de mois | C4: CPU actif sur ROKS | D4: RAM active sur ROKS | E4: CPU encore necessaire sur IKS | F4: RAM encore necessaire sur IKS | G4: CPU en double run (redondant) | H4: RAM en double run (redondant) | I4: Cout ROKS (EUR/mois) | J4: Cout IKS (EUR/mois) | K4: Cout total (EUR/mois) | L4: Surcout double run (EUR/mois)
A5: 46388 | B5: =EOMONTH(A5,0) -> 46418 | C5: =SUMIFS(tblApplications[CPU cible ROKS],tblApplications[Mois de bascule prevu],"<="&$B5,tblApplications[Inclus projection O/N],"O") -> 24 | D5: =SUMIFS(tblApplications[RAM cible ROKS],tblApplications[Mois de bascule prevu],"<="&$B5,tblApplications[Inclus projection O/N],"O") -> 93 | E5: =SUMIFS(tblApplications[CPU cible ROKS],tblApplications[Date arret IKS calculee],">"&$B5,tblApplications[Inclus projection O/N],"O") -> 115 | F5: =SUMIFS(tblApplications[RAM cible ROKS],tblApplications[Date arret IKS calculee],">"&$B5,tblApplications[Inclus projection O/N],"O") -> 439 | G5: =SUMIFS(tblApplications[CPU cible ROKS],tblApplications[Mois de bascule prevu],"<="&$B5,tblApplications[Date arret IKS calculee],">"&$B5,tblApplications[Inclus projection O/N],"O") -> 12 | H5: =SUMIFS(tblApplications[RAM cible ROKS],tblApplications[Mois de bascule prevu],"<="&$B5,tblApplications[Date arret IKS calculee],">"&$B5,tblApplications[Inclus projection O/N],"O") -> 45 | I5: =C5*Tarifs_ABS!$B$6+D5*Tarifs_ABS!$C$6 -> 1377 | J5: =E5*Tarifs_ABS!$B$5+F5*Tarifs_ABS!$C$5 -> 7809 | K5: =I5+J5 -> 9186 | L5: =G5*Tarifs_ABS!$B$5+H5*Tarifs_ABS!$C$5 -> 810
A6: 46419 | B6: =EOMONTH(A6,0) -> 46446 | C6: =SUMIFS(tblApplications[CPU cible ROKS],tblApplications[Mois de bascule prevu],"<="&$B6,tblApplications[Inclus projection O/N],"O") -> 34 | D6: =SUMIFS(tblApplications[RAM cible ROKS],tblApplications[Mois de bascule prevu],"<="&$B6,tblApplications[Inclus projection O/N],"O") -> 128 | E6: =SUMIFS(tblApplications[CPU cible ROKS],tblApplications[Date arret IKS calculee],">"&$B6,tblApplications[Inclus projection O/N],"O") -> 103 | F6: =SUMIFS(tblApplications[RAM cible ROKS],tblApplications[Date arret IKS calculee],">"&$B6,tblApplications[Inclus projection O/N],"O") -> 394 | G6: =SUMIFS(tblApplications[CPU cible ROKS],tblApplications[Mois de bascule prevu],"<="&$B6,tblApplications[Date arret IKS calculee],">"&$B6,tblApplications[Inclus projection O/N],"O") -> 10 | H6: =SUMIFS(tblApplications[RAM cible ROKS],tblApplications[Mois de bascule prevu],"<="&$B6,tblApplications[Date arret IKS calculee],">"&$B6,tblApplications[Inclus projection O/N],"O") -> 35 | I6: =C6*Tarifs_ABS!$B$6+D6*Tarifs_ABS!$C$6 -> 1932 | J6: =E6*Tarifs_ABS!$B$5+F6*Tarifs_ABS!$C$5 -> 6999 | K6: =I6+J6 -> 8931 | L6: =G6*Tarifs_ABS!$B$5+H6*Tarifs_ABS!$C$5 -> 660
A7: 46447 | B7: =EOMONTH(A7,0) -> 46477 | C7: =SUMIFS(tblApplications[CPU cible ROKS],tblApplications[Mois de bascule prevu],"<="&$B7,tblApplications[Inclus projection O/N],"O") -> 57 | D7: =SUMIFS(tblApplications[RAM cible ROKS],tblApplications[Mois de bascule prevu],"<="&$B7,tblApplications[Inclus projection O/N],"O") -> 216 | E7: =SUMIFS(tblApplications[CPU cible ROKS],tblApplications[Date arret IKS calculee],">"&$B7,tblApplications[Inclus projection O/N],"O") -> 93 | F7: =SUMIFS(tblApplications[RAM cible ROKS],tblApplications[Date arret IKS calculee],">"&$B7,tblApplications[Inclus projection O/N],"O") -> 359 | G7: =SUMIFS(tblApplications[CPU cible ROKS],tblApplications[Mois de bascule prevu],"<="&$B7,tblApplications[Date arret IKS calculee],">"&$B7,tblApplications[Inclus projection O/N],"O") -> 23 | H7: =SUMIFS(tblApplications[RAM cible ROKS],tblApplications[Mois de bascule prevu],"<="&$B7,tblApplications[Date arret IKS calculee],">"&$B7,tblApplications[Inclus projection O/N],"O") -> 88 | I7: =C7*Tarifs_ABS!$B$6+D7*Tarifs_ABS!$C$6 -> 3246 | J7: =E7*Tarifs_ABS!$B$5+F7*Tarifs_ABS!$C$5 -> 6339 | K7: =I7+J7 -> 9585 | L7: =G7*Tarifs_ABS!$B$5+H7*Tarifs_ABS!$C$5 -> 1563
A8: 46478 | B8: =EOMONTH(A8,0) -> 46507 | C8: =SUMIFS(tblApplications[CPU cible ROKS],tblApplications[Mois de bascule prevu],"<="&$B8,tblApplications[Inclus projection O/N],"O") -> 81 | D8: =SUMIFS(tblApplications[RAM cible ROKS],tblApplications[Mois de bascule prevu],"<="&$B8,tblApplications[Inclus projection O/N],"O") -> 303 | E8: =SUMIFS(tblApplications[CPU cible ROKS],tblApplications[Date arret IKS calculee],">"&$B8,tblApplications[Inclus projection O/N],"O") -> 70 | F8: =SUMIFS(tblApplications[RAM cible ROKS],tblApplications[Date arret IKS calculee],">"&$B8,tblApplications[Inclus projection O/N],"O") -> 271 | G8: =SUMIFS(tblApplications[CPU cible ROKS],tblApplications[Mois de bascule prevu],"<="&$B8,tblApplications[Date arret IKS calculee],">"&$B8,tblApplications[Inclus projection O/N],"O") -> 24 | H8: =SUMIFS(tblApplications[RAM cible ROKS],tblApplications[Mois de bascule prevu],"<="&$B8,tblApplications[Date arret IKS calculee],">"&$B8,tblApplications[Inclus projection O/N],"O") -> 87 | I8: =C8*Tarifs_ABS!$B$6+D8*Tarifs_ABS!$C$6 -> 4593 | J8: =E8*Tarifs_ABS!$B$5+F8*Tarifs_ABS!$C$5 -> 4776 | K8: =I8+J8 -> 9369 | L8: =G8*Tarifs_ABS!$B$5+H8*Tarifs_ABS!$C$5 -> 1602
A9: 46508 | B9: =EOMONTH(A9,0) -> 46538 | C9: =SUMIFS(tblApplications[CPU cible ROKS],tblApplications[Mois de bascule prevu],"<="&$B9,tblApplications[Inclus projection O/N],"O") -> 117 | D9: =SUMIFS(tblApplications[RAM cible ROKS],tblApplications[Mois de bascule prevu],"<="&$B9,tblApplications[Inclus projection O/N],"O") -> 447 | E9: =SUMIFS(tblApplications[CPU cible ROKS],tblApplications[Date arret IKS calculee],">"&$B9,tblApplications[Inclus projection O/N],"O") -> 46 | F9: =SUMIFS(tblApplications[RAM cible ROKS],tblApplications[Date arret IKS calculee],">"&$B9,tblApplications[Inclus projection O/N],"O") -> 184 | G9: =SUMIFS(tblApplications[CPU cible ROKS],tblApplications[Mois de bascule prevu],"<="&$B9,tblApplications[Date arret IKS calculee],">"&$B9,tblApplications[Inclus projection O/N],"O") -> 36 | H9: =SUMIFS(tblApplications[RAM cible ROKS],tblApplications[Mois de bascule prevu],"<="&$B9,tblApplications[Date arret IKS calculee],">"&$B9,tblApplications[Inclus projection O/N],"O") -> 144 | I9: =C9*Tarifs_ABS!$B$6+D9*Tarifs_ABS!$C$6 -> 6681 | J9: =E9*Tarifs_ABS!$B$5+F9*Tarifs_ABS!$C$5 -> 3174 | K9: =I9+J9 -> 9855 | L9: =G9*Tarifs_ABS!$B$5+H9*Tarifs_ABS!$C$5 -> 2484
A10: 46539 | B10: =EOMONTH(A10,0) -> 46568 | C10: =SUMIFS(tblApplications[CPU cible ROKS],tblApplications[Mois de bascule prevu],"<="&$B10,tblApplications[Inclus projection O/N],"O") -> 127 | D10: =SUMIFS(tblApplications[RAM cible ROKS],tblApplications[Mois de bascule prevu],"<="&$B10,tblApplications[Inclus projection O/N],"O") -> 487 | E10: =SUMIFS(tblApplications[CPU cible ROKS],tblApplications[Date arret IKS calculee],">"&$B10,tblApplications[Inclus projection O/N],"O") -> 46 | F10: =SUMIFS(tblApplications[RAM cible ROKS],tblApplications[Date arret IKS calculee],">"&$B10,tblApplications[Inclus projection O/N],"O") -> 184 | G10: =SUMIFS(tblApplications[CPU cible ROKS],tblApplications[Mois de bascule prevu],"<="&$B10,tblApplications[Date arret IKS calculee],">"&$B10,tblApplications[Inclus projection O/N],"O") -> 46 | H10: =SUMIFS(tblApplications[RAM cible ROKS],tblApplications[Mois de bascule prevu],"<="&$B10,tblApplications[Date arret IKS calculee],">"&$B10,tblApplications[Inclus projection O/N],"O") -> 184 | I10: =C10*Tarifs_ABS!$B$6+D10*Tarifs_ABS!$C$6 -> 7261 | J10: =E10*Tarifs_ABS!$B$5+F10*Tarifs_ABS!$C$5 -> 3174 | K10: =I10+J10 -> 10435 | L10: =G10*Tarifs_ABS!$B$5+H10*Tarifs_ABS!$C$5 -> 3174
A11: 46569 | B11: =EOMONTH(A11,0) -> 46599 | C11: =SUMIFS(tblApplications[CPU cible ROKS],tblApplications[Mois de bascule prevu],"<="&$B11,tblApplications[Inclus projection O/N],"O") -> 127 | D11: =SUMIFS(tblApplications[RAM cible ROKS],tblApplications[Mois de bascule prevu],"<="&$B11,tblApplications[Inclus projection O/N],"O") -> 487 | E11: =SUMIFS(tblApplications[CPU cible ROKS],tblApplications[Date arret IKS calculee],">"&$B11,tblApplications[Inclus projection O/N],"O") -> 0 | F11: =SUMIFS(tblApplications[RAM cible ROKS],tblApplications[Date arret IKS calculee],">"&$B11,tblApplications[Inclus projection O/N],"O") -> 0 | G11: =SUMIFS(tblApplications[CPU cible ROKS],tblApplications[Mois de bascule prevu],"<="&$B11,tblApplications[Date arret IKS calculee],">"&$B11,tblApplications[Inclus projection O/N],"O") -> 0 | H11: =SUMIFS(tblApplications[RAM cible ROKS],tblApplications[Mois de bascule prevu],"<="&$B11,tblApplications[Date arret IKS calculee],">"&$B11,tblApplications[Inclus projection O/N],"O") -> 0 | I11: =C11*Tarifs_ABS!$B$6+D11*Tarifs_ABS!$C$6 -> 7261 | J11: =E11*Tarifs_ABS!$B$5+F11*Tarifs_ABS!$C$5 -> 0 | K11: =I11+J11 -> 7261 | L11: =G11*Tarifs_ABS!$B$5+H11*Tarifs_ABS!$C$5 -> 0
A12: 46600 | B12: =EOMONTH(A12,0) -> 46630 | C12: =SUMIFS(tblApplications[CPU cible ROKS],tblApplications[Mois de bascule prevu],"<="&$B12,tblApplications[Inclus projection O/N],"O") -> 127 | D12: =SUMIFS(tblApplications[RAM cible ROKS],tblApplications[Mois de bascule prevu],"<="&$B12,tblApplications[Inclus projection O/N],"O") -> 487 | E12: =SUMIFS(tblApplications[CPU cible ROKS],tblApplications[Date arret IKS calculee],">"&$B12,tblApplications[Inclus projection O/N],"O") -> 0 | F12: =SUMIFS(tblApplications[RAM cible ROKS],tblApplications[Date arret IKS calculee],">"&$B12,tblApplications[Inclus projection O/N],"O") -> 0 | G12: =SUMIFS(tblApplications[CPU cible ROKS],tblApplications[Mois de bascule prevu],"<="&$B12,tblApplications[Date arret IKS calculee],">"&$B12,tblApplications[Inclus projection O/N],"O") -> 0 | H12: =SUMIFS(tblApplications[RAM cible ROKS],tblApplications[Mois de bascule prevu],"<="&$B12,tblApplications[Date arret IKS calculee],">"&$B12,tblApplications[Inclus projection O/N],"O") -> 0 | I12: =C12*Tarifs_ABS!$B$6+D12*Tarifs_ABS!$C$6 -> 7261 | J12: =E12*Tarifs_ABS!$B$5+F12*Tarifs_ABS!$C$5 -> 0 | K12: =I12+J12 -> 7261 | L12: =G12*Tarifs_ABS!$B$5+H12*Tarifs_ABS!$C$5 -> 0
A13: 46631 | B13: =EOMONTH(A13,0) -> 46660 | C13: =SUMIFS(tblApplications[CPU cible ROKS],tblApplications[Mois de bascule prevu],"<="&$B13,tblApplications[Inclus projection O/N],"O") -> 127 | D13: =SUMIFS(tblApplications[RAM cible ROKS],tblApplications[Mois de bascule prevu],"<="&$B13,tblApplications[Inclus projection O/N],"O") -> 487 | E13: =SUMIFS(tblApplications[CPU cible ROKS],tblApplications[Date arret IKS calculee],">"&$B13,tblApplications[Inclus projection O/N],"O") -> 0 | F13: =SUMIFS(tblApplications[RAM cible ROKS],tblApplications[Date arret IKS calculee],">"&$B13,tblApplications[Inclus projection O/N],"O") -> 0 | G13: =SUMIFS(tblApplications[CPU cible ROKS],tblApplications[Mois de bascule prevu],"<="&$B13,tblApplications[Date arret IKS calculee],">"&$B13,tblApplications[Inclus projection O/N],"O") -> 0 | H13: =SUMIFS(tblApplications[RAM cible ROKS],tblApplications[Mois de bascule prevu],"<="&$B13,tblApplications[Date arret IKS calculee],">"&$B13,tblApplications[Inclus projection O/N],"O") -> 0 | I13: =C13*Tarifs_ABS!$B$6+D13*Tarifs_ABS!$C$6 -> 7261 | J13: =E13*Tarifs_ABS!$B$5+F13*Tarifs_ABS!$C$5 -> 0 | K13: =I13+J13 -> 7261 | L13: =G13*Tarifs_ABS!$B$5+H13*Tarifs_ABS!$C$5 -> 0
A14: 46661 | B14: =EOMONTH(A14,0) -> 46691 | C14: =SUMIFS(tblApplications[CPU cible ROKS],tblApplications[Mois de bascule prevu],"<="&$B14,tblApplications[Inclus projection O/N],"O") -> 127 | D14: =SUMIFS(tblApplications[RAM cible ROKS],tblApplications[Mois de bascule prevu],"<="&$B14,tblApplications[Inclus projection O/N],"O") -> 487 | E14: =SUMIFS(tblApplications[CPU cible ROKS],tblApplications[Date arret IKS calculee],">"&$B14,tblApplications[Inclus projection O/N],"O") -> 0 | F14: =SUMIFS(tblApplications[RAM cible ROKS],tblApplications[Date arret IKS calculee],">"&$B14,tblApplications[Inclus projection O/N],"O") -> 0 | G14: =SUMIFS(tblApplications[CPU cible ROKS],tblApplications[Mois de bascule prevu],"<="&$B14,tblApplications[Date arret IKS calculee],">"&$B14,tblApplications[Inclus projection O/N],"O") -> 0 | H14: =SUMIFS(tblApplications[RAM cible ROKS],tblApplications[Mois de bascule prevu],"<="&$B14,tblApplications[Date arret IKS calculee],">"&$B14,tblApplications[Inclus projection O/N],"O") -> 0 | I14: =C14*Tarifs_ABS!$B$6+D14*Tarifs_ABS!$C$6 -> 7261 | J14: =E14*Tarifs_ABS!$B$5+F14*Tarifs_ABS!$C$5 -> 0 | K14: =I14+J14 -> 7261 | L14: =G14*Tarifs_ABS!$B$5+H14*Tarifs_ABS!$C$5 -> 0
A15: 46692 | B15: =EOMONTH(A15,0) -> 46721 | C15: =SUMIFS(tblApplications[CPU cible ROKS],tblApplications[Mois de bascule prevu],"<="&$B15,tblApplications[Inclus projection O/N],"O") -> 127 | D15: =SUMIFS(tblApplications[RAM cible ROKS],tblApplications[Mois de bascule prevu],"<="&$B15,tblApplications[Inclus projection O/N],"O") -> 487 | E15: =SUMIFS(tblApplications[CPU cible ROKS],tblApplications[Date arret IKS calculee],">"&$B15,tblApplications[Inclus projection O/N],"O") -> 0 | F15: =SUMIFS(tblApplications[RAM cible ROKS],tblApplications[Date arret IKS calculee],">"&$B15,tblApplications[Inclus projection O/N],"O") -> 0 | G15: =SUMIFS(tblApplications[CPU cible ROKS],tblApplications[Mois de bascule prevu],"<="&$B15,tblApplications[Date arret IKS calculee],">"&$B15,tblApplications[Inclus projection O/N],"O") -> 0 | H15: =SUMIFS(tblApplications[RAM cible ROKS],tblApplications[Mois de bascule prevu],"<="&$B15,tblApplications[Date arret IKS calculee],">"&$B15,tblApplications[Inclus projection O/N],"O") -> 0 | I15: =C15*Tarifs_ABS!$B$6+D15*Tarifs_ABS!$C$6 -> 7261 | J15: =E15*Tarifs_ABS!$B$5+F15*Tarifs_ABS!$C$5 -> 0 | K15: =I15+J15 -> 7261 | L15: =G15*Tarifs_ABS!$B$5+H15*Tarifs_ABS!$C$5 -> 0
A16: 46722 | B16: =EOMONTH(A16,0) -> 46752 | C16: =SUMIFS(tblApplications[CPU cible ROKS],tblApplications[Mois de bascule prevu],"<="&$B16,tblApplications[Inclus projection O/N],"O") -> 127 | D16: =SUMIFS(tblApplications[RAM cible ROKS],tblApplications[Mois de bascule prevu],"<="&$B16,tblApplications[Inclus projection O/N],"O") -> 487 | E16: =SUMIFS(tblApplications[CPU cible ROKS],tblApplications[Date arret IKS calculee],">"&$B16,tblApplications[Inclus projection O/N],"O") -> 0 | F16: =SUMIFS(tblApplications[RAM cible ROKS],tblApplications[Date arret IKS calculee],">"&$B16,tblApplications[Inclus projection O/N],"O") -> 0 | G16: =SUMIFS(tblApplications[CPU cible ROKS],tblApplications[Mois de bascule prevu],"<="&$B16,tblApplications[Date arret IKS calculee],">"&$B16,tblApplications[Inclus projection O/N],"O") -> 0 | H16: =SUMIFS(tblApplications[RAM cible ROKS],tblApplications[Mois de bascule prevu],"<="&$B16,tblApplications[Date arret IKS calculee],">"&$B16,tblApplications[Inclus projection O/N],"O") -> 0 | I16: =C16*Tarifs_ABS!$B$6+D16*Tarifs_ABS!$C$6 -> 7261 | J16: =E16*Tarifs_ABS!$B$5+F16*Tarifs_ABS!$C$5 -> 0 | K16: =I16+J16 -> 7261 | L16: =G16*Tarifs_ABS!$B$5+H16*Tarifs_ABS!$C$5 -> 0
B18: Total periode | I18: =SUM(I5:I16) -> 68656 | J18: =SUM(J5:J16) -> 32271 | K18: =SUM(K5:K16) -> 100927 | L18: =SUM(L5:L16) -> 10293
A20: Le surcoût double run isole désormais la charge qui existe réellement des deux côtés au même moment (l'application a déjà basculé sur ROKS mais son IKS n'est pas encore arrêté), pas le coût total pendant la période de coexistence.

Sheet Dashboard
A1: Dashboard, budget migration IKS vers ROKS
A2: Se met à jour automatiquement depuis Consolidation_Mensuelle et Projection_Clusters
A4: 5 indicateurs clés
A5: Coût IKS initial (EUR/mois, tout le périmètre sur IKS) | D5: =(SUMIFS(tblApplications[CPU cible ROKS],tblApplications[Inclus projection O/N],"O")*Tarifs_ABS!$B$5)+(SUMIFS(tblApplications[RAM cible ROKS],tblApplications[Inclus projection O/N],"O")*Tarifs_ABS!$C$5) -> 8637
A6: Coût ROKS cible (EUR/mois, tout le périmètre migré) | D6: =(SUMIFS(tblApplications[CPU cible ROKS],tblApplications[Inclus projection O/N],"O")*Tarifs_ABS!$B$6)+(SUMIFS(tblApplications[RAM cible ROKS],tblApplications[Inclus projection O/N],"O")*Tarifs_ABS!$C$6) -> 7261
A7: Coût total de la migration (EUR, cumulé sur toute la période) | D7: =SUM(Consolidation_Mensuelle!K5:K16) -> 100927
A8: Vrai surcoût du double run (EUR, cumulé) | D8: =SUM(Consolidation_Mensuelle!L5:L16) -> 10293
A9: Nombre de clusters necessitant une extension de capacite | D9: =SUMPRODUCT((COUNTIFS(tblProjection[Cluster],tblClusters[Cluster],tblProjection[Statut],"Seuil depasse")>0)*1) -> 0
A12: Mois | B12: Cout ROKS (EUR) | C12: Cout IKS (EUR) | D12: Surcout double run (EUR) | E12: Cout total (EUR)
A13: =Consolidation_Mensuelle!A5 -> 46388 | B13: =Consolidation_Mensuelle!I5 -> 1377 | C13: =Consolidation_Mensuelle!J5 -> 7809 | D13: =Consolidation_Mensuelle!L5 -> 810 | E13: =Consolidation_Mensuelle!K5 -> 9186
A14: =Consolidation_Mensuelle!A6 -> 46419 | B14: =Consolidation_Mensuelle!I6 -> 1932 | C14: =Consolidation_Mensuelle!J6 -> 6999 | D14: =Consolidation_Mensuelle!L6 -> 660 | E14: =Consolidation_Mensuelle!K6 -> 8931
A15: =Consolidation_Mensuelle!A7 -> 46447 | B15: =Consolidation_Mensuelle!I7 -> 3246 | C15: =Consolidation_Mensuelle!J7 -> 6339 | D15: =Consolidation_Mensuelle!L7 -> 1563 | E15: =Consolidation_Mensuelle!K7 -> 9585
A16: =Consolidation_Mensuelle!A8 -> 46478 | B16: =Consolidation_Mensuelle!I8 -> 4593 | C16: =Consolidation_Mensuelle!J8 -> 4776 | D16: =Consolidation_Mensuelle!L8 -> 1602 | E16: =Consolidation_Mensuelle!K8 -> 9369
A17: =Consolidation_Mensuelle!A9 -> 46508 | B17: =Consolidation_Mensuelle!I9 -> 6681 | C17: =Consolidation_Mensuelle!J9 -> 3174 | D17: =Consolidation_Mensuelle!L9 -> 2484 | E17: =Consolidation_Mensuelle!K9 -> 9855
A18: =Consolidation_Mensuelle!A10 -> 46539 | B18: =Consolidation_Mensuelle!I10 -> 7261 | C18: =Consolidation_Mensuelle!J10 -> 3174 | D18: =Consolidation_Mensuelle!L10 -> 3174 | E18: =Consolidation_Mensuelle!K10 -> 10435
A19: =Consolidation_Mensuelle!A11 -> 46569 | B19: =Consolidation_Mensuelle!I11 -> 7261 | C19: =Consolidation_Mensuelle!J11 -> 0 | D19: =Consolidation_Mensuelle!L11 -> 0 | E19: =Consolidation_Mensuelle!K11 -> 7261
A20: =Consolidation_Mensuelle!A12 -> 46600 | B20: =Consolidation_Mensuelle!I12 -> 7261 | C20: =Consolidation_Mensuelle!J12 -> 0 | D20: =Consolidation_Mensuelle!L12 -> 0 | E20: =Consolidation_Mensuelle!K12 -> 7261
A21: =Consolidation_Mensuelle!A13 -> 46631 | B21: =Consolidation_Mensuelle!I13 -> 7261 | C21: =Consolidation_Mensuelle!J13 -> 0 | D21: =Consolidation_Mensuelle!L13 -> 0 | E21: =Consolidation_Mensuelle!K13 -> 7261
A22: =Consolidation_Mensuelle!A14 -> 46661 | B22: =Consolidation_Mensuelle!I14 -> 7261 | C22: =Consolidation_Mensuelle!J14 -> 0 | D22: =Consolidation_Mensuelle!L14 -> 0 | E22: =Consolidation_Mensuelle!K14 -> 7261
A23: =Consolidation_Mensuelle!A15 -> 46692 | B23: =Consolidation_Mensuelle!I15 -> 7261 | C23: =Consolidation_Mensuelle!J15 -> 0 | D23: =Consolidation_Mensuelle!L15 -> 0 | E23: =Consolidation_Mensuelle!K15 -> 7261
A24: =Consolidation_Mensuelle!A16 -> 46722 | B24: =Consolidation_Mensuelle!I16 -> 7261 | C24: =Consolidation_Mensuelle!J16 -> 0 | D24: =Consolidation_Mensuelle!L16 -> 0 | E24: =Consolidation_Mensuelle!K16 -> 7261
