Workbook

Sheet Dashboard
B1: Dashboard – coûts mensuels de la migration IKS → ROKS
B2: Données recalculées automatiquement depuis Synthèse. La courbe suit l'horizon défini dans Paramètres & ABS.
B3: ="Périmètre affiché : "&C8 -> Périmètre affiché : Tous
B4: Coût total | D4: Coût IKS | F4: Coût ROKS | H4: Surcoût double run | J4: Écart vs sans migration | L4: Contrôles
B5: =SUMIFS(TblCalculs[Coût mensuel],TblCalculs[Environnement],p_envcrit) -> 1364404 | D5: =SUMIFS(TblCalculs[Coût mensuel],TblCalculs[Plateforme],"IKS",TblCalculs[Environnement],p_envcrit) -> 524628 | F5: =SUMIFS(TblCalculs[Coût mensuel],TblCalculs[Plateforme],"ROKS",TblCalculs[Environnement],p_envcrit) -> 839776 | H5: =SUMIFS(TblCalculs[Coût mensuel],TblCalculs[Environnement],p_envcrit)-SUMIFS(TblCalculs[Sans DR – coût],TblCalculs[Environnement],p_envcrit) -> 51507 | J5: =SUMIFS(TblCalculs[Coût mensuel],TblCalculs[Environnement],p_envcrit)-SUMIFS(TblCalculs[Sans migration – coût],TblCalculs[Environnement],p_envcrit) -> -183020 | L5: =Synthèse!C17 -> OK – aucune anomalie
B7: Période : | C7: =CHOOSE(MONTH(p_debut),"janv.","févr.","mars","avr.","mai","juin","juil.","août","sept.","oct.","nov.","déc.")&" "&YEAR(p_debut)&" → "&CHOOSE(MONTH(p_fin),"janv.","févr.","mars","avr.","mai","juin","juil.","août","sept.","oct.","nov.","déc.")&" "&YEAR(p_fin)&" ("&p_horizon&" mois)" -> oct. 2026 → sept. 2029 (36 mois)
B8: Environnement : | C8: Tous | D8: =IF(C8="Tous","*",C8) -> * | E8: ← Tous / PRD / NPRD : filtre les indicateurs et la courbe
B36: Lecture : l'écart entre la courbe IKS qui baisse et ROKS qui monte matérialise la bascule ; la courbe verte montre le surcoût des mois payés en double (double run).
B37: Toutes les courbes sont en € par mois, sur le même axe.
B39: Répartition des coûts par tribe et par domaine (horizon, périmètre du filtre C8)
B40: Coût des clusters : | D40: =SUMIFS(TblCalculs[Coût mensuel],TblCalculs[Environnement],p_envcrit) -> 1364404 | F40: Affecté aux déploiements : | H40: =SUMIFS(TblApplications[Coût total affecté (€)],TblApplications[Environnement],p_envcrit) -> 722062.29 | J40: Socle / non affecté : | L40: =D40-H40 -> 642341.71
B41: Clé : ROKS dès le provisionnement selon le besoin (vCPU + poids × Go) ; IKS jusqu'à la libération selon les ressources libérables. Socle = capacité initiale et planchers non attribués.
B62: Tribe | C62: Domaine | D62: Coût IKS € | E62: Coût ROKS € | F62: Coût total € | I62: Domaine | J62: Coût IKS € | K62: Coût ROKS € | L62: Coût total €
B63: =IFERROR(IF(INDEX(TblTribes[Tribe],1)="","",INDEX(TblTribes[Tribe],1)),"") -> Parcours client | C63: =IF($B63="","",INDEX(TblTribes[Domaine de la tribe],1)) -> Distribution | D63: =IF($B63="","",SUMIFS(TblApplications[Coût IKS affecté (€)],TblApplications[Tribe],$B63,TblApplications[Environnement],p_envcrit)) -> 59472 | E63: =IF($B63="","",SUMIFS(TblApplications[Coût ROKS affecté (€)],TblApplications[Tribe],$B63,TblApplications[Environnement],p_envcrit)) -> 152111.1 | F63: =IF($B63="","",D63+E63) -> 211583.1 | I63: =IFERROR(IF(INDEX(TblDomaines[Domaine],1)="","",INDEX(TblDomaines[Domaine],1)),"") -> Distribution | J63: =IF($I63="","",SUMIFS(TblApplications[Coût IKS affecté (€)],TblApplications[Domaine],$I63,TblApplications[Environnement],p_envcrit)) -> 176292 | K63: =IF($I63="","",SUMIFS(TblApplications[Coût ROKS affecté (€)],TblApplications[Domaine],$I63,TblApplications[Environnement],p_envcrit)) -> 252802.38 | L63: =IF($I63="","",J63+K63) -> 429094.38
B64: =IFERROR(IF(INDEX(TblTribes[Tribe],2)="","",INDEX(TblTribes[Tribe],2)),"") -> Tarification | C64: =IF($B64="","",INDEX(TblTribes[Domaine de la tribe],2)) -> Distribution | D64: =IF($B64="","",SUMIFS(TblApplications[Coût IKS affecté (€)],TblApplications[Tribe],$B64,TblApplications[Environnement],p_envcrit)) -> 116820 | E64: =IF($B64="","",SUMIFS(TblApplications[Coût ROKS affecté (€)],TblApplications[Tribe],$B64,TblApplications[Environnement],p_envcrit)) -> 100691.28 | F64: =IF($B64="","",D64+E64) -> 217511.28 | I64: =IFERROR(IF(INDEX(TblDomaines[Domaine],2)="","",INDEX(TblDomaines[Domaine],2)),"") -> Indemnisation | J64: =IF($I64="","",SUMIFS(TblApplications[Coût IKS affecté (€)],TblApplications[Domaine],$I64,TblApplications[Environnement],p_envcrit)) -> 180540 | K64: =IF($I64="","",SUMIFS(TblApplications[Coût ROKS affecté (€)],TblApplications[Domaine],$I64,TblApplications[Environnement],p_envcrit)) -> 112427.91 | L64: =IF($I64="","",J64+K64) -> 292967.91
B65: =IFERROR(IF(INDEX(TblTribes[Tribe],3)="","",INDEX(TblTribes[Tribe],3)),"") -> Sinistres | C65: =IF($B65="","",INDEX(TblTribes[Domaine de la tribe],3)) -> Indemnisation | D65: =IF($B65="","",SUMIFS(TblApplications[Coût IKS affecté (€)],TblApplications[Tribe],$B65,TblApplications[Environnement],p_envcrit)) -> 180540 | E65: =IF($B65="","",SUMIFS(TblApplications[Coût ROKS affecté (€)],TblApplications[Tribe],$B65,TblApplications[Environnement],p_envcrit)) -> 112427.91 | F65: =IF($B65="","",D65+E65) -> 292967.91 | I65: =IFERROR(IF(INDEX(TblDomaines[Domaine],3)="","",INDEX(TblDomaines[Domaine],3)),"") | J65: =IF($I65="","",SUMIFS(TblApplications[Coût IKS affecté (€)],TblApplications[Domaine],$I65,TblApplications[Environnement],p_envcrit)) | K65: =IF($I65="","",SUMIFS(TblApplications[Coût ROKS affecté (€)],TblApplications[Domaine],$I65,TblApplications[Environnement],p_envcrit)) | L65: =IF($I65="","",J65+K65)
B66: =IFERROR(IF(INDEX(TblTribes[Tribe],4)="","",INDEX(TblTribes[Tribe],4)),"") | C66: =IF($B66="","",INDEX(TblTribes[Domaine de la tribe],4)) | D66: =IF($B66="","",SUMIFS(TblApplications[Coût IKS affecté (€)],TblApplications[Tribe],$B66,TblApplications[Environnement],p_envcrit)) | E66: =IF($B66="","",SUMIFS(TblApplications[Coût ROKS affecté (€)],TblApplications[Tribe],$B66,TblApplications[Environnement],p_envcrit)) | F66: =IF($B66="","",D66+E66) | I66: =IFERROR(IF(INDEX(TblDomaines[Domaine],4)="","",INDEX(TblDomaines[Domaine],4)),"") | J66: =IF($I66="","",SUMIFS(TblApplications[Coût IKS affecté (€)],TblApplications[Domaine],$I66,TblApplications[Environnement],p_envcrit)) | K66: =IF($I66="","",SUMIFS(TblApplications[Coût ROKS affecté (€)],TblApplications[Domaine],$I66,TblApplications[Environnement],p_envcrit)) | L66: =IF($I66="","",J66+K66)
B67: =IFERROR(IF(INDEX(TblTribes[Tribe],5)="","",INDEX(TblTribes[Tribe],5)),"") | C67: =IF($B67="","",INDEX(TblTribes[Domaine de la tribe],5)) | D67: =IF($B67="","",SUMIFS(TblApplications[Coût IKS affecté (€)],TblApplications[Tribe],$B67,TblApplications[Environnement],p_envcrit)) | E67: =IF($B67="","",SUMIFS(TblApplications[Coût ROKS affecté (€)],TblApplications[Tribe],$B67,TblApplications[Environnement],p_envcrit)) | F67: =IF($B67="","",D67+E67) | I67: =IFERROR(IF(INDEX(TblDomaines[Domaine],5)="","",INDEX(TblDomaines[Domaine],5)),"") | J67: =IF($I67="","",SUMIFS(TblApplications[Coût IKS affecté (€)],TblApplications[Domaine],$I67,TblApplications[Environnement],p_envcrit)) | K67: =IF($I67="","",SUMIFS(TblApplications[Coût ROKS affecté (€)],TblApplications[Domaine],$I67,TblApplications[Environnement],p_envcrit)) | L67: =IF($I67="","",J67+K67)
B68: =IFERROR(IF(INDEX(TblTribes[Tribe],6)="","",INDEX(TblTribes[Tribe],6)),"") | C68: =IF($B68="","",INDEX(TblTribes[Domaine de la tribe],6)) | D68: =IF($B68="","",SUMIFS(TblApplications[Coût IKS affecté (€)],TblApplications[Tribe],$B68,TblApplications[Environnement],p_envcrit)) | E68: =IF($B68="","",SUMIFS(TblApplications[Coût ROKS affecté (€)],TblApplications[Tribe],$B68,TblApplications[Environnement],p_envcrit)) | F68: =IF($B68="","",D68+E68) | I68: =IFERROR(IF(INDEX(TblDomaines[Domaine],6)="","",INDEX(TblDomaines[Domaine],6)),"") | J68: =IF($I68="","",SUMIFS(TblApplications[Coût IKS affecté (€)],TblApplications[Domaine],$I68,TblApplications[Environnement],p_envcrit)) | K68: =IF($I68="","",SUMIFS(TblApplications[Coût ROKS affecté (€)],TblApplications[Domaine],$I68,TblApplications[Environnement],p_envcrit)) | L68: =IF($I68="","",J68+K68)
B69: =IFERROR(IF(INDEX(TblTribes[Tribe],7)="","",INDEX(TblTribes[Tribe],7)),"") | C69: =IF($B69="","",INDEX(TblTribes[Domaine de la tribe],7)) | D69: =IF($B69="","",SUMIFS(TblApplications[Coût IKS affecté (€)],TblApplications[Tribe],$B69,TblApplications[Environnement],p_envcrit)) | E69: =IF($B69="","",SUMIFS(TblApplications[Coût ROKS affecté (€)],TblApplications[Tribe],$B69,TblApplications[Environnement],p_envcrit)) | F69: =IF($B69="","",D69+E69) | I69: =IFERROR(IF(INDEX(TblDomaines[Domaine],7)="","",INDEX(TblDomaines[Domaine],7)),"") | J69: =IF($I69="","",SUMIFS(TblApplications[Coût IKS affecté (€)],TblApplications[Domaine],$I69,TblApplications[Environnement],p_envcrit)) | K69: =IF($I69="","",SUMIFS(TblApplications[Coût ROKS affecté (€)],TblApplications[Domaine],$I69,TblApplications[Environnement],p_envcrit)) | L69: =IF($I69="","",J69+K69)
B70: =IFERROR(IF(INDEX(TblTribes[Tribe],8)="","",INDEX(TblTribes[Tribe],8)),"") | C70: =IF($B70="","",INDEX(TblTribes[Domaine de la tribe],8)) | D70: =IF($B70="","",SUMIFS(TblApplications[Coût IKS affecté (€)],TblApplications[Tribe],$B70,TblApplications[Environnement],p_envcrit)) | E70: =IF($B70="","",SUMIFS(TblApplications[Coût ROKS affecté (€)],TblApplications[Tribe],$B70,TblApplications[Environnement],p_envcrit)) | F70: =IF($B70="","",D70+E70) | I70: =IFERROR(IF(INDEX(TblDomaines[Domaine],8)="","",INDEX(TblDomaines[Domaine],8)),"") | J70: =IF($I70="","",SUMIFS(TblApplications[Coût IKS affecté (€)],TblApplications[Domaine],$I70,TblApplications[Environnement],p_envcrit)) | K70: =IF($I70="","",SUMIFS(TblApplications[Coût ROKS affecté (€)],TblApplications[Domaine],$I70,TblApplications[Environnement],p_envcrit)) | L70: =IF($I70="","",J70+K70)
B71: =IFERROR(IF(INDEX(TblTribes[Tribe],9)="","",INDEX(TblTribes[Tribe],9)),"") | C71: =IF($B71="","",INDEX(TblTribes[Domaine de la tribe],9)) | D71: =IF($B71="","",SUMIFS(TblApplications[Coût IKS affecté (€)],TblApplications[Tribe],$B71,TblApplications[Environnement],p_envcrit)) | E71: =IF($B71="","",SUMIFS(TblApplications[Coût ROKS affecté (€)],TblApplications[Tribe],$B71,TblApplications[Environnement],p_envcrit)) | F71: =IF($B71="","",D71+E71) | I71: =IFERROR(IF(INDEX(TblDomaines[Domaine],9)="","",INDEX(TblDomaines[Domaine],9)),"") | J71: =IF($I71="","",SUMIFS(TblApplications[Coût IKS affecté (€)],TblApplications[Domaine],$I71,TblApplications[Environnement],p_envcrit)) | K71: =IF($I71="","",SUMIFS(TblApplications[Coût ROKS affecté (€)],TblApplications[Domaine],$I71,TblApplications[Environnement],p_envcrit)) | L71: =IF($I71="","",J71+K71)
B72: =IFERROR(IF(INDEX(TblTribes[Tribe],10)="","",INDEX(TblTribes[Tribe],10)),"") | C72: =IF($B72="","",INDEX(TblTribes[Domaine de la tribe],10)) | D72: =IF($B72="","",SUMIFS(TblApplications[Coût IKS affecté (€)],TblApplications[Tribe],$B72,TblApplications[Environnement],p_envcrit)) | E72: =IF($B72="","",SUMIFS(TblApplications[Coût ROKS affecté (€)],TblApplications[Tribe],$B72,TblApplications[Environnement],p_envcrit)) | F72: =IF($B72="","",D72+E72) | I72: =IFERROR(IF(INDEX(TblDomaines[Domaine],10)="","",INDEX(TblDomaines[Domaine],10)),"") | J72: =IF($I72="","",SUMIFS(TblApplications[Coût IKS affecté (€)],TblApplications[Domaine],$I72,TblApplications[Environnement],p_envcrit)) | K72: =IF($I72="","",SUMIFS(TblApplications[Coût ROKS affecté (€)],TblApplications[Domaine],$I72,TblApplications[Environnement],p_envcrit)) | L72: =IF($I72="","",J72+K72)
B73: =IFERROR(IF(INDEX(TblTribes[Tribe],11)="","",INDEX(TblTribes[Tribe],11)),"") | C73: =IF($B73="","",INDEX(TblTribes[Domaine de la tribe],11)) | D73: =IF($B73="","",SUMIFS(TblApplications[Coût IKS affecté (€)],TblApplications[Tribe],$B73,TblApplications[Environnement],p_envcrit)) | E73: =IF($B73="","",SUMIFS(TblApplications[Coût ROKS affecté (€)],TblApplications[Tribe],$B73,TblApplications[Environnement],p_envcrit)) | F73: =IF($B73="","",D73+E73) | I73: =IFERROR(IF(INDEX(TblDomaines[Domaine],11)="","",INDEX(TblDomaines[Domaine],11)),"") | J73: =IF($I73="","",SUMIFS(TblApplications[Coût IKS affecté (€)],TblApplications[Domaine],$I73,TblApplications[Environnement],p_envcrit)) | K73: =IF($I73="","",SUMIFS(TblApplications[Coût ROKS affecté (€)],TblApplications[Domaine],$I73,TblApplications[Environnement],p_envcrit)) | L73: =IF($I73="","",J73+K73)
B74: =IFERROR(IF(INDEX(TblTribes[Tribe],12)="","",INDEX(TblTribes[Tribe],12)),"") | C74: =IF($B74="","",INDEX(TblTribes[Domaine de la tribe],12)) | D74: =IF($B74="","",SUMIFS(TblApplications[Coût IKS affecté (€)],TblApplications[Tribe],$B74,TblApplications[Environnement],p_envcrit)) | E74: =IF($B74="","",SUMIFS(TblApplications[Coût ROKS affecté (€)],TblApplications[Tribe],$B74,TblApplications[Environnement],p_envcrit)) | F74: =IF($B74="","",D74+E74) | I74: =IFERROR(IF(INDEX(TblDomaines[Domaine],12)="","",INDEX(TblDomaines[Domaine],12)),"") | J74: =IF($I74="","",SUMIFS(TblApplications[Coût IKS affecté (€)],TblApplications[Domaine],$I74,TblApplications[Environnement],p_envcrit)) | K74: =IF($I74="","",SUMIFS(TblApplications[Coût ROKS affecté (€)],TblApplications[Domaine],$I74,TblApplications[Environnement],p_envcrit)) | L74: =IF($I74="","",J74+K74)
B75: =IFERROR(IF(INDEX(TblTribes[Tribe],13)="","",INDEX(TblTribes[Tribe],13)),"") | C75: =IF($B75="","",INDEX(TblTribes[Domaine de la tribe],13)) | D75: =IF($B75="","",SUMIFS(TblApplications[Coût IKS affecté (€)],TblApplications[Tribe],$B75,TblApplications[Environnement],p_envcrit)) | E75: =IF($B75="","",SUMIFS(TblApplications[Coût ROKS affecté (€)],TblApplications[Tribe],$B75,TblApplications[Environnement],p_envcrit)) | F75: =IF($B75="","",D75+E75) | I75: =IFERROR(IF(INDEX(TblDomaines[Domaine],13)="","",INDEX(TblDomaines[Domaine],13)),"") | J75: =IF($I75="","",SUMIFS(TblApplications[Coût IKS affecté (€)],TblApplications[Domaine],$I75,TblApplications[Environnement],p_envcrit)) | K75: =IF($I75="","",SUMIFS(TblApplications[Coût ROKS affecté (€)],TblApplications[Domaine],$I75,TblApplications[Environnement],p_envcrit)) | L75: =IF($I75="","",J75+K75)
B76: =IFERROR(IF(INDEX(TblTribes[Tribe],14)="","",INDEX(TblTribes[Tribe],14)),"") | C76: =IF($B76="","",INDEX(TblTribes[Domaine de la tribe],14)) | D76: =IF($B76="","",SUMIFS(TblApplications[Coût IKS affecté (€)],TblApplications[Tribe],$B76,TblApplications[Environnement],p_envcrit)) | E76: =IF($B76="","",SUMIFS(TblApplications[Coût ROKS affecté (€)],TblApplications[Tribe],$B76,TblApplications[Environnement],p_envcrit)) | F76: =IF($B76="","",D76+E76) | I76: =IFERROR(IF(INDEX(TblDomaines[Domaine],14)="","",INDEX(TblDomaines[Domaine],14)),"") | J76: =IF($I76="","",SUMIFS(TblApplications[Coût IKS affecté (€)],TblApplications[Domaine],$I76,TblApplications[Environnement],p_envcrit)) | K76: =IF($I76="","",SUMIFS(TblApplications[Coût ROKS affecté (€)],TblApplications[Domaine],$I76,TblApplications[Environnement],p_envcrit)) | L76: =IF($I76="","",J76+K76)
B77: =IFERROR(IF(INDEX(TblTribes[Tribe],15)="","",INDEX(TblTribes[Tribe],15)),"") | C77: =IF($B77="","",INDEX(TblTribes[Domaine de la tribe],15)) | D77: =IF($B77="","",SUMIFS(TblApplications[Coût IKS affecté (€)],TblApplications[Tribe],$B77,TblApplications[Environnement],p_envcrit)) | E77: =IF($B77="","",SUMIFS(TblApplications[Coût ROKS affecté (€)],TblApplications[Tribe],$B77,TblApplications[Environnement],p_envcrit)) | F77: =IF($B77="","",D77+E77) | I77: =IFERROR(IF(INDEX(TblDomaines[Domaine],15)="","",INDEX(TblDomaines[Domaine],15)),"") | J77: =IF($I77="","",SUMIFS(TblApplications[Coût IKS affecté (€)],TblApplications[Domaine],$I77,TblApplications[Environnement],p_envcrit)) | K77: =IF($I77="","",SUMIFS(TblApplications[Coût ROKS affecté (€)],TblApplications[Domaine],$I77,TblApplications[Environnement],p_envcrit)) | L77: =IF($I77="","",J77+K77)
B78: =IFERROR(IF(INDEX(TblTribes[Tribe],16)="","",INDEX(TblTribes[Tribe],16)),"") | C78: =IF($B78="","",INDEX(TblTribes[Domaine de la tribe],16)) | D78: =IF($B78="","",SUMIFS(TblApplications[Coût IKS affecté (€)],TblApplications[Tribe],$B78,TblApplications[Environnement],p_envcrit)) | E78: =IF($B78="","",SUMIFS(TblApplications[Coût ROKS affecté (€)],TblApplications[Tribe],$B78,TblApplications[Environnement],p_envcrit)) | F78: =IF($B78="","",D78+E78) | I78: =IFERROR(IF(INDEX(TblDomaines[Domaine],16)="","",INDEX(TblDomaines[Domaine],16)),"") | J78: =IF($I78="","",SUMIFS(TblApplications[Coût IKS affecté (€)],TblApplications[Domaine],$I78,TblApplications[Environnement],p_envcrit)) | K78: =IF($I78="","",SUMIFS(TblApplications[Coût ROKS affecté (€)],TblApplications[Domaine],$I78,TblApplications[Environnement],p_envcrit)) | L78: =IF($I78="","",J78+K78)
B79: =IFERROR(IF(INDEX(TblTribes[Tribe],17)="","",INDEX(TblTribes[Tribe],17)),"") | C79: =IF($B79="","",INDEX(TblTribes[Domaine de la tribe],17)) | D79: =IF($B79="","",SUMIFS(TblApplications[Coût IKS affecté (€)],TblApplications[Tribe],$B79,TblApplications[Environnement],p_envcrit)) | E79: =IF($B79="","",SUMIFS(TblApplications[Coût ROKS affecté (€)],TblApplications[Tribe],$B79,TblApplications[Environnement],p_envcrit)) | F79: =IF($B79="","",D79+E79) | I79: =IFERROR(IF(INDEX(TblDomaines[Domaine],17)="","",INDEX(TblDomaines[Domaine],17)),"") | J79: =IF($I79="","",SUMIFS(TblApplications[Coût IKS affecté (€)],TblApplications[Domaine],$I79,TblApplications[Environnement],p_envcrit)) | K79: =IF($I79="","",SUMIFS(TblApplications[Coût ROKS affecté (€)],TblApplications[Domaine],$I79,TblApplications[Environnement],p_envcrit)) | L79: =IF($I79="","",J79+K79)
B80: =IFERROR(IF(INDEX(TblTribes[Tribe],18)="","",INDEX(TblTribes[Tribe],18)),"") | C80: =IF($B80="","",INDEX(TblTribes[Domaine de la tribe],18)) | D80: =IF($B80="","",SUMIFS(TblApplications[Coût IKS affecté (€)],TblApplications[Tribe],$B80,TblApplications[Environnement],p_envcrit)) | E80: =IF($B80="","",SUMIFS(TblApplications[Coût ROKS affecté (€)],TblApplications[Tribe],$B80,TblApplications[Environnement],p_envcrit)) | F80: =IF($B80="","",D80+E80) | I80: =IFERROR(IF(INDEX(TblDomaines[Domaine],18)="","",INDEX(TblDomaines[Domaine],18)),"") | J80: =IF($I80="","",SUMIFS(TblApplications[Coût IKS affecté (€)],TblApplications[Domaine],$I80,TblApplications[Environnement],p_envcrit)) | K80: =IF($I80="","",SUMIFS(TblApplications[Coût ROKS affecté (€)],TblApplications[Domaine],$I80,TblApplications[Environnement],p_envcrit)) | L80: =IF($I80="","",J80+K80)
B81: =IFERROR(IF(INDEX(TblTribes[Tribe],19)="","",INDEX(TblTribes[Tribe],19)),"") | C81: =IF($B81="","",INDEX(TblTribes[Domaine de la tribe],19)) | D81: =IF($B81="","",SUMIFS(TblApplications[Coût IKS affecté (€)],TblApplications[Tribe],$B81,TblApplications[Environnement],p_envcrit)) | E81: =IF($B81="","",SUMIFS(TblApplications[Coût ROKS affecté (€)],TblApplications[Tribe],$B81,TblApplications[Environnement],p_envcrit)) | F81: =IF($B81="","",D81+E81) | I81: =IFERROR(IF(INDEX(TblDomaines[Domaine],19)="","",INDEX(TblDomaines[Domaine],19)),"") | J81: =IF($I81="","",SUMIFS(TblApplications[Coût IKS affecté (€)],TblApplications[Domaine],$I81,TblApplications[Environnement],p_envcrit)) | K81: =IF($I81="","",SUMIFS(TblApplications[Coût ROKS affecté (€)],TblApplications[Domaine],$I81,TblApplications[Environnement],p_envcrit)) | L81: =IF($I81="","",J81+K81)
B82: =IFERROR(IF(INDEX(TblTribes[Tribe],20)="","",INDEX(TblTribes[Tribe],20)),"") | C82: =IF($B82="","",INDEX(TblTribes[Domaine de la tribe],20)) | D82: =IF($B82="","",SUMIFS(TblApplications[Coût IKS affecté (€)],TblApplications[Tribe],$B82,TblApplications[Environnement],p_envcrit)) | E82: =IF($B82="","",SUMIFS(TblApplications[Coût ROKS affecté (€)],TblApplications[Tribe],$B82,TblApplications[Environnement],p_envcrit)) | F82: =IF($B82="","",D82+E82) | I82: =IFERROR(IF(INDEX(TblDomaines[Domaine],20)="","",INDEX(TblDomaines[Domaine],20)),"") | J82: =IF($I82="","",SUMIFS(TblApplications[Coût IKS affecté (€)],TblApplications[Domaine],$I82,TblApplications[Environnement],p_envcrit)) | K82: =IF($I82="","",SUMIFS(TblApplications[Coût ROKS affecté (€)],TblApplications[Domaine],$I82,TblApplications[Environnement],p_envcrit)) | L82: =IF($I82="","",J82+K82)
B83: =IFERROR(IF(INDEX(TblTribes[Tribe],21)="","",INDEX(TblTribes[Tribe],21)),"") | C83: =IF($B83="","",INDEX(TblTribes[Domaine de la tribe],21)) | D83: =IF($B83="","",SUMIFS(TblApplications[Coût IKS affecté (€)],TblApplications[Tribe],$B83,TblApplications[Environnement],p_envcrit)) | E83: =IF($B83="","",SUMIFS(TblApplications[Coût ROKS affecté (€)],TblApplications[Tribe],$B83,TblApplications[Environnement],p_envcrit)) | F83: =IF($B83="","",D83+E83)
B84: =IFERROR(IF(INDEX(TblTribes[Tribe],22)="","",INDEX(TblTribes[Tribe],22)),"") | C84: =IF($B84="","",INDEX(TblTribes[Domaine de la tribe],22)) | D84: =IF($B84="","",SUMIFS(TblApplications[Coût IKS affecté (€)],TblApplications[Tribe],$B84,TblApplications[Environnement],p_envcrit)) | E84: =IF($B84="","",SUMIFS(TblApplications[Coût ROKS affecté (€)],TblApplications[Tribe],$B84,TblApplications[Environnement],p_envcrit)) | F84: =IF($B84="","",D84+E84)
B85: =IFERROR(IF(INDEX(TblTribes[Tribe],23)="","",INDEX(TblTribes[Tribe],23)),"") | C85: =IF($B85="","",INDEX(TblTribes[Domaine de la tribe],23)) | D85: =IF($B85="","",SUMIFS(TblApplications[Coût IKS affecté (€)],TblApplications[Tribe],$B85,TblApplications[Environnement],p_envcrit)) | E85: =IF($B85="","",SUMIFS(TblApplications[Coût ROKS affecté (€)],TblApplications[Tribe],$B85,TblApplications[Environnement],p_envcrit)) | F85: =IF($B85="","",D85+E85)
B86: =IFERROR(IF(INDEX(TblTribes[Tribe],24)="","",INDEX(TblTribes[Tribe],24)),"") | C86: =IF($B86="","",INDEX(TblTribes[Domaine de la tribe],24)) | D86: =IF($B86="","",SUMIFS(TblApplications[Coût IKS affecté (€)],TblApplications[Tribe],$B86,TblApplications[Environnement],p_envcrit)) | E86: =IF($B86="","",SUMIFS(TblApplications[Coût ROKS affecté (€)],TblApplications[Tribe],$B86,TblApplications[Environnement],p_envcrit)) | F86: =IF($B86="","",D86+E86)
B87: =IFERROR(IF(INDEX(TblTribes[Tribe],25)="","",INDEX(TblTribes[Tribe],25)),"") | C87: =IF($B87="","",INDEX(TblTribes[Domaine de la tribe],25)) | D87: =IF($B87="","",SUMIFS(TblApplications[Coût IKS affecté (€)],TblApplications[Tribe],$B87,TblApplications[Environnement],p_envcrit)) | E87: =IF($B87="","",SUMIFS(TblApplications[Coût ROKS affecté (€)],TblApplications[Tribe],$B87,TblApplications[Environnement],p_envcrit)) | F87: =IF($B87="","",D87+E87)
B88: =IFERROR(IF(INDEX(TblTribes[Tribe],26)="","",INDEX(TblTribes[Tribe],26)),"") | C88: =IF($B88="","",INDEX(TblTribes[Domaine de la tribe],26)) | D88: =IF($B88="","",SUMIFS(TblApplications[Coût IKS affecté (€)],TblApplications[Tribe],$B88,TblApplications[Environnement],p_envcrit)) | E88: =IF($B88="","",SUMIFS(TblApplications[Coût ROKS affecté (€)],TblApplications[Tribe],$B88,TblApplications[Environnement],p_envcrit)) | F88: =IF($B88="","",D88+E88)
B89: =IFERROR(IF(INDEX(TblTribes[Tribe],27)="","",INDEX(TblTribes[Tribe],27)),"") | C89: =IF($B89="","",INDEX(TblTribes[Domaine de la tribe],27)) | D89: =IF($B89="","",SUMIFS(TblApplications[Coût IKS affecté (€)],TblApplications[Tribe],$B89,TblApplications[Environnement],p_envcrit)) | E89: =IF($B89="","",SUMIFS(TblApplications[Coût ROKS affecté (€)],TblApplications[Tribe],$B89,TblApplications[Environnement],p_envcrit)) | F89: =IF($B89="","",D89+E89)
B90: =IFERROR(IF(INDEX(TblTribes[Tribe],28)="","",INDEX(TblTribes[Tribe],28)),"") | C90: =IF($B90="","",INDEX(TblTribes[Domaine de la tribe],28)) | D90: =IF($B90="","",SUMIFS(TblApplications[Coût IKS affecté (€)],TblApplications[Tribe],$B90,TblApplications[Environnement],p_envcrit)) | E90: =IF($B90="","",SUMIFS(TblApplications[Coût ROKS affecté (€)],TblApplications[Tribe],$B90,TblApplications[Environnement],p_envcrit)) | F90: =IF($B90="","",D90+E90)
B91: =IFERROR(IF(INDEX(TblTribes[Tribe],29)="","",INDEX(TblTribes[Tribe],29)),"") | C91: =IF($B91="","",INDEX(TblTribes[Domaine de la tribe],29)) | D91: =IF($B91="","",SUMIFS(TblApplications[Coût IKS affecté (€)],TblApplications[Tribe],$B91,TblApplications[Environnement],p_envcrit)) | E91: =IF($B91="","",SUMIFS(TblApplications[Coût ROKS affecté (€)],TblApplications[Tribe],$B91,TblApplications[Environnement],p_envcrit)) | F91: =IF($B91="","",D91+E91)
B92: =IFERROR(IF(INDEX(TblTribes[Tribe],30)="","",INDEX(TblTribes[Tribe],30)),"") | C92: =IF($B92="","",INDEX(TblTribes[Domaine de la tribe],30)) | D92: =IF($B92="","",SUMIFS(TblApplications[Coût IKS affecté (€)],TblApplications[Tribe],$B92,TblApplications[Environnement],p_envcrit)) | E92: =IF($B92="","",SUMIFS(TblApplications[Coût ROKS affecté (€)],TblApplications[Tribe],$B92,TblApplications[Environnement],p_envcrit)) | F92: =IF($B92="","",D92+E92)
B93: =IFERROR(IF(INDEX(TblTribes[Tribe],31)="","",INDEX(TblTribes[Tribe],31)),"") | C93: =IF($B93="","",INDEX(TblTribes[Domaine de la tribe],31)) | D93: =IF($B93="","",SUMIFS(TblApplications[Coût IKS affecté (€)],TblApplications[Tribe],$B93,TblApplications[Environnement],p_envcrit)) | E93: =IF($B93="","",SUMIFS(TblApplications[Coût ROKS affecté (€)],TblApplications[Tribe],$B93,TblApplications[Environnement],p_envcrit)) | F93: =IF($B93="","",D93+E93)
B94: =IFERROR(IF(INDEX(TblTribes[Tribe],32)="","",INDEX(TblTribes[Tribe],32)),"") | C94: =IF($B94="","",INDEX(TblTribes[Domaine de la tribe],32)) | D94: =IF($B94="","",SUMIFS(TblApplications[Coût IKS affecté (€)],TblApplications[Tribe],$B94,TblApplications[Environnement],p_envcrit)) | E94: =IF($B94="","",SUMIFS(TblApplications[Coût ROKS affecté (€)],TblApplications[Tribe],$B94,TblApplications[Environnement],p_envcrit)) | F94: =IF($B94="","",D94+E94)
B95: =IFERROR(IF(INDEX(TblTribes[Tribe],33)="","",INDEX(TblTribes[Tribe],33)),"") | C95: =IF($B95="","",INDEX(TblTribes[Domaine de la tribe],33)) | D95: =IF($B95="","",SUMIFS(TblApplications[Coût IKS affecté (€)],TblApplications[Tribe],$B95,TblApplications[Environnement],p_envcrit)) | E95: =IF($B95="","",SUMIFS(TblApplications[Coût ROKS affecté (€)],TblApplications[Tribe],$B95,TblApplications[Environnement],p_envcrit)) | F95: =IF($B95="","",D95+E95)
B96: =IFERROR(IF(INDEX(TblTribes[Tribe],34)="","",INDEX(TblTribes[Tribe],34)),"") | C96: =IF($B96="","",INDEX(TblTribes[Domaine de la tribe],34)) | D96: =IF($B96="","",SUMIFS(TblApplications[Coût IKS affecté (€)],TblApplications[Tribe],$B96,TblApplications[Environnement],p_envcrit)) | E96: =IF($B96="","",SUMIFS(TblApplications[Coût ROKS affecté (€)],TblApplications[Tribe],$B96,TblApplications[Environnement],p_envcrit)) | F96: =IF($B96="","",D96+E96)
B97: =IFERROR(IF(INDEX(TblTribes[Tribe],35)="","",INDEX(TblTribes[Tribe],35)),"") | C97: =IF($B97="","",INDEX(TblTribes[Domaine de la tribe],35)) | D97: =IF($B97="","",SUMIFS(TblApplications[Coût IKS affecté (€)],TblApplications[Tribe],$B97,TblApplications[Environnement],p_envcrit)) | E97: =IF($B97="","",SUMIFS(TblApplications[Coût ROKS affecté (€)],TblApplications[Tribe],$B97,TblApplications[Environnement],p_envcrit)) | F97: =IF($B97="","",D97+E97)
B98: =IFERROR(IF(INDEX(TblTribes[Tribe],36)="","",INDEX(TblTribes[Tribe],36)),"") | C98: =IF($B98="","",INDEX(TblTribes[Domaine de la tribe],36)) | D98: =IF($B98="","",SUMIFS(TblApplications[Coût IKS affecté (€)],TblApplications[Tribe],$B98,TblApplications[Environnement],p_envcrit)) | E98: =IF($B98="","",SUMIFS(TblApplications[Coût ROKS affecté (€)],TblApplications[Tribe],$B98,TblApplications[Environnement],p_envcrit)) | F98: =IF($B98="","",D98+E98)
B99: =IFERROR(IF(INDEX(TblTribes[Tribe],37)="","",INDEX(TblTribes[Tribe],37)),"") | C99: =IF($B99="","",INDEX(TblTribes[Domaine de la tribe],37)) | D99: =IF($B99="","",SUMIFS(TblApplications[Coût IKS affecté (€)],TblApplications[Tribe],$B99,TblApplications[Environnement],p_envcrit)) | E99: =IF($B99="","",SUMIFS(TblApplications[Coût ROKS affecté (€)],TblApplications[Tribe],$B99,TblApplications[Environnement],p_envcrit)) | F99: =IF($B99="","",D99+E99)
B100: =IFERROR(IF(INDEX(TblTribes[Tribe],38)="","",INDEX(TblTribes[Tribe],38)),"") | C100: =IF($B100="","",INDEX(TblTribes[Domaine de la tribe],38)) | D100: =IF($B100="","",SUMIFS(TblApplications[Coût IKS affecté (€)],TblApplications[Tribe],$B100,TblApplications[Environnement],p_envcrit)) | E100: =IF($B100="","",SUMIFS(TblApplications[Coût ROKS affecté (€)],TblApplications[Tribe],$B100,TblApplications[Environnement],p_envcrit)) | F100: =IF($B100="","",D100+E100)
B101: =IFERROR(IF(INDEX(TblTribes[Tribe],39)="","",INDEX(TblTribes[Tribe],39)),"") | C101: =IF($B101="","",INDEX(TblTribes[Domaine de la tribe],39)) | D101: =IF($B101="","",SUMIFS(TblApplications[Coût IKS affecté (€)],TblApplications[Tribe],$B101,TblApplications[Environnement],p_envcrit)) | E101: =IF($B101="","",SUMIFS(TblApplications[Coût ROKS affecté (€)],TblApplications[Tribe],$B101,TblApplications[Environnement],p_envcrit)) | F101: =IF($B101="","",D101+E101)
B102: =IFERROR(IF(INDEX(TblTribes[Tribe],40)="","",INDEX(TblTribes[Tribe],40)),"") | C102: =IF($B102="","",INDEX(TblTribes[Domaine de la tribe],40)) | D102: =IF($B102="","",SUMIFS(TblApplications[Coût IKS affecté (€)],TblApplications[Tribe],$B102,TblApplications[Environnement],p_envcrit)) | E102: =IF($B102="","",SUMIFS(TblApplications[Coût ROKS affecté (€)],TblApplications[Tribe],$B102,TblApplications[Environnement],p_envcrit)) | F102: =IF($B102="","",D102+E102)

Sheet Avancement
B1: Avancement de la migration
B2: Déploiements par action, par tribe, domaine et environnement ; frise des migrations prévues. Filtres ligne 4.
B4: Environnement | C4: Tous | E4: Domaine | F4: Tous | H4: Tribe | I4: Tous | K4: Mois de référence | L4: 46722 | AD4: =IF(C4="Tous","*",C4) -> * | AE4: =IF(F4="Tous","*",F4) -> * | AF4: =IF(I4="Tous","*",I4) -> * | AG4: =IFERROR(DATE(YEAR(L4),MONTH(L4),1),p_debut) -> 46722
B6: Migrés | D6: À migrer | F6: À décommissionner | H6: Décommissionnés | J6: Traités au mois de référence | L6: % traité au mois de référence
B7: =COUNTIFS(TblApplications[Action],"Migré",TblApplications[Environnement],av_envc,TblApplications[Domaine],av_domc,TblApplications[Tribe],av_tric) -> 1 | D7: =COUNTIFS(TblApplications[Action],"À migrer",TblApplications[Environnement],av_envc,TblApplications[Domaine],av_domc,TblApplications[Tribe],av_tric) -> 10 | F7: =COUNTIFS(TblApplications[Action],"À décommissionner",TblApplications[Environnement],av_envc,TblApplications[Domaine],av_domc,TblApplications[Tribe],av_tric) -> 1 | H7: =COUNTIFS(TblApplications[Action],"Décommissionné",TblApplications[Environnement],av_envc,TblApplications[Domaine],av_domc,TblApplications[Tribe],av_tric) -> 1 | J7: =(COUNTIFS(TblApplications[Action],"Migré",TblApplications[Environnement],av_envc,TblApplications[Domaine],av_domc,TblApplications[Tribe],av_tric)+COUNTIFS(TblApplications[Action],"Décommissionné",TblApplications[Environnement],av_envc,TblApplications[Domaine],av_domc,TblApplications[Tribe],av_tric)+COUNTIFS(TblApplications[Action],"À migrer",TblApplications[Mois lib (calc)],"<="&av_mois,TblApplications[Environnement],av_envc,TblApplications[Domaine],av_domc,TblApplications[Tribe],av_tric)+COUNTIFS(TblApplications[Action],"À décommissionner",TblApplications[Mois lib (calc)],"<="&av_mois,TblApplications[Environnement],av_envc,TblApplications[Domaine],av_domc,TblApplications[Tribe],av_tric)) -> 9 | L7: =IFERROR((COUNTIFS(TblApplications[Action],"Migré",TblApplications[Environnement],av_envc,TblApplications[Domaine],av_domc,TblApplications[Tribe],av_tric)+COUNTIFS(TblApplications[Action],"Décommissionné",TblApplications[Environnement],av_envc,TblApplications[Domaine],av_domc,TblApplications[Tribe],av_tric)+COUNTIFS(TblApplications[Action],"À migrer",TblApplications[Mois lib (calc)],"<="&av_mois,TblApplications[Environnement],av_envc,TblApplications[Domaine],av_domc,TblApplications[Tribe],av_tric)+COUNTIFS(TblApplications[Action],"À décommissionner",TblApplications[Mois lib (calc)],"<="&av_mois,TblApplications[Environnement],av_envc,TblApplications[Domaine],av_domc,TblApplications[Tribe],av_tric))/COUNTIFS(TblApplications[ID],"<>",TblApplications[Environnement],av_envc,TblApplications[Domaine],av_domc,TblApplications[Tribe],av_tric),0) -> 0.69230769
B9: Traité = Migré ou Décommissionné, plus les déploiements « À migrer » / « À décommissionner » dont l'IKS est libéré au mois de référence.
B11: Répartition par tribe et par domaine (nombre de déploiements)
B33: Tribe | C33: Domaine | D33: Migré | E33: À migrer | F33: À décommissionner | G33: Décommissionné | H33: Total | K33: Domaine | L33: Migré | M33: À migrer | N33: À décommissionner | O33: Décommissionné | P33: Total
B34: =IFERROR(IF(INDEX(TblTribes[Tribe],1)="","",INDEX(TblTribes[Tribe],1)),"") -> Parcours client | C34: =IF($B34="","",INDEX(TblTribes[Domaine de la tribe],1)) -> Distribution | D34: =IF($B34="","",COUNTIFS(TblApplications[Tribe],$B34,TblApplications[Action],"Migré",TblApplications[Environnement],av_envc,TblApplications[Domaine],av_domc,TblApplications[Tribe],av_tric)) -> 0 | E34: =IF($B34="","",COUNTIFS(TblApplications[Tribe],$B34,TblApplications[Action],"À migrer",TblApplications[Environnement],av_envc,TblApplications[Domaine],av_domc,TblApplications[Tribe],av_tric)) -> 3 | F34: =IF($B34="","",COUNTIFS(TblApplications[Tribe],$B34,TblApplications[Action],"À décommissionner",TblApplications[Environnement],av_envc,TblApplications[Domaine],av_domc,TblApplications[Tribe],av_tric)) -> 1 | G34: =IF($B34="","",COUNTIFS(TblApplications[Tribe],$B34,TblApplications[Action],"Décommissionné",TblApplications[Environnement],av_envc,TblApplications[Domaine],av_domc,TblApplications[Tribe],av_tric)) -> 0 | H34: =IF($B34="","",SUM(D34:G34)) -> 4 | K34: =IFERROR(IF(INDEX(TblDomaines[Domaine],1)="","",INDEX(TblDomaines[Domaine],1)),"") -> Distribution | L34: =IF($K34="","",COUNTIFS(TblApplications[Domaine],$K34,TblApplications[Action],"Migré",TblApplications[Environnement],av_envc,TblApplications[Domaine],av_domc,TblApplications[Tribe],av_tric)) -> 0 | M34: =IF($K34="","",COUNTIFS(TblApplications[Domaine],$K34,TblApplications[Action],"À migrer",TblApplications[Environnement],av_envc,TblApplications[Domaine],av_domc,TblApplications[Tribe],av_tric)) -> 7 | N34: =IF($K34="","",COUNTIFS(TblApplications[Domaine],$K34,TblApplications[Action],"À décommissionner",TblApplications[Environnement],av_envc,TblApplications[Domaine],av_domc,TblApplications[Tribe],av_tric)) -> 1 | O34: =IF($K34="","",COUNTIFS(TblApplications[Domaine],$K34,TblApplications[Action],"Décommissionné",TblApplications[Environnement],av_envc,TblApplications[Domaine],av_domc,TblApplications[Tribe],av_tric)) -> 1 | P34: =IF($K34="","",SUM(L34:O34)) -> 9
B35: =IFERROR(IF(INDEX(TblTribes[Tribe],2)="","",INDEX(TblTribes[Tribe],2)),"") -> Tarification | C35: =IF($B35="","",INDEX(TblTribes[Domaine de la tribe],2)) -> Distribution | D35: =IF($B35="","",COUNTIFS(TblApplications[Tribe],$B35,TblApplications[Action],"Migré",TblApplications[Environnement],av_envc,TblApplications[Domaine],av_domc,TblApplications[Tribe],av_tric)) -> 0 | E35: =IF($B35="","",COUNTIFS(TblApplications[Tribe],$B35,TblApplications[Action],"À migrer",TblApplications[Environnement],av_envc,TblApplications[Domaine],av_domc,TblApplications[Tribe],av_tric)) -> 4 | F35: =IF($B35="","",COUNTIFS(TblApplications[Tribe],$B35,TblApplications[Action],"À décommissionner",TblApplications[Environnement],av_envc,TblApplications[Domaine],av_domc,TblApplications[Tribe],av_tric)) -> 0 | G35: =IF($B35="","",COUNTIFS(TblApplications[Tribe],$B35,TblApplications[Action],"Décommissionné",TblApplications[Environnement],av_envc,TblApplications[Domaine],av_domc,TblApplications[Tribe],av_tric)) -> 1 | H35: =IF($B35="","",SUM(D35:G35)) -> 5 | K35: =IFERROR(IF(INDEX(TblDomaines[Domaine],2)="","",INDEX(TblDomaines[Domaine],2)),"") -> Indemnisation | L35: =IF($K35="","",COUNTIFS(TblApplications[Domaine],$K35,TblApplications[Action],"Migré",TblApplications[Environnement],av_envc,TblApplications[Domaine],av_domc,TblApplications[Tribe],av_tric)) -> 1 | M35: =IF($K35="","",COUNTIFS(TblApplications[Domaine],$K35,TblApplications[Action],"À migrer",TblApplications[Environnement],av_envc,TblApplications[Domaine],av_domc,TblApplications[Tribe],av_tric)) -> 3 | N35: =IF($K35="","",COUNTIFS(TblApplications[Domaine],$K35,TblApplications[Action],"À décommissionner",TblApplications[Environnement],av_envc,TblApplications[Domaine],av_domc,TblApplications[Tribe],av_tric)) -> 0 | O35: =IF($K35="","",COUNTIFS(TblApplications[Domaine],$K35,TblApplications[Action],"Décommissionné",TblApplications[Environnement],av_envc,TblApplications[Domaine],av_domc,TblApplications[Tribe],av_tric)) -> 0 | P35: =IF($K35="","",SUM(L35:O35)) -> 4
B36: =IFERROR(IF(INDEX(TblTribes[Tribe],3)="","",INDEX(TblTribes[Tribe],3)),"") -> Sinistres | C36: =IF($B36="","",INDEX(TblTribes[Domaine de la tribe],3)) -> Indemnisation | D36: =IF($B36="","",COUNTIFS(TblApplications[Tribe],$B36,TblApplications[Action],"Migré",TblApplications[Environnement],av_envc,TblApplications[Domaine],av_domc,TblApplications[Tribe],av_tric)) -> 1 | E36: =IF($B36="","",COUNTIFS(TblApplications[Tribe],$B36,TblApplications[Action],"À migrer",TblApplications[Environnement],av_envc,TblApplications[Domaine],av_domc,TblApplications[Tribe],av_tric)) -> 3 | F36: =IF($B36="","",COUNTIFS(TblApplications[Tribe],$B36,TblApplications[Action],"À décommissionner",TblApplications[Environnement],av_envc,TblApplications[Domaine],av_domc,TblApplications[Tribe],av_tric)) -> 0 | G36: =IF($B36="","",COUNTIFS(TblApplications[Tribe],$B36,TblApplications[Action],"Décommissionné",TblApplications[Environnement],av_envc,TblApplications[Domaine],av_domc,TblApplications[Tribe],av_tric)) -> 0 | H36: =IF($B36="","",SUM(D36:G36)) -> 4 | K36: =IFERROR(IF(INDEX(TblDomaines[Domaine],3)="","",INDEX(TblDomaines[Domaine],3)),"") | L36: =IF($K36="","",COUNTIFS(TblApplications[Domaine],$K36,TblApplications[Action],"Migré",TblApplications[Environnement],av_envc,TblApplications[Domaine],av_domc,TblApplications[Tribe],av_tric)) | M36: =IF($K36="","",COUNTIFS(TblApplications[Domaine],$K36,TblApplications[Action],"À migrer",TblApplications[Environnement],av_envc,TblApplications[Domaine],av_domc,TblApplications[Tribe],av_tric)) | N36: =IF($K36="","",COUNTIFS(TblApplications[Domaine],$K36,TblApplications[Action],"À décommissionner",TblApplications[Environnement],av_envc,TblApplications[Domaine],av_domc,TblApplications[Tribe],av_tric)) | O36: =IF($K36="","",COUNTIFS(TblApplications[Domaine],$K36,TblApplications[Action],"Décommissionné",TblApplications[Environnement],av_envc,TblApplications[Domaine],av_domc,TblApplications[Tribe],av_tric)) | P36: =IF($K36="","",SUM(L36:O36))
B37: =IFERROR(IF(INDEX(TblTribes[Tribe],4)="","",INDEX(TblTribes[Tribe],4)),"") | C37: =IF($B37="","",INDEX(TblTribes[Domaine de la tribe],4)) | D37: =IF($B37="","",COUNTIFS(TblApplications[Tribe],$B37,TblApplications[Action],"Migré",TblApplications[Environnement],av_envc,TblApplications[Domaine],av_domc,TblApplications[Tribe],av_tric)) | E37: =IF($B37="","",COUNTIFS(TblApplications[Tribe],$B37,TblApplications[Action],"À migrer",TblApplications[Environnement],av_envc,TblApplications[Domaine],av_domc,TblApplications[Tribe],av_tric)) | F37: =IF($B37="","",COUNTIFS(TblApplications[Tribe],$B37,TblApplications[Action],"À décommissionner",TblApplications[Environnement],av_envc,TblApplications[Domaine],av_domc,TblApplications[Tribe],av_tric)) | G37: =IF($B37="","",COUNTIFS(TblApplications[Tribe],$B37,TblApplications[Action],"Décommissionné",TblApplications[Environnement],av_envc,TblApplications[Domaine],av_domc,TblApplications[Tribe],av_tric)) | H37: =IF($B37="","",SUM(D37:G37)) | K37: =IFERROR(IF(INDEX(TblDomaines[Domaine],4)="","",INDEX(TblDomaines[Domaine],4)),"") | L37: =IF($K37="","",COUNTIFS(TblApplications[Domaine],$K37,TblApplications[Action],"Migré",TblApplications[Environnement],av_envc,TblApplications[Domaine],av_domc,TblApplications[Tribe],av_tric)) | M37: =IF($K37="","",COUNTIFS(TblApplications[Domaine],$K37,TblApplications[Action],"À migrer",TblApplications[Environnement],av_envc,TblApplications[Domaine],av_domc,TblApplications[Tribe],av_tric)) | N37: =IF($K37="","",COUNTIFS(TblApplications[Domaine],$K37,TblApplications[Action],"À décommissionner",TblApplications[Environnement],av_envc,TblApplications[Domaine],av_domc,TblApplications[Tribe],av_tric)) | O37: =IF($K37="","",COUNTIFS(TblApplications[Domaine],$K37,TblApplications[Action],"Décommissionné",TblApplications[Environnement],av_envc,TblApplications[Domaine],av_domc,TblApplications[Tribe],av_tric)) | P37: =IF($K37="","",SUM(L37:O37))
B38: =IFERROR(IF(INDEX(TblTribes[Tribe],5)="","",INDEX(TblTribes[Tribe],5)),"") | C38: =IF($B38="","",INDEX(TblTribes[Domaine de la tribe],5)) | D38: =IF($B38="","",COUNTIFS(TblApplications[Tribe],$B38,TblApplications[Action],"Migré",TblApplications[Environnement],av_envc,TblApplications[Domaine],av_domc,TblApplications[Tribe],av_tric)) | E38: =IF($B38="","",COUNTIFS(TblApplications[Tribe],$B38,TblApplications[Action],"À migrer",TblApplications[Environnement],av_envc,TblApplications[Domaine],av_domc,TblApplications[Tribe],av_tric)) | F38: =IF($B38="","",COUNTIFS(TblApplications[Tribe],$B38,TblApplications[Action],"À décommissionner",TblApplications[Environnement],av_envc,TblApplications[Domaine],av_domc,TblApplications[Tribe],av_tric)) | G38: =IF($B38="","",COUNTIFS(TblApplications[Tribe],$B38,TblApplications[Action],"Décommissionné",TblApplications[Environnement],av_envc,TblApplications[Domaine],av_domc,TblApplications[Tribe],av_tric)) | H38: =IF($B38="","",SUM(D38:G38)) | K38: =IFERROR(IF(INDEX(TblDomaines[Domaine],5)="","",INDEX(TblDomaines[Domaine],5)),"") | L38: =IF($K38="","",COUNTIFS(TblApplications[Domaine],$K38,TblApplications[Action],"Migré",TblApplications[Environnement],av_envc,TblApplications[Domaine],av_domc,TblApplications[Tribe],av_tric)) | M38: =IF($K38="","",COUNTIFS(TblApplications[Domaine],$K38,TblApplications[Action],"À migrer",TblApplications[Environnement],av_envc,TblApplications[Domaine],av_domc,TblApplications[Tribe],av_tric)) | N38: =IF($K38="","",COUNTIFS(TblApplications[Domaine],$K38,TblApplications[Action],"À décommissionner",TblApplications[Environnement],av_envc,TblApplications[Domaine],av_domc,TblApplications[Tribe],av_tric)) | O38: =IF($K38="","",COUNTIFS(TblApplications[Domaine],$K38,TblApplications[Action],"Décommissionné",TblApplications[Environnement],av_envc,TblApplications[Domaine],av_domc,TblApplications[Tribe],av_tric)) | P38: =IF($K38="","",SUM(L38:O38))
B39: =IFERROR(IF(INDEX(TblTribes[Tribe],6)="","",INDEX(TblTribes[Tribe],6)),"") | C39: =IF($B39="","",INDEX(TblTribes[Domaine de la tribe],6)) | D39: =IF($B39="","",COUNTIFS(TblApplications[Tribe],$B39,TblApplications[Action],"Migré",TblApplications[Environnement],av_envc,TblApplications[Domaine],av_domc,TblApplications[Tribe],av_tric)) | E39: =IF($B39="","",COUNTIFS(TblApplications[Tribe],$B39,TblApplications[Action],"À migrer",TblApplications[Environnement],av_envc,TblApplications[Domaine],av_domc,TblApplications[Tribe],av_tric)) | F39: =IF($B39="","",COUNTIFS(TblApplications[Tribe],$B39,TblApplications[Action],"À décommissionner",TblApplications[Environnement],av_envc,TblApplications[Domaine],av_domc,TblApplications[Tribe],av_tric)) | G39: =IF($B39="","",COUNTIFS(TblApplications[Tribe],$B39,TblApplications[Action],"Décommissionné",TblApplications[Environnement],av_envc,TblApplications[Domaine],av_domc,TblApplications[Tribe],av_tric)) | H39: =IF($B39="","",SUM(D39:G39)) | K39: =IFERROR(IF(INDEX(TblDomaines[Domaine],6)="","",INDEX(TblDomaines[Domaine],6)),"") | L39: =IF($K39="","",COUNTIFS(TblApplications[Domaine],$K39,TblApplications[Action],"Migré",TblApplications[Environnement],av_envc,TblApplications[Domaine],av_domc,TblApplications[Tribe],av_tric)) | M39: =IF($K39="","",COUNTIFS(TblApplications[Domaine],$K39,TblApplications[Action],"À migrer",TblApplications[Environnement],av_envc,TblApplications[Domaine],av_domc,TblApplications[Tribe],av_tric)) | N39: =IF($K39="","",COUNTIFS(TblApplications[Domaine],$K39,TblApplications[Action],"À décommissionner",TblApplications[Environnement],av_envc,TblApplications[Domaine],av_domc,TblApplications[Tribe],av_tric)) | O39: =IF($K39="","",COUNTIFS(TblApplications[Domaine],$K39,TblApplications[Action],"Décommissionné",TblApplications[Environnement],av_envc,TblApplications[Domaine],av_domc,TblApplications[Tribe],av_tric)) | P39: =IF($K39="","",SUM(L39:O39))
B40: =IFERROR(IF(INDEX(TblTribes[Tribe],7)="","",INDEX(TblTribes[Tribe],7)),"") | C40: =IF($B40="","",INDEX(TblTribes[Domaine de la tribe],7)) | D40: =IF($B40="","",COUNTIFS(TblApplications[Tribe],$B40,TblApplications[Action],"Migré",TblApplications[Environnement],av_envc,TblApplications[Domaine],av_domc,TblApplications[Tribe],av_tric)) | E40: =IF($B40="","",COUNTIFS(TblApplications[Tribe],$B40,TblApplications[Action],"À migrer",TblApplications[Environnement],av_envc,TblApplications[Domaine],av_domc,TblApplications[Tribe],av_tric)) | F40: =IF($B40="","",COUNTIFS(TblApplications[Tribe],$B40,TblApplications[Action],"À décommissionner",TblApplications[Environnement],av_envc,TblApplications[Domaine],av_domc,TblApplications[Tribe],av_tric)) | G40: =IF($B40="","",COUNTIFS(TblApplications[Tribe],$B40,TblApplications[Action],"Décommissionné",TblApplications[Environnement],av_envc,TblApplications[Domaine],av_domc,TblApplications[Tribe],av_tric)) | H40: =IF($B40="","",SUM(D40:G40)) | K40: =IFERROR(IF(INDEX(TblDomaines[Domaine],7)="","",INDEX(TblDomaines[Domaine],7)),"") | L40: =IF($K40="","",COUNTIFS(TblApplications[Domaine],$K40,TblApplications[Action],"Migré",TblApplications[Environnement],av_envc,TblApplications[Domaine],av_domc,TblApplications[Tribe],av_tric)) | M40: =IF($K40="","",COUNTIFS(TblApplications[Domaine],$K40,TblApplications[Action],"À migrer",TblApplications[Environnement],av_envc,TblApplications[Domaine],av_domc,TblApplications[Tribe],av_tric)) | N40: =IF($K40="","",COUNTIFS(TblApplications[Domaine],$K40,TblApplications[Action],"À décommissionner",TblApplications[Environnement],av_envc,TblApplications[Domaine],av_domc,TblApplications[Tribe],av_tric)) | O40: =IF($K40="","",COUNTIFS(TblApplications[Domaine],$K40,TblApplications[Action],"Décommissionné",TblApplications[Environnement],av_envc,TblApplications[Domaine],av_domc,TblApplications[Tribe],av_tric)) | P40: =IF($K40="","",SUM(L40:O40))
B41: =IFERROR(IF(INDEX(TblTribes[Tribe],8)="","",INDEX(TblTribes[Tribe],8)),"") | C41: =IF($B41="","",INDEX(TblTribes[Domaine de la tribe],8)) | D41: =IF($B41="","",COUNTIFS(TblApplications[Tribe],$B41,TblApplications[Action],"Migré",TblApplications[Environnement],av_envc,TblApplications[Domaine],av_domc,TblApplications[Tribe],av_tric)) | E41: =IF($B41="","",COUNTIFS(TblApplications[Tribe],$B41,TblApplications[Action],"À migrer",TblApplications[Environnement],av_envc,TblApplications[Domaine],av_domc,TblApplications[Tribe],av_tric)) | F41: =IF($B41="","",COUNTIFS(TblApplications[Tribe],$B41,TblApplications[Action],"À décommissionner",TblApplications[Environnement],av_envc,TblApplications[Domaine],av_domc,TblApplications[Tribe],av_tric)) | G41: =IF($B41="","",COUNTIFS(TblApplications[Tribe],$B41,TblApplications[Action],"Décommissionné",TblApplications[Environnement],av_envc,TblApplications[Domaine],av_domc,TblApplications[Tribe],av_tric)) | H41: =IF($B41="","",SUM(D41:G41)) | K41: =IFERROR(IF(INDEX(TblDomaines[Domaine],8)="","",INDEX(TblDomaines[Domaine],8)),"") | L41: =IF($K41="","",COUNTIFS(TblApplications[Domaine],$K41,TblApplications[Action],"Migré",TblApplications[Environnement],av_envc,TblApplications[Domaine],av_domc,TblApplications[Tribe],av_tric)) | M41: =IF($K41="","",COUNTIFS(TblApplications[Domaine],$K41,TblApplications[Action],"À migrer",TblApplications[Environnement],av_envc,TblApplications[Domaine],av_domc,TblApplications[Tribe],av_tric)) | N41: =IF($K41="","",COUNTIFS(TblApplications[Domaine],$K41,TblApplications[Action],"À décommissionner",TblApplications[Environnement],av_envc,TblApplications[Domaine],av_domc,TblApplications[Tribe],av_tric)) | O41: =IF($K41="","",COUNTIFS(TblApplications[Domaine],$K41,TblApplications[Action],"Décommissionné",TblApplications[Environnement],av_envc,TblApplications[Domaine],av_domc,TblApplications[Tribe],av_tric)) | P41: =IF($K41="","",SUM(L41:O41))
B42: =IFERROR(IF(INDEX(TblTribes[Tribe],9)="","",INDEX(TblTribes[Tribe],9)),"") | C42: =IF($B42="","",INDEX(TblTribes[Domaine de la tribe],9)) | D42: =IF($B42="","",COUNTIFS(TblApplications[Tribe],$B42,TblApplications[Action],"Migré",TblApplications[Environnement],av_envc,TblApplications[Domaine],av_domc,TblApplications[Tribe],av_tric)) | E42: =IF($B42="","",COUNTIFS(TblApplications[Tribe],$B42,TblApplications[Action],"À migrer",TblApplications[Environnement],av_envc,TblApplications[Domaine],av_domc,TblApplications[Tribe],av_tric)) | F42: =IF($B42="","",COUNTIFS(TblApplications[Tribe],$B42,TblApplications[Action],"À décommissionner",TblApplications[Environnement],av_envc,TblApplications[Domaine],av_domc,TblApplications[Tribe],av_tric)) | G42: =IF($B42="","",COUNTIFS(TblApplications[Tribe],$B42,TblApplications[Action],"Décommissionné",TblApplications[Environnement],av_envc,TblApplications[Domaine],av_domc,TblApplications[Tribe],av_tric)) | H42: =IF($B42="","",SUM(D42:G42)) | K42: =IFERROR(IF(INDEX(TblDomaines[Domaine],9)="","",INDEX(TblDomaines[Domaine],9)),"") | L42: =IF($K42="","",COUNTIFS(TblApplications[Domaine],$K42,TblApplications[Action],"Migré",TblApplications[Environnement],av_envc,TblApplications[Domaine],av_domc,TblApplications[Tribe],av_tric)) | M42: =IF($K42="","",COUNTIFS(TblApplications[Domaine],$K42,TblApplications[Action],"À migrer",TblApplications[Environnement],av_envc,TblApplications[Domaine],av_domc,TblApplications[Tribe],av_tric)) | N42: =IF($K42="","",COUNTIFS(TblApplications[Domaine],$K42,TblApplications[Action],"À décommissionner",TblApplications[Environnement],av_envc,TblApplications[Domaine],av_domc,TblApplications[Tribe],av_tric)) | O42: =IF($K42="","",COUNTIFS(TblApplications[Domaine],$K42,TblApplications[Action],"Décommissionné",TblApplications[Environnement],av_envc,TblApplications[Domaine],av_domc,TblApplications[Tribe],av_tric)) | P42: =IF($K42="","",SUM(L42:O42))
B43: =IFERROR(IF(INDEX(TblTribes[Tribe],10)="","",INDEX(TblTribes[Tribe],10)),"") | C43: =IF($B43="","",INDEX(TblTribes[Domaine de la tribe],10)) | D43: =IF($B43="","",COUNTIFS(TblApplications[Tribe],$B43,TblApplications[Action],"Migré",TblApplications[Environnement],av_envc,TblApplications[Domaine],av_domc,TblApplications[Tribe],av_tric)) | E43: =IF($B43="","",COUNTIFS(TblApplications[Tribe],$B43,TblApplications[Action],"À migrer",TblApplications[Environnement],av_envc,TblApplications[Domaine],av_domc,TblApplications[Tribe],av_tric)) | F43: =IF($B43="","",COUNTIFS(TblApplications[Tribe],$B43,TblApplications[Action],"À décommissionner",TblApplications[Environnement],av_envc,TblApplications[Domaine],av_domc,TblApplications[Tribe],av_tric)) | G43: =IF($B43="","",COUNTIFS(TblApplications[Tribe],$B43,TblApplications[Action],"Décommissionné",TblApplications[Environnement],av_envc,TblApplications[Domaine],av_domc,TblApplications[Tribe],av_tric)) | H43: =IF($B43="","",SUM(D43:G43)) | K43: =IFERROR(IF(INDEX(TblDomaines[Domaine],10)="","",INDEX(TblDomaines[Domaine],10)),"") | L43: =IF($K43="","",COUNTIFS(TblApplications[Domaine],$K43,TblApplications[Action],"Migré",TblApplications[Environnement],av_envc,TblApplications[Domaine],av_domc,TblApplications[Tribe],av_tric)) | M43: =IF($K43="","",COUNTIFS(TblApplications[Domaine],$K43,TblApplications[Action],"À migrer",TblApplications[Environnement],av_envc,TblApplications[Domaine],av_domc,TblApplications[Tribe],av_tric)) | N43: =IF($K43="","",COUNTIFS(TblApplications[Domaine],$K43,TblApplications[Action],"À décommissionner",TblApplications[Environnement],av_envc,TblApplications[Domaine],av_domc,TblApplications[Tribe],av_tric)) | O43: =IF($K43="","",COUNTIFS(TblApplications[Domaine],$K43,TblApplications[Action],"Décommissionné",TblApplications[Environnement],av_envc,TblApplications[Domaine],av_domc,TblApplications[Tribe],av_tric)) | P43: =IF($K43="","",SUM(L43:O43))
B44: =IFERROR(IF(INDEX(TblTribes[Tribe],11)="","",INDEX(TblTribes[Tribe],11)),"") | C44: =IF($B44="","",INDEX(TblTribes[Domaine de la tribe],11)) | D44: =IF($B44="","",COUNTIFS(TblApplications[Tribe],$B44,TblApplications[Action],"Migré",TblApplications[Environnement],av_envc,TblApplications[Domaine],av_domc,TblApplications[Tribe],av_tric)) | E44: =IF($B44="","",COUNTIFS(TblApplications[Tribe],$B44,TblApplications[Action],"À migrer",TblApplications[Environnement],av_envc,TblApplications[Domaine],av_domc,TblApplications[Tribe],av_tric)) | F44: =IF($B44="","",COUNTIFS(TblApplications[Tribe],$B44,TblApplications[Action],"À décommissionner",TblApplications[Environnement],av_envc,TblApplications[Domaine],av_domc,TblApplications[Tribe],av_tric)) | G44: =IF($B44="","",COUNTIFS(TblApplications[Tribe],$B44,TblApplications[Action],"Décommissionné",TblApplications[Environnement],av_envc,TblApplications[Domaine],av_domc,TblApplications[Tribe],av_tric)) | H44: =IF($B44="","",SUM(D44:G44)) | K44: =IFERROR(IF(INDEX(TblDomaines[Domaine],11)="","",INDEX(TblDomaines[Domaine],11)),"") | L44: =IF($K44="","",COUNTIFS(TblApplications[Domaine],$K44,TblApplications[Action],"Migré",TblApplications[Environnement],av_envc,TblApplications[Domaine],av_domc,TblApplications[Tribe],av_tric)) | M44: =IF($K44="","",COUNTIFS(TblApplications[Domaine],$K44,TblApplications[Action],"À migrer",TblApplications[Environnement],av_envc,TblApplications[Domaine],av_domc,TblApplications[Tribe],av_tric)) | N44: =IF($K44="","",COUNTIFS(TblApplications[Domaine],$K44,TblApplications[Action],"À décommissionner",TblApplications[Environnement],av_envc,TblApplications[Domaine],av_domc,TblApplications[Tribe],av_tric)) | O44: =IF($K44="","",COUNTIFS(TblApplications[Domaine],$K44,TblApplications[Action],"Décommissionné",TblApplications[Environnement],av_envc,TblApplications[Domaine],av_domc,TblApplications[Tribe],av_tric)) | P44: =IF($K44="","",SUM(L44:O44))
B45: =IFERROR(IF(INDEX(TblTribes[Tribe],12)="","",INDEX(TblTribes[Tribe],12)),"") | C45: =IF($B45="","",INDEX(TblTribes[Domaine de la tribe],12)) | D45: =IF($B45="","",COUNTIFS(TblApplications[Tribe],$B45,TblApplications[Action],"Migré",TblApplications[Environnement],av_envc,TblApplications[Domaine],av_domc,TblApplications[Tribe],av_tric)) | E45: =IF($B45="","",COUNTIFS(TblApplications[Tribe],$B45,TblApplications[Action],"À migrer",TblApplications[Environnement],av_envc,TblApplications[Domaine],av_domc,TblApplications[Tribe],av_tric)) | F45: =IF($B45="","",COUNTIFS(TblApplications[Tribe],$B45,TblApplications[Action],"À décommissionner",TblApplications[Environnement],av_envc,TblApplications[Domaine],av_domc,TblApplications[Tribe],av_tric)) | G45: =IF($B45="","",COUNTIFS(TblApplications[Tribe],$B45,TblApplications[Action],"Décommissionné",TblApplications[Environnement],av_envc,TblApplications[Domaine],av_domc,TblApplications[Tribe],av_tric)) | H45: =IF($B45="","",SUM(D45:G45)) | K45: =IFERROR(IF(INDEX(TblDomaines[Domaine],12)="","",INDEX(TblDomaines[Domaine],12)),"") | L45: =IF($K45="","",COUNTIFS(TblApplications[Domaine],$K45,TblApplications[Action],"Migré",TblApplications[Environnement],av_envc,TblApplications[Domaine],av_domc,TblApplications[Tribe],av_tric)) | M45: =IF($K45="","",COUNTIFS(TblApplications[Domaine],$K45,TblApplications[Action],"À migrer",TblApplications[Environnement],av_envc,TblApplications[Domaine],av_domc,TblApplications[Tribe],av_tric)) | N45: =IF($K45="","",COUNTIFS(TblApplications[Domaine],$K45,TblApplications[Action],"À décommissionner",TblApplications[Environnement],av_envc,TblApplications[Domaine],av_domc,TblApplications[Tribe],av_tric)) | O45: =IF($K45="","",COUNTIFS(TblApplications[Domaine],$K45,TblApplications[Action],"Décommissionné",TblApplications[Environnement],av_envc,TblApplications[Domaine],av_domc,TblApplications[Tribe],av_tric)) | P45: =IF($K45="","",SUM(L45:O45))
B46: =IFERROR(IF(INDEX(TblTribes[Tribe],13)="","",INDEX(TblTribes[Tribe],13)),"") | C46: =IF($B46="","",INDEX(TblTribes[Domaine de la tribe],13)) | D46: =IF($B46="","",COUNTIFS(TblApplications[Tribe],$B46,TblApplications[Action],"Migré",TblApplications[Environnement],av_envc,TblApplications[Domaine],av_domc,TblApplications[Tribe],av_tric)) | E46: =IF($B46="","",COUNTIFS(TblApplications[Tribe],$B46,TblApplications[Action],"À migrer",TblApplications[Environnement],av_envc,TblApplications[Domaine],av_domc,TblApplications[Tribe],av_tric)) | F46: =IF($B46="","",COUNTIFS(TblApplications[Tribe],$B46,TblApplications[Action],"À décommissionner",TblApplications[Environnement],av_envc,TblApplications[Domaine],av_domc,TblApplications[Tribe],av_tric)) | G46: =IF($B46="","",COUNTIFS(TblApplications[Tribe],$B46,TblApplications[Action],"Décommissionné",TblApplications[Environnement],av_envc,TblApplications[Domaine],av_domc,TblApplications[Tribe],av_tric)) | H46: =IF($B46="","",SUM(D46:G46)) | K46: =IFERROR(IF(INDEX(TblDomaines[Domaine],13)="","",INDEX(TblDomaines[Domaine],13)),"") | L46: =IF($K46="","",COUNTIFS(TblApplications[Domaine],$K46,TblApplications[Action],"Migré",TblApplications[Environnement],av_envc,TblApplications[Domaine],av_domc,TblApplications[Tribe],av_tric)) | M46: =IF($K46="","",COUNTIFS(TblApplications[Domaine],$K46,TblApplications[Action],"À migrer",TblApplications[Environnement],av_envc,TblApplications[Domaine],av_domc,TblApplications[Tribe],av_tric)) | N46: =IF($K46="","",COUNTIFS(TblApplications[Domaine],$K46,TblApplications[Action],"À décommissionner",TblApplications[Environnement],av_envc,TblApplications[Domaine],av_domc,TblApplications[Tribe],av_tric)) | O46: =IF($K46="","",COUNTIFS(TblApplications[Domaine],$K46,TblApplications[Action],"Décommissionné",TblApplications[Environnement],av_envc,TblApplications[Domaine],av_domc,TblApplications[Tribe],av_tric)) | P46: =IF($K46="","",SUM(L46:O46))
B47: =IFERROR(IF(INDEX(TblTribes[Tribe],14)="","",INDEX(TblTribes[Tribe],14)),"") | C47: =IF($B47="","",INDEX(TblTribes[Domaine de la tribe],14)) | D47: =IF($B47="","",COUNTIFS(TblApplications[Tribe],$B47,TblApplications[Action],"Migré",TblApplications[Environnement],av_envc,TblApplications[Domaine],av_domc,TblApplications[Tribe],av_tric)) | E47: =IF($B47="","",COUNTIFS(TblApplications[Tribe],$B47,TblApplications[Action],"À migrer",TblApplications[Environnement],av_envc,TblApplications[Domaine],av_domc,TblApplications[Tribe],av_tric)) | F47: =IF($B47="","",COUNTIFS(TblApplications[Tribe],$B47,TblApplications[Action],"À décommissionner",TblApplications[Environnement],av_envc,TblApplications[Domaine],av_domc,TblApplications[Tribe],av_tric)) | G47: =IF($B47="","",COUNTIFS(TblApplications[Tribe],$B47,TblApplications[Action],"Décommissionné",TblApplications[Environnement],av_envc,TblApplications[Domaine],av_domc,TblApplications[Tribe],av_tric)) | H47: =IF($B47="","",SUM(D47:G47)) | K47: =IFERROR(IF(INDEX(TblDomaines[Domaine],14)="","",INDEX(TblDomaines[Domaine],14)),"") | L47: =IF($K47="","",COUNTIFS(TblApplications[Domaine],$K47,TblApplications[Action],"Migré",TblApplications[Environnement],av_envc,TblApplications[Domaine],av_domc,TblApplications[Tribe],av_tric)) | M47: =IF($K47="","",COUNTIFS(TblApplications[Domaine],$K47,TblApplications[Action],"À migrer",TblApplications[Environnement],av_envc,TblApplications[Domaine],av_domc,TblApplications[Tribe],av_tric)) | N47: =IF($K47="","",COUNTIFS(TblApplications[Domaine],$K47,TblApplications[Action],"À décommissionner",TblApplications[Environnement],av_envc,TblApplications[Domaine],av_domc,TblApplications[Tribe],av_tric)) | O47: =IF($K47="","",COUNTIFS(TblApplications[Domaine],$K47,TblApplications[Action],"Décommissionné",TblApplications[Environnement],av_envc,TblApplications[Domaine],av_domc,TblApplications[Tribe],av_tric)) | P47: =IF($K47="","",SUM(L47:O47))
B48: =IFERROR(IF(INDEX(TblTribes[Tribe],15)="","",INDEX(TblTribes[Tribe],15)),"") | C48: =IF($B48="","",INDEX(TblTribes[Domaine de la tribe],15)) | D48: =IF($B48="","",COUNTIFS(TblApplications[Tribe],$B48,TblApplications[Action],"Migré",TblApplications[Environnement],av_envc,TblApplications[Domaine],av_domc,TblApplications[Tribe],av_tric)) | E48: =IF($B48="","",COUNTIFS(TblApplications[Tribe],$B48,TblApplications[Action],"À migrer",TblApplications[Environnement],av_envc,TblApplications[Domaine],av_domc,TblApplications[Tribe],av_tric)) | F48: =IF($B48="","",COUNTIFS(TblApplications[Tribe],$B48,TblApplications[Action],"À décommissionner",TblApplications[Environnement],av_envc,TblApplications[Domaine],av_domc,TblApplications[Tribe],av_tric)) | G48: =IF($B48="","",COUNTIFS(TblApplications[Tribe],$B48,TblApplications[Action],"Décommissionné",TblApplications[Environnement],av_envc,TblApplications[Domaine],av_domc,TblApplications[Tribe],av_tric)) | H48: =IF($B48="","",SUM(D48:G48)) | K48: =IFERROR(IF(INDEX(TblDomaines[Domaine],15)="","",INDEX(TblDomaines[Domaine],15)),"") | L48: =IF($K48="","",COUNTIFS(TblApplications[Domaine],$K48,TblApplications[Action],"Migré",TblApplications[Environnement],av_envc,TblApplications[Domaine],av_domc,TblApplications[Tribe],av_tric)) | M48: =IF($K48="","",COUNTIFS(TblApplications[Domaine],$K48,TblApplications[Action],"À migrer",TblApplications[Environnement],av_envc,TblApplications[Domaine],av_domc,TblApplications[Tribe],av_tric)) | N48: =IF($K48="","",COUNTIFS(TblApplications[Domaine],$K48,TblApplications[Action],"À décommissionner",TblApplications[Environnement],av_envc,TblApplications[Domaine],av_domc,TblApplications[Tribe],av_tric)) | O48: =IF($K48="","",COUNTIFS(TblApplications[Domaine],$K48,TblApplications[Action],"Décommissionné",TblApplications[Environnement],av_envc,TblApplications[Domaine],av_domc,TblApplications[Tribe],av_tric)) | P48: =IF($K48="","",SUM(L48:O48))
B49: =IFERROR(IF(INDEX(TblTribes[Tribe],16)="","",INDEX(TblTribes[Tribe],16)),"") | C49: =IF($B49="","",INDEX(TblTribes[Domaine de la tribe],16)) | D49: =IF($B49="","",COUNTIFS(TblApplications[Tribe],$B49,TblApplications[Action],"Migré",TblApplications[Environnement],av_envc,TblApplications[Domaine],av_domc,TblApplications[Tribe],av_tric)) | E49: =IF($B49="","",COUNTIFS(TblApplications[Tribe],$B49,TblApplications[Action],"À migrer",TblApplications[Environnement],av_envc,TblApplications[Domaine],av_domc,TblApplications[Tribe],av_tric)) | F49: =IF($B49="","",COUNTIFS(TblApplications[Tribe],$B49,TblApplications[Action],"À décommissionner",TblApplications[Environnement],av_envc,TblApplications[Domaine],av_domc,TblApplications[Tribe],av_tric)) | G49: =IF($B49="","",COUNTIFS(TblApplications[Tribe],$B49,TblApplications[Action],"Décommissionné",TblApplications[Environnement],av_envc,TblApplications[Domaine],av_domc,TblApplications[Tribe],av_tric)) | H49: =IF($B49="","",SUM(D49:G49)) | K49: =IFERROR(IF(INDEX(TblDomaines[Domaine],16)="","",INDEX(TblDomaines[Domaine],16)),"") | L49: =IF($K49="","",COUNTIFS(TblApplications[Domaine],$K49,TblApplications[Action],"Migré",TblApplications[Environnement],av_envc,TblApplications[Domaine],av_domc,TblApplications[Tribe],av_tric)) | M49: =IF($K49="","",COUNTIFS(TblApplications[Domaine],$K49,TblApplications[Action],"À migrer",TblApplications[Environnement],av_envc,TblApplications[Domaine],av_domc,TblApplications[Tribe],av_tric)) | N49: =IF($K49="","",COUNTIFS(TblApplications[Domaine],$K49,TblApplications[Action],"À décommissionner",TblApplications[Environnement],av_envc,TblApplications[Domaine],av_domc,TblApplications[Tribe],av_tric)) | O49: =IF($K49="","",COUNTIFS(TblApplications[Domaine],$K49,TblApplications[Action],"Décommissionné",TblApplications[Environnement],av_envc,TblApplications[Domaine],av_domc,TblApplications[Tribe],av_tric)) | P49: =IF($K49="","",SUM(L49:O49))
B50: =IFERROR(IF(INDEX(TblTribes[Tribe],17)="","",INDEX(TblTribes[Tribe],17)),"") | C50: =IF($B50="","",INDEX(TblTribes[Domaine de la tribe],17)) | D50: =IF($B50="","",COUNTIFS(TblApplications[Tribe],$B50,TblApplications[Action],"Migré",TblApplications[Environnement],av_envc,TblApplications[Domaine],av_domc,TblApplications[Tribe],av_tric)) | E50: =IF($B50="","",COUNTIFS(TblApplications[Tribe],$B50,TblApplications[Action],"À migrer",TblApplications[Environnement],av_envc,TblApplications[Domaine],av_domc,TblApplications[Tribe],av_tric)) | F50: =IF($B50="","",COUNTIFS(TblApplications[Tribe],$B50,TblApplications[Action],"À décommissionner",TblApplications[Environnement],av_envc,TblApplications[Domaine],av_domc,TblApplications[Tribe],av_tric)) | G50: =IF($B50="","",COUNTIFS(TblApplications[Tribe],$B50,TblApplications[Action],"Décommissionné",TblApplications[Environnement],av_envc,TblApplications[Domaine],av_domc,TblApplications[Tribe],av_tric)) | H50: =IF($B50="","",SUM(D50:G50)) | K50: =IFERROR(IF(INDEX(TblDomaines[Domaine],17)="","",INDEX(TblDomaines[Domaine],17)),"") | L50: =IF($K50="","",COUNTIFS(TblApplications[Domaine],$K50,TblApplications[Action],"Migré",TblApplications[Environnement],av_envc,TblApplications[Domaine],av_domc,TblApplications[Tribe],av_tric)) | M50: =IF($K50="","",COUNTIFS(TblApplications[Domaine],$K50,TblApplications[Action],"À migrer",TblApplications[Environnement],av_envc,TblApplications[Domaine],av_domc,TblApplications[Tribe],av_tric)) | N50: =IF($K50="","",COUNTIFS(TblApplications[Domaine],$K50,TblApplications[Action],"À décommissionner",TblApplications[Environnement],av_envc,TblApplications[Domaine],av_domc,TblApplications[Tribe],av_tric)) | O50: =IF($K50="","",COUNTIFS(TblApplications[Domaine],$K50,TblApplications[Action],"Décommissionné",TblApplications[Environnement],av_envc,TblApplications[Domaine],av_domc,TblApplications[Tribe],av_tric)) | P50: =IF($K50="","",SUM(L50:O50))
B51: =IFERROR(IF(INDEX(TblTribes[Tribe],18)="","",INDEX(TblTribes[Tribe],18)),"") | C51: =IF($B51="","",INDEX(TblTribes[Domaine de la tribe],18)) | D51: =IF($B51="","",COUNTIFS(TblApplications[Tribe],$B51,TblApplications[Action],"Migré",TblApplications[Environnement],av_envc,TblApplications[Domaine],av_domc,TblApplications[Tribe],av_tric)) | E51: =IF($B51="","",COUNTIFS(TblApplications[Tribe],$B51,TblApplications[Action],"À migrer",TblApplications[Environnement],av_envc,TblApplications[Domaine],av_domc,TblApplications[Tribe],av_tric)) | F51: =IF($B51="","",COUNTIFS(TblApplications[Tribe],$B51,TblApplications[Action],"À décommissionner",TblApplications[Environnement],av_envc,TblApplications[Domaine],av_domc,TblApplications[Tribe],av_tric)) | G51: =IF($B51="","",COUNTIFS(TblApplications[Tribe],$B51,TblApplications[Action],"Décommissionné",TblApplications[Environnement],av_envc,TblApplications[Domaine],av_domc,TblApplications[Tribe],av_tric)) | H51: =IF($B51="","",SUM(D51:G51)) | K51: =IFERROR(IF(INDEX(TblDomaines[Domaine],18)="","",INDEX(TblDomaines[Domaine],18)),"") | L51: =IF($K51="","",COUNTIFS(TblApplications[Domaine],$K51,TblApplications[Action],"Migré",TblApplications[Environnement],av_envc,TblApplications[Domaine],av_domc,TblApplications[Tribe],av_tric)) | M51: =IF($K51="","",COUNTIFS(TblApplications[Domaine],$K51,TblApplications[Action],"À migrer",TblApplications[Environnement],av_envc,TblApplications[Domaine],av_domc,TblApplications[Tribe],av_tric)) | N51: =IF($K51="","",COUNTIFS(TblApplications[Domaine],$K51,TblApplications[Action],"À décommissionner",TblApplications[Environnement],av_envc,TblApplications[Domaine],av_domc,TblApplications[Tribe],av_tric)) | O51: =IF($K51="","",COUNTIFS(TblApplications[Domaine],$K51,TblApplications[Action],"Décommissionné",TblApplications[Environnement],av_envc,TblApplications[Domaine],av_domc,TblApplications[Tribe],av_tric)) | P51: =IF($K51="","",SUM(L51:O51))
B52: =IFERROR(IF(INDEX(TblTribes[Tribe],19)="","",INDEX(TblTribes[Tribe],19)),"") | C52: =IF($B52="","",INDEX(TblTribes[Domaine de la tribe],19)) | D52: =IF($B52="","",COUNTIFS(TblApplications[Tribe],$B52,TblApplications[Action],"Migré",TblApplications[Environnement],av_envc,TblApplications[Domaine],av_domc,TblApplications[Tribe],av_tric)) | E52: =IF($B52="","",COUNTIFS(TblApplications[Tribe],$B52,TblApplications[Action],"À migrer",TblApplications[Environnement],av_envc,TblApplications[Domaine],av_domc,TblApplications[Tribe],av_tric)) | F52: =IF($B52="","",COUNTIFS(TblApplications[Tribe],$B52,TblApplications[Action],"À décommissionner",TblApplications[Environnement],av_envc,TblApplications[Domaine],av_domc,TblApplications[Tribe],av_tric)) | G52: =IF($B52="","",COUNTIFS(TblApplications[Tribe],$B52,TblApplications[Action],"Décommissionné",TblApplications[Environnement],av_envc,TblApplications[Domaine],av_domc,TblApplications[Tribe],av_tric)) | H52: =IF($B52="","",SUM(D52:G52)) | K52: =IFERROR(IF(INDEX(TblDomaines[Domaine],19)="","",INDEX(TblDomaines[Domaine],19)),"") | L52: =IF($K52="","",COUNTIFS(TblApplications[Domaine],$K52,TblApplications[Action],"Migré",TblApplications[Environnement],av_envc,TblApplications[Domaine],av_domc,TblApplications[Tribe],av_tric)) | M52: =IF($K52="","",COUNTIFS(TblApplications[Domaine],$K52,TblApplications[Action],"À migrer",TblApplications[Environnement],av_envc,TblApplications[Domaine],av_domc,TblApplications[Tribe],av_tric)) | N52: =IF($K52="","",COUNTIFS(TblApplications[Domaine],$K52,TblApplications[Action],"À décommissionner",TblApplications[Environnement],av_envc,TblApplications[Domaine],av_domc,TblApplications[Tribe],av_tric)) | O52: =IF($K52="","",COUNTIFS(TblApplications[Domaine],$K52,TblApplications[Action],"Décommissionné",TblApplications[Environnement],av_envc,TblApplications[Domaine],av_domc,TblApplications[Tribe],av_tric)) | P52: =IF($K52="","",SUM(L52:O52))
B53: =IFERROR(IF(INDEX(TblTribes[Tribe],20)="","",INDEX(TblTribes[Tribe],20)),"") | C53: =IF($B53="","",INDEX(TblTribes[Domaine de la tribe],20)) | D53: =IF($B53="","",COUNTIFS(TblApplications[Tribe],$B53,TblApplications[Action],"Migré",TblApplications[Environnement],av_envc,TblApplications[Domaine],av_domc,TblApplications[Tribe],av_tric)) | E53: =IF($B53="","",COUNTIFS(TblApplications[Tribe],$B53,TblApplications[Action],"À migrer",TblApplications[Environnement],av_envc,TblApplications[Domaine],av_domc,TblApplications[Tribe],av_tric)) | F53: =IF($B53="","",COUNTIFS(TblApplications[Tribe],$B53,TblApplications[Action],"À décommissionner",TblApplications[Environnement],av_envc,TblApplications[Domaine],av_domc,TblApplications[Tribe],av_tric)) | G53: =IF($B53="","",COUNTIFS(TblApplications[Tribe],$B53,TblApplications[Action],"Décommissionné",TblApplications[Environnement],av_envc,TblApplications[Domaine],av_domc,TblApplications[Tribe],av_tric)) | H53: =IF($B53="","",SUM(D53:G53)) | K53: =IFERROR(IF(INDEX(TblDomaines[Domaine],20)="","",INDEX(TblDomaines[Domaine],20)),"") | L53: =IF($K53="","",COUNTIFS(TblApplications[Domaine],$K53,TblApplications[Action],"Migré",TblApplications[Environnement],av_envc,TblApplications[Domaine],av_domc,TblApplications[Tribe],av_tric)) | M53: =IF($K53="","",COUNTIFS(TblApplications[Domaine],$K53,TblApplications[Action],"À migrer",TblApplications[Environnement],av_envc,TblApplications[Domaine],av_domc,TblApplications[Tribe],av_tric)) | N53: =IF($K53="","",COUNTIFS(TblApplications[Domaine],$K53,TblApplications[Action],"À décommissionner",TblApplications[Environnement],av_envc,TblApplications[Domaine],av_domc,TblApplications[Tribe],av_tric)) | O53: =IF($K53="","",COUNTIFS(TblApplications[Domaine],$K53,TblApplications[Action],"Décommissionné",TblApplications[Environnement],av_envc,TblApplications[Domaine],av_domc,TblApplications[Tribe],av_tric)) | P53: =IF($K53="","",SUM(L53:O53))
B54: =IFERROR(IF(INDEX(TblTribes[Tribe],21)="","",INDEX(TblTribes[Tribe],21)),"") | C54: =IF($B54="","",INDEX(TblTribes[Domaine de la tribe],21)) | D54: =IF($B54="","",COUNTIFS(TblApplications[Tribe],$B54,TblApplications[Action],"Migré",TblApplications[Environnement],av_envc,TblApplications[Domaine],av_domc,TblApplications[Tribe],av_tric)) | E54: =IF($B54="","",COUNTIFS(TblApplications[Tribe],$B54,TblApplications[Action],"À migrer",TblApplications[Environnement],av_envc,TblApplications[Domaine],av_domc,TblApplications[Tribe],av_tric)) | F54: =IF($B54="","",COUNTIFS(TblApplications[Tribe],$B54,TblApplications[Action],"À décommissionner",TblApplications[Environnement],av_envc,TblApplications[Domaine],av_domc,TblApplications[Tribe],av_tric)) | G54: =IF($B54="","",COUNTIFS(TblApplications[Tribe],$B54,TblApplications[Action],"Décommissionné",TblApplications[Environnement],av_envc,TblApplications[Domaine],av_domc,TblApplications[Tribe],av_tric)) | H54: =IF($B54="","",SUM(D54:G54))
B55: =IFERROR(IF(INDEX(TblTribes[Tribe],22)="","",INDEX(TblTribes[Tribe],22)),"") | C55: =IF($B55="","",INDEX(TblTribes[Domaine de la tribe],22)) | D55: =IF($B55="","",COUNTIFS(TblApplications[Tribe],$B55,TblApplications[Action],"Migré",TblApplications[Environnement],av_envc,TblApplications[Domaine],av_domc,TblApplications[Tribe],av_tric)) | E55: =IF($B55="","",COUNTIFS(TblApplications[Tribe],$B55,TblApplications[Action],"À migrer",TblApplications[Environnement],av_envc,TblApplications[Domaine],av_domc,TblApplications[Tribe],av_tric)) | F55: =IF($B55="","",COUNTIFS(TblApplications[Tribe],$B55,TblApplications[Action],"À décommissionner",TblApplications[Environnement],av_envc,TblApplications[Domaine],av_domc,TblApplications[Tribe],av_tric)) | G55: =IF($B55="","",COUNTIFS(TblApplications[Tribe],$B55,TblApplications[Action],"Décommissionné",TblApplications[Environnement],av_envc,TblApplications[Domaine],av_domc,TblApplications[Tribe],av_tric)) | H55: =IF($B55="","",SUM(D55:G55))
B56: =IFERROR(IF(INDEX(TblTribes[Tribe],23)="","",INDEX(TblTribes[Tribe],23)),"") | C56: =IF($B56="","",INDEX(TblTribes[Domaine de la tribe],23)) | D56: =IF($B56="","",COUNTIFS(TblApplications[Tribe],$B56,TblApplications[Action],"Migré",TblApplications[Environnement],av_envc,TblApplications[Domaine],av_domc,TblApplications[Tribe],av_tric)) | E56: =IF($B56="","",COUNTIFS(TblApplications[Tribe],$B56,TblApplications[Action],"À migrer",TblApplications[Environnement],av_envc,TblApplications[Domaine],av_domc,TblApplications[Tribe],av_tric)) | F56: =IF($B56="","",COUNTIFS(TblApplications[Tribe],$B56,TblApplications[Action],"À décommissionner",TblApplications[Environnement],av_envc,TblApplications[Domaine],av_domc,TblApplications[Tribe],av_tric)) | G56: =IF($B56="","",COUNTIFS(TblApplications[Tribe],$B56,TblApplications[Action],"Décommissionné",TblApplications[Environnement],av_envc,TblApplications[Domaine],av_domc,TblApplications[Tribe],av_tric)) | H56: =IF($B56="","",SUM(D56:G56)) | K56: Environnement | L56: Migré | M56: À migrer | N56: À décommissionner | O56: Décommissionné | P56: Total
B57: =IFERROR(IF(INDEX(TblTribes[Tribe],24)="","",INDEX(TblTribes[Tribe],24)),"") | C57: =IF($B57="","",INDEX(TblTribes[Domaine de la tribe],24)) | D57: =IF($B57="","",COUNTIFS(TblApplications[Tribe],$B57,TblApplications[Action],"Migré",TblApplications[Environnement],av_envc,TblApplications[Domaine],av_domc,TblApplications[Tribe],av_tric)) | E57: =IF($B57="","",COUNTIFS(TblApplications[Tribe],$B57,TblApplications[Action],"À migrer",TblApplications[Environnement],av_envc,TblApplications[Domaine],av_domc,TblApplications[Tribe],av_tric)) | F57: =IF($B57="","",COUNTIFS(TblApplications[Tribe],$B57,TblApplications[Action],"À décommissionner",TblApplications[Environnement],av_envc,TblApplications[Domaine],av_domc,TblApplications[Tribe],av_tric)) | G57: =IF($B57="","",COUNTIFS(TblApplications[Tribe],$B57,TblApplications[Action],"Décommissionné",TblApplications[Environnement],av_envc,TblApplications[Domaine],av_domc,TblApplications[Tribe],av_tric)) | H57: =IF($B57="","",SUM(D57:G57)) | K57: PRD | L57: =COUNTIFS(TblApplications[Environnement],"PRD",TblApplications[Action],"Migré",TblApplications[Environnement],av_envc,TblApplications[Domaine],av_domc,TblApplications[Tribe],av_tric) -> 1 | M57: =COUNTIFS(TblApplications[Environnement],"PRD",TblApplications[Action],"À migrer",TblApplications[Environnement],av_envc,TblApplications[Domaine],av_domc,TblApplications[Tribe],av_tric) -> 3 | N57: =COUNTIFS(TblApplications[Environnement],"PRD",TblApplications[Action],"À décommissionner",TblApplications[Environnement],av_envc,TblApplications[Domaine],av_domc,TblApplications[Tribe],av_tric) -> 0 | O57: =COUNTIFS(TblApplications[Environnement],"PRD",TblApplications[Action],"Décommissionné",TblApplications[Environnement],av_envc,TblApplications[Domaine],av_domc,TblApplications[Tribe],av_tric) -> 0 | P57: =SUM(L57:O57) -> 4
B58: =IFERROR(IF(INDEX(TblTribes[Tribe],25)="","",INDEX(TblTribes[Tribe],25)),"") | C58: =IF($B58="","",INDEX(TblTribes[Domaine de la tribe],25)) | D58: =IF($B58="","",COUNTIFS(TblApplications[Tribe],$B58,TblApplications[Action],"Migré",TblApplications[Environnement],av_envc,TblApplications[Domaine],av_domc,TblApplications[Tribe],av_tric)) | E58: =IF($B58="","",COUNTIFS(TblApplications[Tribe],$B58,TblApplications[Action],"À migrer",TblApplications[Environnement],av_envc,TblApplications[Domaine],av_domc,TblApplications[Tribe],av_tric)) | F58: =IF($B58="","",COUNTIFS(TblApplications[Tribe],$B58,TblApplications[Action],"À décommissionner",TblApplications[Environnement],av_envc,TblApplications[Domaine],av_domc,TblApplications[Tribe],av_tric)) | G58: =IF($B58="","",COUNTIFS(TblApplications[Tribe],$B58,TblApplications[Action],"Décommissionné",TblApplications[Environnement],av_envc,TblApplications[Domaine],av_domc,TblApplications[Tribe],av_tric)) | H58: =IF($B58="","",SUM(D58:G58)) | K58: NPRD | L58: =COUNTIFS(TblApplications[Environnement],"NPRD",TblApplications[Action],"Migré",TblApplications[Environnement],av_envc,TblApplications[Domaine],av_domc,TblApplications[Tribe],av_tric) -> 0 | M58: =COUNTIFS(TblApplications[Environnement],"NPRD",TblApplications[Action],"À migrer",TblApplications[Environnement],av_envc,TblApplications[Domaine],av_domc,TblApplications[Tribe],av_tric) -> 7 | N58: =COUNTIFS(TblApplications[Environnement],"NPRD",TblApplications[Action],"À décommissionner",TblApplications[Environnement],av_envc,TblApplications[Domaine],av_domc,TblApplications[Tribe],av_tric) -> 1 | O58: =COUNTIFS(TblApplications[Environnement],"NPRD",TblApplications[Action],"Décommissionné",TblApplications[Environnement],av_envc,TblApplications[Domaine],av_domc,TblApplications[Tribe],av_tric) -> 1 | P58: =SUM(L58:O58) -> 9
B59: =IFERROR(IF(INDEX(TblTribes[Tribe],26)="","",INDEX(TblTribes[Tribe],26)),"") | C59: =IF($B59="","",INDEX(TblTribes[Domaine de la tribe],26)) | D59: =IF($B59="","",COUNTIFS(TblApplications[Tribe],$B59,TblApplications[Action],"Migré",TblApplications[Environnement],av_envc,TblApplications[Domaine],av_domc,TblApplications[Tribe],av_tric)) | E59: =IF($B59="","",COUNTIFS(TblApplications[Tribe],$B59,TblApplications[Action],"À migrer",TblApplications[Environnement],av_envc,TblApplications[Domaine],av_domc,TblApplications[Tribe],av_tric)) | F59: =IF($B59="","",COUNTIFS(TblApplications[Tribe],$B59,TblApplications[Action],"À décommissionner",TblApplications[Environnement],av_envc,TblApplications[Domaine],av_domc,TblApplications[Tribe],av_tric)) | G59: =IF($B59="","",COUNTIFS(TblApplications[Tribe],$B59,TblApplications[Action],"Décommissionné",TblApplications[Environnement],av_envc,TblApplications[Domaine],av_domc,TblApplications[Tribe],av_tric)) | H59: =IF($B59="","",SUM(D59:G59))
B60: =IFERROR(IF(INDEX(TblTribes[Tribe],27)="","",INDEX(TblTribes[Tribe],27)),"") | C60: =IF($B60="","",INDEX(TblTribes[Domaine de la tribe],27)) | D60: =IF($B60="","",COUNTIFS(TblApplications[Tribe],$B60,TblApplications[Action],"Migré",TblApplications[Environnement],av_envc,TblApplications[Domaine],av_domc,TblApplications[Tribe],av_tric)) | E60: =IF($B60="","",COUNTIFS(TblApplications[Tribe],$B60,TblApplications[Action],"À migrer",TblApplications[Environnement],av_envc,TblApplications[Domaine],av_domc,TblApplications[Tribe],av_tric)) | F60: =IF($B60="","",COUNTIFS(TblApplications[Tribe],$B60,TblApplications[Action],"À décommissionner",TblApplications[Environnement],av_envc,TblApplications[Domaine],av_domc,TblApplications[Tribe],av_tric)) | G60: =IF($B60="","",COUNTIFS(TblApplications[Tribe],$B60,TblApplications[Action],"Décommissionné",TblApplications[Environnement],av_envc,TblApplications[Domaine],av_domc,TblApplications[Tribe],av_tric)) | H60: =IF($B60="","",SUM(D60:G60))
B61: =IFERROR(IF(INDEX(TblTribes[Tribe],28)="","",INDEX(TblTribes[Tribe],28)),"") | C61: =IF($B61="","",INDEX(TblTribes[Domaine de la tribe],28)) | D61: =IF($B61="","",COUNTIFS(TblApplications[Tribe],$B61,TblApplications[Action],"Migré",TblApplications[Environnement],av_envc,TblApplications[Domaine],av_domc,TblApplications[Tribe],av_tric)) | E61: =IF($B61="","",COUNTIFS(TblApplications[Tribe],$B61,TblApplications[Action],"À migrer",TblApplications[Environnement],av_envc,TblApplications[Domaine],av_domc,TblApplications[Tribe],av_tric)) | F61: =IF($B61="","",COUNTIFS(TblApplications[Tribe],$B61,TblApplications[Action],"À décommissionner",TblApplications[Environnement],av_envc,TblApplications[Domaine],av_domc,TblApplications[Tribe],av_tric)) | G61: =IF($B61="","",COUNTIFS(TblApplications[Tribe],$B61,TblApplications[Action],"Décommissionné",TblApplications[Environnement],av_envc,TblApplications[Domaine],av_domc,TblApplications[Tribe],av_tric)) | H61: =IF($B61="","",SUM(D61:G61)) | AV61: Données de la frise (graphique)
B62: =IFERROR(IF(INDEX(TblTribes[Tribe],29)="","",INDEX(TblTribes[Tribe],29)),"") | C62: =IF($B62="","",INDEX(TblTribes[Domaine de la tribe],29)) | D62: =IF($B62="","",COUNTIFS(TblApplications[Tribe],$B62,TblApplications[Action],"Migré",TblApplications[Environnement],av_envc,TblApplications[Domaine],av_domc,TblApplications[Tribe],av_tric)) | E62: =IF($B62="","",COUNTIFS(TblApplications[Tribe],$B62,TblApplications[Action],"À migrer",TblApplications[Environnement],av_envc,TblApplications[Domaine],av_domc,TblApplications[Tribe],av_tric)) | F62: =IF($B62="","",COUNTIFS(TblApplications[Tribe],$B62,TblApplications[Action],"À décommissionner",TblApplications[Environnement],av_envc,TblApplications[Domaine],av_domc,TblApplications[Tribe],av_tric)) | G62: =IF($B62="","",COUNTIFS(TblApplications[Tribe],$B62,TblApplications[Action],"Décommissionné",TblApplications[Environnement],av_envc,TblApplications[Domaine],av_domc,TblApplications[Tribe],av_tric)) | H62: =IF($B62="","",SUM(D62:G62)) | AV62: Mois | AW62: Bascules | AX62: Décommissions | AY62: Traités cumulés | AZ62: % traité cumulé
B63: =IFERROR(IF(INDEX(TblTribes[Tribe],30)="","",INDEX(TblTribes[Tribe],30)),"") | C63: =IF($B63="","",INDEX(TblTribes[Domaine de la tribe],30)) | D63: =IF($B63="","",COUNTIFS(TblApplications[Tribe],$B63,TblApplications[Action],"Migré",TblApplications[Environnement],av_envc,TblApplications[Domaine],av_domc,TblApplications[Tribe],av_tric)) | E63: =IF($B63="","",COUNTIFS(TblApplications[Tribe],$B63,TblApplications[Action],"À migrer",TblApplications[Environnement],av_envc,TblApplications[Domaine],av_domc,TblApplications[Tribe],av_tric)) | F63: =IF($B63="","",COUNTIFS(TblApplications[Tribe],$B63,TblApplications[Action],"À décommissionner",TblApplications[Environnement],av_envc,TblApplications[Domaine],av_domc,TblApplications[Tribe],av_tric)) | G63: =IF($B63="","",COUNTIFS(TblApplications[Tribe],$B63,TblApplications[Action],"Décommissionné",TblApplications[Environnement],av_envc,TblApplications[Domaine],av_domc,TblApplications[Tribe],av_tric)) | H63: =IF($B63="","",SUM(D63:G63)) | AV63: =IF(1>p_horizon,"",EDATE(p_debut,0)) -> 46296 | AW63: =IF(1>p_horizon,"",COUNTIFS(TblApplications[Action],"À migrer",TblApplications[Mois bascule],">="&AV63,TblApplications[Mois bascule],"<"&EDATE(AV63,1),TblApplications[Environnement],av_envc,TblApplications[Domaine],av_domc,TblApplications[Tribe],av_tric)) -> 0 | AX63: =IF(1>p_horizon,"",COUNTIFS(TblApplications[Action],"À décommissionner",TblApplications[Mois lib (calc)],AV63,TblApplications[Environnement],av_envc,TblApplications[Domaine],av_domc,TblApplications[Tribe],av_tric)) -> 0 | AY63: =IF(1>p_horizon,"",COUNTIFS(TblApplications[Action],"Migré",TblApplications[Environnement],av_envc,TblApplications[Domaine],av_domc,TblApplications[Tribe],av_tric)+COUNTIFS(TblApplications[Action],"Décommissionné",TblApplications[Environnement],av_envc,TblApplications[Domaine],av_domc,TblApplications[Tribe],av_tric)+COUNTIFS(TblApplications[Action],"À migrer",TblApplications[Mois lib (calc)],"<="&AV63,TblApplications[Environnement],av_envc,TblApplications[Domaine],av_domc,TblApplications[Tribe],av_tric)+COUNTIFS(TblApplications[Action],"À décommissionner",TblApplications[Mois lib (calc)],"<="&AV63,TblApplications[Environnement],av_envc,TblApplications[Domaine],av_domc,TblApplications[Tribe],av_tric)) -> 2 | AZ63: =IF(1>p_horizon,"",IFERROR(AY63/COUNTIFS(TblApplications[ID],"<>",TblApplications[Environnement],av_envc,TblApplications[Domaine],av_domc,TblApplications[Tribe],av_tric),0)) -> 0.15384615
B64: =IFERROR(IF(INDEX(TblTribes[Tribe],31)="","",INDEX(TblTribes[Tribe],31)),"") | C64: =IF($B64="","",INDEX(TblTribes[Domaine de la tribe],31)) | D64: =IF($B64="","",COUNTIFS(TblApplications[Tribe],$B64,TblApplications[Action],"Migré",TblApplications[Environnement],av_envc,TblApplications[Domaine],av_domc,TblApplications[Tribe],av_tric)) | E64: =IF($B64="","",COUNTIFS(TblApplications[Tribe],$B64,TblApplications[Action],"À migrer",TblApplications[Environnement],av_envc,TblApplications[Domaine],av_domc,TblApplications[Tribe],av_tric)) | F64: =IF($B64="","",COUNTIFS(TblApplications[Tribe],$B64,TblApplications[Action],"À décommissionner",TblApplications[Environnement],av_envc,TblApplications[Domaine],av_domc,TblApplications[Tribe],av_tric)) | G64: =IF($B64="","",COUNTIFS(TblApplications[Tribe],$B64,TblApplications[Action],"Décommissionné",TblApplications[Environnement],av_envc,TblApplications[Domaine],av_domc,TblApplications[Tribe],av_tric)) | H64: =IF($B64="","",SUM(D64:G64)) | AV64: =IF(2>p_horizon,"",EDATE(p_debut,1)) -> 46327 | AW64: =IF(2>p_horizon,"",COUNTIFS(TblApplications[Action],"À migrer",TblApplications[Mois bascule],">="&AV64,TblApplications[Mois bascule],"<"&EDATE(AV64,1),TblApplications[Environnement],av_envc,TblApplications[Domaine],av_domc,TblApplications[Tribe],av_tric)) -> 0 | AX64: =IF(2>p_horizon,"",COUNTIFS(TblApplications[Action],"À décommissionner",TblApplications[Mois lib (calc)],AV64,TblApplications[Environnement],av_envc,TblApplications[Domaine],av_domc,TblApplications[Tribe],av_tric)) -> 0 | AY64: =IF(2>p_horizon,"",COUNTIFS(TblApplications[Action],"Migré",TblApplications[Environnement],av_envc,TblApplications[Domaine],av_domc,TblApplications[Tribe],av_tric)+COUNTIFS(TblApplications[Action],"Décommissionné",TblApplications[Environnement],av_envc,TblApplications[Domaine],av_domc,TblApplications[Tribe],av_tric)+COUNTIFS(TblApplications[Action],"À migrer",TblApplications[Mois lib (calc)],"<="&AV64,TblApplications[Environnement],av_envc,TblApplications[Domaine],av_domc,TblApplications[Tribe],av_tric)+COUNTIFS(TblApplications[Action],"À décommissionner",TblApplications[Mois lib (calc)],"<="&AV64,TblApplications[Environnement],av_envc,TblApplications[Domaine],av_domc,TblApplications[Tribe],av_tric)) -> 2 | AZ64: =IF(2>p_horizon,"",IFERROR(AY64/COUNTIFS(TblApplications[ID],"<>",TblApplications[Environnement],av_envc,TblApplications[Domaine],av_domc,TblApplications[Tribe],av_tric),0)) -> 0.15384615
B65: =IFERROR(IF(INDEX(TblTribes[Tribe],32)="","",INDEX(TblTribes[Tribe],32)),"") | C65: =IF($B65="","",INDEX(TblTribes[Domaine de la tribe],32)) | D65: =IF($B65="","",COUNTIFS(TblApplications[Tribe],$B65,TblApplications[Action],"Migré",TblApplications[Environnement],av_envc,TblApplications[Domaine],av_domc,TblApplications[Tribe],av_tric)) | E65: =IF($B65="","",COUNTIFS(TblApplications[Tribe],$B65,TblApplications[Action],"À migrer",TblApplications[Environnement],av_envc,TblApplications[Domaine],av_domc,TblApplications[Tribe],av_tric)) | F65: =IF($B65="","",COUNTIFS(TblApplications[Tribe],$B65,TblApplications[Action],"À décommissionner",TblApplications[Environnement],av_envc,TblApplications[Domaine],av_domc,TblApplications[Tribe],av_tric)) | G65: =IF($B65="","",COUNTIFS(TblApplications[Tribe],$B65,TblApplications[Action],"Décommissionné",TblApplications[Environnement],av_envc,TblApplications[Domaine],av_domc,TblApplications[Tribe],av_tric)) | H65: =IF($B65="","",SUM(D65:G65)) | AV65: =IF(3>p_horizon,"",EDATE(p_debut,2)) -> 46357 | AW65: =IF(3>p_horizon,"",COUNTIFS(TblApplications[Action],"À migrer",TblApplications[Mois bascule],">="&AV65,TblApplications[Mois bascule],"<"&EDATE(AV65,1),TblApplications[Environnement],av_envc,TblApplications[Domaine],av_domc,TblApplications[Tribe],av_tric)) -> 0 | AX65: =IF(3>p_horizon,"",COUNTIFS(TblApplications[Action],"À décommissionner",TblApplications[Mois lib (calc)],AV65,TblApplications[Environnement],av_envc,TblApplications[Domaine],av_domc,TblApplications[Tribe],av_tric)) -> 0 | AY65: =IF(3>p_horizon,"",COUNTIFS(TblApplications[Action],"Migré",TblApplications[Environnement],av_envc,TblApplications[Domaine],av_domc,TblApplications[Tribe],av_tric)+COUNTIFS(TblApplications[Action],"Décommissionné",TblApplications[Environnement],av_envc,TblApplications[Domaine],av_domc,TblApplications[Tribe],av_tric)+COUNTIFS(TblApplications[Action],"À migrer",TblApplications[Mois lib (calc)],"<="&AV65,TblApplications[Environnement],av_envc,TblApplications[Domaine],av_domc,TblApplications[Tribe],av_tric)+COUNTIFS(TblApplications[Action],"À décommissionner",TblApplications[Mois lib (calc)],"<="&AV65,TblApplications[Environnement],av_envc,TblApplications[Domaine],av_domc,TblApplications[Tribe],av_tric)) -> 2 | AZ65: =IF(3>p_horizon,"",IFERROR(AY65/COUNTIFS(TblApplications[ID],"<>",TblApplications[Environnement],av_envc,TblApplications[Domaine],av_domc,TblApplications[Tribe],av_tric),0)) -> 0.15384615
B66: =IFERROR(IF(INDEX(TblTribes[Tribe],33)="","",INDEX(TblTribes[Tribe],33)),"") | C66: =IF($B66="","",INDEX(TblTribes[Domaine de la tribe],33)) | D66: =IF($B66="","",COUNTIFS(TblApplications[Tribe],$B66,TblApplications[Action],"Migré",TblApplications[Environnement],av_envc,TblApplications[Domaine],av_domc,TblApplications[Tribe],av_tric)) | E66: =IF($B66="","",COUNTIFS(TblApplications[Tribe],$B66,TblApplications[Action],"À migrer",TblApplications[Environnement],av_envc,TblApplications[Domaine],av_domc,TblApplications[Tribe],av_tric)) | F66: =IF($B66="","",COUNTIFS(TblApplications[Tribe],$B66,TblApplications[Action],"À décommissionner",TblApplications[Environnement],av_envc,TblApplications[Domaine],av_domc,TblApplications[Tribe],av_tric)) | G66: =IF($B66="","",COUNTIFS(TblApplications[Tribe],$B66,TblApplications[Action],"Décommissionné",TblApplications[Environnement],av_envc,TblApplications[Domaine],av_domc,TblApplications[Tribe],av_tric)) | H66: =IF($B66="","",SUM(D66:G66)) | AV66: =IF(4>p_horizon,"",EDATE(p_debut,3)) -> 46388 | AW66: =IF(4>p_horizon,"",COUNTIFS(TblApplications[Action],"À migrer",TblApplications[Mois bascule],">="&AV66,TblApplications[Mois bascule],"<"&EDATE(AV66,1),TblApplications[Environnement],av_envc,TblApplications[Domaine],av_domc,TblApplications[Tribe],av_tric)) -> 1 | AX66: =IF(4>p_horizon,"",COUNTIFS(TblApplications[Action],"À décommissionner",TblApplications[Mois lib (calc)],AV66,TblApplications[Environnement],av_envc,TblApplications[Domaine],av_domc,TblApplications[Tribe],av_tric)) -> 0 | AY66: =IF(4>p_horizon,"",COUNTIFS(TblApplications[Action],"Migré",TblApplications[Environnement],av_envc,TblApplications[Domaine],av_domc,TblApplications[Tribe],av_tric)+COUNTIFS(TblApplications[Action],"Décommissionné",TblApplications[Environnement],av_envc,TblApplications[Domaine],av_domc,TblApplications[Tribe],av_tric)+COUNTIFS(TblApplications[Action],"À migrer",TblApplications[Mois lib (calc)],"<="&AV66,TblApplications[Environnement],av_envc,TblApplications[Domaine],av_domc,TblApplications[Tribe],av_tric)+COUNTIFS(TblApplications[Action],"À décommissionner",TblApplications[Mois lib (calc)],"<="&AV66,TblApplications[Environnement],av_envc,TblApplications[Domaine],av_domc,TblApplications[Tribe],av_tric)) -> 2 | AZ66: =IF(4>p_horizon,"",IFERROR(AY66/COUNTIFS(TblApplications[ID],"<>",TblApplications[Environnement],av_envc,TblApplications[Domaine],av_domc,TblApplications[Tribe],av_tric),0)) -> 0.15384615
B67: =IFERROR(IF(INDEX(TblTribes[Tribe],34)="","",INDEX(TblTribes[Tribe],34)),"") | C67: =IF($B67="","",INDEX(TblTribes[Domaine de la tribe],34)) | D67: =IF($B67="","",COUNTIFS(TblApplications[Tribe],$B67,TblApplications[Action],"Migré",TblApplications[Environnement],av_envc,TblApplications[Domaine],av_domc,TblApplications[Tribe],av_tric)) | E67: =IF($B67="","",COUNTIFS(TblApplications[Tribe],$B67,TblApplications[Action],"À migrer",TblApplications[Environnement],av_envc,TblApplications[Domaine],av_domc,TblApplications[Tribe],av_tric)) | F67: =IF($B67="","",COUNTIFS(TblApplications[Tribe],$B67,TblApplications[Action],"À décommissionner",TblApplications[Environnement],av_envc,TblApplications[Domaine],av_domc,TblApplications[Tribe],av_tric)) | G67: =IF($B67="","",COUNTIFS(TblApplications[Tribe],$B67,TblApplications[Action],"Décommissionné",TblApplications[Environnement],av_envc,TblApplications[Domaine],av_domc,TblApplications[Tribe],av_tric)) | H67: =IF($B67="","",SUM(D67:G67)) | AV67: =IF(5>p_horizon,"",EDATE(p_debut,4)) -> 46419 | AW67: =IF(5>p_horizon,"",COUNTIFS(TblApplications[Action],"À migrer",TblApplications[Mois bascule],">="&AV67,TblApplications[Mois bascule],"<"&EDATE(AV67,1),TblApplications[Environnement],av_envc,TblApplications[Domaine],av_domc,TblApplications[Tribe],av_tric)) -> 1 | AX67: =IF(5>p_horizon,"",COUNTIFS(TblApplications[Action],"À décommissionner",TblApplications[Mois lib (calc)],AV67,TblApplications[Environnement],av_envc,TblApplications[Domaine],av_domc,TblApplications[Tribe],av_tric)) -> 0 | AY67: =IF(5>p_horizon,"",COUNTIFS(TblApplications[Action],"Migré",TblApplications[Environnement],av_envc,TblApplications[Domaine],av_domc,TblApplications[Tribe],av_tric)+COUNTIFS(TblApplications[Action],"Décommissionné",TblApplications[Environnement],av_envc,TblApplications[Domaine],av_domc,TblApplications[Tribe],av_tric)+COUNTIFS(TblApplications[Action],"À migrer",TblApplications[Mois lib (calc)],"<="&AV67,TblApplications[Environnement],av_envc,TblApplications[Domaine],av_domc,TblApplications[Tribe],av_tric)+COUNTIFS(TblApplications[Action],"À décommissionner",TblApplications[Mois lib (calc)],"<="&AV67,TblApplications[Environnement],av_envc,TblApplications[Domaine],av_domc,TblApplications[Tribe],av_tric)) -> 3 | AZ67: =IF(5>p_horizon,"",IFERROR(AY67/COUNTIFS(TblApplications[ID],"<>",TblApplications[Environnement],av_envc,TblApplications[Domaine],av_domc,TblApplications[Tribe],av_tric),0)) -> 0.23076923
B68: =IFERROR(IF(INDEX(TblTribes[Tribe],35)="","",INDEX(TblTribes[Tribe],35)),"") | C68: =IF($B68="","",INDEX(TblTribes[Domaine de la tribe],35)) | D68: =IF($B68="","",COUNTIFS(TblApplications[Tribe],$B68,TblApplications[Action],"Migré",TblApplications[Environnement],av_envc,TblApplications[Domaine],av_domc,TblApplications[Tribe],av_tric)) | E68: =IF($B68="","",COUNTIFS(TblApplications[Tribe],$B68,TblApplications[Action],"À migrer",TblApplications[Environnement],av_envc,TblApplications[Domaine],av_domc,TblApplications[Tribe],av_tric)) | F68: =IF($B68="","",COUNTIFS(TblApplications[Tribe],$B68,TblApplications[Action],"À décommissionner",TblApplications[Environnement],av_envc,TblApplications[Domaine],av_domc,TblApplications[Tribe],av_tric)) | G68: =IF($B68="","",COUNTIFS(TblApplications[Tribe],$B68,TblApplications[Action],"Décommissionné",TblApplications[Environnement],av_envc,TblApplications[Domaine],av_domc,TblApplications[Tribe],av_tric)) | H68: =IF($B68="","",SUM(D68:G68)) | AV68: =IF(6>p_horizon,"",EDATE(p_debut,5)) -> 46447 | AW68: =IF(6>p_horizon,"",COUNTIFS(TblApplications[Action],"À migrer",TblApplications[Mois bascule],">="&AV68,TblApplications[Mois bascule],"<"&EDATE(AV68,1),TblApplications[Environnement],av_envc,TblApplications[Domaine],av_domc,TblApplications[Tribe],av_tric)) -> 0 | AX68: =IF(6>p_horizon,"",COUNTIFS(TblApplications[Action],"À décommissionner",TblApplications[Mois lib (calc)],AV68,TblApplications[Environnement],av_envc,TblApplications[Domaine],av_domc,TblApplications[Tribe],av_tric)) -> 0 | AY68: =IF(6>p_horizon,"",COUNTIFS(TblApplications[Action],"Migré",TblApplications[Environnement],av_envc,TblApplications[Domaine],av_domc,TblApplications[Tribe],av_tric)+COUNTIFS(TblApplications[Action],"Décommissionné",TblApplications[Environnement],av_envc,TblApplications[Domaine],av_domc,TblApplications[Tribe],av_tric)+COUNTIFS(TblApplications[Action],"À migrer",TblApplications[Mois lib (calc)],"<="&AV68,TblApplications[Environnement],av_envc,TblApplications[Domaine],av_domc,TblApplications[Tribe],av_tric)+COUNTIFS(TblApplications[Action],"À décommissionner",TblApplications[Mois lib (calc)],"<="&AV68,TblApplications[Environnement],av_envc,TblApplications[Domaine],av_domc,TblApplications[Tribe],av_tric)) -> 4 | AZ68: =IF(6>p_horizon,"",IFERROR(AY68/COUNTIFS(TblApplications[ID],"<>",TblApplications[Environnement],av_envc,TblApplications[Domaine],av_domc,TblApplications[Tribe],av_tric),0)) -> 0.30769231
B69: =IFERROR(IF(INDEX(TblTribes[Tribe],36)="","",INDEX(TblTribes[Tribe],36)),"") | C69: =IF($B69="","",INDEX(TblTribes[Domaine de la tribe],36)) | D69: =IF($B69="","",COUNTIFS(TblApplications[Tribe],$B69,TblApplications[Action],"Migré",TblApplications[Environnement],av_envc,TblApplications[Domaine],av_domc,TblApplications[Tribe],av_tric)) | E69: =IF($B69="","",COUNTIFS(TblApplications[Tribe],$B69,TblApplications[Action],"À migrer",TblApplications[Environnement],av_envc,TblApplications[Domaine],av_domc,TblApplications[Tribe],av_tric)) | F69: =IF($B69="","",COUNTIFS(TblApplications[Tribe],$B69,TblApplications[Action],"À décommissionner",TblApplications[Environnement],av_envc,TblApplications[Domaine],av_domc,TblApplications[Tribe],av_tric)) | G69: =IF($B69="","",COUNTIFS(TblApplications[Tribe],$B69,TblApplications[Action],"Décommissionné",TblApplications[Environnement],av_envc,TblApplications[Domaine],av_domc,TblApplications[Tribe],av_tric)) | H69: =IF($B69="","",SUM(D69:G69)) | AV69: =IF(7>p_horizon,"",EDATE(p_debut,6)) -> 46478 | AW69: =IF(7>p_horizon,"",COUNTIFS(TblApplications[Action],"À migrer",TblApplications[Mois bascule],">="&AV69,TblApplications[Mois bascule],"<"&EDATE(AV69,1),TblApplications[Environnement],av_envc,TblApplications[Domaine],av_domc,TblApplications[Tribe],av_tric)) -> 0 | AX69: =IF(7>p_horizon,"",COUNTIFS(TblApplications[Action],"À décommissionner",TblApplications[Mois lib (calc)],AV69,TblApplications[Environnement],av_envc,TblApplications[Domaine],av_domc,TblApplications[Tribe],av_tric)) -> 0 | AY69: =IF(7>p_horizon,"",COUNTIFS(TblApplications[Action],"Migré",TblApplications[Environnement],av_envc,TblApplications[Domaine],av_domc,TblApplications[Tribe],av_tric)+COUNTIFS(TblApplications[Action],"Décommissionné",TblApplications[Environnement],av_envc,TblApplications[Domaine],av_domc,TblApplications[Tribe],av_tric)+COUNTIFS(TblApplications[Action],"À migrer",TblApplications[Mois lib (calc)],"<="&AV69,TblApplications[Environnement],av_envc,TblApplications[Domaine],av_domc,TblApplications[Tribe],av_tric)+COUNTIFS(TblApplications[Action],"À décommissionner",TblApplications[Mois lib (calc)],"<="&AV69,TblApplications[Environnement],av_envc,TblApplications[Domaine],av_domc,TblApplications[Tribe],av_tric)) -> 4 | AZ69: =IF(7>p_horizon,"",IFERROR(AY69/COUNTIFS(TblApplications[ID],"<>",TblApplications[Environnement],av_envc,TblApplications[Domaine],av_domc,TblApplications[Tribe],av_tric),0)) -> 0.30769231
B70: =IFERROR(IF(INDEX(TblTribes[Tribe],37)="","",INDEX(TblTribes[Tribe],37)),"") | C70: =IF($B70="","",INDEX(TblTribes[Domaine de la tribe],37)) | D70: =IF($B70="","",COUNTIFS(TblApplications[Tribe],$B70,TblApplications[Action],"Migré",TblApplications[Environnement],av_envc,TblApplications[Domaine],av_domc,TblApplications[Tribe],av_tric)) | E70: =IF($B70="","",COUNTIFS(TblApplications[Tribe],$B70,TblApplications[Action],"À migrer",TblApplications[Environnement],av_envc,TblApplications[Domaine],av_domc,TblApplications[Tribe],av_tric)) | F70: =IF($B70="","",COUNTIFS(TblApplications[Tribe],$B70,TblApplications[Action],"À décommissionner",TblApplications[Environnement],av_envc,TblApplications[Domaine],av_domc,TblApplications[Tribe],av_tric)) | G70: =IF($B70="","",COUNTIFS(TblApplications[Tribe],$B70,TblApplications[Action],"Décommissionné",TblApplications[Environnement],av_envc,TblApplications[Domaine],av_domc,TblApplications[Tribe],av_tric)) | H70: =IF($B70="","",SUM(D70:G70)) | AV70: =IF(8>p_horizon,"",EDATE(p_debut,7)) -> 46508 | AW70: =IF(8>p_horizon,"",COUNTIFS(TblApplications[Action],"À migrer",TblApplications[Mois bascule],">="&AV70,TblApplications[Mois bascule],"<"&EDATE(AV70,1),TblApplications[Environnement],av_envc,TblApplications[Domaine],av_domc,TblApplications[Tribe],av_tric)) -> 1 | AX70: =IF(8>p_horizon,"",COUNTIFS(TblApplications[Action],"À décommissionner",TblApplications[Mois lib (calc)],AV70,TblApplications[Environnement],av_envc,TblApplications[Domaine],av_domc,TblApplications[Tribe],av_tric)) -> 0 | AY70: =IF(8>p_horizon,"",COUNTIFS(TblApplications[Action],"Migré",TblApplications[Environnement],av_envc,TblApplications[Domaine],av_domc,TblApplications[Tribe],av_tric)+COUNTIFS(TblApplications[Action],"Décommissionné",TblApplications[Environnement],av_envc,TblApplications[Domaine],av_domc,TblApplications[Tribe],av_tric)+COUNTIFS(TblApplications[Action],"À migrer",TblApplications[Mois lib (calc)],"<="&AV70,TblApplications[Environnement],av_envc,TblApplications[Domaine],av_domc,TblApplications[Tribe],av_tric)+COUNTIFS(TblApplications[Action],"À décommissionner",TblApplications[Mois lib (calc)],"<="&AV70,TblApplications[Environnement],av_envc,TblApplications[Domaine],av_domc,TblApplications[Tribe],av_tric)) -> 4 | AZ70: =IF(8>p_horizon,"",IFERROR(AY70/COUNTIFS(TblApplications[ID],"<>",TblApplications[Environnement],av_envc,TblApplications[Domaine],av_domc,TblApplications[Tribe],av_tric),0)) -> 0.30769231
B71: =IFERROR(IF(INDEX(TblTribes[Tribe],38)="","",INDEX(TblTribes[Tribe],38)),"") | C71: =IF($B71="","",INDEX(TblTribes[Domaine de la tribe],38)) | D71: =IF($B71="","",COUNTIFS(TblApplications[Tribe],$B71,TblApplications[Action],"Migré",TblApplications[Environnement],av_envc,TblApplications[Domaine],av_domc,TblApplications[Tribe],av_tric)) | E71: =IF($B71="","",COUNTIFS(TblApplications[Tribe],$B71,TblApplications[Action],"À migrer",TblApplications[Environnement],av_envc,TblApplications[Domaine],av_domc,TblApplications[Tribe],av_tric)) | F71: =IF($B71="","",COUNTIFS(TblApplications[Tribe],$B71,TblApplications[Action],"À décommissionner",TblApplications[Environnement],av_envc,TblApplications[Domaine],av_domc,TblApplications[Tribe],av_tric)) | G71: =IF($B71="","",COUNTIFS(TblApplications[Tribe],$B71,TblApplications[Action],"Décommissionné",TblApplications[Environnement],av_envc,TblApplications[Domaine],av_domc,TblApplications[Tribe],av_tric)) | H71: =IF($B71="","",SUM(D71:G71)) | AV71: =IF(9>p_horizon,"",EDATE(p_debut,8)) -> 46539 | AW71: =IF(9>p_horizon,"",COUNTIFS(TblApplications[Action],"À migrer",TblApplications[Mois bascule],">="&AV71,TblApplications[Mois bascule],"<"&EDATE(AV71,1),TblApplications[Environnement],av_envc,TblApplications[Domaine],av_domc,TblApplications[Tribe],av_tric)) -> 0 | AX71: =IF(9>p_horizon,"",COUNTIFS(TblApplications[Action],"À décommissionner",TblApplications[Mois lib (calc)],AV71,TblApplications[Environnement],av_envc,TblApplications[Domaine],av_domc,TblApplications[Tribe],av_tric)) -> 1 | AY71: =IF(9>p_horizon,"",COUNTIFS(TblApplications[Action],"Migré",TblApplications[Environnement],av_envc,TblApplications[Domaine],av_domc,TblApplications[Tribe],av_tric)+COUNTIFS(TblApplications[Action],"Décommissionné",TblApplications[Environnement],av_envc,TblApplications[Domaine],av_domc,TblApplications[Tribe],av_tric)+COUNTIFS(TblApplications[Action],"À migrer",TblApplications[Mois lib (calc)],"<="&AV71,TblApplications[Environnement],av_envc,TblApplications[Domaine],av_domc,TblApplications[Tribe],av_tric)+COUNTIFS(TblApplications[Action],"À décommissionner",TblApplications[Mois lib (calc)],"<="&AV71,TblApplications[Environnement],av_envc,TblApplications[Domaine],av_domc,TblApplications[Tribe],av_tric)) -> 5 | AZ71: =IF(9>p_horizon,"",IFERROR(AY71/COUNTIFS(TblApplications[ID],"<>",TblApplications[Environnement],av_envc,TblApplications[Domaine],av_domc,TblApplications[Tribe],av_tric),0)) -> 0.38461538
B72: =IFERROR(IF(INDEX(TblTribes[Tribe],39)="","",INDEX(TblTribes[Tribe],39)),"") | C72: =IF($B72="","",INDEX(TblTribes[Domaine de la tribe],39)) | D72: =IF($B72="","",COUNTIFS(TblApplications[Tribe],$B72,TblApplications[Action],"Migré",TblApplications[Environnement],av_envc,TblApplications[Domaine],av_domc,TblApplications[Tribe],av_tric)) | E72: =IF($B72="","",COUNTIFS(TblApplications[Tribe],$B72,TblApplications[Action],"À migrer",TblApplications[Environnement],av_envc,TblApplications[Domaine],av_domc,TblApplications[Tribe],av_tric)) | F72: =IF($B72="","",COUNTIFS(TblApplications[Tribe],$B72,TblApplications[Action],"À décommissionner",TblApplications[Environnement],av_envc,TblApplications[Domaine],av_domc,TblApplications[Tribe],av_tric)) | G72: =IF($B72="","",COUNTIFS(TblApplications[Tribe],$B72,TblApplications[Action],"Décommissionné",TblApplications[Environnement],av_envc,TblApplications[Domaine],av_domc,TblApplications[Tribe],av_tric)) | H72: =IF($B72="","",SUM(D72:G72)) | AV72: =IF(10>p_horizon,"",EDATE(p_debut,9)) -> 46569 | AW72: =IF(10>p_horizon,"",COUNTIFS(TblApplications[Action],"À migrer",TblApplications[Mois bascule],">="&AV72,TblApplications[Mois bascule],"<"&EDATE(AV72,1),TblApplications[Environnement],av_envc,TblApplications[Domaine],av_domc,TblApplications[Tribe],av_tric)) -> 0 | AX72: =IF(10>p_horizon,"",COUNTIFS(TblApplications[Action],"À décommissionner",TblApplications[Mois lib (calc)],AV72,TblApplications[Environnement],av_envc,TblApplications[Domaine],av_domc,TblApplications[Tribe],av_tric)) -> 0 | AY72: =IF(10>p_horizon,"",COUNTIFS(TblApplications[Action],"Migré",TblApplications[Environnement],av_envc,TblApplications[Domaine],av_domc,TblApplications[Tribe],av_tric)+COUNTIFS(TblApplications[Action],"Décommissionné",TblApplications[Environnement],av_envc,TblApplications[Domaine],av_domc,TblApplications[Tribe],av_tric)+COUNTIFS(TblApplications[Action],"À migrer",TblApplications[Mois lib (calc)],"<="&AV72,TblApplications[Environnement],av_envc,TblApplications[Domaine],av_domc,TblApplications[Tribe],av_tric)+COUNTIFS(TblApplications[Action],"À décommissionner",TblApplications[Mois lib (calc)],"<="&AV72,TblApplications[Environnement],av_envc,TblApplications[Domaine],av_domc,TblApplications[Tribe],av_tric)) -> 6 | AZ72: =IF(10>p_horizon,"",IFERROR(AY72/COUNTIFS(TblApplications[ID],"<>",TblApplications[Environnement],av_envc,TblApplications[Domaine],av_domc,TblApplications[Tribe],av_tric),0)) -> 0.46153846
B73: =IFERROR(IF(INDEX(TblTribes[Tribe],40)="","",INDEX(TblTribes[Tribe],40)),"") | C73: =IF($B73="","",INDEX(TblTribes[Domaine de la tribe],40)) | D73: =IF($B73="","",COUNTIFS(TblApplications[Tribe],$B73,TblApplications[Action],"Migré",TblApplications[Environnement],av_envc,TblApplications[Domaine],av_domc,TblApplications[Tribe],av_tric)) | E73: =IF($B73="","",COUNTIFS(TblApplications[Tribe],$B73,TblApplications[Action],"À migrer",TblApplications[Environnement],av_envc,TblApplications[Domaine],av_domc,TblApplications[Tribe],av_tric)) | F73: =IF($B73="","",COUNTIFS(TblApplications[Tribe],$B73,TblApplications[Action],"À décommissionner",TblApplications[Environnement],av_envc,TblApplications[Domaine],av_domc,TblApplications[Tribe],av_tric)) | G73: =IF($B73="","",COUNTIFS(TblApplications[Tribe],$B73,TblApplications[Action],"Décommissionné",TblApplications[Environnement],av_envc,TblApplications[Domaine],av_domc,TblApplications[Tribe],av_tric)) | H73: =IF($B73="","",SUM(D73:G73)) | AV73: =IF(11>p_horizon,"",EDATE(p_debut,10)) -> 46600 | AW73: =IF(11>p_horizon,"",COUNTIFS(TblApplications[Action],"À migrer",TblApplications[Mois bascule],">="&AV73,TblApplications[Mois bascule],"<"&EDATE(AV73,1),TblApplications[Environnement],av_envc,TblApplications[Domaine],av_domc,TblApplications[Tribe],av_tric)) -> 0 | AX73: =IF(11>p_horizon,"",COUNTIFS(TblApplications[Action],"À décommissionner",TblApplications[Mois lib (calc)],AV73,TblApplications[Environnement],av_envc,TblApplications[Domaine],av_domc,TblApplications[Tribe],av_tric)) -> 0 | AY73: =IF(11>p_horizon,"",COUNTIFS(TblApplications[Action],"Migré",TblApplications[Environnement],av_envc,TblApplications[Domaine],av_domc,TblApplications[Tribe],av_tric)+COUNTIFS(TblApplications[Action],"Décommissionné",TblApplications[Environnement],av_envc,TblApplications[Domaine],av_domc,TblApplications[Tribe],av_tric)+COUNTIFS(TblApplications[Action],"À migrer",TblApplications[Mois lib (calc)],"<="&AV73,TblApplications[Environnement],av_envc,TblApplications[Domaine],av_domc,TblApplications[Tribe],av_tric)+COUNTIFS(TblApplications[Action],"À décommissionner",TblApplications[Mois lib (calc)],"<="&AV73,TblApplications[Environnement],av_envc,TblApplications[Domaine],av_domc,TblApplications[Tribe],av_tric)) -> 6 | AZ73: =IF(11>p_horizon,"",IFERROR(AY73/COUNTIFS(TblApplications[ID],"<>",TblApplications[Environnement],av_envc,TblApplications[Domaine],av_domc,TblApplications[Tribe],av_tric),0)) -> 0.46153846
AV74: =IF(12>p_horizon,"",EDATE(p_debut,11)) -> 46631 | AW74: =IF(12>p_horizon,"",COUNTIFS(TblApplications[Action],"À migrer",TblApplications[Mois bascule],">="&AV74,TblApplications[Mois bascule],"<"&EDATE(AV74,1),TblApplications[Environnement],av_envc,TblApplications[Domaine],av_domc,TblApplications[Tribe],av_tric)) -> 1 | AX74: =IF(12>p_horizon,"",COUNTIFS(TblApplications[Action],"À décommissionner",TblApplications[Mois lib (calc)],AV74,TblApplications[Environnement],av_envc,TblApplications[Domaine],av_domc,TblApplications[Tribe],av_tric)) -> 0 | AY74: =IF(12>p_horizon,"",COUNTIFS(TblApplications[Action],"Migré",TblApplications[Environnement],av_envc,TblApplications[Domaine],av_domc,TblApplications[Tribe],av_tric)+COUNTIFS(TblApplications[Action],"Décommissionné",TblApplications[Environnement],av_envc,TblApplications[Domaine],av_domc,TblApplications[Tribe],av_tric)+COUNTIFS(TblApplications[Action],"À migrer",TblApplications[Mois lib (calc)],"<="&AV74,TblApplications[Environnement],av_envc,TblApplications[Domaine],av_domc,TblApplications[Tribe],av_tric)+COUNTIFS(TblApplications[Action],"À décommissionner",TblApplications[Mois lib (calc)],"<="&AV74,TblApplications[Environnement],av_envc,TblApplications[Domaine],av_domc,TblApplications[Tribe],av_tric)) -> 6 | AZ74: =IF(12>p_horizon,"",IFERROR(AY74/COUNTIFS(TblApplications[ID],"<>",TblApplications[Environnement],av_envc,TblApplications[Domaine],av_domc,TblApplications[Tribe],av_tric),0)) -> 0.46153846
AV75: =IF(13>p_horizon,"",EDATE(p_debut,12)) -> 46661 | AW75: =IF(13>p_horizon,"",COUNTIFS(TblApplications[Action],"À migrer",TblApplications[Mois bascule],">="&AV75,TblApplications[Mois bascule],"<"&EDATE(AV75,1),TblApplications[Environnement],av_envc,TblApplications[Domaine],av_domc,TblApplications[Tribe],av_tric)) -> 2 | AX75: =IF(13>p_horizon,"",COUNTIFS(TblApplications[Action],"À décommissionner",TblApplications[Mois lib (calc)],AV75,TblApplications[Environnement],av_envc,TblApplications[Domaine],av_domc,TblApplications[Tribe],av_tric)) -> 0 | AY75: =IF(13>p_horizon,"",COUNTIFS(TblApplications[Action],"Migré",TblApplications[Environnement],av_envc,TblApplications[Domaine],av_domc,TblApplications[Tribe],av_tric)+COUNTIFS(TblApplications[Action],"Décommissionné",TblApplications[Environnement],av_envc,TblApplications[Domaine],av_domc,TblApplications[Tribe],av_tric)+COUNTIFS(TblApplications[Action],"À migrer",TblApplications[Mois lib (calc)],"<="&AV75,TblApplications[Environnement],av_envc,TblApplications[Domaine],av_domc,TblApplications[Tribe],av_tric)+COUNTIFS(TblApplications[Action],"À décommissionner",TblApplications[Mois lib (calc)],"<="&AV75,TblApplications[Environnement],av_envc,TblApplications[Domaine],av_domc,TblApplications[Tribe],av_tric)) -> 8 | AZ75: =IF(13>p_horizon,"",IFERROR(AY75/COUNTIFS(TblApplications[ID],"<>",TblApplications[Environnement],av_envc,TblApplications[Domaine],av_domc,TblApplications[Tribe],av_tric),0)) -> 0.61538462
B76: Frise des migrations prévues | AV76: =IF(14>p_horizon,"",EDATE(p_debut,13)) -> 46692 | AW76: =IF(14>p_horizon,"",COUNTIFS(TblApplications[Action],"À migrer",TblApplications[Mois bascule],">="&AV76,TblApplications[Mois bascule],"<"&EDATE(AV76,1),TblApplications[Environnement],av_envc,TblApplications[Domaine],av_domc,TblApplications[Tribe],av_tric)) -> 0 | AX76: =IF(14>p_horizon,"",COUNTIFS(TblApplications[Action],"À décommissionner",TblApplications[Mois lib (calc)],AV76,TblApplications[Environnement],av_envc,TblApplications[Domaine],av_domc,TblApplications[Tribe],av_tric)) -> 0 | AY76: =IF(14>p_horizon,"",COUNTIFS(TblApplications[Action],"Migré",TblApplications[Environnement],av_envc,TblApplications[Domaine],av_domc,TblApplications[Tribe],av_tric)+COUNTIFS(TblApplications[Action],"Décommissionné",TblApplications[Environnement],av_envc,TblApplications[Domaine],av_domc,TblApplications[Tribe],av_tric)+COUNTIFS(TblApplications[Action],"À migrer",TblApplications[Mois lib (calc)],"<="&AV76,TblApplications[Environnement],av_envc,TblApplications[Domaine],av_domc,TblApplications[Tribe],av_tric)+COUNTIFS(TblApplications[Action],"À décommissionner",TblApplications[Mois lib (calc)],"<="&AV76,TblApplications[Environnement],av_envc,TblApplications[Domaine],av_domc,TblApplications[Tribe],av_tric)) -> 9 | AZ76: =IF(14>p_horizon,"",IFERROR(AY76/COUNTIFS(TblApplications[ID],"<>",TblApplications[Environnement],av_envc,TblApplications[Domaine],av_domc,TblApplications[Tribe],av_tric),0)) -> 0.69230769
AV77: =IF(15>p_horizon,"",EDATE(p_debut,14)) -> 46722 | AW77: =IF(15>p_horizon,"",COUNTIFS(TblApplications[Action],"À migrer",TblApplications[Mois bascule],">="&AV77,TblApplications[Mois bascule],"<"&EDATE(AV77,1),TblApplications[Environnement],av_envc,TblApplications[Domaine],av_domc,TblApplications[Tribe],av_tric)) -> 0 | AX77: =IF(15>p_horizon,"",COUNTIFS(TblApplications[Action],"À décommissionner",TblApplications[Mois lib (calc)],AV77,TblApplications[Environnement],av_envc,TblApplications[Domaine],av_domc,TblApplications[Tribe],av_tric)) -> 0 | AY77: =IF(15>p_horizon,"",COUNTIFS(TblApplications[Action],"Migré",TblApplications[Environnement],av_envc,TblApplications[Domaine],av_domc,TblApplications[Tribe],av_tric)+COUNTIFS(TblApplications[Action],"Décommissionné",TblApplications[Environnement],av_envc,TblApplications[Domaine],av_domc,TblApplications[Tribe],av_tric)+COUNTIFS(TblApplications[Action],"À migrer",TblApplications[Mois lib (calc)],"<="&AV77,TblApplications[Environnement],av_envc,TblApplications[Domaine],av_domc,TblApplications[Tribe],av_tric)+COUNTIFS(TblApplications[Action],"À décommissionner",TblApplications[Mois lib (calc)],"<="&AV77,TblApplications[Environnement],av_envc,TblApplications[Domaine],av_domc,TblApplications[Tribe],av_tric)) -> 9 | AZ77: =IF(15>p_horizon,"",IFERROR(AY77/COUNTIFS(TblApplications[ID],"<>",TblApplications[Environnement],av_envc,TblApplications[Domaine],av_domc,TblApplications[Tribe],av_tric),0)) -> 0.69230769
AV78: =IF(16>p_horizon,"",EDATE(p_debut,15)) -> 46753 | AW78: =IF(16>p_horizon,"",COUNTIFS(TblApplications[Action],"À migrer",TblApplications[Mois bascule],">="&AV78,TblApplications[Mois bascule],"<"&EDATE(AV78,1),TblApplications[Environnement],av_envc,TblApplications[Domaine],av_domc,TblApplications[Tribe],av_tric)) -> 0 | AX78: =IF(16>p_horizon,"",COUNTIFS(TblApplications[Action],"À décommissionner",TblApplications[Mois lib (calc)],AV78,TblApplications[Environnement],av_envc,TblApplications[Domaine],av_domc,TblApplications[Tribe],av_tric)) -> 0 | AY78: =IF(16>p_horizon,"",COUNTIFS(TblApplications[Action],"Migré",TblApplications[Environnement],av_envc,TblApplications[Domaine],av_domc,TblApplications[Tribe],av_tric)+COUNTIFS(TblApplications[Action],"Décommissionné",TblApplications[Environnement],av_envc,TblApplications[Domaine],av_domc,TblApplications[Tribe],av_tric)+COUNTIFS(TblApplications[Action],"À migrer",TblApplications[Mois lib (calc)],"<="&AV78,TblApplications[Environnement],av_envc,TblApplications[Domaine],av_domc,TblApplications[Tribe],av_tric)+COUNTIFS(TblApplications[Action],"À décommissionner",TblApplications[Mois lib (calc)],"<="&AV78,TblApplications[Environnement],av_envc,TblApplications[Domaine],av_domc,TblApplications[Tribe],av_tric)) -> 9 | AZ78: =IF(16>p_horizon,"",IFERROR(AY78/COUNTIFS(TblApplications[ID],"<>",TblApplications[Environnement],av_envc,TblApplications[Domaine],av_domc,TblApplications[Tribe],av_tric),0)) -> 0.69230769
AV79: =IF(17>p_horizon,"",EDATE(p_debut,16)) -> 46784 | AW79: =IF(17>p_horizon,"",COUNTIFS(TblApplications[Action],"À migrer",TblApplications[Mois bascule],">="&AV79,TblApplications[Mois bascule],"<"&EDATE(AV79,1),TblApplications[Environnement],av_envc,TblApplications[Domaine],av_domc,TblApplications[Tribe],av_tric)) -> 1 | AX79: =IF(17>p_horizon,"",COUNTIFS(TblApplications[Action],"À décommissionner",TblApplications[Mois lib (calc)],AV79,TblApplications[Environnement],av_envc,TblApplications[Domaine],av_domc,TblApplications[Tribe],av_tric)) -> 0 | AY79: =IF(17>p_horizon,"",COUNTIFS(TblApplications[Action],"Migré",TblApplications[Environnement],av_envc,TblApplications[Domaine],av_domc,TblApplications[Tribe],av_tric)+COUNTIFS(TblApplications[Action],"Décommissionné",TblApplications[Environnement],av_envc,TblApplications[Domaine],av_domc,TblApplications[Tribe],av_tric)+COUNTIFS(TblApplications[Action],"À migrer",TblApplications[Mois lib (calc)],"<="&AV79,TblApplications[Environnement],av_envc,TblApplications[Domaine],av_domc,TblApplications[Tribe],av_tric)+COUNTIFS(TblApplications[Action],"À décommissionner",TblApplications[Mois lib (calc)],"<="&AV79,TblApplications[Environnement],av_envc,TblApplications[Domaine],av_domc,TblApplications[Tribe],av_tric)) -> 9 | AZ79: =IF(17>p_horizon,"",IFERROR(AY79/COUNTIFS(TblApplications[ID],"<>",TblApplications[Environnement],av_envc,TblApplications[Domaine],av_domc,TblApplications[Tribe],av_tric),0)) -> 0.69230769
AV80: =IF(18>p_horizon,"",EDATE(p_debut,17)) -> 46813 | AW80: =IF(18>p_horizon,"",COUNTIFS(TblApplications[Action],"À migrer",TblApplications[Mois bascule],">="&AV80,TblApplications[Mois bascule],"<"&EDATE(AV80,1),TblApplications[Environnement],av_envc,TblApplications[Domaine],av_domc,TblApplications[Tribe],av_tric)) -> 0 | AX80: =IF(18>p_horizon,"",COUNTIFS(TblApplications[Action],"À décommissionner",TblApplications[Mois lib (calc)],AV80,TblApplications[Environnement],av_envc,TblApplications[Domaine],av_domc,TblApplications[Tribe],av_tric)) -> 0 | AY80: =IF(18>p_horizon,"",COUNTIFS(TblApplications[Action],"Migré",TblApplications[Environnement],av_envc,TblApplications[Domaine],av_domc,TblApplications[Tribe],av_tric)+COUNTIFS(TblApplications[Action],"Décommissionné",TblApplications[Environnement],av_envc,TblApplications[Domaine],av_domc,TblApplications[Tribe],av_tric)+COUNTIFS(TblApplications[Action],"À migrer",TblApplications[Mois lib (calc)],"<="&AV80,TblApplications[Environnement],av_envc,TblApplications[Domaine],av_domc,TblApplications[Tribe],av_tric)+COUNTIFS(TblApplications[Action],"À décommissionner",TblApplications[Mois lib (calc)],"<="&AV80,TblApplications[Environnement],av_envc,TblApplications[Domaine],av_domc,TblApplications[Tribe],av_tric)) -> 10 | AZ80: =IF(18>p_horizon,"",IFERROR(AY80/COUNTIFS(TblApplications[ID],"<>",TblApplications[Environnement],av_envc,TblApplications[Domaine],av_domc,TblApplications[Tribe],av_tric),0)) -> 0.76923077
AV81: =IF(19>p_horizon,"",EDATE(p_debut,18)) -> 46844 | AW81: =IF(19>p_horizon,"",COUNTIFS(TblApplications[Action],"À migrer",TblApplications[Mois bascule],">="&AV81,TblApplications[Mois bascule],"<"&EDATE(AV81,1),TblApplications[Environnement],av_envc,TblApplications[Domaine],av_domc,TblApplications[Tribe],av_tric)) -> 0 | AX81: =IF(19>p_horizon,"",COUNTIFS(TblApplications[Action],"À décommissionner",TblApplications[Mois lib (calc)],AV81,TblApplications[Environnement],av_envc,TblApplications[Domaine],av_domc,TblApplications[Tribe],av_tric)) -> 0 | AY81: =IF(19>p_horizon,"",COUNTIFS(TblApplications[Action],"Migré",TblApplications[Environnement],av_envc,TblApplications[Domaine],av_domc,TblApplications[Tribe],av_tric)+COUNTIFS(TblApplications[Action],"Décommissionné",TblApplications[Environnement],av_envc,TblApplications[Domaine],av_domc,TblApplications[Tribe],av_tric)+COUNTIFS(TblApplications[Action],"À migrer",TblApplications[Mois lib (calc)],"<="&AV81,TblApplications[Environnement],av_envc,TblApplications[Domaine],av_domc,TblApplications[Tribe],av_tric)+COUNTIFS(TblApplications[Action],"À décommissionner",TblApplications[Mois lib (calc)],"<="&AV81,TblApplications[Environnement],av_envc,TblApplications[Domaine],av_domc,TblApplications[Tribe],av_tric)) -> 10 | AZ81: =IF(19>p_horizon,"",IFERROR(AY81/COUNTIFS(TblApplications[ID],"<>",TblApplications[Environnement],av_envc,TblApplications[Domaine],av_domc,TblApplications[Tribe],av_tric),0)) -> 0.76923077
AV82: =IF(20>p_horizon,"",EDATE(p_debut,19)) -> 46874 | AW82: =IF(20>p_horizon,"",COUNTIFS(TblApplications[Action],"À migrer",TblApplications[Mois bascule],">="&AV82,TblApplications[Mois bascule],"<"&EDATE(AV82,1),TblApplications[Environnement],av_envc,TblApplications[Domaine],av_domc,TblApplications[Tribe],av_tric)) -> 2 | AX82: =IF(20>p_horizon,"",COUNTIFS(TblApplications[Action],"À décommissionner",TblApplications[Mois lib (calc)],AV82,TblApplications[Environnement],av_envc,TblApplications[Domaine],av_domc,TblApplications[Tribe],av_tric)) -> 0 | AY82: =IF(20>p_horizon,"",COUNTIFS(TblApplications[Action],"Migré",TblApplications[Environnement],av_envc,TblApplications[Domaine],av_domc,TblApplications[Tribe],av_tric)+COUNTIFS(TblApplications[Action],"Décommissionné",TblApplications[Environnement],av_envc,TblApplications[Domaine],av_domc,TblApplications[Tribe],av_tric)+COUNTIFS(TblApplications[Action],"À migrer",TblApplications[Mois lib (calc)],"<="&AV82,TblApplications[Environnement],av_envc,TblApplications[Domaine],av_domc,TblApplications[Tribe],av_tric)+COUNTIFS(TblApplications[Action],"À décommissionner",TblApplications[Mois lib (calc)],"<="&AV82,TblApplications[Environnement],av_envc,TblApplications[Domaine],av_domc,TblApplications[Tribe],av_tric)) -> 10 | AZ82: =IF(20>p_horizon,"",IFERROR(AY82/COUNTIFS(TblApplications[ID],"<>",TblApplications[Environnement],av_envc,TblApplications[Domaine],av_domc,TblApplications[Tribe],av_tric),0)) -> 0.76923077
AV83: =IF(21>p_horizon,"",EDATE(p_debut,20)) -> 46905 | AW83: =IF(21>p_horizon,"",COUNTIFS(TblApplications[Action],"À migrer",TblApplications[Mois bascule],">="&AV83,TblApplications[Mois bascule],"<"&EDATE(AV83,1),TblApplications[Environnement],av_envc,TblApplications[Domaine],av_domc,TblApplications[Tribe],av_tric)) -> 0 | AX83: =IF(21>p_horizon,"",COUNTIFS(TblApplications[Action],"À décommissionner",TblApplications[Mois lib (calc)],AV83,TblApplications[Environnement],av_envc,TblApplications[Domaine],av_domc,TblApplications[Tribe],av_tric)) -> 0 | AY83: =IF(21>p_horizon,"",COUNTIFS(TblApplications[Action],"Migré",TblApplications[Environnement],av_envc,TblApplications[Domaine],av_domc,TblApplications[Tribe],av_tric)+COUNTIFS(TblApplications[Action],"Décommissionné",TblApplications[Environnement],av_envc,TblApplications[Domaine],av_domc,TblApplications[Tribe],av_tric)+COUNTIFS(TblApplications[Action],"À migrer",TblApplications[Mois lib (calc)],"<="&AV83,TblApplications[Environnement],av_envc,TblApplications[Domaine],av_domc,TblApplications[Tribe],av_tric)+COUNTIFS(TblApplications[Action],"À décommissionner",TblApplications[Mois lib (calc)],"<="&AV83,TblApplications[Environnement],av_envc,TblApplications[Domaine],av_domc,TblApplications[Tribe],av_tric)) -> 12 | AZ83: =IF(21>p_horizon,"",IFERROR(AY83/COUNTIFS(TblApplications[ID],"<>",TblApplications[Environnement],av_envc,TblApplications[Domaine],av_domc,TblApplications[Tribe],av_tric),0)) -> 0.92307692
AV84: =IF(22>p_horizon,"",EDATE(p_debut,21)) -> 46935 | AW84: =IF(22>p_horizon,"",COUNTIFS(TblApplications[Action],"À migrer",TblApplications[Mois bascule],">="&AV84,TblApplications[Mois bascule],"<"&EDATE(AV84,1),TblApplications[Environnement],av_envc,TblApplications[Domaine],av_domc,TblApplications[Tribe],av_tric)) -> 0 | AX84: =IF(22>p_horizon,"",COUNTIFS(TblApplications[Action],"À décommissionner",TblApplications[Mois lib (calc)],AV84,TblApplications[Environnement],av_envc,TblApplications[Domaine],av_domc,TblApplications[Tribe],av_tric)) -> 0 | AY84: =IF(22>p_horizon,"",COUNTIFS(TblApplications[Action],"Migré",TblApplications[Environnement],av_envc,TblApplications[Domaine],av_domc,TblApplications[Tribe],av_tric)+COUNTIFS(TblApplications[Action],"Décommissionné",TblApplications[Environnement],av_envc,TblApplications[Domaine],av_domc,TblApplications[Tribe],av_tric)+COUNTIFS(TblApplications[Action],"À migrer",TblApplications[Mois lib (calc)],"<="&AV84,TblApplications[Environnement],av_envc,TblApplications[Domaine],av_domc,TblApplications[Tribe],av_tric)+COUNTIFS(TblApplications[Action],"À décommissionner",TblApplications[Mois lib (calc)],"<="&AV84,TblApplications[Environnement],av_envc,TblApplications[Domaine],av_domc,TblApplications[Tribe],av_tric)) -> 12 | AZ84: =IF(22>p_horizon,"",IFERROR(AY84/COUNTIFS(TblApplications[ID],"<>",TblApplications[Environnement],av_envc,TblApplications[Domaine],av_domc,TblApplications[Tribe],av_tric),0)) -> 0.92307692
AV85: =IF(23>p_horizon,"",EDATE(p_debut,22)) -> 46966 | AW85: =IF(23>p_horizon,"",COUNTIFS(TblApplications[Action],"À migrer",TblApplications[Mois bascule],">="&AV85,TblApplications[Mois bascule],"<"&EDATE(AV85,1),TblApplications[Environnement],av_envc,TblApplications[Domaine],av_domc,TblApplications[Tribe],av_tric)) -> 0 | AX85: =IF(23>p_horizon,"",COUNTIFS(TblApplications[Action],"À décommissionner",TblApplications[Mois lib (calc)],AV85,TblApplications[Environnement],av_envc,TblApplications[Domaine],av_domc,TblApplications[Tribe],av_tric)) -> 0 | AY85: =IF(23>p_horizon,"",COUNTIFS(TblApplications[Action],"Migré",TblApplications[Environnement],av_envc,TblApplications[Domaine],av_domc,TblApplications[Tribe],av_tric)+COUNTIFS(TblApplications[Action],"Décommissionné",TblApplications[Environnement],av_envc,TblApplications[Domaine],av_domc,TblApplications[Tribe],av_tric)+COUNTIFS(TblApplications[Action],"À migrer",TblApplications[Mois lib (calc)],"<="&AV85,TblApplications[Environnement],av_envc,TblApplications[Domaine],av_domc,TblApplications[Tribe],av_tric)+COUNTIFS(TblApplications[Action],"À décommissionner",TblApplications[Mois lib (calc)],"<="&AV85,TblApplications[Environnement],av_envc,TblApplications[Domaine],av_domc,TblApplications[Tribe],av_tric)) -> 12 | AZ85: =IF(23>p_horizon,"",IFERROR(AY85/COUNTIFS(TblApplications[ID],"<>",TblApplications[Environnement],av_envc,TblApplications[Domaine],av_domc,TblApplications[Tribe],av_tric),0)) -> 0.92307692
AV86: =IF(24>p_horizon,"",EDATE(p_debut,23)) -> 46997 | AW86: =IF(24>p_horizon,"",COUNTIFS(TblApplications[Action],"À migrer",TblApplications[Mois bascule],">="&AV86,TblApplications[Mois bascule],"<"&EDATE(AV86,1),TblApplications[Environnement],av_envc,TblApplications[Domaine],av_domc,TblApplications[Tribe],av_tric)) -> 0 | AX86: =IF(24>p_horizon,"",COUNTIFS(TblApplications[Action],"À décommissionner",TblApplications[Mois lib (calc)],AV86,TblApplications[Environnement],av_envc,TblApplications[Domaine],av_domc,TblApplications[Tribe],av_tric)) -> 0 | AY86: =IF(24>p_horizon,"",COUNTIFS(TblApplications[Action],"Migré",TblApplications[Environnement],av_envc,TblApplications[Domaine],av_domc,TblApplications[Tribe],av_tric)+COUNTIFS(TblApplications[Action],"Décommissionné",TblApplications[Environnement],av_envc,TblApplications[Domaine],av_domc,TblApplications[Tribe],av_tric)+COUNTIFS(TblApplications[Action],"À migrer",TblApplications[Mois lib (calc)],"<="&AV86,TblApplications[Environnement],av_envc,TblApplications[Domaine],av_domc,TblApplications[Tribe],av_tric)+COUNTIFS(TblApplications[Action],"À décommissionner",TblApplications[Mois lib (calc)],"<="&AV86,TblApplications[Environnement],av_envc,TblApplications[Domaine],av_domc,TblApplications[Tribe],av_tric)) -> 12 | AZ86: =IF(24>p_horizon,"",IFERROR(AY86/COUNTIFS(TblApplications[ID],"<>",TblApplications[Environnement],av_envc,TblApplications[Domaine],av_domc,TblApplications[Tribe],av_tric),0)) -> 0.92307692
AV87: =IF(25>p_horizon,"",EDATE(p_debut,24)) -> 47027 | AW87: =IF(25>p_horizon,"",COUNTIFS(TblApplications[Action],"À migrer",TblApplications[Mois bascule],">="&AV87,TblApplications[Mois bascule],"<"&EDATE(AV87,1),TblApplications[Environnement],av_envc,TblApplications[Domaine],av_domc,TblApplications[Tribe],av_tric)) -> 1 | AX87: =IF(25>p_horizon,"",COUNTIFS(TblApplications[Action],"À décommissionner",TblApplications[Mois lib (calc)],AV87,TblApplications[Environnement],av_envc,TblApplications[Domaine],av_domc,TblApplications[Tribe],av_tric)) -> 0 | AY87: =IF(25>p_horizon,"",COUNTIFS(TblApplications[Action],"Migré",TblApplications[Environnement],av_envc,TblApplications[Domaine],av_domc,TblApplications[Tribe],av_tric)+COUNTIFS(TblApplications[Action],"Décommissionné",TblApplications[Environnement],av_envc,TblApplications[Domaine],av_domc,TblApplications[Tribe],av_tric)+COUNTIFS(TblApplications[Action],"À migrer",TblApplications[Mois lib (calc)],"<="&AV87,TblApplications[Environnement],av_envc,TblApplications[Domaine],av_domc,TblApplications[Tribe],av_tric)+COUNTIFS(TblApplications[Action],"À décommissionner",TblApplications[Mois lib (calc)],"<="&AV87,TblApplications[Environnement],av_envc,TblApplications[Domaine],av_domc,TblApplications[Tribe],av_tric)) -> 12 | AZ87: =IF(25>p_horizon,"",IFERROR(AY87/COUNTIFS(TblApplications[ID],"<>",TblApplications[Environnement],av_envc,TblApplications[Domaine],av_domc,TblApplications[Tribe],av_tric),0)) -> 0.92307692
AV88: =IF(26>p_horizon,"",EDATE(p_debut,25)) -> 47058 | AW88: =IF(26>p_horizon,"",COUNTIFS(TblApplications[Action],"À migrer",TblApplications[Mois bascule],">="&AV88,TblApplications[Mois bascule],"<"&EDATE(AV88,1),TblApplications[Environnement],av_envc,TblApplications[Domaine],av_domc,TblApplications[Tribe],av_tric)) -> 0 | AX88: =IF(26>p_horizon,"",COUNTIFS(TblApplications[Action],"À décommissionner",TblApplications[Mois lib (calc)],AV88,TblApplications[Environnement],av_envc,TblApplications[Domaine],av_domc,TblApplications[Tribe],av_tric)) -> 0 | AY88: =IF(26>p_horizon,"",COUNTIFS(TblApplications[Action],"Migré",TblApplications[Environnement],av_envc,TblApplications[Domaine],av_domc,TblApplications[Tribe],av_tric)+COUNTIFS(TblApplications[Action],"Décommissionné",TblApplications[Environnement],av_envc,TblApplications[Domaine],av_domc,TblApplications[Tribe],av_tric)+COUNTIFS(TblApplications[Action],"À migrer",TblApplications[Mois lib (calc)],"<="&AV88,TblApplications[Environnement],av_envc,TblApplications[Domaine],av_domc,TblApplications[Tribe],av_tric)+COUNTIFS(TblApplications[Action],"À décommissionner",TblApplications[Mois lib (calc)],"<="&AV88,TblApplications[Environnement],av_envc,TblApplications[Domaine],av_domc,TblApplications[Tribe],av_tric)) -> 12 | AZ88: =IF(26>p_horizon,"",IFERROR(AY88/COUNTIFS(TblApplications[ID],"<>",TblApplications[Environnement],av_envc,TblApplications[Domaine],av_domc,TblApplications[Tribe],av_tric),0)) -> 0.92307692
AV89: =IF(27>p_horizon,"",EDATE(p_debut,26)) -> 47088 | AW89: =IF(27>p_horizon,"",COUNTIFS(TblApplications[Action],"À migrer",TblApplications[Mois bascule],">="&AV89,TblApplications[Mois bascule],"<"&EDATE(AV89,1),TblApplications[Environnement],av_envc,TblApplications[Domaine],av_domc,TblApplications[Tribe],av_tric)) -> 0 | AX89: =IF(27>p_horizon,"",COUNTIFS(TblApplications[Action],"À décommissionner",TblApplications[Mois lib (calc)],AV89,TblApplications[Environnement],av_envc,TblApplications[Domaine],av_domc,TblApplications[Tribe],av_tric)) -> 0 | AY89: =IF(27>p_horizon,"",COUNTIFS(TblApplications[Action],"Migré",TblApplications[Environnement],av_envc,TblApplications[Domaine],av_domc,TblApplications[Tribe],av_tric)+COUNTIFS(TblApplications[Action],"Décommissionné",TblApplications[Environnement],av_envc,TblApplications[Domaine],av_domc,TblApplications[Tribe],av_tric)+COUNTIFS(TblApplications[Action],"À migrer",TblApplications[Mois lib (calc)],"<="&AV89,TblApplications[Environnement],av_envc,TblApplications[Domaine],av_domc,TblApplications[Tribe],av_tric)+COUNTIFS(TblApplications[Action],"À décommissionner",TblApplications[Mois lib (calc)],"<="&AV89,TblApplications[Environnement],av_envc,TblApplications[Domaine],av_domc,TblApplications[Tribe],av_tric)) -> 13 | AZ89: =IF(27>p_horizon,"",IFERROR(AY89/COUNTIFS(TblApplications[ID],"<>",TblApplications[Environnement],av_envc,TblApplications[Domaine],av_domc,TblApplications[Tribe],av_tric),0)) -> 1
AV90: =IF(28>p_horizon,"",EDATE(p_debut,27)) -> 47119 | AW90: =IF(28>p_horizon,"",COUNTIFS(TblApplications[Action],"À migrer",TblApplications[Mois bascule],">="&AV90,TblApplications[Mois bascule],"<"&EDATE(AV90,1),TblApplications[Environnement],av_envc,TblApplications[Domaine],av_domc,TblApplications[Tribe],av_tric)) -> 0 | AX90: =IF(28>p_horizon,"",COUNTIFS(TblApplications[Action],"À décommissionner",TblApplications[Mois lib (calc)],AV90,TblApplications[Environnement],av_envc,TblApplications[Domaine],av_domc,TblApplications[Tribe],av_tric)) -> 0 | AY90: =IF(28>p_horizon,"",COUNTIFS(TblApplications[Action],"Migré",TblApplications[Environnement],av_envc,TblApplications[Domaine],av_domc,TblApplications[Tribe],av_tric)+COUNTIFS(TblApplications[Action],"Décommissionné",TblApplications[Environnement],av_envc,TblApplications[Domaine],av_domc,TblApplications[Tribe],av_tric)+COUNTIFS(TblApplications[Action],"À migrer",TblApplications[Mois lib (calc)],"<="&AV90,TblApplications[Environnement],av_envc,TblApplications[Domaine],av_domc,TblApplications[Tribe],av_tric)+COUNTIFS(TblApplications[Action],"À décommissionner",TblApplications[Mois lib (calc)],"<="&AV90,TblApplications[Environnement],av_envc,TblApplications[Domaine],av_domc,TblApplications[Tribe],av_tric)) -> 13 | AZ90: =IF(28>p_horizon,"",IFERROR(AY90/COUNTIFS(TblApplications[ID],"<>",TblApplications[Environnement],av_envc,TblApplications[Domaine],av_domc,TblApplications[Tribe],av_tric),0)) -> 1
AV91: =IF(29>p_horizon,"",EDATE(p_debut,28)) -> 47150 | AW91: =IF(29>p_horizon,"",COUNTIFS(TblApplications[Action],"À migrer",TblApplications[Mois bascule],">="&AV91,TblApplications[Mois bascule],"<"&EDATE(AV91,1),TblApplications[Environnement],av_envc,TblApplications[Domaine],av_domc,TblApplications[Tribe],av_tric)) -> 0 | AX91: =IF(29>p_horizon,"",COUNTIFS(TblApplications[Action],"À décommissionner",TblApplications[Mois lib (calc)],AV91,TblApplications[Environnement],av_envc,TblApplications[Domaine],av_domc,TblApplications[Tribe],av_tric)) -> 0 | AY91: =IF(29>p_horizon,"",COUNTIFS(TblApplications[Action],"Migré",TblApplications[Environnement],av_envc,TblApplications[Domaine],av_domc,TblApplications[Tribe],av_tric)+COUNTIFS(TblApplications[Action],"Décommissionné",TblApplications[Environnement],av_envc,TblApplications[Domaine],av_domc,TblApplications[Tribe],av_tric)+COUNTIFS(TblApplications[Action],"À migrer",TblApplications[Mois lib (calc)],"<="&AV91,TblApplications[Environnement],av_envc,TblApplications[Domaine],av_domc,TblApplications[Tribe],av_tric)+COUNTIFS(TblApplications[Action],"À décommissionner",TblApplications[Mois lib (calc)],"<="&AV91,TblApplications[Environnement],av_envc,TblApplications[Domaine],av_domc,TblApplications[Tribe],av_tric)) -> 13 | AZ91: =IF(29>p_horizon,"",IFERROR(AY91/COUNTIFS(TblApplications[ID],"<>",TblApplications[Environnement],av_envc,TblApplications[Domaine],av_domc,TblApplications[Tribe],av_tric),0)) -> 1
AV92: =IF(30>p_horizon,"",EDATE(p_debut,29)) -> 47178 | AW92: =IF(30>p_horizon,"",COUNTIFS(TblApplications[Action],"À migrer",TblApplications[Mois bascule],">="&AV92,TblApplications[Mois bascule],"<"&EDATE(AV92,1),TblApplications[Environnement],av_envc,TblApplications[Domaine],av_domc,TblApplications[Tribe],av_tric)) -> 0 | AX92: =IF(30>p_horizon,"",COUNTIFS(TblApplications[Action],"À décommissionner",TblApplications[Mois lib (calc)],AV92,TblApplications[Environnement],av_envc,TblApplications[Domaine],av_domc,TblApplications[Tribe],av_tric)) -> 0 | AY92: =IF(30>p_horizon,"",COUNTIFS(TblApplications[Action],"Migré",TblApplications[Environnement],av_envc,TblApplications[Domaine],av_domc,TblApplications[Tribe],av_tric)+COUNTIFS(TblApplications[Action],"Décommissionné",TblApplications[Environnement],av_envc,TblApplications[Domaine],av_domc,TblApplications[Tribe],av_tric)+COUNTIFS(TblApplications[Action],"À migrer",TblApplications[Mois lib (calc)],"<="&AV92,TblApplications[Environnement],av_envc,TblApplications[Domaine],av_domc,TblApplications[Tribe],av_tric)+COUNTIFS(TblApplications[Action],"À décommissionner",TblApplications[Mois lib (calc)],"<="&AV92,TblApplications[Environnement],av_envc,TblApplications[Domaine],av_domc,TblApplications[Tribe],av_tric)) -> 13 | AZ92: =IF(30>p_horizon,"",IFERROR(AY92/COUNTIFS(TblApplications[ID],"<>",TblApplications[Environnement],av_envc,TblApplications[Domaine],av_domc,TblApplications[Tribe],av_tric),0)) -> 1
AV93: =IF(31>p_horizon,"",EDATE(p_debut,30)) -> 47209 | AW93: =IF(31>p_horizon,"",COUNTIFS(TblApplications[Action],"À migrer",TblApplications[Mois bascule],">="&AV93,TblApplications[Mois bascule],"<"&EDATE(AV93,1),TblApplications[Environnement],av_envc,TblApplications[Domaine],av_domc,TblApplications[Tribe],av_tric)) -> 0 | AX93: =IF(31>p_horizon,"",COUNTIFS(TblApplications[Action],"À décommissionner",TblApplications[Mois lib (calc)],AV93,TblApplications[Environnement],av_envc,TblApplications[Domaine],av_domc,TblApplications[Tribe],av_tric)) -> 0 | AY93: =IF(31>p_horizon,"",COUNTIFS(TblApplications[Action],"Migré",TblApplications[Environnement],av_envc,TblApplications[Domaine],av_domc,TblApplications[Tribe],av_tric)+COUNTIFS(TblApplications[Action],"Décommissionné",TblApplications[Environnement],av_envc,TblApplications[Domaine],av_domc,TblApplications[Tribe],av_tric)+COUNTIFS(TblApplications[Action],"À migrer",TblApplications[Mois lib (calc)],"<="&AV93,TblApplications[Environnement],av_envc,TblApplications[Domaine],av_domc,TblApplications[Tribe],av_tric)+COUNTIFS(TblApplications[Action],"À décommissionner",TblApplications[Mois lib (calc)],"<="&AV93,TblApplications[Environnement],av_envc,TblApplications[Domaine],av_domc,TblApplications[Tribe],av_tric)) -> 13 | AZ93: =IF(31>p_horizon,"",IFERROR(AY93/COUNTIFS(TblApplications[ID],"<>",TblApplications[Environnement],av_envc,TblApplications[Domaine],av_domc,TblApplications[Tribe],av_tric),0)) -> 1
AV94: =IF(32>p_horizon,"",EDATE(p_debut,31)) -> 47239 | AW94: =IF(32>p_horizon,"",COUNTIFS(TblApplications[Action],"À migrer",TblApplications[Mois bascule],">="&AV94,TblApplications[Mois bascule],"<"&EDATE(AV94,1),TblApplications[Environnement],av_envc,TblApplications[Domaine],av_domc,TblApplications[Tribe],av_tric)) -> 0 | AX94: =IF(32>p_horizon,"",COUNTIFS(TblApplications[Action],"À décommissionner",TblApplications[Mois lib (calc)],AV94,TblApplications[Environnement],av_envc,TblApplications[Domaine],av_domc,TblApplications[Tribe],av_tric)) -> 0 | AY94: =IF(32>p_horizon,"",COUNTIFS(TblApplications[Action],"Migré",TblApplications[Environnement],av_envc,TblApplications[Domaine],av_domc,TblApplications[Tribe],av_tric)+COUNTIFS(TblApplications[Action],"Décommissionné",TblApplications[Environnement],av_envc,TblApplications[Domaine],av_domc,TblApplications[Tribe],av_tric)+COUNTIFS(TblApplications[Action],"À migrer",TblApplications[Mois lib (calc)],"<="&AV94,TblApplications[Environnement],av_envc,TblApplications[Domaine],av_domc,TblApplications[Tribe],av_tric)+COUNTIFS(TblApplications[Action],"À décommissionner",TblApplications[Mois lib (calc)],"<="&AV94,TblApplications[Environnement],av_envc,TblApplications[Domaine],av_domc,TblApplications[Tribe],av_tric)) -> 13 | AZ94: =IF(32>p_horizon,"",IFERROR(AY94/COUNTIFS(TblApplications[ID],"<>",TblApplications[Environnement],av_envc,TblApplications[Domaine],av_domc,TblApplications[Tribe],av_tric),0)) -> 1
AV95: =IF(33>p_horizon,"",EDATE(p_debut,32)) -> 47270 | AW95: =IF(33>p_horizon,"",COUNTIFS(TblApplications[Action],"À migrer",TblApplications[Mois bascule],">="&AV95,TblApplications[Mois bascule],"<"&EDATE(AV95,1),TblApplications[Environnement],av_envc,TblApplications[Domaine],av_domc,TblApplications[Tribe],av_tric)) -> 0 | AX95: =IF(33>p_horizon,"",COUNTIFS(TblApplications[Action],"À décommissionner",TblApplications[Mois lib (calc)],AV95,TblApplications[Environnement],av_envc,TblApplications[Domaine],av_domc,TblApplications[Tribe],av_tric)) -> 0 | AY95: =IF(33>p_horizon,"",COUNTIFS(TblApplications[Action],"Migré",TblApplications[Environnement],av_envc,TblApplications[Domaine],av_domc,TblApplications[Tribe],av_tric)+COUNTIFS(TblApplications[Action],"Décommissionné",TblApplications[Environnement],av_envc,TblApplications[Domaine],av_domc,TblApplications[Tribe],av_tric)+COUNTIFS(TblApplications[Action],"À migrer",TblApplications[Mois lib (calc)],"<="&AV95,TblApplications[Environnement],av_envc,TblApplications[Domaine],av_domc,TblApplications[Tribe],av_tric)+COUNTIFS(TblApplications[Action],"À décommissionner",TblApplications[Mois lib (calc)],"<="&AV95,TblApplications[Environnement],av_envc,TblApplications[Domaine],av_domc,TblApplications[Tribe],av_tric)) -> 13 | AZ95: =IF(33>p_horizon,"",IFERROR(AY95/COUNTIFS(TblApplications[ID],"<>",TblApplications[Environnement],av_envc,TblApplications[Domaine],av_domc,TblApplications[Tribe],av_tric),0)) -> 1
B96: La frise détaillée par déploiement est dans l'onglet « Frise » (mêmes filtres). | AV96: =IF(34>p_horizon,"",EDATE(p_debut,33)) -> 47300 | AW96: =IF(34>p_horizon,"",COUNTIFS(TblApplications[Action],"À migrer",TblApplications[Mois bascule],">="&AV96,TblApplications[Mois bascule],"<"&EDATE(AV96,1),TblApplications[Environnement],av_envc,TblApplications[Domaine],av_domc,TblApplications[Tribe],av_tric)) -> 0 | AX96: =IF(34>p_horizon,"",COUNTIFS(TblApplications[Action],"À décommissionner",TblApplications[Mois lib (calc)],AV96,TblApplications[Environnement],av_envc,TblApplications[Domaine],av_domc,TblApplications[Tribe],av_tric)) -> 0 | AY96: =IF(34>p_horizon,"",COUNTIFS(TblApplications[Action],"Migré",TblApplications[Environnement],av_envc,TblApplications[Domaine],av_domc,TblApplications[Tribe],av_tric)+COUNTIFS(TblApplications[Action],"Décommissionné",TblApplications[Environnement],av_envc,TblApplications[Domaine],av_domc,TblApplications[Tribe],av_tric)+COUNTIFS(TblApplications[Action],"À migrer",TblApplications[Mois lib (calc)],"<="&AV96,TblApplications[Environnement],av_envc,TblApplications[Domaine],av_domc,TblApplications[Tribe],av_tric)+COUNTIFS(TblApplications[Action],"À décommissionner",TblApplications[Mois lib (calc)],"<="&AV96,TblApplications[Environnement],av_envc,TblApplications[Domaine],av_domc,TblApplications[Tribe],av_tric)) -> 13 | AZ96: =IF(34>p_horizon,"",IFERROR(AY96/COUNTIFS(TblApplications[ID],"<>",TblApplications[Environnement],av_envc,TblApplications[Domaine],av_domc,TblApplications[Tribe],av_tric),0)) -> 1
AV97: =IF(35>p_horizon,"",EDATE(p_debut,34)) -> 47331 | AW97: =IF(35>p_horizon,"",COUNTIFS(TblApplications[Action],"À migrer",TblApplications[Mois bascule],">="&AV97,TblApplications[Mois bascule],"<"&EDATE(AV97,1),TblApplications[Environnement],av_envc,TblApplications[Domaine],av_domc,TblApplications[Tribe],av_tric)) -> 0 | AX97: =IF(35>p_horizon,"",COUNTIFS(TblApplications[Action],"À décommissionner",TblApplications[Mois lib (calc)],AV97,TblApplications[Environnement],av_envc,TblApplications[Domaine],av_domc,TblApplications[Tribe],av_tric)) -> 0 | AY97: =IF(35>p_horizon,"",COUNTIFS(TblApplications[Action],"Migré",TblApplications[Environnement],av_envc,TblApplications[Domaine],av_domc,TblApplications[Tribe],av_tric)+COUNTIFS(TblApplications[Action],"Décommissionné",TblApplications[Environnement],av_envc,TblApplications[Domaine],av_domc,TblApplications[Tribe],av_tric)+COUNTIFS(TblApplications[Action],"À migrer",TblApplications[Mois lib (calc)],"<="&AV97,TblApplications[Environnement],av_envc,TblApplications[Domaine],av_domc,TblApplications[Tribe],av_tric)+COUNTIFS(TblApplications[Action],"À décommissionner",TblApplications[Mois lib (calc)],"<="&AV97,TblApplications[Environnement],av_envc,TblApplications[Domaine],av_domc,TblApplications[Tribe],av_tric)) -> 13 | AZ97: =IF(35>p_horizon,"",IFERROR(AY97/COUNTIFS(TblApplications[ID],"<>",TblApplications[Environnement],av_envc,TblApplications[Domaine],av_domc,TblApplications[Tribe],av_tric),0)) -> 1
AV98: =IF(36>p_horizon,"",EDATE(p_debut,35)) -> 47362 | AW98: =IF(36>p_horizon,"",COUNTIFS(TblApplications[Action],"À migrer",TblApplications[Mois bascule],">="&AV98,TblApplications[Mois bascule],"<"&EDATE(AV98,1),TblApplications[Environnement],av_envc,TblApplications[Domaine],av_domc,TblApplications[Tribe],av_tric)) -> 0 | AX98: =IF(36>p_horizon,"",COUNTIFS(TblApplications[Action],"À décommissionner",TblApplications[Mois lib (calc)],AV98,TblApplications[Environnement],av_envc,TblApplications[Domaine],av_domc,TblApplications[Tribe],av_tric)) -> 0 | AY98: =IF(36>p_horizon,"",COUNTIFS(TblApplications[Action],"Migré",TblApplications[Environnement],av_envc,TblApplications[Domaine],av_domc,TblApplications[Tribe],av_tric)+COUNTIFS(TblApplications[Action],"Décommissionné",TblApplications[Environnement],av_envc,TblApplications[Domaine],av_domc,TblApplications[Tribe],av_tric)+COUNTIFS(TblApplications[Action],"À migrer",TblApplications[Mois lib (calc)],"<="&AV98,TblApplications[Environnement],av_envc,TblApplications[Domaine],av_domc,TblApplications[Tribe],av_tric)+COUNTIFS(TblApplications[Action],"À décommissionner",TblApplications[Mois lib (calc)],"<="&AV98,TblApplications[Environnement],av_envc,TblApplications[Domaine],av_domc,TblApplications[Tribe],av_tric)) -> 13 | AZ98: =IF(36>p_horizon,"",IFERROR(AY98/COUNTIFS(TblApplications[ID],"<>",TblApplications[Environnement],av_envc,TblApplications[Domaine],av_domc,TblApplications[Tribe],av_tric),0)) -> 1

Sheet Frise
B1: Frise des migrations par déploiement
B2: Utilise les filtres de l'onglet Avancement (environnement, domaine, tribe) ; colonne rouge = mois de référence.
B4: ="Filtres actifs (onglet Avancement) : environnement "&Avancement!C4&" · domaine "&Avancement!F4&" · tribe "&Avancement!I4&" · mois de référence "&TEXT(MONTH(av_mois),"00")&"/"&YEAR(av_mois) -> Filtres actifs (onglet Avancement) : environnement Tous · domaine Tous · tribe Tous · mois de référence 12/2027
B6: Frise par déploiement (filtrée, triée par ordre de saisie)
G7: IKS | I7: Double run | K7: Bascule | M7: ROKS | O7: Décom.
B8: ID | C8: Application | D8: Env | E8: Couloir | F8: Action | G8: =IF(1>p_horizon,"",EDATE(p_debut,0)) -> 46296 | H8: =IF(2>p_horizon,"",EDATE(p_debut,1)) -> 46327 | I8: =IF(3>p_horizon,"",EDATE(p_debut,2)) -> 46357 | J8: =IF(4>p_horizon,"",EDATE(p_debut,3)) -> 46388 | K8: =IF(5>p_horizon,"",EDATE(p_debut,4)) -> 46419 | L8: =IF(6>p_horizon,"",EDATE(p_debut,5)) -> 46447 | M8: =IF(7>p_horizon,"",EDATE(p_debut,6)) -> 46478 | N8: =IF(8>p_horizon,"",EDATE(p_debut,7)) -> 46508 | O8: =IF(9>p_horizon,"",EDATE(p_debut,8)) -> 46539 | P8: =IF(10>p_horizon,"",EDATE(p_debut,9)) -> 46569 | Q8: =IF(11>p_horizon,"",EDATE(p_debut,10)) -> 46600 | R8: =IF(12>p_horizon,"",EDATE(p_debut,11)) -> 46631 | S8: =IF(13>p_horizon,"",EDATE(p_debut,12)) -> 46661 | T8: =IF(14>p_horizon,"",EDATE(p_debut,13)) -> 46692 | U8: =IF(15>p_horizon,"",EDATE(p_debut,14)) -> 46722 | V8: =IF(16>p_horizon,"",EDATE(p_debut,15)) -> 46753 | W8: =IF(17>p_horizon,"",EDATE(p_debut,16)) -> 46784 | X8: =IF(18>p_horizon,"",EDATE(p_debut,17)) -> 46813 | Y8: =IF(19>p_horizon,"",EDATE(p_debut,18)) -> 46844 | Z8: =IF(20>p_horizon,"",EDATE(p_debut,19)) -> 46874 | AA8: =IF(21>p_horizon,"",EDATE(p_debut,20)) -> 46905 | AB8: =IF(22>p_horizon,"",EDATE(p_debut,21)) -> 46935 | AC8: =IF(23>p_horizon,"",EDATE(p_debut,22)) -> 46966 | AD8: =IF(24>p_horizon,"",EDATE(p_debut,23)) -> 46997 | AE8: =IF(25>p_horizon,"",EDATE(p_debut,24)) -> 47027 | AF8: =IF(26>p_horizon,"",EDATE(p_debut,25)) -> 47058 | AG8: =IF(27>p_horizon,"",EDATE(p_debut,26)) -> 47088 | AH8: =IF(28>p_horizon,"",EDATE(p_debut,27)) -> 47119 | AI8: =IF(29>p_horizon,"",EDATE(p_debut,28)) -> 47150 | AJ8: =IF(30>p_horizon,"",EDATE(p_debut,29)) -> 47178 | AK8: =IF(31>p_horizon,"",EDATE(p_debut,30)) -> 47209 | AL8: =IF(32>p_horizon,"",EDATE(p_debut,31)) -> 47239 | AM8: =IF(33>p_horizon,"",EDATE(p_debut,32)) -> 47270 | AN8: =IF(34>p_horizon,"",EDATE(p_debut,33)) -> 47300 | AO8: =IF(35>p_horizon,"",EDATE(p_debut,34)) -> 47331 | AP8: =IF(36>p_horizon,"",EDATE(p_debut,35)) -> 47362
A9: =IFERROR(MATCH(1,TblApplications[Rang frise],0),"") -> 1 | B9: =IF($A9="","",INDEX(TblApplications[ID],$A9)) -> APP-01 | C9: =IF($A9="","",INDEX(TblApplications[Application],$A9)) -> Portail assuré (démo) | D9: =IF($A9="","",INDEX(TblApplications[Environnement],$A9)) -> NPRD | E9: =IF($A9="","",INDEX(TblApplications[Couloir],$A9)) -> DEV1 | F9: =IF($A9="","",INDEX(TblApplications[Action],$A9)) -> À migrer | G9: =IF(OR($A9="",G$8=""),"",IF($F9="Migré","ROKS",IF($F9="À décommissionner",IF(G$8<$AS9,"IKS","Décom."),IF(OR($AQ9="",$AS9=""),"",IF(G$8<$AQ9,"IKS",IF(G$8<$AS9,IF(G$8=$AR9,"Bascule","Double run"),"ROKS")))))) -> IKS | H9: =IF(OR($A9="",H$8=""),"",IF($F9="Migré","ROKS",IF($F9="À décommissionner",IF(H$8<$AS9,"IKS","Décom."),IF(OR($AQ9="",$AS9=""),"",IF(H$8<$AQ9,"IKS",IF(H$8<$AS9,IF(H$8=$AR9,"Bascule","Double run"),"ROKS")))))) -> IKS | I9: =IF(OR($A9="",I$8=""),"",IF($F9="Migré","ROKS",IF($F9="À décommissionner",IF(I$8<$AS9,"IKS","Décom."),IF(OR($AQ9="",$AS9=""),"",IF(I$8<$AQ9,"IKS",IF(I$8<$AS9,IF(I$8=$AR9,"Bascule","Double run"),"ROKS")))))) -> IKS | J9: =IF(OR($A9="",J$8=""),"",IF($F9="Migré","ROKS",IF($F9="À décommissionner",IF(J$8<$AS9,"IKS","Décom."),IF(OR($AQ9="",$AS9=""),"",IF(J$8<$AQ9,"IKS",IF(J$8<$AS9,IF(J$8=$AR9,"Bascule","Double run"),"ROKS")))))) -> Bascule | K9: =IF(OR($A9="",K$8=""),"",IF($F9="Migré","ROKS",IF($F9="À décommissionner",IF(K$8<$AS9,"IKS","Décom."),IF(OR($AQ9="",$AS9=""),"",IF(K$8<$AQ9,"IKS",IF(K$8<$AS9,IF(K$8=$AR9,"Bascule","Double run"),"ROKS")))))) -> ROKS | L9: =IF(OR($A9="",L$8=""),"",IF($F9="Migré","ROKS",IF($F9="À décommissionner",IF(L$8<$AS9,"IKS","Décom."),IF(OR($AQ9="",$AS9=""),"",IF(L$8<$AQ9,"IKS",IF(L$8<$AS9,IF(L$8=$AR9,"Bascule","Double run"),"ROKS")))))) -> ROKS | M9: =IF(OR($A9="",M$8=""),"",IF($F9="Migré","ROKS",IF($F9="À décommissionner",IF(M$8<$AS9,"IKS","Décom."),IF(OR($AQ9="",$AS9=""),"",IF(M$8<$AQ9,"IKS",IF(M$8<$AS9,IF(M$8=$AR9,"Bascule","Double run"),"ROKS")))))) -> ROKS | N9: =IF(OR($A9="",N$8=""),"",IF($F9="Migré","ROKS",IF($F9="À décommissionner",IF(N$8<$AS9,"IKS","Décom."),IF(OR($AQ9="",$AS9=""),"",IF(N$8<$AQ9,"IKS",IF(N$8<$AS9,IF(N$8=$AR9,"Bascule","Double run"),"ROKS")))))) -> ROKS | ... AP9: =IF(OR($A9="",AP$8=""),"",IF($F9="Migré","ROKS",IF($F9="À décommissionner",IF(AP$8<$AS9,"IKS","Décom."),IF(OR($AQ9="",$AS9=""),"",IF(AP$8<$AQ9,"IKS",IF(AP$8<$AS9,IF(AP$8=$AR9,"Bascule","Double run"),"ROKS")))))) -> ROKS | AQ9: =IF($A9="","",INDEX(TblApplications[Mois prov (calc)],$A9)) -> 46388 | AR9: =IF($A9="","",IFERROR(DATE(YEAR(INDEX(TblApplications[Mois bascule],$A9)),MONTH(INDEX(TblApplications[Mois bascule],$A9)),1),"")) -> 46388 | AS9: =IF($A9="","",INDEX(TblApplications[Mois lib (calc)],$A9)) -> 46419
A10: =IFERROR(MATCH(2,TblApplications[Rang frise],0),"") -> 2 | B10: =IF($A10="","",INDEX(TblApplications[ID],$A10)) -> APP-01 | C10: =IF($A10="","",INDEX(TblApplications[Application],$A10)) -> Portail assuré (démo) | D10: =IF($A10="","",INDEX(TblApplications[Environnement],$A10)) -> NPRD | E10: =IF($A10="","",INDEX(TblApplications[Couloir],$A10)) -> INT1 | F10: =IF($A10="","",INDEX(TblApplications[Action],$A10)) -> À migrer | G10: =IF(OR($A10="",G$8=""),"",IF($F10="Migré","ROKS",IF($F10="À décommissionner",IF(G$8<$AS10,"IKS","Décom."),IF(OR($AQ10="",$AS10=""),"",IF(G$8<$AQ10,"IKS",IF(G$8<$AS10,IF(G$8=$AR10,"Bascule","Double run"),"ROKS")))))) -> IKS | H10: =IF(OR($A10="",H$8=""),"",IF($F10="Migré","ROKS",IF($F10="À décommissionner",IF(H$8<$AS10,"IKS","Décom."),IF(OR($AQ10="",$AS10=""),"",IF(H$8<$AQ10,"IKS",IF(H$8<$AS10,IF(H$8=$AR10,"Bascule","Double run"),"ROKS")))))) -> IKS | I10: =IF(OR($A10="",I$8=""),"",IF($F10="Migré","ROKS",IF($F10="À décommissionner",IF(I$8<$AS10,"IKS","Décom."),IF(OR($AQ10="",$AS10=""),"",IF(I$8<$AQ10,"IKS",IF(I$8<$AS10,IF(I$8=$AR10,"Bascule","Double run"),"ROKS")))))) -> IKS | J10: =IF(OR($A10="",J$8=""),"",IF($F10="Migré","ROKS",IF($F10="À décommissionner",IF(J$8<$AS10,"IKS","Décom."),IF(OR($AQ10="",$AS10=""),"",IF(J$8<$AQ10,"IKS",IF(J$8<$AS10,IF(J$8=$AR10,"Bascule","Double run"),"ROKS")))))) -> Double run | K10: =IF(OR($A10="",K$8=""),"",IF($F10="Migré","ROKS",IF($F10="À décommissionner",IF(K$8<$AS10,"IKS","Décom."),IF(OR($AQ10="",$AS10=""),"",IF(K$8<$AQ10,"IKS",IF(K$8<$AS10,IF(K$8=$AR10,"Bascule","Double run"),"ROKS")))))) -> Bascule | L10: =IF(OR($A10="",L$8=""),"",IF($F10="Migré","ROKS",IF($F10="À décommissionner",IF(L$8<$AS10,"IKS","Décom."),IF(OR($AQ10="",$AS10=""),"",IF(L$8<$AQ10,"IKS",IF(L$8<$AS10,IF(L$8=$AR10,"Bascule","Double run"),"ROKS")))))) -> ROKS | M10: =IF(OR($A10="",M$8=""),"",IF($F10="Migré","ROKS",IF($F10="À décommissionner",IF(M$8<$AS10,"IKS","Décom."),IF(OR($AQ10="",$AS10=""),"",IF(M$8<$AQ10,"IKS",IF(M$8<$AS10,IF(M$8=$AR10,"Bascule","Double run"),"ROKS")))))) -> ROKS | N10: =IF(OR($A10="",N$8=""),"",IF($F10="Migré","ROKS",IF($F10="À décommissionner",IF(N$8<$AS10,"IKS","Décom."),IF(OR($AQ10="",$AS10=""),"",IF(N$8<$AQ10,"IKS",IF(N$8<$AS10,IF(N$8=$AR10,"Bascule","Double run"),"ROKS")))))) -> ROKS | ... AP10: =IF(OR($A10="",AP$8=""),"",IF($F10="Migré","ROKS",IF($F10="À décommissionner",IF(AP$8<$AS10,"IKS","Décom."),IF(OR($AQ10="",$AS10=""),"",IF(AP$8<$AQ10,"IKS",IF(AP$8<$AS10,IF(AP$8=$AR10,"Bascule","Double run"),"ROKS")))))) -> ROKS | AQ10: =IF($A10="","",INDEX(TblApplications[Mois prov (calc)],$A10)) -> 46388 | AR10: =IF($A10="","",IFERROR(DATE(YEAR(INDEX(TblApplications[Mois bascule],$A10)),MONTH(INDEX(TblApplications[Mois bascule],$A10)),1),"")) -> 46419 | AS10: =IF($A10="","",INDEX(TblApplications[Mois lib (calc)],$A10)) -> 46447
A11: =IFERROR(MATCH(3,TblApplications[Rang frise],0),"") -> 3 | B11: =IF($A11="","",INDEX(TblApplications[ID],$A11)) -> APP-01 | C11: =IF($A11="","",INDEX(TblApplications[Application],$A11)) -> Portail assuré (démo) | D11: =IF($A11="","",INDEX(TblApplications[Environnement],$A11)) -> PRD | E11: =IF($A11="","",INDEX(TblApplications[Couloir],$A11)) -> PRD | F11: =IF($A11="","",INDEX(TblApplications[Action],$A11)) -> À migrer | G11: =IF(OR($A11="",G$8=""),"",IF($F11="Migré","ROKS",IF($F11="À décommissionner",IF(G$8<$AS11,"IKS","Décom."),IF(OR($AQ11="",$AS11=""),"",IF(G$8<$AQ11,"IKS",IF(G$8<$AS11,IF(G$8=$AR11,"Bascule","Double run"),"ROKS")))))) -> IKS | H11: =IF(OR($A11="",H$8=""),"",IF($F11="Migré","ROKS",IF($F11="À décommissionner",IF(H$8<$AS11,"IKS","Décom."),IF(OR($AQ11="",$AS11=""),"",IF(H$8<$AQ11,"IKS",IF(H$8<$AS11,IF(H$8=$AR11,"Bascule","Double run"),"ROKS")))))) -> IKS | I11: =IF(OR($A11="",I$8=""),"",IF($F11="Migré","ROKS",IF($F11="À décommissionner",IF(I$8<$AS11,"IKS","Décom."),IF(OR($AQ11="",$AS11=""),"",IF(I$8<$AQ11,"IKS",IF(I$8<$AS11,IF(I$8=$AR11,"Bascule","Double run"),"ROKS")))))) -> IKS | J11: =IF(OR($A11="",J$8=""),"",IF($F11="Migré","ROKS",IF($F11="À décommissionner",IF(J$8<$AS11,"IKS","Décom."),IF(OR($AQ11="",$AS11=""),"",IF(J$8<$AQ11,"IKS",IF(J$8<$AS11,IF(J$8=$AR11,"Bascule","Double run"),"ROKS")))))) -> IKS | K11: =IF(OR($A11="",K$8=""),"",IF($F11="Migré","ROKS",IF($F11="À décommissionner",IF(K$8<$AS11,"IKS","Décom."),IF(OR($AQ11="",$AS11=""),"",IF(K$8<$AQ11,"IKS",IF(K$8<$AS11,IF(K$8=$AR11,"Bascule","Double run"),"ROKS")))))) -> IKS | L11: =IF(OR($A11="",L$8=""),"",IF($F11="Migré","ROKS",IF($F11="À décommissionner",IF(L$8<$AS11,"IKS","Décom."),IF(OR($AQ11="",$AS11=""),"",IF(L$8<$AQ11,"IKS",IF(L$8<$AS11,IF(L$8=$AR11,"Bascule","Double run"),"ROKS")))))) -> IKS | M11: =IF(OR($A11="",M$8=""),"",IF($F11="Migré","ROKS",IF($F11="À décommissionner",IF(M$8<$AS11,"IKS","Décom."),IF(OR($AQ11="",$AS11=""),"",IF(M$8<$AQ11,"IKS",IF(M$8<$AS11,IF(M$8=$AR11,"Bascule","Double run"),"ROKS")))))) -> Double run | N11: =IF(OR($A11="",N$8=""),"",IF($F11="Migré","ROKS",IF($F11="À décommissionner",IF(N$8<$AS11,"IKS","Décom."),IF(OR($AQ11="",$AS11=""),"",IF(N$8<$AQ11,"IKS",IF(N$8<$AS11,IF(N$8=$AR11,"Bascule","Double run"),"ROKS")))))) -> Bascule | ... AP11: =IF(OR($A11="",AP$8=""),"",IF($F11="Migré","ROKS",IF($F11="À décommissionner",IF(AP$8<$AS11,"IKS","Décom."),IF(OR($AQ11="",$AS11=""),"",IF(AP$8<$AQ11,"IKS",IF(AP$8<$AS11,IF(AP$8=$AR11,"Bascule","Double run"),"ROKS")))))) -> ROKS | AQ11: =IF($A11="","",INDEX(TblApplications[Mois prov (calc)],$A11)) -> 46478 | AR11: =IF($A11="","",IFERROR(DATE(YEAR(INDEX(TblApplications[Mois bascule],$A11)),MONTH(INDEX(TblApplications[Mois bascule],$A11)),1),"")) -> 46508 | AS11: =IF($A11="","",INDEX(TblApplications[Mois lib (calc)],$A11)) -> 46569
A12: =IFERROR(MATCH(4,TblApplications[Rang frise],0),"") -> 4 | B12: =IF($A12="","",INDEX(TblApplications[ID],$A12)) -> APP-02 | C12: =IF($A12="","",INDEX(TblApplications[Application],$A12)) -> Moteur tarification (démo) | D12: =IF($A12="","",INDEX(TblApplications[Environnement],$A12)) -> NPRD | E12: =IF($A12="","",INDEX(TblApplications[Couloir],$A12)) -> DEV1 | F12: =IF($A12="","",INDEX(TblApplications[Action],$A12)) -> À migrer | G12: =IF(OR($A12="",G$8=""),"",IF($F12="Migré","ROKS",IF($F12="À décommissionner",IF(G$8<$AS12,"IKS","Décom."),IF(OR($AQ12="",$AS12=""),"",IF(G$8<$AQ12,"IKS",IF(G$8<$AS12,IF(G$8=$AR12,"Bascule","Double run"),"ROKS")))))) -> IKS | H12: =IF(OR($A12="",H$8=""),"",IF($F12="Migré","ROKS",IF($F12="À décommissionner",IF(H$8<$AS12,"IKS","Décom."),IF(OR($AQ12="",$AS12=""),"",IF(H$8<$AQ12,"IKS",IF(H$8<$AS12,IF(H$8=$AR12,"Bascule","Double run"),"ROKS")))))) -> IKS | I12: =IF(OR($A12="",I$8=""),"",IF($F12="Migré","ROKS",IF($F12="À décommissionner",IF(I$8<$AS12,"IKS","Décom."),IF(OR($AQ12="",$AS12=""),"",IF(I$8<$AQ12,"IKS",IF(I$8<$AS12,IF(I$8=$AR12,"Bascule","Double run"),"ROKS")))))) -> IKS | J12: =IF(OR($A12="",J$8=""),"",IF($F12="Migré","ROKS",IF($F12="À décommissionner",IF(J$8<$AS12,"IKS","Décom."),IF(OR($AQ12="",$AS12=""),"",IF(J$8<$AQ12,"IKS",IF(J$8<$AS12,IF(J$8=$AR12,"Bascule","Double run"),"ROKS")))))) -> IKS | K12: =IF(OR($A12="",K$8=""),"",IF($F12="Migré","ROKS",IF($F12="À décommissionner",IF(K$8<$AS12,"IKS","Décom."),IF(OR($AQ12="",$AS12=""),"",IF(K$8<$AQ12,"IKS",IF(K$8<$AS12,IF(K$8=$AR12,"Bascule","Double run"),"ROKS")))))) -> IKS | L12: =IF(OR($A12="",L$8=""),"",IF($F12="Migré","ROKS",IF($F12="À décommissionner",IF(L$8<$AS12,"IKS","Décom."),IF(OR($AQ12="",$AS12=""),"",IF(L$8<$AQ12,"IKS",IF(L$8<$AS12,IF(L$8=$AR12,"Bascule","Double run"),"ROKS")))))) -> IKS | M12: =IF(OR($A12="",M$8=""),"",IF($F12="Migré","ROKS",IF($F12="À décommissionner",IF(M$8<$AS12,"IKS","Décom."),IF(OR($AQ12="",$AS12=""),"",IF(M$8<$AQ12,"IKS",IF(M$8<$AS12,IF(M$8=$AR12,"Bascule","Double run"),"ROKS")))))) -> IKS | N12: =IF(OR($A12="",N$8=""),"",IF($F12="Migré","ROKS",IF($F12="À décommissionner",IF(N$8<$AS12,"IKS","Décom."),IF(OR($AQ12="",$AS12=""),"",IF(N$8<$AQ12,"IKS",IF(N$8<$AS12,IF(N$8=$AR12,"Bascule","Double run"),"ROKS")))))) -> IKS | ... AP12: =IF(OR($A12="",AP$8=""),"",IF($F12="Migré","ROKS",IF($F12="À décommissionner",IF(AP$8<$AS12,"IKS","Décom."),IF(OR($AQ12="",$AS12=""),"",IF(AP$8<$AQ12,"IKS",IF(AP$8<$AS12,IF(AP$8=$AR12,"Bascule","Double run"),"ROKS")))))) -> ROKS | AQ12: =IF($A12="","",INDEX(TblApplications[Mois prov (calc)],$A12)) -> 46631 | AR12: =IF($A12="","",IFERROR(DATE(YEAR(INDEX(TblApplications[Mois bascule],$A12)),MONTH(INDEX(TblApplications[Mois bascule],$A12)),1),"")) -> 46631 | AS12: =IF($A12="","",INDEX(TblApplications[Mois lib (calc)],$A12)) -> 46661
A13: =IFERROR(MATCH(5,TblApplications[Rang frise],0),"") -> 5 | B13: =IF($A13="","",INDEX(TblApplications[ID],$A13)) -> APP-02 | C13: =IF($A13="","",INDEX(TblApplications[Application],$A13)) -> Moteur tarification (démo) | D13: =IF($A13="","",INDEX(TblApplications[Environnement],$A13)) -> NPRD | E13: =IF($A13="","",INDEX(TblApplications[Couloir],$A13)) -> DEV2 | F13: =IF($A13="","",INDEX(TblApplications[Action],$A13)) -> À migrer | G13: =IF(OR($A13="",G$8=""),"",IF($F13="Migré","ROKS",IF($F13="À décommissionner",IF(G$8<$AS13,"IKS","Décom."),IF(OR($AQ13="",$AS13=""),"",IF(G$8<$AQ13,"IKS",IF(G$8<$AS13,IF(G$8=$AR13,"Bascule","Double run"),"ROKS")))))) -> IKS | H13: =IF(OR($A13="",H$8=""),"",IF($F13="Migré","ROKS",IF($F13="À décommissionner",IF(H$8<$AS13,"IKS","Décom."),IF(OR($AQ13="",$AS13=""),"",IF(H$8<$AQ13,"IKS",IF(H$8<$AS13,IF(H$8=$AR13,"Bascule","Double run"),"ROKS")))))) -> IKS | I13: =IF(OR($A13="",I$8=""),"",IF($F13="Migré","ROKS",IF($F13="À décommissionner",IF(I$8<$AS13,"IKS","Décom."),IF(OR($AQ13="",$AS13=""),"",IF(I$8<$AQ13,"IKS",IF(I$8<$AS13,IF(I$8=$AR13,"Bascule","Double run"),"ROKS")))))) -> IKS | J13: =IF(OR($A13="",J$8=""),"",IF($F13="Migré","ROKS",IF($F13="À décommissionner",IF(J$8<$AS13,"IKS","Décom."),IF(OR($AQ13="",$AS13=""),"",IF(J$8<$AQ13,"IKS",IF(J$8<$AS13,IF(J$8=$AR13,"Bascule","Double run"),"ROKS")))))) -> IKS | K13: =IF(OR($A13="",K$8=""),"",IF($F13="Migré","ROKS",IF($F13="À décommissionner",IF(K$8<$AS13,"IKS","Décom."),IF(OR($AQ13="",$AS13=""),"",IF(K$8<$AQ13,"IKS",IF(K$8<$AS13,IF(K$8=$AR13,"Bascule","Double run"),"ROKS")))))) -> IKS | L13: =IF(OR($A13="",L$8=""),"",IF($F13="Migré","ROKS",IF($F13="À décommissionner",IF(L$8<$AS13,"IKS","Décom."),IF(OR($AQ13="",$AS13=""),"",IF(L$8<$AQ13,"IKS",IF(L$8<$AS13,IF(L$8=$AR13,"Bascule","Double run"),"ROKS")))))) -> IKS | M13: =IF(OR($A13="",M$8=""),"",IF($F13="Migré","ROKS",IF($F13="À décommissionner",IF(M$8<$AS13,"IKS","Décom."),IF(OR($AQ13="",$AS13=""),"",IF(M$8<$AQ13,"IKS",IF(M$8<$AS13,IF(M$8=$AR13,"Bascule","Double run"),"ROKS")))))) -> IKS | N13: =IF(OR($A13="",N$8=""),"",IF($F13="Migré","ROKS",IF($F13="À décommissionner",IF(N$8<$AS13,"IKS","Décom."),IF(OR($AQ13="",$AS13=""),"",IF(N$8<$AQ13,"IKS",IF(N$8<$AS13,IF(N$8=$AR13,"Bascule","Double run"),"ROKS")))))) -> IKS | ... AP13: =IF(OR($A13="",AP$8=""),"",IF($F13="Migré","ROKS",IF($F13="À décommissionner",IF(AP$8<$AS13,"IKS","Décom."),IF(OR($AQ13="",$AS13=""),"",IF(AP$8<$AQ13,"IKS",IF(AP$8<$AS13,IF(AP$8=$AR13,"Bascule","Double run"),"ROKS")))))) -> ROKS | AQ13: =IF($A13="","",INDEX(TblApplications[Mois prov (calc)],$A13)) -> 46631 | AR13: =IF($A13="","",IFERROR(DATE(YEAR(INDEX(TblApplications[Mois bascule],$A13)),MONTH(INDEX(TblApplications[Mois bascule],$A13)),1),"")) -> 46661 | AS13: =IF($A13="","",INDEX(TblApplications[Mois lib (calc)],$A13)) -> 46661
A14: =IFERROR(MATCH(6,TblApplications[Rang frise],0),"") -> 6 | B14: =IF($A14="","",INDEX(TblApplications[ID],$A14)) -> APP-02 | C14: =IF($A14="","",INDEX(TblApplications[Application],$A14)) -> Moteur tarification (démo) | D14: =IF($A14="","",INDEX(TblApplications[Environnement],$A14)) -> NPRD | E14: =IF($A14="","",INDEX(TblApplications[Couloir],$A14)) -> INT1 | F14: =IF($A14="","",INDEX(TblApplications[Action],$A14)) -> À migrer | G14: =IF(OR($A14="",G$8=""),"",IF($F14="Migré","ROKS",IF($F14="À décommissionner",IF(G$8<$AS14,"IKS","Décom."),IF(OR($AQ14="",$AS14=""),"",IF(G$8<$AQ14,"IKS",IF(G$8<$AS14,IF(G$8=$AR14,"Bascule","Double run"),"ROKS")))))) -> IKS | H14: =IF(OR($A14="",H$8=""),"",IF($F14="Migré","ROKS",IF($F14="À décommissionner",IF(H$8<$AS14,"IKS","Décom."),IF(OR($AQ14="",$AS14=""),"",IF(H$8<$AQ14,"IKS",IF(H$8<$AS14,IF(H$8=$AR14,"Bascule","Double run"),"ROKS")))))) -> IKS | I14: =IF(OR($A14="",I$8=""),"",IF($F14="Migré","ROKS",IF($F14="À décommissionner",IF(I$8<$AS14,"IKS","Décom."),IF(OR($AQ14="",$AS14=""),"",IF(I$8<$AQ14,"IKS",IF(I$8<$AS14,IF(I$8=$AR14,"Bascule","Double run"),"ROKS")))))) -> IKS | J14: =IF(OR($A14="",J$8=""),"",IF($F14="Migré","ROKS",IF($F14="À décommissionner",IF(J$8<$AS14,"IKS","Décom."),IF(OR($AQ14="",$AS14=""),"",IF(J$8<$AQ14,"IKS",IF(J$8<$AS14,IF(J$8=$AR14,"Bascule","Double run"),"ROKS")))))) -> IKS | K14: =IF(OR($A14="",K$8=""),"",IF($F14="Migré","ROKS",IF($F14="À décommissionner",IF(K$8<$AS14,"IKS","Décom."),IF(OR($AQ14="",$AS14=""),"",IF(K$8<$AQ14,"IKS",IF(K$8<$AS14,IF(K$8=$AR14,"Bascule","Double run"),"ROKS")))))) -> IKS | L14: =IF(OR($A14="",L$8=""),"",IF($F14="Migré","ROKS",IF($F14="À décommissionner",IF(L$8<$AS14,"IKS","Décom."),IF(OR($AQ14="",$AS14=""),"",IF(L$8<$AQ14,"IKS",IF(L$8<$AS14,IF(L$8=$AR14,"Bascule","Double run"),"ROKS")))))) -> IKS | M14: =IF(OR($A14="",M$8=""),"",IF($F14="Migré","ROKS",IF($F14="À décommissionner",IF(M$8<$AS14,"IKS","Décom."),IF(OR($AQ14="",$AS14=""),"",IF(M$8<$AQ14,"IKS",IF(M$8<$AS14,IF(M$8=$AR14,"Bascule","Double run"),"ROKS")))))) -> IKS | N14: =IF(OR($A14="",N$8=""),"",IF($F14="Migré","ROKS",IF($F14="À décommissionner",IF(N$8<$AS14,"IKS","Décom."),IF(OR($AQ14="",$AS14=""),"",IF(N$8<$AQ14,"IKS",IF(N$8<$AS14,IF(N$8=$AR14,"Bascule","Double run"),"ROKS")))))) -> IKS | ... AP14: =IF(OR($A14="",AP$8=""),"",IF($F14="Migré","ROKS",IF($F14="À décommissionner",IF(AP$8<$AS14,"IKS","Décom."),IF(OR($AQ14="",$AS14=""),"",IF(AP$8<$AQ14,"IKS",IF(AP$8<$AS14,IF(AP$8=$AR14,"Bascule","Double run"),"ROKS")))))) -> ROKS | AQ14: =IF($A14="","",INDEX(TblApplications[Mois prov (calc)],$A14)) -> 46661 | AR14: =IF($A14="","",IFERROR(DATE(YEAR(INDEX(TblApplications[Mois bascule],$A14)),MONTH(INDEX(TblApplications[Mois bascule],$A14)),1),"")) -> 46661 | AS14: =IF($A14="","",INDEX(TblApplications[Mois lib (calc)],$A14)) -> 46692
A15: =IFERROR(MATCH(7,TblApplications[Rang frise],0),"") -> 7 | B15: =IF($A15="","",INDEX(TblApplications[ID],$A15)) -> APP-02 | C15: =IF($A15="","",INDEX(TblApplications[Application],$A15)) -> Moteur tarification (démo) | D15: =IF($A15="","",INDEX(TblApplications[Environnement],$A15)) -> PRD | E15: =IF($A15="","",INDEX(TblApplications[Couloir],$A15)) -> PRD | F15: =IF($A15="","",INDEX(TblApplications[Action],$A15)) -> À migrer | G15: =IF(OR($A15="",G$8=""),"",IF($F15="Migré","ROKS",IF($F15="À décommissionner",IF(G$8<$AS15,"IKS","Décom."),IF(OR($AQ15="",$AS15=""),"",IF(G$8<$AQ15,"IKS",IF(G$8<$AS15,IF(G$8=$AR15,"Bascule","Double run"),"ROKS")))))) -> IKS | H15: =IF(OR($A15="",H$8=""),"",IF($F15="Migré","ROKS",IF($F15="À décommissionner",IF(H$8<$AS15,"IKS","Décom."),IF(OR($AQ15="",$AS15=""),"",IF(H$8<$AQ15,"IKS",IF(H$8<$AS15,IF(H$8=$AR15,"Bascule","Double run"),"ROKS")))))) -> IKS | I15: =IF(OR($A15="",I$8=""),"",IF($F15="Migré","ROKS",IF($F15="À décommissionner",IF(I$8<$AS15,"IKS","Décom."),IF(OR($AQ15="",$AS15=""),"",IF(I$8<$AQ15,"IKS",IF(I$8<$AS15,IF(I$8=$AR15,"Bascule","Double run"),"ROKS")))))) -> IKS | J15: =IF(OR($A15="",J$8=""),"",IF($F15="Migré","ROKS",IF($F15="À décommissionner",IF(J$8<$AS15,"IKS","Décom."),IF(OR($AQ15="",$AS15=""),"",IF(J$8<$AQ15,"IKS",IF(J$8<$AS15,IF(J$8=$AR15,"Bascule","Double run"),"ROKS")))))) -> IKS | K15: =IF(OR($A15="",K$8=""),"",IF($F15="Migré","ROKS",IF($F15="À décommissionner",IF(K$8<$AS15,"IKS","Décom."),IF(OR($AQ15="",$AS15=""),"",IF(K$8<$AQ15,"IKS",IF(K$8<$AS15,IF(K$8=$AR15,"Bascule","Double run"),"ROKS")))))) -> IKS | L15: =IF(OR($A15="",L$8=""),"",IF($F15="Migré","ROKS",IF($F15="À décommissionner",IF(L$8<$AS15,"IKS","Décom."),IF(OR($AQ15="",$AS15=""),"",IF(L$8<$AQ15,"IKS",IF(L$8<$AS15,IF(L$8=$AR15,"Bascule","Double run"),"ROKS")))))) -> IKS | M15: =IF(OR($A15="",M$8=""),"",IF($F15="Migré","ROKS",IF($F15="À décommissionner",IF(M$8<$AS15,"IKS","Décom."),IF(OR($AQ15="",$AS15=""),"",IF(M$8<$AQ15,"IKS",IF(M$8<$AS15,IF(M$8=$AR15,"Bascule","Double run"),"ROKS")))))) -> IKS | N15: =IF(OR($A15="",N$8=""),"",IF($F15="Migré","ROKS",IF($F15="À décommissionner",IF(N$8<$AS15,"IKS","Décom."),IF(OR($AQ15="",$AS15=""),"",IF(N$8<$AQ15,"IKS",IF(N$8<$AS15,IF(N$8=$AR15,"Bascule","Double run"),"ROKS")))))) -> IKS | ... AP15: =IF(OR($A15="",AP$8=""),"",IF($F15="Migré","ROKS",IF($F15="À décommissionner",IF(AP$8<$AS15,"IKS","Décom."),IF(OR($AQ15="",$AS15=""),"",IF(AP$8<$AQ15,"IKS",IF(AP$8<$AS15,IF(AP$8=$AR15,"Bascule","Double run"),"ROKS")))))) -> ROKS | AQ15: =IF($A15="","",INDEX(TblApplications[Mois prov (calc)],$A15)) -> 46753 | AR15: =IF($A15="","",IFERROR(DATE(YEAR(INDEX(TblApplications[Mois bascule],$A15)),MONTH(INDEX(TblApplications[Mois bascule],$A15)),1),"")) -> 46784 | AS15: =IF($A15="","",INDEX(TblApplications[Mois lib (calc)],$A15)) -> 46813
A16: =IFERROR(MATCH(8,TblApplications[Rang frise],0),"") -> 8 | B16: =IF($A16="","",INDEX(TblApplications[ID],$A16)) -> APP-03 | C16: =IF($A16="","",INDEX(TblApplications[Application],$A16)) -> API sinistres (démo) | D16: =IF($A16="","",INDEX(TblApplications[Environnement],$A16)) -> NPRD | E16: =IF($A16="","",INDEX(TblApplications[Couloir],$A16)) -> INT1 | F16: =IF($A16="","",INDEX(TblApplications[Action],$A16)) -> À migrer | G16: =IF(OR($A16="",G$8=""),"",IF($F16="Migré","ROKS",IF($F16="À décommissionner",IF(G$8<$AS16,"IKS","Décom."),IF(OR($AQ16="",$AS16=""),"",IF(G$8<$AQ16,"IKS",IF(G$8<$AS16,IF(G$8=$AR16,"Bascule","Double run"),"ROKS")))))) -> IKS | H16: =IF(OR($A16="",H$8=""),"",IF($F16="Migré","ROKS",IF($F16="À décommissionner",IF(H$8<$AS16,"IKS","Décom."),IF(OR($AQ16="",$AS16=""),"",IF(H$8<$AQ16,"IKS",IF(H$8<$AS16,IF(H$8=$AR16,"Bascule","Double run"),"ROKS")))))) -> IKS | I16: =IF(OR($A16="",I$8=""),"",IF($F16="Migré","ROKS",IF($F16="À décommissionner",IF(I$8<$AS16,"IKS","Décom."),IF(OR($AQ16="",$AS16=""),"",IF(I$8<$AQ16,"IKS",IF(I$8<$AS16,IF(I$8=$AR16,"Bascule","Double run"),"ROKS")))))) -> IKS | J16: =IF(OR($A16="",J$8=""),"",IF($F16="Migré","ROKS",IF($F16="À décommissionner",IF(J$8<$AS16,"IKS","Décom."),IF(OR($AQ16="",$AS16=""),"",IF(J$8<$AQ16,"IKS",IF(J$8<$AS16,IF(J$8=$AR16,"Bascule","Double run"),"ROKS")))))) -> IKS | K16: =IF(OR($A16="",K$8=""),"",IF($F16="Migré","ROKS",IF($F16="À décommissionner",IF(K$8<$AS16,"IKS","Décom."),IF(OR($AQ16="",$AS16=""),"",IF(K$8<$AQ16,"IKS",IF(K$8<$AS16,IF(K$8=$AR16,"Bascule","Double run"),"ROKS")))))) -> IKS | L16: =IF(OR($A16="",L$8=""),"",IF($F16="Migré","ROKS",IF($F16="À décommissionner",IF(L$8<$AS16,"IKS","Décom."),IF(OR($AQ16="",$AS16=""),"",IF(L$8<$AQ16,"IKS",IF(L$8<$AS16,IF(L$8=$AR16,"Bascule","Double run"),"ROKS")))))) -> IKS | M16: =IF(OR($A16="",M$8=""),"",IF($F16="Migré","ROKS",IF($F16="À décommissionner",IF(M$8<$AS16,"IKS","Décom."),IF(OR($AQ16="",$AS16=""),"",IF(M$8<$AQ16,"IKS",IF(M$8<$AS16,IF(M$8=$AR16,"Bascule","Double run"),"ROKS")))))) -> IKS | N16: =IF(OR($A16="",N$8=""),"",IF($F16="Migré","ROKS",IF($F16="À décommissionner",IF(N$8<$AS16,"IKS","Décom."),IF(OR($AQ16="",$AS16=""),"",IF(N$8<$AQ16,"IKS",IF(N$8<$AS16,IF(N$8=$AR16,"Bascule","Double run"),"ROKS")))))) -> IKS | ... AP16: =IF(OR($A16="",AP$8=""),"",IF($F16="Migré","ROKS",IF($F16="À décommissionner",IF(AP$8<$AS16,"IKS","Décom."),IF(OR($AQ16="",$AS16=""),"",IF(AP$8<$AQ16,"IKS",IF(AP$8<$AS16,IF(AP$8=$AR16,"Bascule","Double run"),"ROKS")))))) -> ROKS | AQ16: =IF($A16="","",INDEX(TblApplications[Mois prov (calc)],$A16)) -> 46844 | AR16: =IF($A16="","",IFERROR(DATE(YEAR(INDEX(TblApplications[Mois bascule],$A16)),MONTH(INDEX(TblApplications[Mois bascule],$A16)),1),"")) -> 46874 | AS16: =IF($A16="","",INDEX(TblApplications[Mois lib (calc)],$A16)) -> 46905
A17: =IFERROR(MATCH(9,TblApplications[Rang frise],0),"") -> 9 | B17: =IF($A17="","",INDEX(TblApplications[ID],$A17)) -> APP-03 | C17: =IF($A17="","",INDEX(TblApplications[Application],$A17)) -> API sinistres (démo) | D17: =IF($A17="","",INDEX(TblApplications[Environnement],$A17)) -> NPRD | E17: =IF($A17="","",INDEX(TblApplications[Couloir],$A17)) -> INT2 | F17: =IF($A17="","",INDEX(TblApplications[Action],$A17)) -> À migrer | G17: =IF(OR($A17="",G$8=""),"",IF($F17="Migré","ROKS",IF($F17="À décommissionner",IF(G$8<$AS17,"IKS","Décom."),IF(OR($AQ17="",$AS17=""),"",IF(G$8<$AQ17,"IKS",IF(G$8<$AS17,IF(G$8=$AR17,"Bascule","Double run"),"ROKS")))))) -> IKS | H17: =IF(OR($A17="",H$8=""),"",IF($F17="Migré","ROKS",IF($F17="À décommissionner",IF(H$8<$AS17,"IKS","Décom."),IF(OR($AQ17="",$AS17=""),"",IF(H$8<$AQ17,"IKS",IF(H$8<$AS17,IF(H$8=$AR17,"Bascule","Double run"),"ROKS")))))) -> IKS | I17: =IF(OR($A17="",I$8=""),"",IF($F17="Migré","ROKS",IF($F17="À décommissionner",IF(I$8<$AS17,"IKS","Décom."),IF(OR($AQ17="",$AS17=""),"",IF(I$8<$AQ17,"IKS",IF(I$8<$AS17,IF(I$8=$AR17,"Bascule","Double run"),"ROKS")))))) -> IKS | J17: =IF(OR($A17="",J$8=""),"",IF($F17="Migré","ROKS",IF($F17="À décommissionner",IF(J$8<$AS17,"IKS","Décom."),IF(OR($AQ17="",$AS17=""),"",IF(J$8<$AQ17,"IKS",IF(J$8<$AS17,IF(J$8=$AR17,"Bascule","Double run"),"ROKS")))))) -> IKS | K17: =IF(OR($A17="",K$8=""),"",IF($F17="Migré","ROKS",IF($F17="À décommissionner",IF(K$8<$AS17,"IKS","Décom."),IF(OR($AQ17="",$AS17=""),"",IF(K$8<$AQ17,"IKS",IF(K$8<$AS17,IF(K$8=$AR17,"Bascule","Double run"),"ROKS")))))) -> IKS | L17: =IF(OR($A17="",L$8=""),"",IF($F17="Migré","ROKS",IF($F17="À décommissionner",IF(L$8<$AS17,"IKS","Décom."),IF(OR($AQ17="",$AS17=""),"",IF(L$8<$AQ17,"IKS",IF(L$8<$AS17,IF(L$8=$AR17,"Bascule","Double run"),"ROKS")))))) -> IKS | M17: =IF(OR($A17="",M$8=""),"",IF($F17="Migré","ROKS",IF($F17="À décommissionner",IF(M$8<$AS17,"IKS","Décom."),IF(OR($AQ17="",$AS17=""),"",IF(M$8<$AQ17,"IKS",IF(M$8<$AS17,IF(M$8=$AR17,"Bascule","Double run"),"ROKS")))))) -> IKS | N17: =IF(OR($A17="",N$8=""),"",IF($F17="Migré","ROKS",IF($F17="À décommissionner",IF(N$8<$AS17,"IKS","Décom."),IF(OR($AQ17="",$AS17=""),"",IF(N$8<$AQ17,"IKS",IF(N$8<$AS17,IF(N$8=$AR17,"Bascule","Double run"),"ROKS")))))) -> IKS | ... AP17: =IF(OR($A17="",AP$8=""),"",IF($F17="Migré","ROKS",IF($F17="À décommissionner",IF(AP$8<$AS17,"IKS","Décom."),IF(OR($AQ17="",$AS17=""),"",IF(AP$8<$AQ17,"IKS",IF(AP$8<$AS17,IF(AP$8=$AR17,"Bascule","Double run"),"ROKS")))))) -> ROKS | AQ17: =IF($A17="","",INDEX(TblApplications[Mois prov (calc)],$A17)) -> 46844 | AR17: =IF($A17="","",IFERROR(DATE(YEAR(INDEX(TblApplications[Mois bascule],$A17)),MONTH(INDEX(TblApplications[Mois bascule],$A17)),1),"")) -> 46874 | AS17: =IF($A17="","",INDEX(TblApplications[Mois lib (calc)],$A17)) -> 46905
A18: =IFERROR(MATCH(10,TblApplications[Rang frise],0),"") -> 10 | B18: =IF($A18="","",INDEX(TblApplications[ID],$A18)) -> APP-03 | C18: =IF($A18="","",INDEX(TblApplications[Application],$A18)) -> API sinistres (démo) | D18: =IF($A18="","",INDEX(TblApplications[Environnement],$A18)) -> PRD | E18: =IF($A18="","",INDEX(TblApplications[Couloir],$A18)) -> PRD | F18: =IF($A18="","",INDEX(TblApplications[Action],$A18)) -> À migrer | G18: =IF(OR($A18="",G$8=""),"",IF($F18="Migré","ROKS",IF($F18="À décommissionner",IF(G$8<$AS18,"IKS","Décom."),IF(OR($AQ18="",$AS18=""),"",IF(G$8<$AQ18,"IKS",IF(G$8<$AS18,IF(G$8=$AR18,"Bascule","Double run"),"ROKS")))))) -> IKS | H18: =IF(OR($A18="",H$8=""),"",IF($F18="Migré","ROKS",IF($F18="À décommissionner",IF(H$8<$AS18,"IKS","Décom."),IF(OR($AQ18="",$AS18=""),"",IF(H$8<$AQ18,"IKS",IF(H$8<$AS18,IF(H$8=$AR18,"Bascule","Double run"),"ROKS")))))) -> IKS | I18: =IF(OR($A18="",I$8=""),"",IF($F18="Migré","ROKS",IF($F18="À décommissionner",IF(I$8<$AS18,"IKS","Décom."),IF(OR($AQ18="",$AS18=""),"",IF(I$8<$AQ18,"IKS",IF(I$8<$AS18,IF(I$8=$AR18,"Bascule","Double run"),"ROKS")))))) -> IKS | J18: =IF(OR($A18="",J$8=""),"",IF($F18="Migré","ROKS",IF($F18="À décommissionner",IF(J$8<$AS18,"IKS","Décom."),IF(OR($AQ18="",$AS18=""),"",IF(J$8<$AQ18,"IKS",IF(J$8<$AS18,IF(J$8=$AR18,"Bascule","Double run"),"ROKS")))))) -> IKS | K18: =IF(OR($A18="",K$8=""),"",IF($F18="Migré","ROKS",IF($F18="À décommissionner",IF(K$8<$AS18,"IKS","Décom."),IF(OR($AQ18="",$AS18=""),"",IF(K$8<$AQ18,"IKS",IF(K$8<$AS18,IF(K$8=$AR18,"Bascule","Double run"),"ROKS")))))) -> IKS | L18: =IF(OR($A18="",L$8=""),"",IF($F18="Migré","ROKS",IF($F18="À décommissionner",IF(L$8<$AS18,"IKS","Décom."),IF(OR($AQ18="",$AS18=""),"",IF(L$8<$AQ18,"IKS",IF(L$8<$AS18,IF(L$8=$AR18,"Bascule","Double run"),"ROKS")))))) -> IKS | M18: =IF(OR($A18="",M$8=""),"",IF($F18="Migré","ROKS",IF($F18="À décommissionner",IF(M$8<$AS18,"IKS","Décom."),IF(OR($AQ18="",$AS18=""),"",IF(M$8<$AQ18,"IKS",IF(M$8<$AS18,IF(M$8=$AR18,"Bascule","Double run"),"ROKS")))))) -> IKS | N18: =IF(OR($A18="",N$8=""),"",IF($F18="Migré","ROKS",IF($F18="À décommissionner",IF(N$8<$AS18,"IKS","Décom."),IF(OR($AQ18="",$AS18=""),"",IF(N$8<$AQ18,"IKS",IF(N$8<$AS18,IF(N$8=$AR18,"Bascule","Double run"),"ROKS")))))) -> IKS | ... AP18: =IF(OR($A18="",AP$8=""),"",IF($F18="Migré","ROKS",IF($F18="À décommissionner",IF(AP$8<$AS18,"IKS","Décom."),IF(OR($AQ18="",$AS18=""),"",IF(AP$8<$AQ18,"IKS",IF(AP$8<$AS18,IF(AP$8=$AR18,"Bascule","Double run"),"ROKS")))))) -> ROKS | AQ18: =IF($A18="","",INDEX(TblApplications[Mois prov (calc)],$A18)) -> 46997 | AR18: =IF($A18="","",IFERROR(DATE(YEAR(INDEX(TblApplications[Mois bascule],$A18)),MONTH(INDEX(TblApplications[Mois bascule],$A18)),1),"")) -> 47027 | AS18: =IF($A18="","",INDEX(TblApplications[Mois lib (calc)],$A18)) -> 47088
A19: =IFERROR(MATCH(11,TblApplications[Rang frise],0),"") -> 11 | B19: =IF($A19="","",INDEX(TblApplications[ID],$A19)) -> APP-04 | C19: =IF($A19="","",INDEX(TblApplications[Application],$A19)) -> Extranet partenaires (démo) | D19: =IF($A19="","",INDEX(TblApplications[Environnement],$A19)) -> NPRD | E19: =IF($A19="","",INDEX(TblApplications[Couloir],$A19)) -> INT1 | F19: =IF($A19="","",INDEX(TblApplications[Action],$A19)) -> À décommissionner | G19: =IF(OR($A19="",G$8=""),"",IF($F19="Migré","ROKS",IF($F19="À décommissionner",IF(G$8<$AS19,"IKS","Décom."),IF(OR($AQ19="",$AS19=""),"",IF(G$8<$AQ19,"IKS",IF(G$8<$AS19,IF(G$8=$AR19,"Bascule","Double run"),"ROKS")))))) -> IKS | H19: =IF(OR($A19="",H$8=""),"",IF($F19="Migré","ROKS",IF($F19="À décommissionner",IF(H$8<$AS19,"IKS","Décom."),IF(OR($AQ19="",$AS19=""),"",IF(H$8<$AQ19,"IKS",IF(H$8<$AS19,IF(H$8=$AR19,"Bascule","Double run"),"ROKS")))))) -> IKS | I19: =IF(OR($A19="",I$8=""),"",IF($F19="Migré","ROKS",IF($F19="À décommissionner",IF(I$8<$AS19,"IKS","Décom."),IF(OR($AQ19="",$AS19=""),"",IF(I$8<$AQ19,"IKS",IF(I$8<$AS19,IF(I$8=$AR19,"Bascule","Double run"),"ROKS")))))) -> IKS | J19: =IF(OR($A19="",J$8=""),"",IF($F19="Migré","ROKS",IF($F19="À décommissionner",IF(J$8<$AS19,"IKS","Décom."),IF(OR($AQ19="",$AS19=""),"",IF(J$8<$AQ19,"IKS",IF(J$8<$AS19,IF(J$8=$AR19,"Bascule","Double run"),"ROKS")))))) -> IKS | K19: =IF(OR($A19="",K$8=""),"",IF($F19="Migré","ROKS",IF($F19="À décommissionner",IF(K$8<$AS19,"IKS","Décom."),IF(OR($AQ19="",$AS19=""),"",IF(K$8<$AQ19,"IKS",IF(K$8<$AS19,IF(K$8=$AR19,"Bascule","Double run"),"ROKS")))))) -> IKS | L19: =IF(OR($A19="",L$8=""),"",IF($F19="Migré","ROKS",IF($F19="À décommissionner",IF(L$8<$AS19,"IKS","Décom."),IF(OR($AQ19="",$AS19=""),"",IF(L$8<$AQ19,"IKS",IF(L$8<$AS19,IF(L$8=$AR19,"Bascule","Double run"),"ROKS")))))) -> IKS | M19: =IF(OR($A19="",M$8=""),"",IF($F19="Migré","ROKS",IF($F19="À décommissionner",IF(M$8<$AS19,"IKS","Décom."),IF(OR($AQ19="",$AS19=""),"",IF(M$8<$AQ19,"IKS",IF(M$8<$AS19,IF(M$8=$AR19,"Bascule","Double run"),"ROKS")))))) -> IKS | N19: =IF(OR($A19="",N$8=""),"",IF($F19="Migré","ROKS",IF($F19="À décommissionner",IF(N$8<$AS19,"IKS","Décom."),IF(OR($AQ19="",$AS19=""),"",IF(N$8<$AQ19,"IKS",IF(N$8<$AS19,IF(N$8=$AR19,"Bascule","Double run"),"ROKS")))))) -> IKS | ... AP19: =IF(OR($A19="",AP$8=""),"",IF($F19="Migré","ROKS",IF($F19="À décommissionner",IF(AP$8<$AS19,"IKS","Décom."),IF(OR($AQ19="",$AS19=""),"",IF(AP$8<$AQ19,"IKS",IF(AP$8<$AS19,IF(AP$8=$AR19,"Bascule","Double run"),"ROKS")))))) -> Décom. | AQ19: =IF($A19="","",INDEX(TblApplications[Mois prov (calc)],$A19)) | AR19: =IF($A19="","",IFERROR(DATE(YEAR(INDEX(TblApplications[Mois bascule],$A19)),MONTH(INDEX(TblApplications[Mois bascule],$A19)),1),"")) -> -29 | AS19: =IF($A19="","",INDEX(TblApplications[Mois lib (calc)],$A19)) -> 46539
A20: =IFERROR(MATCH(12,TblApplications[Rang frise],0),"") -> 12 | B20: =IF($A20="","",INDEX(TblApplications[ID],$A20)) -> APP-05 | C20: =IF($A20="","",INDEX(TblApplications[Application],$A20)) -> Batch éditique (démo) | D20: =IF($A20="","",INDEX(TblApplications[Environnement],$A20)) -> PRD | E20: =IF($A20="","",INDEX(TblApplications[Couloir],$A20)) -> PRD | F20: =IF($A20="","",INDEX(TblApplications[Action],$A20)) -> Migré | G20: =IF(OR($A20="",G$8=""),"",IF($F20="Migré","ROKS",IF($F20="À décommissionner",IF(G$8<$AS20,"IKS","Décom."),IF(OR($AQ20="",$AS20=""),"",IF(G$8<$AQ20,"IKS",IF(G$8<$AS20,IF(G$8=$AR20,"Bascule","Double run"),"ROKS")))))) -> ROKS | H20: =IF(OR($A20="",H$8=""),"",IF($F20="Migré","ROKS",IF($F20="À décommissionner",IF(H$8<$AS20,"IKS","Décom."),IF(OR($AQ20="",$AS20=""),"",IF(H$8<$AQ20,"IKS",IF(H$8<$AS20,IF(H$8=$AR20,"Bascule","Double run"),"ROKS")))))) -> ROKS | I20: =IF(OR($A20="",I$8=""),"",IF($F20="Migré","ROKS",IF($F20="À décommissionner",IF(I$8<$AS20,"IKS","Décom."),IF(OR($AQ20="",$AS20=""),"",IF(I$8<$AQ20,"IKS",IF(I$8<$AS20,IF(I$8=$AR20,"Bascule","Double run"),"ROKS")))))) -> ROKS | J20: =IF(OR($A20="",J$8=""),"",IF($F20="Migré","ROKS",IF($F20="À décommissionner",IF(J$8<$AS20,"IKS","Décom."),IF(OR($AQ20="",$AS20=""),"",IF(J$8<$AQ20,"IKS",IF(J$8<$AS20,IF(J$8=$AR20,"Bascule","Double run"),"ROKS")))))) -> ROKS | K20: =IF(OR($A20="",K$8=""),"",IF($F20="Migré","ROKS",IF($F20="À décommissionner",IF(K$8<$AS20,"IKS","Décom."),IF(OR($AQ20="",$AS20=""),"",IF(K$8<$AQ20,"IKS",IF(K$8<$AS20,IF(K$8=$AR20,"Bascule","Double run"),"ROKS")))))) -> ROKS | L20: =IF(OR($A20="",L$8=""),"",IF($F20="Migré","ROKS",IF($F20="À décommissionner",IF(L$8<$AS20,"IKS","Décom."),IF(OR($AQ20="",$AS20=""),"",IF(L$8<$AQ20,"IKS",IF(L$8<$AS20,IF(L$8=$AR20,"Bascule","Double run"),"ROKS")))))) -> ROKS | M20: =IF(OR($A20="",M$8=""),"",IF($F20="Migré","ROKS",IF($F20="À décommissionner",IF(M$8<$AS20,"IKS","Décom."),IF(OR($AQ20="",$AS20=""),"",IF(M$8<$AQ20,"IKS",IF(M$8<$AS20,IF(M$8=$AR20,"Bascule","Double run"),"ROKS")))))) -> ROKS | N20: =IF(OR($A20="",N$8=""),"",IF($F20="Migré","ROKS",IF($F20="À décommissionner",IF(N$8<$AS20,"IKS","Décom."),IF(OR($AQ20="",$AS20=""),"",IF(N$8<$AQ20,"IKS",IF(N$8<$AS20,IF(N$8=$AR20,"Bascule","Double run"),"ROKS")))))) -> ROKS | ... AP20: =IF(OR($A20="",AP$8=""),"",IF($F20="Migré","ROKS",IF($F20="À décommissionner",IF(AP$8<$AS20,"IKS","Décom."),IF(OR($AQ20="",$AS20=""),"",IF(AP$8<$AQ20,"IKS",IF(AP$8<$AS20,IF(AP$8=$AR20,"Bascule","Double run"),"ROKS")))))) -> ROKS | AQ20: =IF($A20="","",INDEX(TblApplications[Mois prov (calc)],$A20)) | AR20: =IF($A20="","",IFERROR(DATE(YEAR(INDEX(TblApplications[Mois bascule],$A20)),MONTH(INDEX(TblApplications[Mois bascule],$A20)),1),"")) -> -29 | AS20: =IF($A20="","",INDEX(TblApplications[Mois lib (calc)],$A20))
A21: =IFERROR(MATCH(13,TblApplications[Rang frise],0),"") | B21: =IF($A21="","",INDEX(TblApplications[ID],$A21)) | C21: =IF($A21="","",INDEX(TblApplications[Application],$A21)) | D21: =IF($A21="","",INDEX(TblApplications[Environnement],$A21)) | E21: =IF($A21="","",INDEX(TblApplications[Couloir],$A21)) | F21: =IF($A21="","",INDEX(TblApplications[Action],$A21)) | G21: =IF(OR($A21="",G$8=""),"",IF($F21="Migré","ROKS",IF($F21="À décommissionner",IF(G$8<$AS21,"IKS","Décom."),IF(OR($AQ21="",$AS21=""),"",IF(G$8<$AQ21,"IKS",IF(G$8<$AS21,IF(G$8=$AR21,"Bascule","Double run"),"ROKS")))))) | H21: =IF(OR($A21="",H$8=""),"",IF($F21="Migré","ROKS",IF($F21="À décommissionner",IF(H$8<$AS21,"IKS","Décom."),IF(OR($AQ21="",$AS21=""),"",IF(H$8<$AQ21,"IKS",IF(H$8<$AS21,IF(H$8=$AR21,"Bascule","Double run"),"ROKS")))))) | I21: =IF(OR($A21="",I$8=""),"",IF($F21="Migré","ROKS",IF($F21="À décommissionner",IF(I$8<$AS21,"IKS","Décom."),IF(OR($AQ21="",$AS21=""),"",IF(I$8<$AQ21,"IKS",IF(I$8<$AS21,IF(I$8=$AR21,"Bascule","Double run"),"ROKS")))))) | J21: =IF(OR($A21="",J$8=""),"",IF($F21="Migré","ROKS",IF($F21="À décommissionner",IF(J$8<$AS21,"IKS","Décom."),IF(OR($AQ21="",$AS21=""),"",IF(J$8<$AQ21,"IKS",IF(J$8<$AS21,IF(J$8=$AR21,"Bascule","Double run"),"ROKS")))))) | K21: =IF(OR($A21="",K$8=""),"",IF($F21="Migré","ROKS",IF($F21="À décommissionner",IF(K$8<$AS21,"IKS","Décom."),IF(OR($AQ21="",$AS21=""),"",IF(K$8<$AQ21,"IKS",IF(K$8<$AS21,IF(K$8=$AR21,"Bascule","Double run"),"ROKS")))))) | L21: =IF(OR($A21="",L$8=""),"",IF($F21="Migré","ROKS",IF($F21="À décommissionner",IF(L$8<$AS21,"IKS","Décom."),IF(OR($AQ21="",$AS21=""),"",IF(L$8<$AQ21,"IKS",IF(L$8<$AS21,IF(L$8=$AR21,"Bascule","Double run"),"ROKS")))))) | M21: =IF(OR($A21="",M$8=""),"",IF($F21="Migré","ROKS",IF($F21="À décommissionner",IF(M$8<$AS21,"IKS","Décom."),IF(OR($AQ21="",$AS21=""),"",IF(M$8<$AQ21,"IKS",IF(M$8<$AS21,IF(M$8=$AR21,"Bascule","Double run"),"ROKS")))))) | N21: =IF(OR($A21="",N$8=""),"",IF($F21="Migré","ROKS",IF($F21="À décommissionner",IF(N$8<$AS21,"IKS","Décom."),IF(OR($AQ21="",$AS21=""),"",IF(N$8<$AQ21,"IKS",IF(N$8<$AS21,IF(N$8=$AR21,"Bascule","Double run"),"ROKS")))))) | ... AP21: =IF(OR($A21="",AP$8=""),"",IF($F21="Migré","ROKS",IF($F21="À décommissionner",IF(AP$8<$AS21,"IKS","Décom."),IF(OR($AQ21="",$AS21=""),"",IF(AP$8<$AQ21,"IKS",IF(AP$8<$AS21,IF(AP$8=$AR21,"Bascule","Double run"),"ROKS")))))) | AQ21: =IF($A21="","",INDEX(TblApplications[Mois prov (calc)],$A21)) | AR21: =IF($A21="","",IFERROR(DATE(YEAR(INDEX(TblApplications[Mois bascule],$A21)),MONTH(INDEX(TblApplications[Mois bascule],$A21)),1),"")) | AS21: =IF($A21="","",INDEX(TblApplications[Mois lib (calc)],$A21))
A22: =IFERROR(MATCH(14,TblApplications[Rang frise],0),"") | B22: =IF($A22="","",INDEX(TblApplications[ID],$A22)) | C22: =IF($A22="","",INDEX(TblApplications[Application],$A22)) | D22: =IF($A22="","",INDEX(TblApplications[Environnement],$A22)) | E22: =IF($A22="","",INDEX(TblApplications[Couloir],$A22)) | F22: =IF($A22="","",INDEX(TblApplications[Action],$A22)) | G22: =IF(OR($A22="",G$8=""),"",IF($F22="Migré","ROKS",IF($F22="À décommissionner",IF(G$8<$AS22,"IKS","Décom."),IF(OR($AQ22="",$AS22=""),"",IF(G$8<$AQ22,"IKS",IF(G$8<$AS22,IF(G$8=$AR22,"Bascule","Double run"),"ROKS")))))) | H22: =IF(OR($A22="",H$8=""),"",IF($F22="Migré","ROKS",IF($F22="À décommissionner",IF(H$8<$AS22,"IKS","Décom."),IF(OR($AQ22="",$AS22=""),"",IF(H$8<$AQ22,"IKS",IF(H$8<$AS22,IF(H$8=$AR22,"Bascule","Double run"),"ROKS")))))) | I22: =IF(OR($A22="",I$8=""),"",IF($F22="Migré","ROKS",IF($F22="À décommissionner",IF(I$8<$AS22,"IKS","Décom."),IF(OR($AQ22="",$AS22=""),"",IF(I$8<$AQ22,"IKS",IF(I$8<$AS22,IF(I$8=$AR22,"Bascule","Double run"),"ROKS")))))) | J22: =IF(OR($A22="",J$8=""),"",IF($F22="Migré","ROKS",IF($F22="À décommissionner",IF(J$8<$AS22,"IKS","Décom."),IF(OR($AQ22="",$AS22=""),"",IF(J$8<$AQ22,"IKS",IF(J$8<$AS22,IF(J$8=$AR22,"Bascule","Double run"),"ROKS")))))) | K22: =IF(OR($A22="",K$8=""),"",IF($F22="Migré","ROKS",IF($F22="À décommissionner",IF(K$8<$AS22,"IKS","Décom."),IF(OR($AQ22="",$AS22=""),"",IF(K$8<$AQ22,"IKS",IF(K$8<$AS22,IF(K$8=$AR22,"Bascule","Double run"),"ROKS")))))) | L22: =IF(OR($A22="",L$8=""),"",IF($F22="Migré","ROKS",IF($F22="À décommissionner",IF(L$8<$AS22,"IKS","Décom."),IF(OR($AQ22="",$AS22=""),"",IF(L$8<$AQ22,"IKS",IF(L$8<$AS22,IF(L$8=$AR22,"Bascule","Double run"),"ROKS")))))) | M22: =IF(OR($A22="",M$8=""),"",IF($F22="Migré","ROKS",IF($F22="À décommissionner",IF(M$8<$AS22,"IKS","Décom."),IF(OR($AQ22="",$AS22=""),"",IF(M$8<$AQ22,"IKS",IF(M$8<$AS22,IF(M$8=$AR22,"Bascule","Double run"),"ROKS")))))) | N22: =IF(OR($A22="",N$8=""),"",IF($F22="Migré","ROKS",IF($F22="À décommissionner",IF(N$8<$AS22,"IKS","Décom."),IF(OR($AQ22="",$AS22=""),"",IF(N$8<$AQ22,"IKS",IF(N$8<$AS22,IF(N$8=$AR22,"Bascule","Double run"),"ROKS")))))) | ... AP22: =IF(OR($A22="",AP$8=""),"",IF($F22="Migré","ROKS",IF($F22="À décommissionner",IF(AP$8<$AS22,"IKS","Décom."),IF(OR($AQ22="",$AS22=""),"",IF(AP$8<$AQ22,"IKS",IF(AP$8<$AS22,IF(AP$8=$AR22,"Bascule","Double run"),"ROKS")))))) | AQ22: =IF($A22="","",INDEX(TblApplications[Mois prov (calc)],$A22)) | AR22: =IF($A22="","",IFERROR(DATE(YEAR(INDEX(TblApplications[Mois bascule],$A22)),MONTH(INDEX(TblApplications[Mois bascule],$A22)),1),"")) | AS22: =IF($A22="","",INDEX(TblApplications[Mois lib (calc)],$A22))
A23: =IFERROR(MATCH(15,TblApplications[Rang frise],0),"") | B23: =IF($A23="","",INDEX(TblApplications[ID],$A23)) | C23: =IF($A23="","",INDEX(TblApplications[Application],$A23)) | D23: =IF($A23="","",INDEX(TblApplications[Environnement],$A23)) | E23: =IF($A23="","",INDEX(TblApplications[Couloir],$A23)) | F23: =IF($A23="","",INDEX(TblApplications[Action],$A23)) | G23: =IF(OR($A23="",G$8=""),"",IF($F23="Migré","ROKS",IF($F23="À décommissionner",IF(G$8<$AS23,"IKS","Décom."),IF(OR($AQ23="",$AS23=""),"",IF(G$8<$AQ23,"IKS",IF(G$8<$AS23,IF(G$8=$AR23,"Bascule","Double run"),"ROKS")))))) | H23: =IF(OR($A23="",H$8=""),"",IF($F23="Migré","ROKS",IF($F23="À décommissionner",IF(H$8<$AS23,"IKS","Décom."),IF(OR($AQ23="",$AS23=""),"",IF(H$8<$AQ23,"IKS",IF(H$8<$AS23,IF(H$8=$AR23,"Bascule","Double run"),"ROKS")))))) | I23: =IF(OR($A23="",I$8=""),"",IF($F23="Migré","ROKS",IF($F23="À décommissionner",IF(I$8<$AS23,"IKS","Décom."),IF(OR($AQ23="",$AS23=""),"",IF(I$8<$AQ23,"IKS",IF(I$8<$AS23,IF(I$8=$AR23,"Bascule","Double run"),"ROKS")))))) | J23: =IF(OR($A23="",J$8=""),"",IF($F23="Migré","ROKS",IF($F23="À décommissionner",IF(J$8<$AS23,"IKS","Décom."),IF(OR($AQ23="",$AS23=""),"",IF(J$8<$AQ23,"IKS",IF(J$8<$AS23,IF(J$8=$AR23,"Bascule","Double run"),"ROKS")))))) | K23: =IF(OR($A23="",K$8=""),"",IF($F23="Migré","ROKS",IF($F23="À décommissionner",IF(K$8<$AS23,"IKS","Décom."),IF(OR($AQ23="",$AS23=""),"",IF(K$8<$AQ23,"IKS",IF(K$8<$AS23,IF(K$8=$AR23,"Bascule","Double run"),"ROKS")))))) | L23: =IF(OR($A23="",L$8=""),"",IF($F23="Migré","ROKS",IF($F23="À décommissionner",IF(L$8<$AS23,"IKS","Décom."),IF(OR($AQ23="",$AS23=""),"",IF(L$8<$AQ23,"IKS",IF(L$8<$AS23,IF(L$8=$AR23,"Bascule","Double run"),"ROKS")))))) | M23: =IF(OR($A23="",M$8=""),"",IF($F23="Migré","ROKS",IF($F23="À décommissionner",IF(M$8<$AS23,"IKS","Décom."),IF(OR($AQ23="",$AS23=""),"",IF(M$8<$AQ23,"IKS",IF(M$8<$AS23,IF(M$8=$AR23,"Bascule","Double run"),"ROKS")))))) | N23: =IF(OR($A23="",N$8=""),"",IF($F23="Migré","ROKS",IF($F23="À décommissionner",IF(N$8<$AS23,"IKS","Décom."),IF(OR($AQ23="",$AS23=""),"",IF(N$8<$AQ23,"IKS",IF(N$8<$AS23,IF(N$8=$AR23,"Bascule","Double run"),"ROKS")))))) | ... AP23: =IF(OR($A23="",AP$8=""),"",IF($F23="Migré","ROKS",IF($F23="À décommissionner",IF(AP$8<$AS23,"IKS","Décom."),IF(OR($AQ23="",$AS23=""),"",IF(AP$8<$AQ23,"IKS",IF(AP$8<$AS23,IF(AP$8=$AR23,"Bascule","Double run"),"ROKS")))))) | AQ23: =IF($A23="","",INDEX(TblApplications[Mois prov (calc)],$A23)) | AR23: =IF($A23="","",IFERROR(DATE(YEAR(INDEX(TblApplications[Mois bascule],$A23)),MONTH(INDEX(TblApplications[Mois bascule],$A23)),1),"")) | AS23: =IF($A23="","",INDEX(TblApplications[Mois lib (calc)],$A23))
A24: =IFERROR(MATCH(16,TblApplications[Rang frise],0),"") | B24: =IF($A24="","",INDEX(TblApplications[ID],$A24)) | C24: =IF($A24="","",INDEX(TblApplications[Application],$A24)) | D24: =IF($A24="","",INDEX(TblApplications[Environnement],$A24)) | E24: =IF($A24="","",INDEX(TblApplications[Couloir],$A24)) | F24: =IF($A24="","",INDEX(TblApplications[Action],$A24)) | G24: =IF(OR($A24="",G$8=""),"",IF($F24="Migré","ROKS",IF($F24="À décommissionner",IF(G$8<$AS24,"IKS","Décom."),IF(OR($AQ24="",$AS24=""),"",IF(G$8<$AQ24,"IKS",IF(G$8<$AS24,IF(G$8=$AR24,"Bascule","Double run"),"ROKS")))))) | H24: =IF(OR($A24="",H$8=""),"",IF($F24="Migré","ROKS",IF($F24="À décommissionner",IF(H$8<$AS24,"IKS","Décom."),IF(OR($AQ24="",$AS24=""),"",IF(H$8<$AQ24,"IKS",IF(H$8<$AS24,IF(H$8=$AR24,"Bascule","Double run"),"ROKS")))))) | I24: =IF(OR($A24="",I$8=""),"",IF($F24="Migré","ROKS",IF($F24="À décommissionner",IF(I$8<$AS24,"IKS","Décom."),IF(OR($AQ24="",$AS24=""),"",IF(I$8<$AQ24,"IKS",IF(I$8<$AS24,IF(I$8=$AR24,"Bascule","Double run"),"ROKS")))))) | J24: =IF(OR($A24="",J$8=""),"",IF($F24="Migré","ROKS",IF($F24="À décommissionner",IF(J$8<$AS24,"IKS","Décom."),IF(OR($AQ24="",$AS24=""),"",IF(J$8<$AQ24,"IKS",IF(J$8<$AS24,IF(J$8=$AR24,"Bascule","Double run"),"ROKS")))))) | K24: =IF(OR($A24="",K$8=""),"",IF($F24="Migré","ROKS",IF($F24="À décommissionner",IF(K$8<$AS24,"IKS","Décom."),IF(OR($AQ24="",$AS24=""),"",IF(K$8<$AQ24,"IKS",IF(K$8<$AS24,IF(K$8=$AR24,"Bascule","Double run"),"ROKS")))))) | L24: =IF(OR($A24="",L$8=""),"",IF($F24="Migré","ROKS",IF($F24="À décommissionner",IF(L$8<$AS24,"IKS","Décom."),IF(OR($AQ24="",$AS24=""),"",IF(L$8<$AQ24,"IKS",IF(L$8<$AS24,IF(L$8=$AR24,"Bascule","Double run"),"ROKS")))))) | M24: =IF(OR($A24="",M$8=""),"",IF($F24="Migré","ROKS",IF($F24="À décommissionner",IF(M$8<$AS24,"IKS","Décom."),IF(OR($AQ24="",$AS24=""),"",IF(M$8<$AQ24,"IKS",IF(M$8<$AS24,IF(M$8=$AR24,"Bascule","Double run"),"ROKS")))))) | N24: =IF(OR($A24="",N$8=""),"",IF($F24="Migré","ROKS",IF($F24="À décommissionner",IF(N$8<$AS24,"IKS","Décom."),IF(OR($AQ24="",$AS24=""),"",IF(N$8<$AQ24,"IKS",IF(N$8<$AS24,IF(N$8=$AR24,"Bascule","Double run"),"ROKS")))))) | ... AP24: =IF(OR($A24="",AP$8=""),"",IF($F24="Migré","ROKS",IF($F24="À décommissionner",IF(AP$8<$AS24,"IKS","Décom."),IF(OR($AQ24="",$AS24=""),"",IF(AP$8<$AQ24,"IKS",IF(AP$8<$AS24,IF(AP$8=$AR24,"Bascule","Double run"),"ROKS")))))) | AQ24: =IF($A24="","",INDEX(TblApplications[Mois prov (calc)],$A24)) | AR24: =IF($A24="","",IFERROR(DATE(YEAR(INDEX(TblApplications[Mois bascule],$A24)),MONTH(INDEX(TblApplications[Mois bascule],$A24)),1),"")) | AS24: =IF($A24="","",INDEX(TblApplications[Mois lib (calc)],$A24))
A25: =IFERROR(MATCH(17,TblApplications[Rang frise],0),"") | B25: =IF($A25="","",INDEX(TblApplications[ID],$A25)) | C25: =IF($A25="","",INDEX(TblApplications[Application],$A25)) | D25: =IF($A25="","",INDEX(TblApplications[Environnement],$A25)) | E25: =IF($A25="","",INDEX(TblApplications[Couloir],$A25)) | F25: =IF($A25="","",INDEX(TblApplications[Action],$A25)) | G25: =IF(OR($A25="",G$8=""),"",IF($F25="Migré","ROKS",IF($F25="À décommissionner",IF(G$8<$AS25,"IKS","Décom."),IF(OR($AQ25="",$AS25=""),"",IF(G$8<$AQ25,"IKS",IF(G$8<$AS25,IF(G$8=$AR25,"Bascule","Double run"),"ROKS")))))) | H25: =IF(OR($A25="",H$8=""),"",IF($F25="Migré","ROKS",IF($F25="À décommissionner",IF(H$8<$AS25,"IKS","Décom."),IF(OR($AQ25="",$AS25=""),"",IF(H$8<$AQ25,"IKS",IF(H$8<$AS25,IF(H$8=$AR25,"Bascule","Double run"),"ROKS")))))) | I25: =IF(OR($A25="",I$8=""),"",IF($F25="Migré","ROKS",IF($F25="À décommissionner",IF(I$8<$AS25,"IKS","Décom."),IF(OR($AQ25="",$AS25=""),"",IF(I$8<$AQ25,"IKS",IF(I$8<$AS25,IF(I$8=$AR25,"Bascule","Double run"),"ROKS")))))) | J25: =IF(OR($A25="",J$8=""),"",IF($F25="Migré","ROKS",IF($F25="À décommissionner",IF(J$8<$AS25,"IKS","Décom."),IF(OR($AQ25="",$AS25=""),"",IF(J$8<$AQ25,"IKS",IF(J$8<$AS25,IF(J$8=$AR25,"Bascule","Double run"),"ROKS")))))) | K25: =IF(OR($A25="",K$8=""),"",IF($F25="Migré","ROKS",IF($F25="À décommissionner",IF(K$8<$AS25,"IKS","Décom."),IF(OR($AQ25="",$AS25=""),"",IF(K$8<$AQ25,"IKS",IF(K$8<$AS25,IF(K$8=$AR25,"Bascule","Double run"),"ROKS")))))) | L25: =IF(OR($A25="",L$8=""),"",IF($F25="Migré","ROKS",IF($F25="À décommissionner",IF(L$8<$AS25,"IKS","Décom."),IF(OR($AQ25="",$AS25=""),"",IF(L$8<$AQ25,"IKS",IF(L$8<$AS25,IF(L$8=$AR25,"Bascule","Double run"),"ROKS")))))) | M25: =IF(OR($A25="",M$8=""),"",IF($F25="Migré","ROKS",IF($F25="À décommissionner",IF(M$8<$AS25,"IKS","Décom."),IF(OR($AQ25="",$AS25=""),"",IF(M$8<$AQ25,"IKS",IF(M$8<$AS25,IF(M$8=$AR25,"Bascule","Double run"),"ROKS")))))) | N25: =IF(OR($A25="",N$8=""),"",IF($F25="Migré","ROKS",IF($F25="À décommissionner",IF(N$8<$AS25,"IKS","Décom."),IF(OR($AQ25="",$AS25=""),"",IF(N$8<$AQ25,"IKS",IF(N$8<$AS25,IF(N$8=$AR25,"Bascule","Double run"),"ROKS")))))) | ... AP25: =IF(OR($A25="",AP$8=""),"",IF($F25="Migré","ROKS",IF($F25="À décommissionner",IF(AP$8<$AS25,"IKS","Décom."),IF(OR($AQ25="",$AS25=""),"",IF(AP$8<$AQ25,"IKS",IF(AP$8<$AS25,IF(AP$8=$AR25,"Bascule","Double run"),"ROKS")))))) | AQ25: =IF($A25="","",INDEX(TblApplications[Mois prov (calc)],$A25)) | AR25: =IF($A25="","",IFERROR(DATE(YEAR(INDEX(TblApplications[Mois bascule],$A25)),MONTH(INDEX(TblApplications[Mois bascule],$A25)),1),"")) | AS25: =IF($A25="","",INDEX(TblApplications[Mois lib (calc)],$A25))
A26: =IFERROR(MATCH(18,TblApplications[Rang frise],0),"") | B26: =IF($A26="","",INDEX(TblApplications[ID],$A26)) | C26: =IF($A26="","",INDEX(TblApplications[Application],$A26)) | D26: =IF($A26="","",INDEX(TblApplications[Environnement],$A26)) | E26: =IF($A26="","",INDEX(TblApplications[Couloir],$A26)) | F26: =IF($A26="","",INDEX(TblApplications[Action],$A26)) | G26: =IF(OR($A26="",G$8=""),"",IF($F26="Migré","ROKS",IF($F26="À décommissionner",IF(G$8<$AS26,"IKS","Décom."),IF(OR($AQ26="",$AS26=""),"",IF(G$8<$AQ26,"IKS",IF(G$8<$AS26,IF(G$8=$AR26,"Bascule","Double run"),"ROKS")))))) | H26: =IF(OR($A26="",H$8=""),"",IF($F26="Migré","ROKS",IF($F26="À décommissionner",IF(H$8<$AS26,"IKS","Décom."),IF(OR($AQ26="",$AS26=""),"",IF(H$8<$AQ26,"IKS",IF(H$8<$AS26,IF(H$8=$AR26,"Bascule","Double run"),"ROKS")))))) | I26: =IF(OR($A26="",I$8=""),"",IF($F26="Migré","ROKS",IF($F26="À décommissionner",IF(I$8<$AS26,"IKS","Décom."),IF(OR($AQ26="",$AS26=""),"",IF(I$8<$AQ26,"IKS",IF(I$8<$AS26,IF(I$8=$AR26,"Bascule","Double run"),"ROKS")))))) | J26: =IF(OR($A26="",J$8=""),"",IF($F26="Migré","ROKS",IF($F26="À décommissionner",IF(J$8<$AS26,"IKS","Décom."),IF(OR($AQ26="",$AS26=""),"",IF(J$8<$AQ26,"IKS",IF(J$8<$AS26,IF(J$8=$AR26,"Bascule","Double run"),"ROKS")))))) | K26: =IF(OR($A26="",K$8=""),"",IF($F26="Migré","ROKS",IF($F26="À décommissionner",IF(K$8<$AS26,"IKS","Décom."),IF(OR($AQ26="",$AS26=""),"",IF(K$8<$AQ26,"IKS",IF(K$8<$AS26,IF(K$8=$AR26,"Bascule","Double run"),"ROKS")))))) | L26: =IF(OR($A26="",L$8=""),"",IF($F26="Migré","ROKS",IF($F26="À décommissionner",IF(L$8<$AS26,"IKS","Décom."),IF(OR($AQ26="",$AS26=""),"",IF(L$8<$AQ26,"IKS",IF(L$8<$AS26,IF(L$8=$AR26,"Bascule","Double run"),"ROKS")))))) | M26: =IF(OR($A26="",M$8=""),"",IF($F26="Migré","ROKS",IF($F26="À décommissionner",IF(M$8<$AS26,"IKS","Décom."),IF(OR($AQ26="",$AS26=""),"",IF(M$8<$AQ26,"IKS",IF(M$8<$AS26,IF(M$8=$AR26,"Bascule","Double run"),"ROKS")))))) | N26: =IF(OR($A26="",N$8=""),"",IF($F26="Migré","ROKS",IF($F26="À décommissionner",IF(N$8<$AS26,"IKS","Décom."),IF(OR($AQ26="",$AS26=""),"",IF(N$8<$AQ26,"IKS",IF(N$8<$AS26,IF(N$8=$AR26,"Bascule","Double run"),"ROKS")))))) | ... AP26: =IF(OR($A26="",AP$8=""),"",IF($F26="Migré","ROKS",IF($F26="À décommissionner",IF(AP$8<$AS26,"IKS","Décom."),IF(OR($AQ26="",$AS26=""),"",IF(AP$8<$AQ26,"IKS",IF(AP$8<$AS26,IF(AP$8=$AR26,"Bascule","Double run"),"ROKS")))))) | AQ26: =IF($A26="","",INDEX(TblApplications[Mois prov (calc)],$A26)) | AR26: =IF($A26="","",IFERROR(DATE(YEAR(INDEX(TblApplications[Mois bascule],$A26)),MONTH(INDEX(TblApplications[Mois bascule],$A26)),1),"")) | AS26: =IF($A26="","",INDEX(TblApplications[Mois lib (calc)],$A26))
